Workbook

Sheet Trang bìa
C2: Công ty Cổ phần AgriPack
B6: Mô tả | E6: Mã màu
B7: Mã cổ phiếu | C7: Công ty Cổ phần AgriPack (chưa niêm yết, chưa có mã cổ phiếu) | E7: Aaa | F7: Giả định (ô nhập liệu)
B8: Sàn niêm yết | C8: Chưa niêm yết – định giá cổ phần cho vòng gọi vốn Series A | E8: Aaa | F8: Dữ liệu lịch sử
B9: Ngày update | C9: 46302 | E9: Aaa | F9: Công thức
B10: Miêu tả ngắn gọn | C10: Mô hình định giá cổ phần trước vòng gọi vốn bằng DCF, VC Method và Multiples. | E10: Aaa | F10: Link đến các trang khác
B11: Thông tin doanh nghiệp | F11: Note (ghi chú, nguồn, lý do)
E13: Thông tin về mô hình
B14: Cấu trúc các Tab | E14: Tiền tệ | F14: VND
B15: Trang bìa | C15: Thông tin chung, mã màu, cấu trúc file và thông tin mô hình | E15: Đơn vị | F15: Nghìn đồng; tỷ đồng ở Multiples, Summary, Sensitivity, Chart_Data
B16: Hướng dẫn | C16: Hướng dẫn của file mẫu (giảng viên) | E16: Thời điểm định giá | F16: 01/10/2026 (BCTC đến 31/12/2025)
B17: Investment | C17: Kế hoạch đầu tư tài sản của file mẫu | E17: Rf (TPCP 10 năm, 01/10/2026) | F17: ='Discount rate'!B12 -> 0.04588
B18: Income Statement | C18: Báo cáo kết quả kinh doanh 2023A–2030E (theo chức năng, VAS) | E18: WACC | F18: ='Discount rate'!E4 -> 0.14130984
B19: Balance Sheet | C19: Bảng cân đối kế toán 2023A–2030E | E19: Pre-money khuyến nghị (tỷ đồng) | F19: =Summary!B8 -> 26.007498
B20: Cash Flow Statement | C20: Báo cáo lưu chuyển tiền tệ 2023A–2030E
B21: Discount rate | C21: Chi phí vốn: Rf, ERP, CRP, beta, Ke, Kd và WACC
B22: Assumption | C22: Tỷ lệ giả định tổng hợp 2026E–2030E, g và RONIC
B23: Drivers | C23: Động lực dự phóng: sản lượng × giá, chi phí, CAPEX, VLĐ, vay, thuế, kịch bản
B24: Pro Forma | C24: KQKD dự phóng, CAPEX, vốn lưu động và nhu cầu vốn
B25: DCF | C25: Định giá chiết khấu dòng tiền tự do (FCFF)
B26: VCM | C26: Định giá theo VC Method (thoái vốn 2030, tỷ lệ thất bại 40%)
B27: Multiples | C27: Định giá theo bội số so sánh EV/EBITDA và P/E
B28: Summary | C28: Tổng hợp định giá, khoảng giá trị, kịch bản và độ nhạy theo nhân tố
B29: Sensitivity | C29: Bảng độ nhạy DCF và VC Method
B30: Checks | C30: Kiểm tra cân đối và liên kết giữa các sheet

Sheet Hướng dẫn
B4: Three Statement Model
I6: Năm hiện tại | J6: 2026
C8: LƯU Ý
B9: Model Legend
C11: Ô nhập liệu | D11: ABC | E11: Chỉ nhập dữ liệu vào những ô màu vàng này
C13: Tất cả các ô khác đã được nhập sẵn hàm hoặc là ô chứa dữ liệu cho trước. KHÔNG thay đổi những ô này!

Sheet Investment
A1: Các khoản đầu tư dự kiến 5 năm
B3: Đơn giá (nghìn đồng) | C3: Số lượng | D3: Thành tiền | E3: Tháng | F3: Năm | G3: Thời gian sử dụng | H3: Giá trị còn lại
D4: =SUM(D5:D7) -> 24090000 | F4: ='Cash Flow Statement'!E2+1 -> 2026
A5: Nhà máy sản xuất | B5: 30550000 | C5: 0 | D5: =B5*C5 -> 0 | E5: 10 | G5: 8
A6: Thiết bị sản xuất | B6: 3600000 | C6: 5 | D6: =B6*C6 -> 18000000 | E6: 11 | G6: 5
A7: Xe tải chở hàng | B7: 1218000 | C7: 5 | D7: =B7*C7 -> 6090000 | E7: 11 | G7: 5
D8: =SUM(D9:D10) -> 77100000 | F8: =F4+1 -> 2027
A9: Nhà máy sản xuất | B9: 30550000 | C9: 2 | D9: =B9*C9 -> 61100000 | E9: 10 | G9: 7
A10: Kho hàng | B10: 4000000 | C10: 4 | D10: =B10*C10 -> 16000000 | E10: 5 | G10: 7
D11: =SUM(D12) -> 22640000 | F11: =F8+1 -> 2028 | I11: Đầu tư mạnh tăng trưởng mở rộng KD
A12: Thiết bị sản xuất | B12: 5660000 | C12: 4 | D12: =B12*C12 -> 22640000 | E12: 9 | G12: 5 | I12: CAPEX/Revenue = 60%
D13: =SUM(D14) -> 35220000 | F13: =F11+1 -> 2029
A14: Thiết bị sản xuất | B14: 5870000 | C14: 6 | D14: =B14*C14 -> 35220000 | E14: 4 | G14: 8
D15: =SUM(D16:D17) -> 32460000 | F15: =F13+1 -> 2030
A16: Nâng cấp văn phòng | B16: 8115000 | C16: 4 | D16: =B16*C16 -> 32460000 | E16: 1 | G16: 6

Sheet Income Statement
A1: Income Statement | D1: Đơn vị: Nghìn đồng
B2: ='Hướng dẫn'!J6-3 -> 2023 | C2: =B2+1 -> 2024 | D2: =C2+1 -> 2025 | E2: =D2+1 -> 2026 | F2: =E2+1 -> 2027 | G2: =F2+1 -> 2028 | H2: =G2+1 -> 2029 | I2: =H2+1 -> 2030 | J2: Ngoài kỳ dự phóng 5 năm – không sử dụng
A3: Doanh thu bán hàng
A4: Doanh thu 1 | B4: 15055000 | C4: 24088000 | D4: 38059040 | E4: =Drivers!F14 -> 51242691 | F4: =Drivers!G14 -> 65334432 | G4: =Drivers!H14 -> 79969344 | H4: =Drivers!I14 -> 1.1011779e+08 | I4: =Drivers!J14 -> 1.4040018e+08
A5: Doanh thu 2 | B5: 3020000 | C5: 4228000 | D5: 5898060 | E5: =Drivers!F21 -> 7339545.9 | F5: =Drivers!G21 -> 8983604.1 | G5: =Drivers!H21 -> 10629400 | H5: =Drivers!I21 -> 13877745 | I5: =Drivers!J21 -> 16986360
A6: Doanh thu 3 | B6: 1520000 | C6: 2280000 | D6: 2736000 | E6: =Drivers!F28 -> 3610152 | F6: =Drivers!G28 -> 4763595.6 | G6: =Drivers!H28 -> 6188863.4 | H6: =Drivers!I28 -> 8794374.8 | I6: =Drivers!J28 -> 11782703
A7: Doanh thu 4 | B7: 0 | C7: 566000 | D7: 1188600 | E7: =Drivers!F35 -> 1930286.4 | F7: =Drivers!G35 -> 2938861 | G7: =Drivers!H35 -> 4325268.7 | H7: =Drivers!I35 -> 7463251.2 | I7: =Drivers!J35 -> 10984040
A9: (-) Khoản giảm trừ | B9: -156760 | C9: -233715 | D9: -335171.9 | E9: =-SUM(E4:E7)*Drivers!F38 -> -448858.73 | F9: =-SUM(F4:F7)*Drivers!G38 -> -574143.45 | G9: =-SUM(G4:G7)*Drivers!H38 -> -707790.14 | H9: =-SUM(H4:H7)*Drivers!I38 -> -981772.11 | I9: =-SUM(I4:I7)*Drivers!J38 -> -1261073
A11: Doanh thu thuần | B11: 19438240 | C11: 30928285 | D11: 47546528 | E11: =SUM(E4:E10) -> 63673817 | F11: =SUM(F4:F10) -> 81446349 | G11: =SUM(G4:G10) -> 1.0040509e+08 | H11: =SUM(H4:H10) -> 1.3927139e+08 | I11: =SUM(I4:I10) -> 1.7889221e+08
A13: Giá vốn hàng bán
A14: Chi phí biến đổi | B14: 4956751.2 | C14: 7732071.2 | D14: 11648899 | E14: =Drivers!F56 -> 15918454 | F14: =Drivers!G56 -> 20361587 | G14: =Drivers!H56 -> 25603297 | H14: =Drivers!I56 -> 37603274 | I14: =Drivers!J56 -> 47406435
A15: Chi phí cố định | B15: 1055000 | C15: 1160500 | D15: 1276550 | E15: =Drivers!F57 -> 1404205 | F15: =Drivers!G57 -> 1544625.5 | G15: =Drivers!H57 -> 1699088.1 | H15: =Drivers!I57 -> 2768996.9 | I15: =Drivers!J57 -> 3045896.5
A16: Tiền lương bộ phận sản xuất (70% quỹ lương) | B16: =Drivers!$C$167*B53 -> 4894400 | C16: =Drivers!$C$167*C53 -> 5383840 | D16: =Drivers!$C$167*D53 -> 7537376 | E16: =Drivers!$C$167*E53 -> 10028626 | F16: =Drivers!$C$167*F53 -> 12827800 | G16: =Drivers!$C$167*G53 -> 16165219 | H16: =Drivers!$C$167*H53 -> 22910143 | I16: =Drivers!$C$167*I53 -> 28801646
A17: Khấu hao TSCĐ sản xuất (90% khấu hao) | B17: =Drivers!$C$168*B69 -> 1288980 | C17: =Drivers!$C$168*C69 -> 2137752 | D17: =Drivers!$C$168*D69 -> 2818756.8 | E17: =Drivers!$C$168*E69 -> 3367885 | F17: =Drivers!$C$168*F69 -> 4743239.4 | G17: =Drivers!$C$168*G69 -> 6062670.3 | H17: =Drivers!$C$168*H69 -> 13111107 | I17: =Drivers!$C$168*I69 -> 14916065
A18: Tổng Giá vốn hàng bán | B18: =SUM(B14:B17) -> 12195131 | C18: =SUM(C14:C17) -> 16414163 | D18: =SUM(D14:D17) -> 23281582 | E18: =SUM(E14:E17) -> 30719170 | F18: =SUM(F14:F17) -> 39477252 | G18: =SUM(G14:G17) -> 49530274 | H18: =SUM(H14:H17) -> 76393522 | I18: =SUM(I14:I17) -> 94170042
A19: Lợi nhuận gộp | B19: =B11-B18 -> 7243108.8 | C19: =C11-C18 -> 14514122 | D19: =D11-D18 -> 24264946 | E19: =E11-E18 -> 32954647 | F19: =F11-F18 -> 41969097 | G19: =G11-G18 -> 50874812 | H19: =H11-H18 -> 62877865 | I19: =I11-I18 -> 84722167
A20: Biên lợi nhuận gộp | B20: =B19/B11 -> 0.37262164 | C20: =C19/C11 -> 0.46928311 | D20: =D19/D11 -> 0.51034107 | E20: =E19/E11 -> 0.51755412 | F20: =F19/F11 -> 0.51529746 | G20: =G19/G11 -> 0.50669557 | H20: =H19/H11 -> 0.45147727 | I20: =I19/I11 -> 0.47359339
A21: Chi phí
A22: Chi phí Bán hàng và quản lý doanh nghiệp
A23: Tiền lương bộ phận bán hàng & quản lý (30% quỹ lương) | B23: =(1-Drivers!$C$167)*B53 -> 2097600 | C23: =(1-Drivers!$C$167)*C53 -> 2307360 | D23: =(1-Drivers!$C$167)*D53 -> 3230304 | E23: =(1-Drivers!$C$167)*E53 -> 4297982.6 | F23: =(1-Drivers!$C$167)*F53 -> 5497628.6 | G23: =(1-Drivers!$C$167)*G53 -> 6927951 | H23: =(1-Drivers!$C$167)*H53 -> 9818632.7 | I23: =(1-Drivers!$C$167)*I53 -> 12343562
A24: Thuê mặt bằng | B24: 3977000 | C24: 5368950 | D24: 7570219.5 | E24: =Drivers!F67 -> 8478645.8 | F24: =Drivers!G67 -> 9496083.3 | G24: =Drivers!H67 -> 10920496 | H24: =Drivers!I67 -> 14196645 | I24: =Drivers!J67 -> 15900242
A25: Khấu hao TSCĐ bộ phận bán hàng & quản lý (10% khấu hao) | B25: =(1-Drivers!$C$168)*B69 -> 143220 | C25: =(1-Drivers!$C$168)*C69 -> 237528 | D25: =(1-Drivers!$C$168)*D69 -> 313195.2 | E25: =(1-Drivers!$C$168)*E69 -> 374209.44 | F25: =(1-Drivers!$C$168)*F69 -> 527026.6 | G25: =(1-Drivers!$C$168)*G69 -> 673630.03 | H25: =(1-Drivers!$C$168)*H69 -> 1456789.7 | I25: =(1-Drivers!$C$168)*I69 -> 1657340.5
A26: Sửa chữa, bảo dưỡng | B26: 950000 | C26: 1615000 | D26: 2083350 | E26: =Drivers!F69 -> 2801647.9 | F26: =Drivers!G69 -> 3583639.4 | G26: =Drivers!H69 -> 4417823.8 | H26: =Drivers!I69 -> 6127941 | I26: =Drivers!J69 -> 7871257.2
A27: Furniture & Fixtures | B27: 0 | C27: 0 | D27: 0 | E27: 0 | F27: 0 | G27: 0 | H27: 0 | I27: 0
A28: Chi phí dịch vụ chung (điện, nước...) | B28: 1200000 | C28: 1800000 | D28: 2250000 | E28: =Drivers!F71 -> 3183690.8 | F28: =Drivers!G71 -> 4072317.4 | G28: =Drivers!H71 -> 5020254.3 | H28: =Drivers!I71 -> 6963569.3 | I28: =Drivers!J71 -> 8944610.5
A29: Internet & Communications | B29: 0 | C29: 0 | D29: 0 | E29: 0 | F29: 0 | G29: 0 | H29: 0 | I29: 0
A30: Infrastructure Services | B30: 0 | C30: 0 | D30: 0 | E30: 0 | F30: 0 | G30: 0 | H30: 0 | I30: 0
A31: Software | B31: 0 | C31: 0 | D31: 0 | E31: 0 | F31: 0 | G31: 0 | H31: 0 | I31: 0
A32: Bank Service Charges | B32: 0 | C32: 0 | D32: 0 | E32: 0 | F32: 0 | G32: 0 | H32: 0 | I32: 0
A33: Business Licenses and Permits | B33: 0 | C33: 0 | D33: 0 | E33: 0 | F33: 0 | G33: 0 | H33: 0 | I33: 0
A34: Conferences, Dues, and Subscriptions | B34: 0 | C34: 0 | D34: 0 | E34: 0 | F34: 0 | G34: 0 | H34: 0 | I34: 0
A35: Văn phòng phẩm | B35: 0 | C35: 0 | D35: 0 | E35: 0 | F35: 0 | G35: 0 | H35: 0 | I35: 0
A36: Gifts | B36: 0 | C36: 0 | D36: 0 | E36: 0 | F36: 0 | G36: 0 | H36: 0 | I36: 0
A37: Printing , Postage and Delivery | B37: 0 | C37: 0 | D37: 0 | E37: 0 | F37: 0 | G37: 0 | H37: 0 | I37: 0
A38: Miscellaneous | B38: 0 | C38: 0 | D38: 0 | E38: 0 | F38: 0 | G38: 0 | H38: 0 | I38: 0
A39: Recruiting Expense | B39: 0 | C39: 0 | D39: 0 | E39: 0 | F39: 0 | G39: 0 | H39: 0 | I39: 0
A40: Hỗ trợ tiền ăn cho CNV | B40: 2150000 | C40: 2580000 | D40: 3096000 | E40: =Drivers!F65 -> 4011450.5 | F40: =Drivers!G65 -> 5131120 | G40: =Drivers!H65 -> 6466087.6 | H40: =Drivers!I65 -> 9164057.2 | I40: =Drivers!J65 -> 11520658
A41: Equipment Rental | B41: 0 | C41: 0 | D41: 0 | E41: 0 | F41: 0 | G41: 0 | H41: 0 | I41: 0
A42: Other Tech Expense | B42: 0 | C42: 0 | D42: 0 | E42: 0 | F42: 0 | G42: 0 | H42: 0 | I42: 0
A43: Professional Services (dùng cho: Kiểm nghiệm, chứng nhận & R&D vật liệu) | B43: 0 | C43: 0 | D43: 0 | E43: =Drivers!F75 -> 382042.9 | F43: =Drivers!G75 -> 488678.09 | G43: =Drivers!H75 -> 602430.52 | H43: =Drivers!I75 -> 835628.32 | I43: =Drivers!J75 -> 1073353.3
A44: Accounting Fees | B44: 0 | C44: 0 | D44: 0 | E44: 0 | F44: 0 | G44: 0 | H44: 0 | I44: 0
A45: Legal Fees | B45: 0 | C45: 0 | D45: 0 | E45: 0 | F45: 0 | G45: 0 | H45: 0 | I45: 0
A46: Consultant Fees | B46: 0 | C46: 0 | D46: 0 | E46: 0 | F46: 0 | G46: 0 | H46: 0 | I46: 0
A47: Other Professional Services | B47: 0 | C47: 0 | D47: 0 | E47: 0 | F47: 0 | G47: 0 | H47: 0 | I47: 0
A48: Marketing | B48: 920000 | C48: 966000 | D48: 1159200 | E48: =Drivers!F73 -> 1782866.9 | F48: =Drivers!G73 -> 2443390.5 | G48: =Drivers!H73 -> 3012152.6 | H48: =Drivers!I73 -> 4178141.6 | I48: =Drivers!J73 -> 5008981.9
A49: Public Relations | B49: 0 | C49: 0 | D49: 0 | E49: 0 | F49: 0 | G49: 0 | H49: 0 | I49: 0
A50: Tổng Chi phí bán hàng và quản lý doanh nghiệp | B50: =SUM(B23:B49) -> 11437820 | C50: =SUM(C23:C49) -> 14874838 | D50: =SUM(D23:D49) -> 19702269 | E50: =SUM(E23:E49) -> 25312537 | F50: =SUM(F23:F49) -> 31239884 | G50: =SUM(G23:G49) -> 38040826 | H50: =SUM(H23:H49) -> 52741404 | I50: =SUM(I23:I49) -> 64320006
A52: Tiền lương
A53: Tổng quỹ tiền lương (trước phân bổ) | B53: 6992000 | C53: 7691200 | D53: 10767680 | E53: =Drivers!F63 -> 14326609 | F53: =Drivers!G63 -> 18325429 | G53: =Drivers!H63 -> 23093170 | H53: =Drivers!I63 -> 32728776 | I53: =Drivers!J63 -> 41145208
A54: (−) Phân bổ vào giá vốn hàng bán (70%) | B54: =-B16 -> -4894400 | C54: =-C16 -> -5383840 | D54: =-D16 -> -7537376 | E54: =-E16 -> -10028626 | F54: =-F16 -> -12827800 | G54: =-G16 -> -16165219 | H54: =-H16 -> -22910143 | I54: =-I16 -> -28801646
A55: (−) Phân bổ vào chi phí bán hàng & QLDN (30%) | B55: =-B23 -> -2097600 | C55: =-C23 -> -2307360 | D55: =-D23 -> -3230304 | E55: =-E23 -> -4297982.6 | F55: =-F23 -> -5497628.6 | G55: =-G23 -> -6927951 | H55: =-H23 -> -9818632.7 | I55: =-I23 -> -12343562
A56: Payroll Processing Fees | B56: 0 | C56: 0 | D56: 0 | E56: 0 | F56: 0 | G56: 0 | H56: 0 | I56: 0
A57: Bonuses | B57: 0 | C57: 0 | D57: 0 | E57: 0 | F57: 0 | G57: 0 | H57: 0 | I57: 0
A58: Commissions | B58: 0 | C58: 0 | D58: 0 | E58: 0 | F58: 0 | G58: 0 | H58: 0 | I58: 0
A59: Tiền lương chưa phân bổ (= 0) | B59: =SUM(B53:B58) -> 0 | C59: =SUM(C53:C58) -> 0 | D59: =SUM(D53:D58) -> 0 | E59: =SUM(E53:E58) -> 0 | F59: =SUM(F53:F58) -> 0 | G59: =SUM(G53:G58) -> 0 | H59: =SUM(H53:H58) -> 0 | I59: =SUM(I53:I58) -> 0
A61: Tổng chi phí bán hàng & QLDN (theo chức năng) | B61: =SUM(B50,B59) -> 11437820 | C61: =SUM(C50,C59) -> 14874838 | D61: =SUM(D50,D59) -> 19702269 | E61: =SUM(E50,E59) -> 25312537 | F61: =SUM(F50,F59) -> 31239884 | G61: =SUM(G50,G59) -> 38040826 | H61: =SUM(H50,H59) -> 52741404 | I61: =SUM(I50,I59) -> 64320006
A63: Lợi nhuận thuần từ HĐKD trước lãi vay (EBIT) | B63: =B19-B61 -> -4194711.2 | C63: =C19-C61 -> -360716.25 | D63: =D19-D61 -> 4562677.2 | E63: =E19-E61 -> 7642109.6 | F63: =F19-F61 -> 10729213 | G63: =G19-G61 -> 12833987 | H63: =H19-H61 -> 10136460 | I63: =I19-I61 -> 20402161
A64: Thu/chi khác
A65: Interest Income | B65: 0 | C65: 0 | D65: 0 | E65: 0 | F65: 0 | G65: 0 | H65: 0 | I65: 0
A66: Other Income | B66: 0 | C66: 0 | D66: 0 | E66: 0 | F66: 0 | G66: 0 | H66: 0 | I66: 0
A67: Chi phí tài chính | B67: 114300 | C67: 142560 | D67: 142182 | E67: =Drivers!F130 -> 160260 | F67: =Drivers!G130 -> 160260 | G67: =Drivers!H130 -> 2118159.2 | H67: =Drivers!I130 -> 4076058.4 | I67: =Drivers!J130 -> 3684478.5
A68: Bad Debt Expense | B68: 0 | C68: 0 | D68: 0 | E68: 0 | F68: 0 | G68: 0 | H68: 0 | I68: 0
A69: Khấu hao (ghi nhớ – đã phân bổ 90% vào GVHB, 10% vào CPBH & QLDN) | B69: 1432200 | C69: 2375280 | D69: 3131952 | E69: =Drivers!F99 -> 3742094.4 | F69: =Drivers!G99 -> 5270266 | G69: =Drivers!H99 -> 6736300.3 | H69: =Drivers!I99 -> 14567897 | I69: =Drivers!J99 -> 16573405
A70: Amortization | B70: 0 | C70: 0 | D70: 0 | E70: 0 | F70: 0 | G70: 0 | H70: 0 | I70: 0
A72: Tổng chi phí tài chính (khấu hao đã nằm trong GVHB và CPBH & QLDN) | B72: =SUM(B65:B68,B70:B71) -> 114300 | C72: =SUM(C65:C68,C70:C71) -> 142560 | D72: =SUM(D65:D68,D70:D71) -> 142182 | E72: =SUM(E65:E68,E70:E71) -> 160260 | F72: =SUM(F65:F68,F70:F71) -> 160260 | G72: =SUM(G65:G68,G70:G71) -> 2118159.2 | H72: =SUM(H65:H68,H70:H71) -> 4076058.4 | I72: =SUM(I65:I68,I70:I71) -> 3684478.5
A74: Lợi nhuận trước thuế | B74: =B63-B72 -> -4309011.2 | C74: =C63-C72 -> -503276.25 | D74: =D63-D72 -> 4420495.2 | E74: =E63-E72 -> 7481849.6 | F74: =F63-F72 -> 10568953 | G74: =G63-G72 -> 10715827 | H74: =H63-H72 -> 6060401.9 | I74: =I63-I72 -> 16717683
A75: Thuế
A76: Thuế thu nhập doanh nghiệp | B76: 0 | C76: 0 | D76: 0 | E76: =Drivers!F138 -> 902709.76 | F76: =Drivers!G138 -> 2113790.6 | G76: =Drivers!H138 -> 2143165.5 | H76: =Drivers!I138 -> 1212080.4 | I76: =Drivers!J138 -> 3343536.5
A78: Lợi nhuận sau thuế | B78: =B74-B76 -> -4309011.2 | C78: =C74-C76 -> -503276.25 | D78: =D74-D76 -> 4420495.2 | E78: =E74-E76 -> 6579139.9 | F78: =F74-F76 -> 8455162.4 | G78: =G74-G76 -> 8572661.9 | H78: =H74-H76 -> 4848321.5 | I78: =I74-I76 -> 13374146
A80: EBITDA = EBIT + khấu hao | B80: =SUM(B63,B69) -> -2762511.2 | C80: =SUM(C63,C69) -> 2014563.8 | D80: =SUM(D63,D69) -> 7694629.2 | E80: =SUM(E63,E69) -> 11384204 | F80: =SUM(F63,F69) -> 15999479 | G80: =SUM(G63,G69) -> 19570287 | H80: =SUM(H63,H69) -> 24704357 | I80: =SUM(I63,I69) -> 36975566
A81: Biên EBITDA | B81: =B80/B11 -> -0.14211735 | C81: =C80/C11 -> 0.065136614 | D81: =D80/D11 -> 0.16183367 | E81: =E80/E11 -> 0.17878941 | F81: =F80/F11 -> 0.19644194 | G81: =G80/G11 -> 0.1949133 | H81: =H80/H11 -> 0.17738286 | I81: =I80/I11 -> 0.20669187

Sheet Balance Sheet
A1: Balance Sheet | F1: Đơn vị: Nghìn đồng
C2: ='Hướng dẫn'!J6-3 -> 2023 | E2: =C2+1 -> 2024 | F2: =E2+1 -> 2025 | G2: =F2+1 -> 2026 | H2: =G2+1 -> 2027 | I2: =H2+1 -> 2028 | J2: =I2+1 -> 2029 | K2: =J2+1 -> 2030 | L2: Ngoài kỳ dự phóng – không sử dụng
A3: Tài sản ngắn hạn | C3: 01/01/2023 (đầu kỳ) | D3: 31/12/2023
A4: Tiền và các khoản tương đương tiền
B5: Tiền mặt | C5: 910000 | D5: 43988.8 | E5: 1735532.6 | F5: 2933481.8 | G5: ='Cash Flow Statement'!F34 -> 38400238 | H5: ='Cash Flow Statement'!G34 -> 36454184 | I5: ='Cash Flow Statement'!H34 -> 21617752 | J5: ='Cash Flow Statement'!I34 -> 14952947 | K5: ='Cash Flow Statement'!J34 -> 12623217
B6: Tổng tiền mặt | C6: 910000 | D6: 43988.8 | E6: 1735532.6 | F6: 2933481.8 | G6: =SUM(G5) -> 38400238 | H6: =SUM(H5) -> 36454184 | I6: =SUM(I5) -> 21617752 | J6: =SUM(J5) -> 14952947 | K6: =SUM(K5) -> 12623217
A7: Hàng tồn kho
B8: Hàng tồn kho | C8: 1785000 | D8: 2499000 | E8: 2998800 | F8: 3748500 | G8: =Drivers!F106 -> 4745934 | H8: =Drivers!G106 -> 6001702.1 | I8: =Drivers!H106 -> 7480105.5 | J8: =Drivers!I106 -> 11613941 | K8: =Drivers!J106 -> 13822557
B9: Tổng hàng tồn kho | C9: 1785000 | D9: 2499000 | E9: 2998800 | F9: 3748500 | G9: =SUM(G8) -> 4745934 | H9: =SUM(H8) -> 6001702.1 | I9: =SUM(I8) -> 7480105.5 | J9: =SUM(J8) -> 11613941 | K9: =SUM(K8) -> 13822557
A10: Khoản phải thu
B11: Phải thu khách hàng | C11: 1050000 | D11: 1260000 | E11: 1537200 | F11: 1767780 | G11: =Drivers!F108 -> 3140078.6 | H11: =Drivers!G108 -> 4909095 | I11: =Drivers!H108 -> 7152143.2 | J11: =Drivers!I108 -> 11446963 | K11: =Drivers!J108 -> 14703469
B12: Tổng khoản phải thu | C12: 1050000 | D12: 1260000 | E12: 1537200 | F12: 1767780 | G12: =SUM(G11) -> 3140078.6 | H12: =SUM(H11) -> 4909095 | I12: =SUM(I11) -> 7152143.2 | J12: =SUM(J11) -> 11446963 | K12: =SUM(K11) -> 14703469
A13: Tài sản ngắn hạn khác
B14: Other Receivable | C14: 0 | D14: 0 | E14: 0 | F14: 0 | G14: 0 | H14: 0 | I14: 0 | J14: 0 | K14: 0
B15: Chi phí trả trước | C15: 890000 | D15: 1068000 | E15: 1495200 | F15: 1794240 | G15: =Drivers!F110*$F$15/$F$19 -> 2204363.7 | H15: =Drivers!G110*$F$15/$F$19 -> 2819642.1 | I15: =Drivers!H110*$F$15/$F$19 -> 3475986.5 | J15: =Drivers!I110*$F$15/$F$19 -> 4821523.3 | K15: =Drivers!J110*$F$15/$F$19 -> 6193181.3
B16: Prepaid Insurance | C16: - | D16: - | E16: - | F16: - | G16: 0 | H16: 0 | I16: 0 | J16: 0 | K16: 0
B17: Unbilled Revenue | C17: - | D17: - | E17: - | F17: - | G17: 0 | H17: 0 | I17: 0 | J17: 0 | K17: 0
B18: Tài sản ngắn hạn khác | C18: 150000 | D18: 165000 | E18: 214500 | F18: 278850 | G18: =Drivers!F110*$F$18/$F$19 -> 342588.96 | H18: =Drivers!G110*$F$18/$F$19 -> 438211.84 | I18: =Drivers!H110*$F$18/$F$19 -> 540216.94 | J18: =Drivers!I110*$F$18/$F$19 -> 749332.18 | K18: =Drivers!J110*$F$18/$F$19 -> 962507.03
B19: Tổng tài sản ngắn hạn khác | C19: 1040000 | D19: 1233000 | E19: 1709700 | F19: 2073090 | G19: =SUM(G14:G18) -> 2546952.7 | H19: =SUM(H14:H18) -> 3257854 | I19: =SUM(I14:I18) -> 4016203.5 | J19: =SUM(J14:J18) -> 5570855.4 | K19: =SUM(K14:K18) -> 7155688.4
A21: Tổng tài sản ngắn hạn | C21: 4785000 | D21: 5035988.8 | E21: 7981232.5 | F21: 10522852 | G21: =SUM(G6,G9,G12,G19) -> 48833203 | H21: =SUM(H6,H9,H12,H19) -> 50622835 | I21: =SUM(I6,I9,I12,I19) -> 40266204 | J21: =SUM(J6,J9,J12,J19) -> 43584707 | K21: =SUM(K6,K9,K12,K19) -> 48304931
A22: Tài sản dài hạn
A23: Khấu khao
B24: Khấu hao lũy kế | C24: 2850000 | D24: 4282200 | E24: 6657480 | F24: 9789432 | G24: =SUM(F24,'Income Statement'!E69) -> 13531526 | H24: =SUM(G24,'Income Statement'!F69) -> 18801792 | I24: =SUM(H24,'Income Statement'!G69) -> 25538093 | J24: =SUM(I24,'Income Statement'!H69) -> 40105990 | K24: =SUM(J24,'Income Statement'!I69) -> 56679395
B25: Accumulated Amortization | C25: 0 | D25: 0 | E25: 0 | F25: 0 | G25: =SUM(F25,'Income Statement'!E70) -> 0 | H25: =SUM(G25,'Income Statement'!F70) -> 0 | I25: =SUM(H25,'Income Statement'!G70) -> 0 | J25: =SUM(I25,'Income Statement'!H70) -> 0 | K25: =SUM(J25,'Income Statement'!I70) -> 0
A26: Tài sản dài hạn
B27: Tài sản cố định vô hình | C27: 985000 | D27: 985000 | E27: 1020000 | F27: 1020000 | G27: =F27 -> 1020000 | H27: =G27 -> 1020000 | I27: =H27 -> 1020000 | J27: =I27 -> 1020000 | K27: =J27 -> 1020000
B28: Thiết bị, nhà xưởng | C28: 10220000 | D28: 13797000 | E28: 19315800 | F28: 21633696 | G28: =SUM(F28,Drivers!F96) -> 34368459 | H28: =SUM(G28,Drivers!G96) -> 46585412 | I28: =SUM(H28,Drivers!H96) -> 1.1184872e+08 | J28: =SUM(I28,Drivers!I96) -> 1.2856128e+08 | K28: =SUM(J28,Drivers!J96) -> 1.4645051e+08
B29: Văn phòng | C29: 3580000 | D29: 5012000 | E29: 5763800 | F29: 8530424 | G29: =F29 -> 8530424 | H29: =G29 -> 8530424 | I29: =H29 -> 8530424 | J29: =I29 -> 8530424 | K29: =J29 -> 8530424
A30: Tổng tài sản dài hạn | C30: 11935000 | D30: 15511800 | E30: 19442120 | F30: 21394688 | G30: =SUM(G27:G29)-G24-G25 -> 30387357 | H30: =SUM(H27:H29)-H24-H25 -> 37334043 | I30: =SUM(I27:I29)-I24-I25 -> 95861049 | J30: =SUM(J27:J29)-J24-J25 -> 98005719 | K30: =SUM(K27:K29)-K24-K25 -> 99321535
A32: Tổng tài sản | C32: 16720000 | D32: 20547789 | E32: 27423353 | F32: 31917540 | G32: =SUM(G21,G30) -> 79220560 | H32: =SUM(H21,H30) -> 87956878 | I32: =SUM(I21,I30) -> 1.3612725e+08 | J32: =SUM(J21,J30) -> 1.4159043e+08 | K32: =SUM(K21,K30) -> 1.4762647e+08
C33: 0 | D33: 0 | E33: 0 | F33: 0
A34: Nợ phải trả và Vốn chủ sở hữu
A35: Nợ ngắn hạn
A36: Khoản phải trả
B37: Phải trả người bán | C37: 120000 | D37: 156000 | E37: 202800 | F37: 263640 | G37: =Drivers!F112 -> 474593.4 | H37: =Drivers!G112 -> 720204.25 | I37: =Drivers!H112 -> 1122015.8 | J37: =Drivers!I112 -> 1659134.4 | K37: =Drivers!J112 -> 2073383.5
B38: Tổng khoản khải trả | C38: 120000 | D38: 156000 | E38: 202800 | F38: 263640 | G38: =SUM(G37) -> 474593.4 | H38: =SUM(H37) -> 720204.25 | I38: =SUM(I37) -> 1122015.8 | J38: =SUM(J37) -> 1659134.4 | K38: =SUM(K37) -> 2073383.5
A39: Credit Cards
B40: Credit Card 1 | C40: 0 | D40: 0 | E40: 0 | F40: 0 | G40: 0 | H40: 0 | I40: 0 | J40: 0 | K40: 0
B41: Credit Card 2 | C41: 0 | D41: 0 | E41: 0 | F41: 0 | G41: 0 | H41: 0 | I41: 0 | J41: 0 | K41: 0
B42: Total Credit Cards Payable | C42: 0 | D42: 0 | E42: 0 | F42: 0 | G42: =SUM(G40:G41) -> 0 | H42: =SUM(H40:H41) -> 0 | I42: =SUM(I40:I41) -> 0 | J42: =SUM(J40:J41) -> 0 | K42: =SUM(K40:K41) -> 0
A43: Nợ vay ngắn hạn
B44: Khoản vay 1 | C44: 100000 | D44: 90000 | E44: 108000 | F44: 102600 | G44: =Drivers!F122 -> 102600 | H44: =Drivers!G122 -> 102600 | I44: =Drivers!H122 -> 102600 | J44: =Drivers!I122 -> 102600 | K44: =Drivers!J122 -> 102600
B45: Tổng nợ vay ngắn hạn | C45: 100000 | D45: 90000 | E45: 108000 | F45: 102600 | G45: =SUM(G44:G44) -> 102600 | H45: =SUM(H44:H44) -> 102600 | I45: =SUM(I44:I44) -> 102600 | J45: =SUM(J44:J44) -> 102600 | K45: =SUM(K44:K44) -> 102600
A46: Deferred Income/Advances from Customers
B47: Deferred Income - current | C47: 0 | D47: 0 | E47: 0 | F47: 0 | G47: 0 | H47: 0 | I47: 0 | J47: 0 | K47: 0
B48: Total Deferred Income | C48: 0 | D48: 0 | E48: 0 | F48: 0 | G48: =SUM(G47) -> 0 | H48: =SUM(H47) -> 0 | I48: =SUM(I47) -> 0 | J48: =SUM(J47) -> 0 | K48: =SUM(K47) -> 0
A49: Nợ phải trả ngắn hạn khác
B50: Accrued Expenses | C50: 0 | D50: 0 | E50: 0 | F50: 0 | G50: 0 | H50: 0 | I50: 0 | J50: 0 | K50: 0
B51: Accrued Income Taxes | C51: 0 | D51: 0 | E51: 0 | F51: 0 | G51: 0 | H51: 0 | I51: 0 | J51: 0 | K51: 0
B52: Nợ phải trả ngắn hạn khác | C52: 36000 | D52: 46800 | E52: 60840 | F52: 79092 | G52: =Drivers!F114 -> 127347.63 | H52: =Drivers!G114 -> 162892.7 | I52: =Drivers!H114 -> 200810.17 | J52: =Drivers!I114 -> 278542.77 | K52: =Drivers!J114 -> 357784.42
B53: Tổng nợ phải trả ngắn hạn khác | C53: 36000 | D53: 46800 | E53: 60840 | F53: 79092 | G53: =SUM(G50:G52) -> 127347.63 | H53: =SUM(H50:H52) -> 162892.7 | I53: =SUM(I50:I52) -> 200810.17 | J53: =SUM(J50:J52) -> 278542.77 | K53: =SUM(K50:K52) -> 357784.42
A55: Tổng nợ ngắn hạn | C55: 256000 | D55: 292800 | E55: 371640 | F55: 445332 | G55: =SUM(G38,G42,G45,G48,G53) -> 704541.04 | H55: =SUM(H38,H42,H45,H48,H53) -> 985696.95 | I55: =SUM(I38,I42,I45,I48,I53) -> 1425426 | J55: =SUM(J38,J42,J45,J48,J53) -> 2040277.2 | K55: =SUM(K38,K42,K45,K48,K53) -> 2533767.9
A57: Nợ dài hạn
B58: Nợ vay dài hạn | C58: 1200000 | D58: 1200000 | E58: 1500000 | F58: 1500000 | G58: =Drivers!F128 -> 1500000 | H58: =Drivers!G128 -> 1500000 | I58: =Drivers!H128 -> 40657984 | J58: =Drivers!I128 -> 40657984 | K58: =Drivers!J128 -> 32826387
B59: Deferred Income Taxes | C59: 0 | D59: 0 | E59: 0 | F59: 0 | G59: 0 | H59: 0 | I59: 0 | J59: 0 | K59: 0
B60: Nợ dài hạn khác | C60: 0 | D60: 0 | E60: 0 | F60: 0 | G60: 0 | H60: 0 | I60: 0 | J60: 0 | K60: 0
A61: Tổng nợ dài hạn | C61: 1200000 | D61: 1200000 | E61: 1500000 | F61: 1500000 | G61: =SUM(G58:G60) -> 1500000 | H61: =SUM(H58:H60) -> 1500000 | I61: =SUM(I58:I60) -> 40657984 | J61: =SUM(J58:J60) -> 40657984 | K61: =SUM(K58:K60) -> 32826387
A63: Tổng nợ phải trả | C63: 1456000 | D63: 1492800 | E63: 1871640 | F63: 1945332 | G63: =SUM(G55,G61) -> 2204541 | H63: =SUM(H55,H61) -> 2485697 | I63: =SUM(I55,I61) -> 42083410 | J63: =SUM(J55,J61) -> 42698261 | K63: =SUM(K55,K61) -> 35360155
C64: 0 | D64: 0 | E64: 0 | F64: 0
A65: Vốn chủ sở hữu
B66: Paid-in Capital | C66: 0 | D66: 0 | E66: 0 | F66: 0 | G66: 0 | H66: 0 | I66: 0 | J66: 0 | K66: 0
B67: Vốn cổ phần | C67: 17044000 | D67: 17044000 | E67: 25144000 | F67: 32144000 | G67: =SUM(F67,F69) -> 32144000 | H67: =SUM(G67,G69) -> 72608671 | I67: =SUM(H67,H69) -> 72608671 | J67: =SUM(I67,I69) -> 72608671 | K67: =SUM(J67,J69) -> 72608671
B68: Preferred Stock | C68: 0 | D68: 0 | E68: 0 | F68: 0 | G68: 0 | H68: 0 | I68: 0 | J68: 0 | K68: 0
B69: Vốn cổ phần tăng thêm | C69: 0 | D69: 8100000 | E69: 7000000 | F69: 0 | G69: =Drivers!F132 -> 40464671 | H69: =Drivers!G132 -> 0 | I69: =Drivers!H132 -> 0 | J69: =Drivers!I132 -> 0 | K69: =Drivers!J132 -> 0
B70: Capital Raising Round B | C70: 0 | D70: 0 | E70: 0 | F70: 0 | G70: 0 | H70: 0 | I70: 0 | J70: 0 | K70: 0
B71: Capital Raising Round C | C71: 0 | D71: 0 | E71: 0 | F71: 0 | G71: 0 | H71: 0 | I71: 0 | J71: 0 | K71: 0
B72: Lợi nhuận giữ lại | C72: -1780000 | D72: -6089011.2 | E72: -6592287.5 | F72: -2171792.2 | G72: =SUM('Income Statement'!E78,F72) -> 4407347.6 | H72: =SUM('Income Statement'!F78,G72) -> 12862510 | I72: =SUM('Income Statement'!G78,H72) -> 21435172 | J72: =SUM('Income Statement'!H78,I72) -> 26283493 | K72: =SUM('Income Statement'!I78,J72) -> 39657639
A73: Tổng vốn chủ sở hữu | C73: 15264000 | D73: 19054989 | E73: 25551713 | F73: 29972208 | G73: =SUM(G66:G72) -> 77016019 | H73: =SUM(H66:H72) -> 85471181 | I73: =SUM(I66:I72) -> 94043843 | J73: =SUM(J66:J72) -> 98892165 | K73: =SUM(K66:K72) -> 1.1226631e+08
A75: Tổng nguồn vốn | C75: 16720000 | D75: 20547789 | E75: 27423353 | F75: 31917540 | G75: =SUM(G63,G73) -> 79220560 | H75: =SUM(H63,H73) -> 87956878 | I75: =SUM(I63,I73) -> 1.3612725e+08 | J75: =SUM(J63,J73) -> 1.4159043e+08 | K75: =SUM(K63,K73) -> 1.4762647e+08
D77: =ROUND(D32-D75,0) -> 0 | E77: =ROUND(E32-E75,0) -> 0 | F77: =ROUND(F32-F75,0) -> 0 | G77: =ROUND(G32-G75,0) -> 0 | H77: =ROUND(H32-H75,0) -> 0 | I77: =ROUND(I32-I75,0) -> 0 | J77: =ROUND(J32-J75,0) -> 0 | K77: =ROUND(K32-K75,0) -> 0

Sheet Cash Flow Statement
A1: Statement of Cash Flows | E1: Đơn vị: Nghìn đồng
C2: ='Income Statement'!B2 -> 2023 | D2: =C2+1 -> 2024 | E2: =D2+1 -> 2025 | F2: =E2+1 -> 2026 | G2: =F2+1 -> 2027 | H2: =G2+1 -> 2028 | I2: =H2+1 -> 2029 | J2: =I2+1 -> 2030 | K2: Ngoài kỳ dự phóng – không sử dụng
A3: Hoạt động kinh doanh
B4: Lợi nhuận sau thuế | C4: -4309011.2 | D4: -503276.25 | E4: 4420495.2 | F4: ='Income Statement'!E78 -> 6579139.9 | G4: ='Income Statement'!F78 -> 8455162.4 | H4: ='Income Statement'!G78 -> 8572661.9 | I4: ='Income Statement'!H78 -> 4848321.5 | J4: ='Income Statement'!I78 -> 13374146
B6: Khấu hao | C6: 1432200 | D6: 2375280 | E6: 3131952 | F6: ='Income Statement'!E69 -> 3742094.4 | G6: ='Income Statement'!F69 -> 5270266 | H6: ='Income Statement'!G69 -> 6736300.3 | I6: ='Income Statement'!H69 -> 14567897 | J6: ='Income Statement'!I69 -> 16573405
A8: Biến động Tài sản ngắn hạn
B9: Khoản phải thu | C9: -210000 | D9: -277200 | E9: -230580 | F9: ='Balance Sheet'!F11-'Balance Sheet'!G11 -> -1372298.6 | G9: ='Balance Sheet'!G11-'Balance Sheet'!H11 -> -1769016.4 | H9: ='Balance Sheet'!H11-'Balance Sheet'!I11 -> -2243048.2 | I9: ='Balance Sheet'!I11-'Balance Sheet'!J11 -> -4294820.1 | J9: ='Balance Sheet'!J11-'Balance Sheet'!K11 -> -3256506
B10: Hàng tồn kho | C10: -714000 | D10: -499800 | E10: -749700 | F10: ='Balance Sheet'!F9-'Balance Sheet'!G9 -> -997434.04 | G10: ='Balance Sheet'!G9-'Balance Sheet'!H9 -> -1255768.1 | H10: ='Balance Sheet'!H9-'Balance Sheet'!I9 -> -1478403.4 | I10: ='Balance Sheet'!I9-'Balance Sheet'!J9 -> -4133835.5 | J10: ='Balance Sheet'!J9-'Balance Sheet'!K9 -> -2208615.7
B11: Tài sản ngắn hạn khác | C11: -193000 | D11: -476700 | E11: -363390 | F11: ='Balance Sheet'!F19-'Balance Sheet'!G19 -> -473862.68 | G11: ='Balance Sheet'!G19-'Balance Sheet'!H19 -> -710901.28 | H11: ='Balance Sheet'!H19-'Balance Sheet'!I19 -> -758349.51 | I11: ='Balance Sheet'!I19-'Balance Sheet'!J19 -> -1554652 | J11: ='Balance Sheet'!J19-'Balance Sheet'!K19 -> -1584832.9
A12: Biến động Nợ ngắn hạn
B13: Khoản phải trả | C13: 36000 | D13: 46800 | E13: 60840 | F13: ='Balance Sheet'!G38-'Balance Sheet'!F38 -> 210953.4 | G13: ='Balance Sheet'!H38-'Balance Sheet'!G38 -> 245610.85 | H13: ='Balance Sheet'!I38-'Balance Sheet'!H38 -> 401811.57 | I13: ='Balance Sheet'!J38-'Balance Sheet'!I38 -> 537118.6 | J13: ='Balance Sheet'!K38-'Balance Sheet'!J38 -> 414249.07
B14: ='Balance Sheet'!A43 -> Nợ vay ngắn hạn | C14: -10000 | D14: 18000 | E14: -5400 | F14: ='Balance Sheet'!G45-'Balance Sheet'!F45 -> 0 | G14: ='Balance Sheet'!H45-'Balance Sheet'!G45 -> 0 | H14: ='Balance Sheet'!I45-'Balance Sheet'!H45 -> 0 | I14: ='Balance Sheet'!J45-'Balance Sheet'!I45 -> 0 | J14: ='Balance Sheet'!K45-'Balance Sheet'!J45 -> 0
B15: Nợ ngắn hạn khác | C15: 10800 | D15: 14040 | E15: 18252 | F15: =('Balance Sheet'!G53-'Balance Sheet'!F53)+('Balance Sheet'!G48-'Balance Sheet'!F48) -> 48255.634 | G15: =('Balance Sheet'!H53-'Balance Sheet'!G53)+('Balance Sheet'!H48-'Balance Sheet'!G48) -> 35545.064 | H15: =('Balance Sheet'!I53-'Balance Sheet'!H53)+('Balance Sheet'!I48-'Balance Sheet'!H48) -> 37917.476 | I15: =('Balance Sheet'!J53-'Balance Sheet'!I53)+('Balance Sheet'!J48-'Balance Sheet'!I48) -> 77732.599 | J15: =('Balance Sheet'!K53-'Balance Sheet'!J53)+('Balance Sheet'!K48-'Balance Sheet'!J48) -> 79241.646
A17: Lưu chuyển tiền thuần từ hoạt động kinh doanh | C17: -3957011.2 | D17: 697143.75 | E17: 6282469.2 | F17: =SUM(F4:F16) -> 7736847.9 | G17: =SUM(G4:G16) -> 10270899 | H17: =SUM(H4:H16) -> 11268890 | I17: =SUM(I4:I16) -> 10047762 | J17: =SUM(J4:J16) -> 23391087
A19: Đầu tư
B20: Biến động Tài sản cố định | C20: -5009000 | D20: -6305600 | E20: -5084520 | F20: =SUM('Balance Sheet'!F27:F29)-SUM('Balance Sheet'!G27:G29) -> -12734763 | G20: =SUM('Balance Sheet'!G27:G29)-SUM('Balance Sheet'!H27:H29) -> -12216952 | H20: =SUM('Balance Sheet'!H27:H29)-SUM('Balance Sheet'!I27:I29) -> -65263306 | I20: =SUM('Balance Sheet'!I27:I29)-SUM('Balance Sheet'!J27:J29) -> -16712566 | J20: =SUM('Balance Sheet'!J27:J29)-SUM('Balance Sheet'!K27:K29) -> -17889221
A22: Lưu chuyển tiền thuần từ hoạt động đầu tư | C22: -5009000 | D22: -6305600 | E22: -5084520 | F22: =SUM(F20:F21) -> -12734763 | G22: =SUM(G20:G21) -> -12216952 | H22: =SUM(H20:H21) -> -65263306 | I22: =SUM(I20:I21) -> -16712566 | J22: =SUM(J20:J21) -> -17889221
A24: Tài chính
B25: Nhận vốn góp cổ phần | C25: 8100000 | D25: 7000000 | E25: 0 | F25: ='Balance Sheet'!G69 -> 40464671 | G25: ='Balance Sheet'!H69 -> 0 | H25: ='Balance Sheet'!I69 -> 0 | I25: ='Balance Sheet'!J69 -> 0 | J25: ='Balance Sheet'!K69 -> 0
B26: Vay (trả) nợ dài hạn | C26: 0 | D26: 300000 | E26: 0 | F26: =('Balance Sheet'!G58-'Balance Sheet'!F58) -> 0 | G26: =('Balance Sheet'!H58-'Balance Sheet'!G58) -> 0 | H26: =('Balance Sheet'!I58-'Balance Sheet'!H58) -> 39157984 | I26: =('Balance Sheet'!J58-'Balance Sheet'!I58) -> 0 | J26: =('Balance Sheet'!K58-'Balance Sheet'!J58) -> -7831596.8
A28: Lưu chuyển tiền thuần từ hoạt động tài chính | C28: 8100000 | D28: 7300000 | E28: 0 | F28: =SUM(F25:F27) -> 40464671 | G28: =SUM(G25:G27) -> 0 | H28: =SUM(H25:H27) -> 39157984 | I28: =SUM(I25:I27) -> 0 | J28: =SUM(J25:J27) -> -7831596.8
A30: Số dư tiền mặt đầu kỳ | C30: 910000 | D30: 43988.8 | E30: 1735532.6 | F30: =E34 -> 2933481.8 | G30: =F34 -> 38400238 | H30: =G34 -> 36454184 | I30: =H34 -> 21617752 | J30: =I34 -> 14952947
A32: Biến động tiền mặt trong kỳ | C32: -866011.2 | D32: 1691543.8 | E32: 1197949.2 | F32: =SUM(F17,F22,F28) -> 35466756 | G32: =SUM(G17,G22,G28) -> -1946053.7 | H32: =SUM(H17,H22,H28) -> -14836432 | I32: =SUM(I17,I22,I28) -> -6664804.2 | J32: =SUM(J17,J22,J28) -> -2329730.5
A34: Số dư tiền mặt cuối kỳ | C34: 43988.8 | D34: 1735532.6 | E34: 2933481.8 | F34: =SUM(F32,F30) -> 38400238 | G34: =SUM(G32,G30) -> 36454184 | H34: =SUM(H32,H30) -> 21617752 | I34: =SUM(I32,I30) -> 14952947 | J34: =SUM(J32,J30) -> 12623217

Sheet Discount rate
A1: Discount rate calculation
A2: Beta | B2: =B22 -> 1.5006496 | D2: Chi phí vốn CSH | E2: =B3+B2*(B4-B3) -> 0.16788282
A3: Risk-free rate | B3: =B12 -> 0.04588 | D3: Chi phí vốn nợ (sau thuế) | E3: =B14*(1-Assumption!B13) -> 0.08
A4: Market return | B4: =B23 -> 0.12718 | D4: WACC | E4: =(B6*E2+B7*E3)/B8 -> 0.14130984
A6: Vốn CSH | B6: ='Balance Sheet'!I73 -> 94043843
A7: Nợ vay dài hạn | B7: =SUM('Balance Sheet'!I58,'Balance Sheet'!I45) -> 40760584
A8: Total | B8: =SUM(B6:B7) -> 1.3480443e+08
A11: CƠ SỞ TÍNH CHI PHÍ VỐN | C11: Nguồn / lý do
A12: Lợi suất phi rủi ro Rf | B12: 0.04588 | C12: Nguồn: lợi suất TPCP Việt Nam kỳ hạn 10 năm ngày 01/10/2026 = 4,588% https://vn.investing.com/rates-bonds/vietnam-10-year-bond-yield-historical-data
A13: ERP thị trường phát triển | B13: 0.0423 | C13: Nguồn: Damodaran (01/2026) – ERP thị trường trưởng thành 4,23% https://pages.stern.nyu.edu/~adamodar/New_Home_Page/datafile/ctryprem.html
A14: Lãi suất vay trước thuế (Kd) | B14: 0.1 | C14: Lý do: lãi suất cho vay VND 8,1–10,5%/năm (6/2026); DN nhỏ vay ở nửa trên khung → 10%. Nguồn: NHNN (2026), Mục 3.1.3.
A15: Phần bù rủi ro quốc gia Việt Nam (CRP) | B15: 0.039 | C15: ƯỚC TÍNH: Moody's Ba2 (triển vọng tích cực từ 5/2026); chênh lệch vỡ nợ Ba2 ~2,9% × hệ số biến động cổ phiếu/trái phiếu ~1,35 (phương pháp Damodaran). Nguồn: Moody's (2026); Damodaran (2026). https://pages.stern.nyu.edu/~adamodar/New_Home_Page/datafile/ctryprem.html
A16: ERP Việt Nam = ERP phát triển + CRP | B16: =SUM(B13,B15) -> 0.0813
A17: Beta không đòn bẩy ngành bao bì (βu) | B17: 0.78 | C17: Nguồn: Damodaran (01/2026) – beta không đòn bẩy ngành Packaging & Container 0,78 https://pages.stern.nyu.edu/~adamodar/New_Home_Page/datafile/Betas.html
A18: D/E mục tiêu (BCĐKT dự phóng 2028, sau huy động) | B18: =B7/B6 -> 0.43342108 | C18: Công thức: D/E theo BCĐKT dự phóng cuối 2028 – năm đầu tư lớn (sau huy động vốn cổ phần và khoản vay trung hạn).
A19: Thuế suất | B19: =Assumption!B13 -> 0.2 | C19: Nguồn: Luật Thuế TNDN 67/2025/QH15 (20%).
A20: Beta có đòn bẩy = βu × [1 + (1 − t) × D/E] | B20: =B17*(1+(1-B19)*B18) -> 1.0504548
A21: Hệ số tương quan ρ (NĐT VC đa dạng hóa một phần) | B21: 0.7 | C21: Công thức: beta tổng = beta có đòn bẩy / ρ (B23 = B21/B22), trong đó ρ là hệ số tương quan giữa danh mục của nhà đầu tư VC và thị trường. ρ = 0,7 vì quỹ VC nắm 20–30 khoản đầu tư nên chỉ đa dạng hóa một phần. Nguồn: Damodaran (2009), Valuing Young, Start-up and Growth Companies.
A22: Beta điều chỉnh cho startup (total beta = β / ρ) | B22: =B20/B21 -> 1.5006496
A23: Lợi suất thị trường kỳ vọng = Rf + ERP Việt Nam | B23: =SUM(B12,B16) -> 0.12718

Sheet Assumption
A1: Assumption | B1: ='Income Statement'!D2 -> 2025 | C1: =B1+1 -> 2026 | D1: =C1+1 -> 2027 | E1: =D1+1 -> 2028 | F1: =E1+1 -> 2029 | G1: =F1+1 -> 2030
A2: % Tăng trưởng doanh thu | B2: ='Income Statement'!D11/'Income Statement'!C11-1 -> 0.53731538 | C2: =Drivers!F40 -> 0.33918962 | D2: =Drivers!G40 -> 0.27911837 | E2: =Drivers!H40 -> 0.23277578 | F2: =Drivers!I40 -> 0.38709493 | G2: =Drivers!J40 -> 0.28448645
A3: GVHB/Doanh thu | B3: ='Income Statement'!D18/'Income Statement'!D11 -> 0.48965893 | C3: =Drivers!F84 -> 0.48244588 | D3: =Drivers!G84 -> 0.48470254 | E3: =Drivers!H84 -> 0.49330443 | F3: =Drivers!I84 -> 0.54852273 | G3: =Drivers!J84 -> 0.52640661
A4: Tổng CP hoạt động/Doanh thu | B4: ='Income Statement'!D61/'Income Statement'!D11 -> 0.4143787 | C4: =Drivers!F90 -> 0.39753447 | D4: =Drivers!G90 -> 0.38356396 | E4: =Drivers!H90 -> 0.37887349 | F4: =Drivers!I90 -> 0.37869519 | G4: =Drivers!J90 -> 0.35954615
A5: CP Tài chính/Doanh thu | B5: ='Income Statement'!D67/'Income Statement'!D11 -> 0.0029903761 | C5: =Drivers!F131 -> 0.0025168901 | D5: =Drivers!G131 -> 0.0019676757 | E5: =Drivers!H131 -> 0.021096134 | F5: =Drivers!I131 -> 0.02926702 | G5: =Drivers!J131 -> 0.020596082
A6: TSNH (ngoài tiền)/Doanh thu | B6: =('Balance Sheet'!F21-'Balance Sheet'!F6)/'Income Statement'!D11 -> 0.15961986 | C6: =SUM(Drivers!F106,Drivers!F108,Drivers!F110)/Drivers!F39 -> 0.16385016 | D6: =SUM(Drivers!G106,Drivers!G108,Drivers!G110)/Drivers!G39 -> 0.173963 | E6: =SUM(Drivers!H106,Drivers!H108,Drivers!H110)/Drivers!H39 -> 0.18573215 | F6: =SUM(Drivers!I106,Drivers!I108,Drivers!I110)/Drivers!I39 -> 0.2055825 | G6: =SUM(Drivers!J106,Drivers!J108,Drivers!J110)/Drivers!J39 -> 0.1994593
A7: Nợ ngắn hạn (ngoài vay)/Doanh thu | B7: =('Balance Sheet'!F55-'Balance Sheet'!F45)/'Income Statement'!D11 -> 0.0072083497 | C7: =SUM(Drivers!F112,Drivers!F114)/Drivers!F39 -> 0.0094535096 | D7: =SUM(Drivers!G112,Drivers!G114)/Drivers!G39 -> 0.010842683 | E7: =SUM(Drivers!H112,Drivers!H114)/Drivers!H39 -> 0.01317489 | F7: =SUM(Drivers!I112,Drivers!I114)/Drivers!I39 -> 0.01391296 | G7: =SUM(Drivers!J112,Drivers!J114)/Drivers!J39 -> 0.013590127
A8: Hàng tồn kho/TSNH ngoài tiền | B8: ='Balance Sheet'!F9/('Balance Sheet'!F21-'Balance Sheet'!F6) -> 0.49391451 | C8: =Drivers!F106/SUM(Drivers!F106,Drivers!F108,Drivers!F110) -> 0.4548979 | D8: =Drivers!G106/SUM(Drivers!G106,Drivers!G108,Drivers!G110) -> 0.42359023 | E8: =Drivers!H106/SUM(Drivers!H106,Drivers!H108,Drivers!H110) -> 0.40111133 | F8: =Drivers!I106/SUM(Drivers!I106,Drivers!I108,Drivers!I110) -> 0.40563141 | G8: =Drivers!J106/SUM(Drivers!J106,Drivers!J108,Drivers!J110) -> 0.38738488
A9: Khoản phải thu/TSNH ngoài tiền | B9: ='Balance Sheet'!F12/('Balance Sheet'!F21-'Balance Sheet'!F6) -> 0.23292842 | C9: =Drivers!F108/SUM(Drivers!F106,Drivers!F108,Drivers!F110) -> 0.30097662 | D9: =Drivers!G108/SUM(Drivers!G106,Drivers!G108,Drivers!G110) -> 0.34647582 | E9: =Drivers!H108/SUM(Drivers!H106,Drivers!H108,Drivers!H110) -> 0.38352476 | F9: =Drivers!I108/SUM(Drivers!I106,Drivers!I108,Drivers!I110) -> 0.3997995 | G9: =Drivers!J108/SUM(Drivers!J106,Drivers!J108,Drivers!J110) -> 0.41207295
A10: Khoản phải trả/Nợ NH ngoài vay | B10: ='Balance Sheet'!F38/('Balance Sheet'!F55-'Balance Sheet'!F45) -> 0.76923077 | C10: =Drivers!F112/SUM(Drivers!F112,Drivers!F114) -> 0.78843836 | D10: =Drivers!G112/SUM(Drivers!G112,Drivers!G114) -> 0.81554381 | E10: =Drivers!H112/SUM(Drivers!H112,Drivers!H114) -> 0.84819608 | F10: =Drivers!I112/SUM(Drivers!I112,Drivers!I114) -> 0.85624914 | G10: =Drivers!J112/SUM(Drivers!J112,Drivers!J114) -> 0.85283435
A11: CAPEX/Doanh thu | B11: ='Pro Forma'!B25/'Income Statement'!D11 -> 0.10693778 | C11: =Drivers!F94 -> 0.2 | D11: =Drivers!G94 -> 0.15 | E11: =Drivers!H94 -> 0.65 | F11: =Drivers!I94 -> 0.12 | G11: =Drivers!J94 -> 0.1
A13: Thuế suất thuế TNDN | B13: 0.2 | C13: Nguồn: Luật Thuế TNDN 67/2025/QH15 – thuế suất phổ thông 20%
A14: Tỷ lệ tăng trưởng vĩnh viễn | B14: 0.05 | C14: Lý do: tăng trưởng dài hạn danh nghĩa VND 5%: lạm phát mục tiêu ~4–4,5% cộng tăng trưởng thực thấp; thấp hơn GDP danh nghĩa VN (~10–12%) và thấp hơn Rf + tăng trưởng thực. Nguồn: NHNN, Quốc hội (mục tiêu CPI 2026 ~4,5%); Damodaran (2026). https://congbao.chinhphu.vn/van-ban/nghi-quyet-so-244-2025-qh15-46693.htm
A15: Tỷ lệ khấu hao | B15: 0.12
A16: Tỷ lệ chiết khấu WACC | B16: ='Discount rate'!E4 -> 0.14130984
A17: Lợi nhuận trên vốn đầu tư mới sau 2030 (RONIC) = ROIC 2030E | B17: =DCF!B39 -> 0.12311588
A19: Ghi chú: các tỷ lệ 2026E–2030E là kết quả của mô hình động lực ở sheet Drivers

Sheet Drivers
A1: GIẢ ĐỊNH CHI TIẾT & MÔ HÌNH ĐỘNG LỰC (DRIVERS) – AgriPack
A2: Đơn vị: nghìn đồng
A3: Kịch bản đang chạy (1 = Bear, 2 = Base, 3 = Bull) | C3: 2 | D3: =CHOOSE(C3,"Bear","Base","Bull") -> Base
A6: Chỉ tiêu | B6: Đơn vị / cơ sở | C6: 2023A | D6: 2024A | E6: 2025A | F6: 2026E | G6: 2027E | H6: 2028E | I6: 2029E | J6: 2030E | L6: Giả định
A7: năm (dùng cho công thức) | C7: 2023 | D7: 2024 | E7: 2025 | F7: 2026 | G7: 2027 | H7: 2028 | I7: 2029 | J7: 2030
A8: A. DOANH THU THEO PHÂN KHÚC (Sản lượng × Giá bán)
A9: A1. Bao bì F&B/FMCG (hộp, khay ép khuôn từ bã mía + vỏ trứng)
A10: Giá bán bình quân (ASP) | B10: nghìn đ/sản phẩm | E10: 2.5 | F10: =E10*(1+F11) -> 2.55 | G10: =F10*(1+G11) -> 2.601 | H10: =G10*(1+H11) -> 2.65302 | I10: =H10*(1+I11) -> 2.7060804 | J10: =I10*(1+J11) -> 2.760202 | L10: Lý do: giá 2025 lấy cận dưới khung giá hộp/khay 2.500–4.000đ/cái của nhóm vì doanh thu gồm cả khay nhỏ và đơn hàng sỉ; cao hơn hộp bã mía 500 ml bán lẻ 1.900–2.700đ nhờ ép khuôn theo mẫu. Nguồn: bảng chiến lược giá (Mục 1.2.2), bảng giá hộp 500 ml (Mục 1.1.1)
A11: Tăng giá bán bình quân | B11: %/năm | F11: =CHOOSE($C$3,$C$144,$D$144,$E$144) -> 0.02 | G11: =CHOOSE($C$3,$C$144,$D$144,$E$144) -> 0.02 | H11: =CHOOSE($C$3,$C$144,$D$144,$E$144) -> 0.02 | I11: =CHOOSE($C$3,$C$144,$D$144,$E$144) -> 0.02 | J11: =CHOOSE($C$3,$C$144,$D$144,$E$144) -> 0.02 | L11: Lý do: Base +2%/năm, thấp hơn CPI 8T/2026 (+4,45%) vì khách hàng B2B có sức mạnh đàm phán rất cao và bao bì nhựa rẻ hơn nhiều lần (Mục 3.1.2, 3.2.3); Bear +1%, Bull +2,5%. Nguồn: Cục Thống kê (2026); phân tích ngành của nhóm.
A12: Sản lượng quy đổi | B12: sản phẩm | C12: =C14/$E$10 -> 6022000 | D12: =D14/$E$10 -> 9635200 | E12: =E14/$E$10 -> 15223616 | F12: =E12*(1+F13) -> 20095173 | G12: =F12*(1+G13) -> 25118966 | H12: =G12*(1+H13) -> 30142760 | I12: =H12*(1+I13) -> 40692726 | J12: =I12*(1+J13) -> 50865907 | L12: Lịch sử = doanh thu / ASP 2025 (quy đổi, giả định giá không đổi 2023–25 – do BCTC không công bố sản lượng).
A13: Tăng trưởng sản lượng | B13: % | D13: =D12/C12-1 -> 0.6 | E13: =E12/D12-1 -> 0.58 | F13: =F150*CHOOSE($C$3,$C$143,$D$143,$E$143) -> 0.32 | G13: =G150*CHOOSE($C$3,$C$143,$D$143,$E$143) -> 0.25 | H13: =H150*CHOOSE($C$3,$C$143,$D$143,$E$143) -> 0.2 | I13: =I150*CHOOSE($C$3,$C$143,$D$143,$E$143) -> 0.35 | J13: =J150*CHOOSE($C$3,$C$143,$D$143,$E$143) -> 0.25 | L13: Lý do: sản lượng bị giới hạn bởi công suất: 2026 +32% nhờ máy ép bổ sung (CAPEX 20% DT); 2027 +25% khi khai thác tối đa nhà máy hiện hữu; 2028 +20% vì nhà máy mới đang xây (đầu tư lớn theo đề bài); 2029 +35% khi 2 dây chuyền mới chạy; 2030 +25%. Lịch sử +60% (2024), +58% (2025). Nguồn: BCTC 2023–2025; giả định của nhóm.
A14: Doanh thu F&B/FMCG | B14: nghìn đồng | C14: ='Income Statement'!B4 -> 15055000 | D14: ='Income Statement'!C4 -> 24088000 | E14: ='Income Statement'!D4 -> 38059040 | F14: =F12*F10 -> 51242691 | G14: =G12*G10 -> 65334432 | H14: =H12*H10 -> 79969344 | I14: =I12*I10 -> 1.1011779e+08 | J14: =J12*J10 -> 1.4040018e+08
A16: A2. Thiết kế & sản xuất khuôn theo mẫu
A17: Giá bình quân/bộ khuôn | B17: nghìn đ/bộ | E17: 20000 | F17: =E17*(1+F18) -> 20400 | G17: =F17*(1+G18) -> 20808 | H17: =G17*(1+H18) -> 21224.16 | I17: =H17*(1+I18) -> 21648.643 | J17: =I17*(1+J18) -> 22081.616 | L17: Lý do: ~20 triệu đồng/bộ khuôn, bằng giá tham chiếu khuôn ép bã mía/tre. Nguồn: bảng chiến lược giá (Mục 1.2.2).
A18: Tăng giá | B18: %/năm | F18: =F11 -> 0.02 | G18: =G11 -> 0.02 | H18: =H11 -> 0.02 | I18: =I11 -> 0.02 | J18: =J11 -> 0.02
A19: Số bộ khuôn bàn giao | B19: bộ | C19: =C21/$E$17 -> 151 | D19: =D21/$E$17 -> 211.4 | E19: =E21/$E$17 -> 294.903 | F19: =E19*(1+F20) -> 359.78166 | G19: =F19*(1+G20) -> 431.73799 | H19: =G19*(1+H20) -> 500.81607 | I19: =H19*(1+I20) -> 641.04457 | J19: =I19*(1+J20) -> 769.25348
A20: Tăng trưởng số bộ khuôn | B20: % | D20: =D19/C19-1 -> 0.4 | E20: =E19/D19-1 -> 0.395 | F20: =F151*CHOOSE($C$3,$C$143,$D$143,$E$143) -> 0.22 | G20: =G151*CHOOSE($C$3,$C$143,$D$143,$E$143) -> 0.2 | H20: =H151*CHOOSE($C$3,$C$143,$D$143,$E$143) -> 0.16 | I20: =I151*CHOOSE($C$3,$C$143,$D$143,$E$143) -> 0.28 | J20: =J151*CHOOSE($C$3,$C$143,$D$143,$E$143) -> 0.2 | L20: Lý do: số bộ khuôn gắn với số SKU/khách hàng mới; chậm lại năm 2028 khi nhà máy mới đang xây, tăng nhanh năm 2029 khi có công suất mới và mở thị trường miền Bắc. Lịch sử +40% (2024), +39,5% (2025). Nguồn: BCTC 2023–2025; giả định của nhóm.
A21: Doanh thu thiết kế & khuôn | B21: nghìn đồng | C21: ='Income Statement'!B5 -> 3020000 | D21: ='Income Statement'!C5 -> 4228000 | E21: ='Income Statement'!D5 -> 5898060 | F21: =F19*F17 -> 7339545.9 | G21: =G19*G17 -> 8983604.1 | H21: =H19*H17 -> 10629400 | I21: =I19*I17 -> 13877745 | J21: =J19*J17 -> 16986360
A23: A3. Đệm bảo vệ nội thất / thương mại điện tử
A24: Giá bình quân | B24: nghìn đ/m² | E24: 22.5 | F24: =E24*(1+F25) -> 22.8375 | G24: =F24*(1+G25) -> 23.180062 | H24: =G24*(1+H25) -> 23.527763 | I24: =H24*(1+I25) -> 23.88068 | J24: =I24*(1+J25) -> 24.23889 | L24: Lý do: trung điểm khung 15.000–30.000đ/m² của vật liệu đệm định hình (PE foam) mà sản phẩm thay thế. Nguồn: báo giá PE foam định hình trên thị trường (2026); https://mutxophabac.com/xop-dinh-hinh-nha-san-xuat-gia-re/
A25: Tăng giá | B25: %/năm | F25: =CHOOSE($C$3,$C$145,$D$145,$E$145) -> 0.015 | G25: =CHOOSE($C$3,$C$145,$D$145,$E$145) -> 0.015 | H25: =CHOOSE($C$3,$C$145,$D$145,$E$145) -> 0.015 | I25: =CHOOSE($C$3,$C$145,$D$145,$E$145) -> 0.015 | J25: =CHOOSE($C$3,$C$145,$D$145,$E$145) -> 0.015 | L25: Lý do: đệm bảo vệ cạnh tranh trực tiếp với EPE/PE foam giá rẻ (áp lực thay thế cao, Mục 3.2.6) nên chỉ tăng 1,5%/năm (Base); Bear 0,5%, Bull 2%. Nguồn: phân tích ngành của nhóm.
A26: Diện tích quy đổi | B26: m² | C26: =C28/$E$24 -> 67555.556 | D26: =D28/$E$24 -> 101333.33 | E26: =E28/$E$24 -> 121600 | F26: =E26*(1+F27) -> 158080 | G26: =F26*(1+G27) -> 205504 | H26: =G26*(1+H27) -> 263045.12 | I26: =H26*(1+I27) -> 368263.17 | J26: =I26*(1+J27) -> 486107.38
A27: Tăng trưởng diện tích | B27: % | D27: =D26/C26-1 -> 0.5 | E27: =E26/D26-1 -> 0.2 | F27: =F152*CHOOSE($C$3,$C$143,$D$143,$E$143) -> 0.3 | G27: =G152*CHOOSE($C$3,$C$143,$D$143,$E$143) -> 0.3 | H27: =H152*CHOOSE($C$3,$C$143,$D$143,$E$143) -> 0.28 | I27: =I152*CHOOSE($C$3,$C$143,$D$143,$E$143) -> 0.4 | J27: =J152*CHOOSE($C$3,$C$143,$D$143,$E$143) -> 0.32 | L27: Lý do: bám theo tăng trưởng TMĐT ~18%/năm và khách hàng nội thất xuất khẩu; năm 2029 +40% nhờ công suất mới. Nguồn: Mục 3.2.2; BCTC 2023–2025.
A28: Doanh thu nội thất/TMĐT | B28: nghìn đồng | C28: ='Income Statement'!B6 -> 1520000 | D28: ='Income Statement'!C6 -> 2280000 | E28: ='Income Statement'!D6 -> 2736000 | F28: =F26*F24 -> 3610152 | G28: =G26*G24 -> 4763595.6 | H28: =H26*H24 -> 6188863.4 | I28: =I26*I24 -> 8794374.8 | J28: =J26*J24 -> 11782703
A30: A4. Đệm bảo vệ thiết bị, linh kiện điện tử
A31: Giá bình quân | B31: nghìn đ/m² | E31: 40 | F31: =E31*(1+F32) -> 40.6 | G31: =F31*(1+G32) -> 41.209 | H31: =G31*(1+H32) -> 41.827135 | I31: =H31*(1+I32) -> 42.454542 | J31: =I31*(1+J32) -> 43.09136 | L31: Lý do: trung điểm khung 25.000–55.000đ/m² của khay EPE/EPE chống tĩnh điện mà sản phẩm thay thế. Nguồn: báo giá khay EPE trên thị trường (2026)
A32: Tăng giá | B32: %/năm | F32: =F25 -> 0.015 | G32: =G25 -> 0.015 | H32: =H25 -> 0.015 | I32: =I25 -> 0.015 | J32: =J25 -> 0.015
A33: Diện tích quy đổi | B33: m² | C33: =C35/$E$31 -> 0 | D33: =D35/$E$31 -> 14150 | E33: =E35/$E$31 -> 29715 | F33: =E33*(1+F34) -> 47544 | G33: =F33*(1+G34) -> 71316 | H33: =G33*(1+H34) -> 103408.2 | I33: =H33*(1+I34) -> 175793.94 | J33: =I33*(1+J34) -> 254901.21
A34: Tăng trưởng diện tích | B34: % | E34: =E33/D33-1 -> 1.1 | F34: =F153*CHOOSE($C$3,$C$143,$D$143,$E$143) -> 0.6 | G34: =G153*CHOOSE($C$3,$C$143,$D$143,$E$143) -> 0.5 | H34: =H153*CHOOSE($C$3,$C$143,$D$143,$E$143) -> 0.45 | I34: =I153*CHOOSE($C$3,$C$143,$D$143,$E$143) -> 0.7 | J34: =J153*CHOOSE($C$3,$C$143,$D$143,$E$143) -> 0.45 | L34: Lý do: nền nhỏ (1,2 tỷ đồng năm 2025); thay thế khay EPS/EPE cho khách hàng FDI điện tử khi chuỗi cung ứng xuất khẩu yêu cầu xanh hóa.
A35: Doanh thu điện tử | B35: nghìn đồng | C35: ='Income Statement'!B7 -> 0 | D35: ='Income Statement'!C7 -> 566000 | E35: ='Income Statement'!D7 -> 1188600 | F35: =F33*F31 -> 1930286.4 | G35: =G33*G31 -> 2938861 | H35: =H33*H31 -> 4325268.7 | I35: =I33*I31 -> 7463251.2 | J35: =J33*J31 -> 10984040
A37: Tổng doanh thu gộp | B37: nghìn đồng | C37: =SUM(C14,C21,C28,C35) -> 19595000 | D37: =SUM(D14,D21,D28,D35) -> 31162000 | E37: =SUM(E14,E21,E28,E35) -> 47881700 | F37: =SUM(F14,F21,F28,F35) -> 64122676 | G37: =SUM(G14,G21,G28,G35) -> 82020492 | H37: =SUM(H14,H21,H28,H35) -> 1.0111288e+08 | I37: =SUM(I14,I21,I28,I35) -> 1.4025316e+08 | J37: =SUM(J14,J21,J28,J35) -> 1.8015328e+08
A38: Khoản giảm trừ / doanh thu gộp | B38: % | C38: =-'Income Statement'!B9/C37 -> 0.008 | D38: =-'Income Statement'!C9/D37 -> 0.0075 | E38: =-'Income Statement'!D9/E37 -> 0.007 | F38: 0.007 | G38: 0.007 | H38: 0.007 | I38: 0.007 | J38: 0.007 | L38: Lý do: giữ mức 2025 (0,70% doanh thu gộp), xu hướng giảm từ 0,80% (2023). Nguồn: BCTC 2023–2025
A39: Doanh thu thuần | B39: nghìn đồng | C39: ='Income Statement'!B11 -> 19438240 | D39: ='Income Statement'!C11 -> 30928285 | E39: ='Income Statement'!D11 -> 47546528 | F39: =F37*(1-F38) -> 63673817 | G39: =G37*(1-G38) -> 81446349 | H39: =H37*(1-H38) -> 1.0040509e+08 | I39: =I37*(1-I38) -> 1.3927139e+08 | J39: =J37*(1-J38) -> 1.7889221e+08
A40: Tăng trưởng doanh thu thuần | B40: % | D40: =D39/C39-1 -> 0.59110521 | E40: =E39/D39-1 -> 0.53731538 | F40: =F39/E39-1 -> 0.33918962 | G40: =G39/F39-1 -> 0.27911837 | H40: =H39/G39-1 -> 0.23277578 | I40: =I39/H39-1 -> 0.38709493 | J40: =J39/I39-1 -> 0.28448645
A41: Tỷ trọng F&B/FMCG trong doanh thu gộp | B41: % | C41: =C14/C37 -> 0.76830824 | D41: =D14/D37 -> 0.77299275 | E41: =E14/E37 -> 0.79485565 | F41: =F14/F37 -> 0.79913527 | G41: =G14/G37 -> 0.79656229 | H41: =H14/H37 -> 0.79089179 | I41: =I14/I37 -> 0.78513588 | J41: =J14/J37 -> 0.77933733
A43: A5. Kiểm tra công suất (vòng quay tài sản) & thị phần ngầm định
A44: Nguyên giá TSCĐ bình quân | B44: nghìn đồng | C44: =SUM('Balance Sheet'!C27:C29,C97)/2 -> 17289500 | D44: =SUM(C97:D97)/2 -> 22946800 | E44: =SUM(D97:E97)/2 -> 28641860 | F44: =SUM(E97:F97)/2 -> 37551502 | G44: =SUM(F97:G97)/2 -> 50027360 | H44: =SUM(G97:H97)/2 -> 88767489 | I44: =SUM(H97:I97)/2 -> 1.2975543e+08 | J44: =SUM(I97:J97)/2 -> 1.4705632e+08
A45: Vòng quay nguyên giá TSCĐ (DT thuần / NG bình quân) | B45: lần | C45: =C39/C44 -> 1.1242801 | D45: =D39/D44 -> 1.3478256 | E45: =E39/E44 -> 1.6600363 | F45: =F39/F44 -> 1.6956397 | G45: =G39/G44 -> 1.6280361 | H45: =H39/H44 -> 1.131102 | I45: =I39/I44 -> 1.0733377 | J45: =J39/J44 -> 1.2164877 | L45: Vòng quay 2025 = 1,66x. Nếu vòng quay dự phóng < 2025 → còn công suất trống (không cần CAPEX lớn tiếp theo); nếu >> 2025 → dự báo vượt công suất.
A46: Tỷ giá USD/VND bình quân | B46: VND/USD | E46: 26000 | F46: 26300 | G46: =F46*(1+0.02) -> 26826 | H46: =G46*(1+0.02) -> 27362.52 | I46: =H46*(1+0.02) -> 27909.77 | J46: =I46*(1+0.02) -> 28467.966 | L46: Lý do: dùng để quy đổi doanh thu sang USD khi so với TAM/SAM của IMARC. 2025: 26.000; 2026: 26.300; sau đó VND mất giá 2%/năm. Nguồn: Vietcombank (tỷ giá bán ra); MBS Research dự báo 26.800–27.000 cuối 2026 (Mục 3.1.4).
A47: Doanh thu F&B/FMCG quy USD | B47: triệu USD | E47: =E14*1000/E46/1000000 -> 1.4638092 | F47: =F14*1000/F46/1000000 -> 1.9483913 | G47: =G14*1000/G46/1000000 -> 2.4354891 | H47: =H14*1000/H46/1000000 -> 2.922587 | I47: =I14*1000/I46/1000000 -> 3.9454924 | J47: =J14*1000/J46/1000000 -> 4.9318655
A48: SAM: bao bì dùng một lần phân hủy sinh học ngành F&B VN | B48: triệu USD | E48: 33.93 | F48: =E48*(1+0.0473) -> 35.534889 | G48: =F48*(1+0.0473) -> 37.215689 | H48: =G48*(1+0.0473) -> 38.975991 | I48: =H48*(1+0.0473) -> 40.819556 | J48: =I48*(1+0.0473) -> 42.750321 | L48: Lý do: SAM = bao bì dùng một lần phân hủy sinh học cho ngành dịch vụ ăn uống VN, 33,93 triệu USD (2025), CAGR 4,73%. Nguồn: IMARC Group (2025), Mục 1.2.1.
A49: Thị phần ngầm định trong SAM | B49: % | E49: =E47/E48 -> 0.043142035 | F49: =F47/F48 -> 0.054830376 | G49: =G47/G48 -> 0.065442537 | H49: =H47/H48 -> 0.074984288 | I49: =I47/I48 -> 0.096656917 | J49: =J47/J48 -> 0.11536441 | L49: Nếu thị phần dự phóng vượt 15% SAM, giả định này hơi cao vì quy mô SAM của IMARC hiện khá hẹp, chủ yếu tập trung vào nhóm sản phẩm dùng một lần trong ngành dịch vụ ăn uống. Do đó, để mức tăng trưởng này hợp lý hơn, AgriPack cần mở rộng sang các phân khúc khác như bao bì FMCG, thương mại điện tử, xuất khẩu và các sản phẩm thay thế nhựa dùng một lần trong dài hạn.
A50: TAM: thị trường bao bì xanh VN | B50: triệu USD | E50: 1129.79 | F50: =E50*(1+0.0415) -> 1176.6763 | G50: =F50*(1+0.0415) -> 1225.5084 | H50: =G50*(1+0.0415) -> 1276.3669 | I50: =H50*(1+0.0415) -> 1329.3362 | J50: =I50*(1+0.0415) -> 1384.5036 | L50: Lý do: TAM = thị trường bao bì xanh VN 1.129,79 triệu USD (2025), CAGR 4,15% (2026–2034). Nguồn: IMARC Group (2025), Mục 1.2.1.
A51: Thị phần ngầm định trong TAM (toàn bộ doanh thu) | B51: % | E51: =(E39*1000/E46/1000000)/E50 -> 0.0016186306 | F51: =(F39*1000/F46/1000000)/F50 -> 0.0020575393 | G51: =(G39*1000/G46/1000000)/G50 -> 0.0024774188 | H51: =(H39*1000/H46/1000000)/H50 -> 0.0028749088 | I51: =(I39*1000/I46/1000000)/I50 -> 0.0037537972 | J51: =(J39*1000/J46/1000000)/J50 -> 0.0045387984
A53: B. GIÁ VỐN & CHI PHÍ HOẠT ĐỘNG
A54: Giá vốn hàng bán
A55: Chi phí biến đổi (NVL, nhân công trực tiếp) / DT thuần | B55: % | C55: ='Income Statement'!B14/C39 -> 0.255 | D55: ='Income Statement'!C14/D39 -> 0.25 | E55: ='Income Statement'!D14/E39 -> 0.245 | F55: =F154+CHOOSE($C$3,$C$146,$D$146,$E$146) -> 0.25 | G55: =G154+CHOOSE($C$3,$C$146,$D$146,$E$146) -> 0.25 | H55: =H154+CHOOSE($C$3,$C$146,$D$146,$E$146) -> 0.255 | I55: =I154+CHOOSE($C$3,$C$146,$D$146,$E$146) -> 0.27 | J55: =J154+CHOOSE($C$3,$C$146,$D$146,$E$146) -> 0.265 | L55: Lý do: 25,5% → 25,0% → 24,5% (2023–25). Tăng lên 25,0–27,0% vì lạm phát tác động chủ yếu vào chi phí thu gom, vận chuyển, sấy và năng lượng (Mục 3.1.2), bã mía bị cạnh tranh bởi lò hơi nhà máy đường và các nhà sản xuất bao bì sợi trước mốc dừng nhựa dùng một lần 2030; năm đầu chạy nhà máy mới hao hụt cao. Nguồn: BCTC 2023–2025; Cục Thống kê (CPI 8T/2026 +4,45%, nhóm nhà ở-điện-nước +6,71%).
A56: Chi phí biến đổi | B56: nghìn đồng | C56: ='Income Statement'!B14 -> 4956751.2 | D56: ='Income Statement'!C14 -> 7732071.2 | E56: ='Income Statement'!D14 -> 11648899 | F56: =F39*F55 -> 15918454 | G56: =G39*G55 -> 20361587 | H56: =H39*H55 -> 25603297 | I56: =I39*I55 -> 37603274 | J56: =J39*J55 -> 47406435
A57: Chi phí cố định sản xuất | B57: nghìn đồng | C57: ='Income Statement'!B15 -> 1055000 | D57: ='Income Statement'!C15 -> 1160500 | E57: ='Income Statement'!D15 -> 1276550 | F57: =E57*(1+F58)+F59 -> 1404205 | G57: =F57*(1+G58)+G59 -> 1544625.5 | H57: =G57*(1+H58)+H59 -> 1699088.1 | I57: =H57*(1+I58)+I59 -> 2768996.9 | J57: =I57*(1+J58)+J59 -> 3045896.5
A58: Tăng chi phí cố định sản xuất (nền) | B58: % | D58: =D57/C57-1 -> 0.1 | E58: =E57/D57-1 -> 0.1 | F58: 0.1 | G58: 0.1 | H58: 0.1 | I58: 0.1 | J58: 0.1 | L58: Lý do: giữ mức tăng 10%/năm như 2024–2025. Nguồn: BCTC 2023–2025
A59: Chi phí cố định tăng thêm của nhà máy mới | B59: nghìn đồng | F59: =IF(F$7=$C$156+1,$C$160,0) -> 0 | G59: =IF(G$7=$C$156+1,$C$160,0) -> 0 | H59: =IF(H$7=$C$156+1,$C$160,0) -> 0 | I59: =IF(I$7=$C$156+1,$C$160,0) -> 900000 | J59: =IF(J$7=$C$156+1,$C$160,0) -> 0 | L59: Lý do: bước nhảy chi phí cố định (phòng QC, bảo trì, quản đốc) 0,9 tỷ đồng/năm khi 2 nhà máy mới vận hành. Nguồn: giả định của nhóm.
A60: Giá vốn theo BCTC gốc (NVL, nhân công theo sản lượng, chi phí cố định SX) | B60: nghìn đồng | C60: =SUM(C56:C57) -> 6011751.2 | D60: =SUM(D56:D57) -> 8892571.2 | E60: =SUM(E56:E57) -> 12925449 | F60: =SUM(F56:F57) -> 17322659 | G60: =SUM(G56:G57) -> 21906213 | H60: =SUM(H56:H57) -> 27302385 | I60: =SUM(I56:I57) -> 40372271 | J60: =SUM(J56:J57) -> 50452332 | L60: Theo tính chất, chưa gồm tiền lương và khấu hao. Là cơ sở tính số ngày tồn kho/phải trả (DIO, DPO) như BCTC 2023–2025.
A61: Chi phí hoạt động
A62: Chi phí nhân sự / DT thuần | B62: % | C62: ='Income Statement'!B53/C39 -> 0.35970335 | D62: ='Income Statement'!C53/D39 -> 0.24867852 | E62: ='Income Statement'!D53/E39 -> 0.22646617 | F62: =F155+CHOOSE($C$3,$C$147,$D$147,$E$147) -> 0.225 | G62: =G155+CHOOSE($C$3,$C$147,$D$147,$E$147) -> 0.225 | H62: =H155+CHOOSE($C$3,$C$147,$D$147,$E$147) -> 0.23 | I62: =I155+CHOOSE($C$3,$C$147,$D$147,$E$147) -> 0.235 | J62: =J155+CHOOSE($C$3,$C$147,$D$147,$E$147) -> 0.23 | L62: Lý do: 36,0% → 24,9% → 22,6% (2023–25). Giảm chậm lại (22,5–23,5%) vì lương tối thiểu vùng tăng 7,2% từ 01/01/2026 và nhà máy mới phải tuyển trước khi đạt công suất. Nguồn: BCTC 2023–2025; Nghị định 293/2025/NĐ-CP.
A63: Chi phí nhân sự (tiền lương) | B63: nghìn đồng | C63: ='Income Statement'!B53 -> 6992000 | D63: ='Income Statement'!C53 -> 7691200 | E63: ='Income Statement'!D53 -> 10767680 | F63: =F39*F62 -> 14326609 | G63: =G39*G62 -> 18325429 | H63: =H39*H62 -> 23093170 | I63: =I39*I62 -> 32728776 | J63: =J39*J62 -> 41145208
A64: Hỗ trợ tiền ăn / tiền lương | B64: % | C64: ='Income Statement'!B40/'Income Statement'!B53 -> 0.30749428 | D64: ='Income Statement'!C40/'Income Statement'!C53 -> 0.3354483 | E64: ='Income Statement'!D40/'Income Statement'!D53 -> 0.28752712 | F64: 0.28 | G64: 0.28 | H64: 0.28 | I64: 0.28 | J64: 0.28 | L64: Lý do: giữ ~mức 2025 (28,8% quỹ lương). Nguồn: BCTC 2023–2025.
A65: Hỗ trợ tiền ăn CNV | B65: nghìn đồng | C65: ='Income Statement'!B40 -> 2150000 | D65: ='Income Statement'!C40 -> 2580000 | E65: ='Income Statement'!D40 -> 3096000 | F65: =F63*F64 -> 4011450.5 | G65: =G63*G64 -> 5131120 | H65: =H63*H64 -> 6466087.6 | I65: =I63*I64 -> 9164057.2 | J65: =J63*J64 -> 11520658
A66: Tăng chi phí thuê mặt bằng | B66: % | D66: =D67/C67-1 -> 0.35 | E66: =E67/D67-1 -> 0.41 | F66: =IF(F$7=$C$156+1,$C$163,IF(F$7=$C$156,$C$162,IF(F$7=2026,$C$164,$C$161))) -> 0.12 | G66: =IF(G$7=$C$156+1,$C$163,IF(G$7=$C$156,$C$162,IF(G$7=2026,$C$164,$C$161))) -> 0.12 | H66: =IF(H$7=$C$156+1,$C$163,IF(H$7=$C$156,$C$162,IF(H$7=2026,$C$164,$C$161))) -> 0.15 | I66: =IF(I$7=$C$156+1,$C$163,IF(I$7=$C$156,$C$162,IF(I$7=2026,$C$164,$C$161))) -> 0.3 | J66: =IF(J$7=$C$156+1,$C$163,IF(J$7=$C$156,$C$162,IF(J$7=2026,$C$164,$C$161))) -> 0.12 | L66: Lý do: tiền thuê tăng 35%, 41% (2024–25) khi thuê thêm kho, xưởng. Sau đó tăng chậm (12%/năm) vì nhà máy mới là tài sản tự đầu tư; năm sau đầu tư lớn +30% do thuê kho vệ tinh gần khách hàng. Nguồn: BCTC 2023–2025; giả định của nhóm.
A67: Thuê mặt bằng | B67: nghìn đồng | C67: ='Income Statement'!B24 -> 3977000 | D67: ='Income Statement'!C24 -> 5368950 | E67: ='Income Statement'!D24 -> 7570219.5 | F67: =E67*(1+F66) -> 8478645.8 | G67: =F67*(1+G66) -> 9496083.3 | H67: =G67*(1+H66) -> 10920496 | I67: =H67*(1+I66) -> 14196645 | J67: =I67*(1+J66) -> 15900242
A68: Sửa chữa, bảo dưỡng / DT | B68: % | C68: ='Income Statement'!B26/C39 -> 0.048872737 | D68: ='Income Statement'!C26/D39 -> 0.052217574 | E68: ='Income Statement'!D26/E39 -> 0.043817079 | F68: 0.044 | G68: 0.044 | H68: 0.044 | I68: 0.044 | J68: 0.044 | L68: Lý do: giữ ~mức 2025 (4,4% DT; 2023–24: 4,9%, 5,2%). Nguồn: BCTC 2023–2025.
A69: Sửa chữa, bảo dưỡng | B69: nghìn đồng | C69: ='Income Statement'!B26 -> 950000 | D69: ='Income Statement'!C26 -> 1615000 | E69: ='Income Statement'!D26 -> 2083350 | F69: =F39*F68 -> 2801647.9 | G69: =G39*G68 -> 3583639.4 | H69: =H39*H68 -> 4417823.8 | I69: =I39*I68 -> 6127941 | J69: =J39*J68 -> 7871257.2
A70: Điện, nước, dịch vụ chung / DT | B70: % | C70: ='Income Statement'!B28/C39 -> 0.061733984 | D70: ='Income Statement'!C28/D39 -> 0.058199153 | E70: ='Income Statement'!D28/E39 -> 0.047322067 | F70: 0.05 | G70: 0.05 | H70: 0.05 | I70: 0.05 | J70: 0.05 | L70: Lý do: 6,2% → 5,8% → 4,7% (2023–25). Nâng lên 5,0% vì sấy, ép nhiệt tốn điện và giá bán lẻ điện bình quân tăng 4,8% ngày 11/10/2024 và 4,8% ngày 10/5/2025 (2.204,07 đ/kWh). Nguồn: BCTC 2023–2025; Quyết định 1279/QĐ-BCT (2025); Mục 3.1.2.
A71: Điện, nước, dịch vụ chung | B71: nghìn đồng | C71: ='Income Statement'!B28 -> 1200000 | D71: ='Income Statement'!C28 -> 1800000 | E71: ='Income Statement'!D28 -> 2250000 | F71: =F39*F70 -> 3183690.8 | G71: =G39*G70 -> 4072317.4 | H71: =H39*H70 -> 5020254.3 | I71: =I39*I70 -> 6963569.3 | J71: =J39*J70 -> 8944610.5
A72: Marketing / DT | B72: % | C72: ='Income Statement'!B48/C39 -> 0.047329388 | D72: ='Income Statement'!C48/D39 -> 0.031233546 | E72: ='Income Statement'!D48/E39 -> 0.024380329 | F72: 0.028 | G72: 0.03 | H72: 0.03 | I72: 0.03 | J72: 0.028 | L72: Lý do: 4,7% → 3,1% → 2,4% (2023–25). Tăng lại 2,8–3,0% khi mở rộng ra miền Bắc và khách hàng FDI (hội chợ, mẫu thử). Nguồn: BCTC 2023–2025; Mục 1.2.1.
A73: Marketing | B73: nghìn đồng | C73: ='Income Statement'!B48 -> 920000 | D73: ='Income Statement'!C48 -> 966000 | E73: ='Income Statement'!D48 -> 1159200 | F73: =F39*F72 -> 1782866.9 | G73: =G39*G72 -> 2443390.5 | H73: =H39*H72 -> 3012152.6 | I73: =I39*I72 -> 4178141.6 | J73: =J39*J72 -> 5008981.9
A74: Kiểm nghiệm, chứng nhận & R&D vật liệu / DT | B74: % | C74: 0 | D74: 0 | E74: 0 | F74: 0.006 | G74: 0.006 | H74: 0.006 | I74: 0.006 | J74: 0.006 | L74: Lý do: dòng chi phí mới 0,6% DT cho kiểm nghiệm bao bì tiếp xúc trực tiếp với thực phẩm, chứng nhận phân hủy (BPI, OK compost) và R&D lớp chống thấm không PFAS. Nguồn: Thông tư 27/2026/TT-BYT (hiệu lực 01/7/2026); Mục 3.1.6.1
A75: Kiểm nghiệm, chứng nhận & R&D | B75: nghìn đồng | C75: 0 | D75: 0 | E75: 0 | F75: =F39*F74 -> 382042.9 | G75: =G39*G74 -> 488678.09 | H75: =H39*H74 -> 602430.52 | I75: =I39*I74 -> 835628.32 | J75: =J39*J74 -> 1073353.3
A76: Chi phí hoạt động theo tính chất (tiền lương + chi phí khác, không gồm khấu hao) | B76: nghìn đồng | C76: =SUM(C63,C65,C67,C69,C71,C73,C75) -> 16189000 | D76: =SUM(D63,D65,D67,D69,D71,D73,D75) -> 20021150 | E76: =SUM(E63,E65,E67,E69,E71,E73,E75) -> 26926450 | F76: =SUM(F63,F65,F67,F69,F71,F73,F75) -> 34966954 | G76: =SUM(G63,G65,G67,G69,G71,G73,G75) -> 43540657 | H76: =SUM(H63,H65,H67,H69,H71,H73,H75) -> 53532415 | I76: =SUM(I63,I65,I67,I69,I71,I73,I75) -> 74194758 | J76: =SUM(J63,J65,J67,J69,J71,J73,J75) -> 91464311
A77: EBITDA | B77: nghìn đồng | C77: =C39-C60-C76 -> -2762511.2 | D77: =D39-D60-D76 -> 2014563.8 | E77: =E39-E60-E76 -> 7694629.2 | F77: =F39-F60-F76 -> 11384204 | G77: =G39-G60-G76 -> 15999479 | H77: =H39-H60-H76 -> 19570287 | I77: =I39-I60-I76 -> 24704357 | J77: =J39-J60-J76 -> 36975566
A78: Biên EBITDA | B78: % | C78: =C77/C39 -> -0.14211735 | D78: =D77/D39 -> 0.065136614 | E78: =E77/E39 -> 0.16183367 | F78: =F77/F39 -> 0.17878941 | G78: =G77/G39 -> 0.19644194 | H78: =H77/H39 -> 0.1949133 | I78: =I77/I39 -> 0.17738286 | J78: =J77/J39 -> 0.20669187
A80: B2. BCKQKD theo chức năng
A81: Tiền lương bộ phận sản xuất (phân bổ vào giá vốn) | B81: nghìn đồng | C81: =C63*$C$167 -> 4894400 | D81: =D63*$C$167 -> 5383840 | E81: =E63*$C$167 -> 7537376 | F81: =F63*$C$167 -> 10028626 | G81: =G63*$C$167 -> 12827800 | H81: =H63*$C$167 -> 16165219 | I81: =I63*$C$167 -> 22910143 | J81: =J63*$C$167 -> 28801646
A82: Khấu hao TSCĐ sản xuất (phân bổ vào giá vốn) | B82: nghìn đồng | C82: =C99*$C$168 -> 1288980 | D82: =D99*$C$168 -> 2137752 | E82: =E99*$C$168 -> 2818756.8 | F82: =F99*$C$168 -> 3367885 | G82: =G99*$C$168 -> 4743239.4 | H82: =H99*$C$168 -> 6062670.3 | I82: =I99*$C$168 -> 13111107 | J82: =J99*$C$168 -> 14916065
A83: Tổng giá vốn hàng bán (theo chức năng) | B83: nghìn đồng | C83: =SUM(C60,C81,C82) -> 12195131 | D83: =SUM(D60,D81,D82) -> 16414163 | E83: =SUM(E60,E81,E82) -> 23281582 | F83: =SUM(F60,F81,F82) -> 30719170 | G83: =SUM(G60,G81,G82) -> 39477252 | H83: =SUM(H60,H81,H82) -> 49530274 | I83: =SUM(I60,I81,I82) -> 76393522 | J83: =SUM(J60,J81,J82) -> 94170042
A84: GVHB / DT thuần | B84: % | C84: =C83/C39 -> 0.62737836 | D84: =D83/D39 -> 0.53071689 | E84: =E83/E39 -> 0.48965893 | F84: =F83/F39 -> 0.48244588 | G84: =G83/G39 -> 0.48470254 | H84: =H83/H39 -> 0.49330443 | I84: =I83/I39 -> 0.54852273 | J84: =J83/J39 -> 0.52640661
A85: Biên lợi nhuận gộp (sau phân bổ tiền lương và khấu hao) | B85: % | C85: =1-C84 -> 0.37262164 | D85: =1-D84 -> 0.46928311 | E85: =1-E84 -> 0.51034107 | F85: =1-F84 -> 0.51755412 | G85: =1-G84 -> 0.51529746 | H85: =1-H84 -> 0.50669557 | I85: =1-I84 -> 0.45147727 | J85: =1-J84 -> 0.47359339 | L85: BCTC gốc hạch toán toàn bộ tiền lương và khấu hao ngoài giá vốn nên biên gộp 69–73%. Mô hình phân bổ 70% tiền lương (công nhân, quản đốc, QC) và 90% khấu hao (máy ép, sấy, nhà xưởng) vào giá vốn theo đặc thù nhà máy sản xuất.
A86: Biên gộp theo BCTC gốc (tham khảo, chưa phân bổ) | B86: % | C86: =1-C60/C39 -> 0.69072554 | D86: =1-D60/D39 -> 0.71247771 | E86: =1-E60/E39 -> 0.72815156 | F86: =1-F60/F39 -> 0.7279469 | G86: =1-G60/G39 -> 0.73103506 | H86: =1-H60/H39 -> 0.72807767 | I86: =1-I60/I39 -> 0.71011798 | J86: =1-J60/J39 -> 0.71797357
A87: Tiền lương bộ phận bán hàng & quản lý | B87: nghìn đồng | C87: =C63*(1-$C$167) -> 2097600 | D87: =D63*(1-$C$167) -> 2307360 | E87: =E63*(1-$C$167) -> 3230304 | F87: =F63*(1-$C$167) -> 4297982.6 | G87: =G63*(1-$C$167) -> 5497628.6 | H87: =H63*(1-$C$167) -> 6927951 | I87: =I63*(1-$C$167) -> 9818632.7 | J87: =J63*(1-$C$167) -> 12343562
A88: Khấu hao TSCĐ bộ phận bán hàng & quản lý | B88: nghìn đồng | C88: =C99*(1-$C$168) -> 143220 | D88: =D99*(1-$C$168) -> 237528 | E88: =E99*(1-$C$168) -> 313195.2 | F88: =F99*(1-$C$168) -> 374209.44 | G88: =G99*(1-$C$168) -> 527026.6 | H88: =H99*(1-$C$168) -> 673630.03 | I88: =I99*(1-$C$168) -> 1456789.7 | J88: =J99*(1-$C$168) -> 1657340.5
A89: Tổng chi phí bán hàng & QLDN (theo chức năng) | B89: nghìn đồng | C89: =SUM(C87,C65,C67,C69,C71,C73,C75,C88) -> 11437820 | D89: =SUM(D87,D65,D67,D69,D71,D73,D75,D88) -> 14874838 | E89: =SUM(E87,E65,E67,E69,E71,E73,E75,E88) -> 19702269 | F89: =SUM(F87,F65,F67,F69,F71,F73,F75,F88) -> 25312537 | G89: =SUM(G87,G65,G67,G69,G71,G73,G75,G88) -> 31239884 | H89: =SUM(H87,H65,H67,H69,H71,H73,H75,H88) -> 38040826 | I89: =SUM(I87,I65,I67,I69,I71,I73,I75,I88) -> 52741404 | J89: =SUM(J87,J65,J67,J69,J71,J73,J75,J88) -> 64320006
A90: CPBH & QLDN / DT thuần | B90: % | C90: =C89/C39 -> 0.5884185 | D90: =D89/D39 -> 0.4809461 | E90: =E89/E39 -> 0.4143787 | F90: =F89/F39 -> 0.39753447 | G90: =G89/G39 -> 0.38356396 | H90: =H89/H39 -> 0.37887349 | I90: =I89/I39 -> 0.37869519 | J90: =J89/J39 -> 0.35954615
A91: EBIT = DT thuần − GVHB − CPBH & QLDN (= EBITDA − khấu hao) | B91: nghìn đồng | C91: =C39-C83-C89 -> -4194711.2 | D91: =D39-D83-D89 -> -360716.25 | E91: =E39-E83-E89 -> 4562677.2 | F91: =F39-F83-F89 -> 7642109.6 | G91: =G39-G83-G89 -> 10729213 | H91: =H39-H83-H89 -> 12833987 | I91: =I39-I83-I89 -> 10136460 | J91: =J39-J83-J89 -> 20402161
A93: C. CAPEX, TÀI SẢN CỐ ĐỊNH & KHẤU HAO
A94: CAPEX / DT thuần (tỷ lệ tái đầu tư) | B94: % | C94: =C96/C39 -> 0.25768794 | D94: =D96/D39 -> 0.2038781 | E94: =E96/E39 -> 0.10693778 | F94: =IF(F$7=$C$156,$C$158,IF(F$7=$C$156+1,$C$159,F95)) -> 0.2 | G94: =IF(G$7=$C$156,$C$158,IF(G$7=$C$156+1,$C$159,G95)) -> 0.15 | H94: =IF(H$7=$C$156,$C$158,IF(H$7=$C$156+1,$C$159,H95)) -> 0.65 | I94: =IF(I$7=$C$156,$C$158,IF(I$7=$C$156+1,$C$159,I95)) -> 0.12 | J94: =IF(J$7=$C$156,$C$158,IF(J$7=$C$156+1,$C$159,J95)) -> 0.1 | L94: Lý do: tỷ lệ tái đầu tư = CAPEX/DT từng năm: 2026 20% (máy ép, xe tải, kho), 2027 15% (mở rộng nhà máy hiện hữu), 2028 65% (đầu tư lớn theo đề bài), 2029 12% (hoàn thiện, chạy thử), 2030 10%. Ngành: trung vị CAPEX/DT của 16 DN bao bì niêm yết 2023–25 là 3,1%, tứ phân vị trên 8,3%, DN đang mở rộng 13–30% (Fig. A10).
A95: Tỷ lệ CAPEX năm thường | B95: % | F95: 0.2 | G95: 0.15 | H95: 0.1 | I95: 0.1 | J95: 0.1 | L95: Lý do: 2026: 20% (mức mặc định của file mẫu, tương đương 2024 là 20,4%) cho máy ép, xe tải, kho; sau mở rộng 10% ≈ khấu hao/DT (duy trì + nâng cấp). Nguồn: file Excel mẫu; BCTC 2023–2025; FiinX (Fig. A10).
A96: CAPEX | B96: nghìn đồng | C96: =SUM('Balance Sheet'!D27:D29)-SUM('Balance Sheet'!C27:C29) -> 5009000 | D96: =SUM('Balance Sheet'!E27:E29)-SUM('Balance Sheet'!D27:D29) -> 6305600 | E96: =SUM('Balance Sheet'!F27:F29)-SUM('Balance Sheet'!E27:E29) -> 5084520 | F96: =F39*F94 -> 12734763 | G96: =G39*G94 -> 12216952 | H96: =H39*H94 -> 65263306 | I96: =I39*I94 -> 16712566 | J96: =J39*J94 -> 17889221
A97: Nguyên giá TSCĐ cuối kỳ | B97: nghìn đồng | C97: =SUM('Balance Sheet'!D27:D29) -> 19794000 | D97: =SUM('Balance Sheet'!E27:E29) -> 26099600 | E97: =SUM('Balance Sheet'!F27:F29) -> 31184120 | F97: =SUM(E97,F96) -> 43918883 | G97: =SUM(F97,G96) -> 56135836 | H97: =SUM(G97,H96) -> 1.2139914e+08 | I97: =SUM(H97,I96) -> 1.3811171e+08 | J97: =SUM(I97,J96) -> 1.5600093e+08
A98: Tỷ lệ khấu hao (% nguyên giá đầu kỳ) | B98: % | D98: =D99/C97 -> 0.12 | E98: =E99/D97 -> 0.12 | F98: =Assumption!$B$15 -> 0.12 | G98: =Assumption!$B$15 -> 0.12 | H98: =Assumption!$B$15 -> 0.12 | I98: =Assumption!$B$15 -> 0.12 | J98: =Assumption!$B$15 -> 0.12 | L98: Lý do: 12% nguyên giá đầu kỳ, khớp số liệu 2024–2025. Nguồn: file Excel mẫu (Assumption!D17); BCTC 2024–2025.
A99: Khấu hao | B99: nghìn đồng | C99: ='Income Statement'!B69 -> 1432200 | D99: ='Income Statement'!C69 -> 2375280 | E99: ='Income Statement'!D69 -> 3131952 | F99: =E97*F98 -> 3742094.4 | G99: =F97*G98 -> 5270266 | H99: =G97*H98 -> 6736300.3 | I99: =H97*I98 -> 14567897 | J99: =I97*J98 -> 16573405
A100: Khấu hao lũy kế | B100: nghìn đồng | C100: ='Balance Sheet'!D24 -> 4282200 | D100: ='Balance Sheet'!E24 -> 6657480 | E100: ='Balance Sheet'!F24 -> 9789432 | F100: =SUM(E100,F99) -> 13531526 | G100: =SUM(F100,G99) -> 18801792 | H100: =SUM(G100,H99) -> 25538093 | I100: =SUM(H100,I99) -> 40105990 | J100: =SUM(I100,J99) -> 56679395
A101: Giá trị còn lại TSCĐ | B101: nghìn đồng | C101: =C97-C100 -> 15511800 | D101: =D97-D100 -> 19442120 | E101: =E97-E100 -> 21394688 | F101: =F97-F100 -> 30387357 | G101: =G97-G100 -> 37334043 | H101: =H97-H100 -> 95861049 | I101: =I97-I100 -> 98005719 | J101: =J97-J100 -> 99321535
A102: Khấu hao / DT | B102: % | C102: =C99/C39 -> 0.07367951 | D102: =D99/D39 -> 0.076799603 | E102: =E99/E39 -> 0.065871308 | F102: =F99/F39 -> 0.058769751 | G102: =G99/G39 -> 0.064708438 | H102: =H99/H39 -> 0.067091225 | I102: =I99/I39 -> 0.10460079 | J102: =J99/J39 -> 0.092644644
A104: D. VỐN LƯU ĐỘNG
A105: Số ngày tồn kho (DIO, theo giá vốn chưa gồm lương, khấu hao) | B105: ngày | C105: ='Balance Sheet'!D9/C60*365 -> 151.72534 | D105: ='Balance Sheet'!E9/D60*365 -> 123.08723 | E105: ='Balance Sheet'!F9/E60*365 -> 105.85338 | F105: 100 | G105: 100 | H105: 100 | I105: 105 | J105: 100 | L105: Lý do: 152 → 123 → 106 ngày (2023–25), cao do tích trữ bã mía theo vụ ép (khoảng tháng 11–4). Giữ ~100 ngày; 2029 tăng lên 105 ngày để tích trữ cho 2 dây chuyền mới.
A106: Hàng tồn kho | B106: nghìn đồng | C106: ='Balance Sheet'!D9 -> 2499000 | D106: ='Balance Sheet'!E9 -> 2998800 | E106: ='Balance Sheet'!F9 -> 3748500 | F106: =F60*F105/365 -> 4745934 | G106: =G60*G105/365 -> 6001702.1 | H106: =H60*H105/365 -> 7480105.5 | I106: =I60*I105/365 -> 11613941 | J106: =J60*J105/365 -> 13822557
A107: Số ngày phải thu (DSO, theo DT) | B107: ngày | C107: ='Balance Sheet'!D12/C39*365 -> 23.659549 | D107: ='Balance Sheet'!E12/D39*365 -> 18.141258 | E107: ='Balance Sheet'!F12/E39*365 -> 13.570701 | F107: 18 | G107: 22 | H107: 26 | I107: 30 | J107: 30 | L107: Lý do: 24 → 18 → 14 ngày (2023–25), rất ngắn cho B2B vì nhiều khách F&B nhỏ trả ngay. Khi phục vụ chuỗi F&B, FMCG, FDI điện tử (điều khoản 30–45 ngày), DSO tăng dần lên 30 ngày. Nguồn: BCTC 2023–2025; Mục 3.2.6 (khách hàng B2B có sức mạnh cao).
A108: Phải thu khách hàng | B108: nghìn đồng | C108: ='Balance Sheet'!D12 -> 1260000 | D108: ='Balance Sheet'!E12 -> 1537200 | E108: ='Balance Sheet'!F12 -> 1767780 | F108: =F39*F107/365 -> 3140078.6 | G108: =G39*G107/365 -> 4909095 | H108: =H39*H107/365 -> 7152143.2 | I108: =I39*I107/365 -> 11446963 | J108: =J39*J107/365 -> 14703469
A109: TSNH khác (chi phí trả trước...) / DT | B109: % | C109: ='Balance Sheet'!D19/C39 -> 0.063431669 | D109: ='Balance Sheet'!E19/D39 -> 0.055279496 | E109: ='Balance Sheet'!F19/E39 -> 0.043601291 | F109: 0.04 | G109: 0.04 | H109: 0.04 | I109: 0.04 | J109: 0.04 | L109: Lý do: 6,3% → 5,5% → 4,4% (2023–25); giữ 4,0%. Nguồn: BCTC 2023–2025.
A110: TSNH khác | B110: nghìn đồng | C110: ='Balance Sheet'!D19 -> 1233000 | D110: ='Balance Sheet'!E19 -> 1709700 | E110: ='Balance Sheet'!F19 -> 2073090 | F110: =F39*F109 -> 2546952.7 | G110: =G39*G109 -> 3257854 | H110: =H39*H109 -> 4016203.5 | I110: =I39*I109 -> 5570855.4 | J110: =J39*J109 -> 7155688.4
A111: Số ngày phải trả (DPO, theo giá vốn chưa gồm lương, khấu hao) | B111: ngày | C111: ='Balance Sheet'!D38/C60*365 -> 9.4714498 | D111: ='Balance Sheet'!E38/D60*365 -> 8.3240266 | E111: ='Balance Sheet'!F38/E60*365 -> 7.444894 | F111: 10 | G111: 12 | H111: 15 | I111: 15 | J111: 15 | L111: Lý do: 9 → 8 → 7 ngày (2023–25). Quy mô lớn hơn giúp đàm phán kỳ hạn 15 ngày với nhà máy đường và đơn vị thu gom. Nguồn: BCTC 2023–2025.
...

Sheet Pro Forma
A1: Báo cáo kết quả hoạt động kinh doanh (dự kiến) 5 năm
B2: 0 | C2: 1 | D2: 2 | E2: 3 | F2: 4 | G2: 5
B3: ='Income Statement'!D2 -> 2025 | C3: =B3+1 -> 2026 | D3: =C3+1 -> 2027 | E3: =D3+1 -> 2028 | F3: =E3+1 -> 2029 | G3: =F3+1 -> 2030
A4: Doanh thu | B4: ='Income Statement'!D11 -> 47546528 | C4: =B4*(1+Assumption!C2) -> 63673817 | D4: =C4*(1+Assumption!D2) -> 81446349 | E4: =D4*(1+Assumption!E2) -> 1.0040509e+08 | F4: =E4*(1+Assumption!F2) -> 1.3927139e+08 | G4: =F4*(1+Assumption!G2) -> 1.7889221e+08
A5: Giá vốn hàng bán (gồm 70% tiền lương, 90% khấu hao) | B5: ='Income Statement'!D18 -> 23281582 | C5: =C4*Assumption!C3 -> 30719170 | D5: =D4*Assumption!D3 -> 39477252 | E5: =E4*Assumption!E3 -> 49530274 | F5: =F4*Assumption!F3 -> 76393522 | G5: =G4*Assumption!G3 -> 94170042
A6: Lợi nhuận gộp | B6: =B4-B5 -> 24264946 | C6: =C4-C5 -> 32954647 | D6: =D4-D5 -> 41969097 | E6: =E4-E5 -> 50874812 | F6: =F4-F5 -> 62877865 | G6: =G4-G5 -> 84722167
A7: Chi phí bán hàng & QLDN (gồm 30% tiền lương, 10% khấu hao) | B7: ='Income Statement'!D61 -> 19702269 | C7: =C4*Assumption!C4 -> 25312537 | D7: =D4*Assumption!D4 -> 31239884 | E7: =E4*Assumption!E4 -> 38040826 | F7: =F4*Assumption!F4 -> 52741404 | G7: =G4*Assumption!G4 -> 64320006
A8: Chi phí thuê cửa hàng | B8: 0 | C8: 0 | D8: 0 | E8: 0 | F8: 0 | G8: 0
A9: Khấu hao (đã phân bổ vào GVHB và CPBH & QLDN) | B9: ='Income Statement'!D69 -> 3131952 | C9: =Assumption!$B$15*B22 -> 3742094.4 | D9: =Assumption!$B$15*C22 -> 5270266 | E9: =Assumption!$B$15*D22 -> 6736300.3 | F9: =Assumption!$B$15*E22 -> 14567897 | G9: =Assumption!$B$15*F22 -> 16573405
A10: Lợi nhuận trước thuế và lãi vay (EBIT) | B10: =B6-B7-B8 -> 4562677.2 | C10: =C6-C7-C8 -> 7642109.6 | D10: =D6-D7-D8 -> 10729213 | E10: =E6-E7-E8 -> 12833987 | F10: =F6-F7-F8 -> 10136460 | G10: =G6-G7-G8 -> 20402161
A11: Chi phí tài chính | B11: ='Income Statement'!D67 -> 142182 | C11: =C4*Assumption!C5 -> 160260 | D11: =D4*Assumption!D5 -> 160260 | E11: =E4*Assumption!E5 -> 2118159.2 | F11: =F4*Assumption!F5 -> 4076058.4 | G11: =G4*Assumption!G5 -> 3684478.5
A12: Lợi nhuận trước thuế | B12: =B10-B11 -> 4420495.2 | C12: =C10-C11 -> 7481849.6 | D12: =D10-D11 -> 10568953 | E12: =E10-E11 -> 10715827 | F12: =F10-F11 -> 6060401.9 | G12: =G10-G11 -> 16717683
A13: Thuế TNDN | B13: 0 | C13: =Drivers!F138 -> 902709.76 | D13: =Drivers!G138 -> 2113790.6 | E13: =Drivers!H138 -> 2143165.5 | F13: =Drivers!I138 -> 1212080.4 | G13: =Drivers!J138 -> 3343536.5
A14: Lợi nhuận sau thuế | B14: =B12-B13 -> 4420495.2 | C14: =C12-C13 -> 6579139.9 | D14: =D12-D13 -> 8455162.4 | E14: =E12-E13 -> 8572661.9 | F14: =F12-F13 -> 4848321.5 | G14: =G12-G13 -> 13374146
A17: Tính toán chi tiết:
A19: Chi phí đầu tư tài sản cố định (CAPEX)
B21: =B3 -> 2025 | C21: =B21+1 -> 2026 | D21: =C21+1 -> 2027 | E21: =D21+1 -> 2028 | F21: =E21+1 -> 2029 | G21: =F21+1 -> 2030
A22: Tài sản dài hạn | B22: =SUM('Balance Sheet'!F27:F29) -> 31184120 | C22: =SUM(B22,C25) -> 43918883 | D22: =SUM(C22,D25) -> 56135836 | E22: =SUM(D22,E25) -> 1.2139914e+08 | F22: =SUM(E22,F25) -> 1.3811171e+08 | G22: =SUM(F22,G25) -> 1.5600093e+08
A23: Khấu hao lũy kế | B23: ='Balance Sheet'!F24 -> 9789432 | C23: =SUM(B23,C9) -> 13531526 | D23: =SUM(C23,D9) -> 18801792 | E23: =SUM(D23,E9) -> 25538093 | F23: =SUM(E23,F9) -> 40105990 | G23: =SUM(F23,G9) -> 56679395
A24: Tổng tài sản dài hạn (ròng) | B24: =B22-B23 -> 21394688 | C24: =C22-C23 -> 30387357 | D24: =D22-D23 -> 37334043 | E24: =E22-E23 -> 95861049 | F24: =F22-F23 -> 98005719 | G24: =G22-G23 -> 99321535
A25: CAPEX | B25: =B22-SUM('Balance Sheet'!E27:E29) -> 5084520 | C25: =C4*Assumption!C11 -> 12734763 | D25: =D4*Assumption!D11 -> 12216952 | E25: =E4*Assumption!E11 -> 65263306 | F25: =F4*Assumption!F11 -> 16712566 | G25: =G4*Assumption!G11 -> 17889221
A28: Điều chỉnh Vốn lưu động ròng
B30: =B21 -> 2025 | C30: =B30+1 -> 2026 | D30: =C30+1 -> 2027 | E30: =D30+1 -> 2028 | F30: =E30+1 -> 2029 | G30: =F30+1 -> 2030
A31: Tài sản ngắn hạn (ngoài tiền) | B31: ='Balance Sheet'!F21-'Balance Sheet'!F6 -> 7589370 | C31: =C4*Assumption!C6 -> 10432965 | D31: =D4*Assumption!D6 -> 14168651 | E31: =E4*Assumption!E6 -> 18648452 | F31: =F4*Assumption!F6 -> 28631760 | G31: =G4*Assumption!G6 -> 35681714
A32: Hàng tồn kho | B32: ='Balance Sheet'!F9 -> 3748500 | C32: =C31*Assumption!C8 -> 4745934 | D32: =D31*Assumption!D8 -> 6001702.1 | E32: =E31*Assumption!E8 -> 7480105.5 | F32: =F31*Assumption!F8 -> 11613941 | G32: =G31*Assumption!G8 -> 13822557
A33: Khoản phải thu ngắn hạn | B33: ='Balance Sheet'!F12 -> 1767780 | C33: =C31*Assumption!C9 -> 3140078.6 | D33: =D31*Assumption!D9 -> 4909095 | E33: =E31*Assumption!E9 -> 7152143.2 | F33: =F31*Assumption!F9 -> 11446963 | G33: =G31*Assumption!G9 -> 14703469
A34: Nợ ngắn hạn (ngoài vay) | B34: ='Balance Sheet'!F55-'Balance Sheet'!F45 -> 342732 | C34: =C4*Assumption!C7 -> 601941.04 | D34: =D4*Assumption!D7 -> 883096.95 | E34: =E4*Assumption!E7 -> 1322826 | F34: =F4*Assumption!F7 -> 1937677.2 | G34: =G4*Assumption!G7 -> 2431167.9
A35: Khoản phải trả ngắn hạn | B35: ='Balance Sheet'!F38 -> 263640 | C35: =C34*Assumption!C10 -> 474593.4 | D35: =D34*Assumption!D10 -> 720204.25 | E35: =E34*Assumption!E10 -> 1122015.8 | F35: =F34*Assumption!F10 -> 1659134.4 | G35: =G34*Assumption!G10 -> 2073383.5
A36: Vốn lưu động hoạt động ròng (TSNH ngoài tiền − Nợ NH ngoài vay) | B36: =B31-B34 -> 7246638 | C36: =C31-C34 -> 9831024.3 | D36: =D31-D34 -> 13285554 | E36: =E31-E34 -> 17325626 | F36: =F31-F34 -> 26694083 | G36: =G31-G34 -> 33250546
A37: Biến động VLĐ ròng | C37: =C36-B36 -> 2584386.3 | D37: =D36-C36 -> 3454529.8 | E37: =E36-D36 -> 4040072 | F37: =F36-E36 -> 9368456.4 | G37: =G36-F36 -> 6556463.9
A40: Xác định nhu cầu vốn
A41: Cash Flow Statment Pro-forma
B42: 0 | C42: 1 | D42: 2 | E42: 3 | F42: 4 | G42: 5
B43: =B30 -> 2025 | C43: =B43+1 -> 2026 | D43: =C43+1 -> 2027 | E43: =D43+1 -> 2028 | F43: =E43+1 -> 2029 | G43: =F43+1 -> 2030
A44: ='Cash Flow Statement'!A3 -> Hoạt động kinh doanh
A45: ='Cash Flow Statement'!B4 -> Lợi nhuận sau thuế | B45: =B14 -> 4420495.2 | C45: =C14 -> 6579139.9 | D45: =D14 -> 8455162.4 | E45: =E14 -> 8572661.9 | F45: =F14 -> 4848321.5 | G45: =G14 -> 13374146
A46: ='Cash Flow Statement'!B6 -> Khấu hao | B46: =B9 -> 3131952 | C46: =C9 -> 3742094.4 | D46: =D9 -> 5270266 | E46: =E9 -> 6736300.3 | F46: =F9 -> 14567897 | G46: =G9 -> 16573405
A47: Biến động TSNH | B47: =SUM('Cash Flow Statement'!E9:E11) -> -1343670 | C47: =B31-C31 -> -2843595.4 | D47: =C31-D31 -> -3735685.7 | E47: =D31-E31 -> -4479801.1 | F47: =E31-F31 -> -9983307.6 | G47: =F31-G31 -> -7049954.6
A48: Biến động Nợ NH | B48: =SUM('Cash Flow Statement'!E13:E15) -> 73692 | C48: =C34-B34 -> 259209.04 | D48: =D34-C34 -> 281155.91 | E48: =E34-D34 -> 439729.05 | F48: =F34-E34 -> 614851.2 | G48: =G34-F34 -> 493490.72
A49: Lưu chuyển tiền thuần từ HĐKD | B49: =SUM(B45:B48) -> 6282469.2 | C49: =SUM(C45:C48) -> 7736847.9 | D49: =SUM(D45:D48) -> 10270899 | E49: =SUM(E45:E48) -> 11268890 | F49: =SUM(F45:F48) -> 10047762 | G49: =SUM(G45:G48) -> 23391087
A50: Hoạt động đầu tư
A51: Lưu chuyển tiền thuần từ HĐ đầu tư | B51: ='Cash Flow Statement'!E20 -> -5084520 | C51: =-C25 -> -12734763 | D51: =-D25 -> -12216952 | E51: =-E25 -> -65263306 | F51: =-F25 -> -16712566 | G51: =-G25 -> -17889221
A52: Hoạt động tài chính
A53: Lưu chuyển tiền thuần từ HĐ tài chính (vay/trả nợ theo kế hoạch, chưa gồm vốn cổ phần) | B53: ='Cash Flow Statement'!E28 -> 0 | C53: =(Drivers!F122-Drivers!E122)+(Drivers!F128-Drivers!E128) -> 0 | D53: =(Drivers!G122-Drivers!F122)+(Drivers!G128-Drivers!F128) -> 0 | E53: =(Drivers!H122-Drivers!G122)+(Drivers!H128-Drivers!G128) -> 39157984 | F53: =(Drivers!I122-Drivers!H122)+(Drivers!I128-Drivers!H128) -> 0 | G53: =(Drivers!J122-Drivers!I122)+(Drivers!J128-Drivers!I128) -> -7831596.8
A55: Số dư tiền mặt đầu kỳ | B55: ='Cash Flow Statement'!E30 -> 1735532.6 | C55: =B57 -> 2933481.8 | D55: =C57 -> -2064433.7 | E55: =D57 -> -4010487.4 | F55: =E57 -> -18846920 | G55: =F57 -> -25511724
A56: Biến động tiền mặt trong kỳ | B56: ='Cash Flow Statement'!E32 -> 1197949.2 | C56: =SUM(C49,C51,C53) -> -4997915.4 | D56: =SUM(D49,D51,D53) -> -1946053.7 | E56: =SUM(E49,E51,E53) -> -14836432 | F56: =SUM(F49,F51,F53) -> -6664804.2 | G56: =SUM(G49,G51,G53) -> -2329730.5
A57: Số dư tiền mặt cuối kỳ | B57: ='Cash Flow Statement'!E34 -> 2933481.8 | C57: =SUM(C55,C56) -> -2064433.7 | D57: =SUM(D55,D56) -> -4010487.4 | E57: =SUM(E55,E56) -> -18846920 | F57: =SUM(F55,F56) -> -25511724 | G57: =SUM(G55,G56) -> -27841454
A58: Thiếu hụt so với tiền mặt tối thiểu (trước khi gọi vốn cổ phần) | C58: =MAX(0,Drivers!F121-C57) -> 5248124.5 | D58: =MAX(0,Drivers!G121-D57) -> 8082804.9 | E58: =MAX(0,Drivers!H121-E57) -> 23867174 | F58: =MAX(0,Drivers!I121-F57) -> 32475293 | G58: =MAX(0,Drivers!J121-G57) -> 36786065
A59: Nhu cầu vốn | B59: =MAX(C58:G58) -> 36786065
A60: (+) Dự phòng | B60: =B59*0.1 -> 3678606.5
A61: Tổng vốn cần huy động | B61: =SUM(B59:B60) -> 40464671

Sheet DCF
A1: Dòng tiền tự do (FCFF) của doanh nghiệp
A3: Số năm chiết khấu từ t0 = 01/10/2026 (B3 = phần năm 2026 còn lại) | B3: 0.25 | C3: =B3 -> 0.25 | D3: =C3+1 -> 1.25 | E3: =D3+1 -> 2.25 | F3: =E3+1 -> 3.25 | G3: =F3+1 -> 4.25
B4: ='Income Statement'!D2 -> 2025 | C4: =B4+1 -> 2026 | D4: =C4+1 -> 2027 | E4: =D4+1 -> 2028 | F4: =E4+1 -> 2029 | G4: =F4+1 -> 2030 | H4: =G4+1 -> 2031
A5: Lợi nhuận sau thuế trước lãi vay EBIT*(1-t) | C5: ='Pro Forma'!C10-Drivers!F136*MAX(0,'Pro Forma'!C10-Drivers!F134) -> 6712155.7 | D5: ='Pro Forma'!D10-Drivers!G136*MAX(0,'Pro Forma'!D10-Drivers!G134) -> 8583370.4 | E5: ='Pro Forma'!E10-Drivers!H136*MAX(0,'Pro Forma'!E10-Drivers!H134) -> 10267189 | F5: ='Pro Forma'!F10-Drivers!I136*MAX(0,'Pro Forma'!F10-Drivers!I134) -> 8109168.2 | G5: ='Pro Forma'!G10-Drivers!J136*MAX(0,'Pro Forma'!G10-Drivers!J134) -> 16321729
A6: + Khấu hao | C6: ='Pro Forma'!C9 -> 3742094.4 | D6: ='Pro Forma'!D9 -> 5270266 | E6: ='Pro Forma'!E9 -> 6736300.3 | F6: ='Pro Forma'!F9 -> 14567897 | G6: ='Pro Forma'!G9 -> 16573405
A7: - Điều chỉnh VLĐ | C7: ='Pro Forma'!C37 -> 2584386.3 | D7: ='Pro Forma'!D37 -> 3454529.8 | E7: ='Pro Forma'!E37 -> 4040072 | F7: ='Pro Forma'!F37 -> 9368456.4 | G7: ='Pro Forma'!G37 -> 6556463.9
A8: - CAPEX | C8: ='Pro Forma'!C25 -> 12734763 | D8: ='Pro Forma'!D25 -> 12216952 | E8: ='Pro Forma'!E25 -> 65263306 | F8: ='Pro Forma'!F25 -> 16712566 | G8: ='Pro Forma'!G25 -> 17889221
H9: FCFF 2031 chuẩn hóa
A10: Dòng tiền tự do (FCFF) | C10: =C5+C6-C7-C8 -> -4864899.6 | D10: =D5+D6-D7-D8 -> -1817845.7 | E10: =E5+E6-E7-E8 -> -52299889 | F10: =F5+F6-F7-F8 -> -3403957.5 | G10: =G5+G6-G7-G8 -> 8449449.1 | H10: =G5*(1+Assumption!B14)*(1-Assumption!B14/Assumption!B17) -> 10177781 | I10: FCFF 2031 = NOPAT 2031 × (1 − g/RONIC): phần tái đầu tư chỉ vừa đủ cho tăng trưởng g
A11: Tỷ lệ dòng tiền năm được tính (2026: chỉ quý IV) | C11: =B3 -> 0.25 | D11: 1 | E11: 1 | F11: 1 | G11: 1
A12: Giá trị cuối kỳ tại t=5 = FCFF 2031 / (WACC − g) | G12: =H10/(Assumption!B16-Assumption!B14) -> 1.1146423e+08
A14: Giá trị hiện tại của các dòng tiền | C14: =C10*C11/(1+Assumption!$B$16)^C3 -> -1176692.6 | D14: =D10*D11/(1+Assumption!$B$16)^D3 -> -1540999.8 | E14: =E10*E11/(1+Assumption!$B$16)^E3 -> -38845682 | F14: =F10*F11/(1+Assumption!$B$16)^F3 -> -2215249 | G14: =(G10*G11+G12)/(1+Assumption!$B$16)^G3 -> 68375985
A16: Giá trị doanh nghiệp | C16: =SUM(C14:G14) -> 24597361
A19: Nhu cầu vốn | B19: ='Pro Forma'!B61 -> 40464671
A20: Tỷ lệ nắm giữ | B20: =B19/B21 -> 0.63764628
A21: Post-money value | B21: =SUM(B22,B19) -> 63459433
A22: Pre-money value | B22: =B33 -> 22994761 | D22: Pitch: Kêu gọi | E22: =B19 -> 40464671 | F22: nghìn đồng tương ứng | G22: =B20 -> 0.63764628 | H22: cổ phần.
A26: CẦU NỐI EV → VỐN CSH & KIỂM TRA
A27: PV dòng tiền tự do Q4/2026–2030 | B27: =SUM(C14:F14)+G10*G11/(1+Assumption!B16)^G3 -> -38960663
A28: PV giá trị cuối kỳ | B28: =G12/(1+Assumption!B16)^G3 -> 63558024
A29: Giá trị doanh nghiệp (EV) | B29: =C16 -> 24597361
A30: Tỷ trọng giá trị cuối kỳ / EV | B30: =B28/B29 -> 2.5839367
A31: (+) Tiền mặt ước tính 30/09/2026 = tiền 31/12/2025 + 75% FCFF 2026 (≥ 0) | B31: =MAX(0,'Balance Sheet'!F6+(1-B3)*C10) -> 0
A32: (−) Nợ vay 30/09/2026 (= 31/12/2025; không vay mới trong 2026) | B32: =SUM('Balance Sheet'!F45,'Balance Sheet'!F58) -> 1602600
A33: Giá trị vốn CSH trước gọi vốn (pre-money) | B33: =B29+B31-B32 -> 22994761
A34: EV/EBITDA 2025A ngầm định | B34: =B29/Drivers!E77 -> 3.1966922
A35: EV/EBITDA 2026E ngầm định | B35: =B29/Drivers!F77 -> 2.1606571
A36: P/E 2026E ngầm định (pre-money) | B36: =B33/'Income Statement'!E78 -> 3.4951015
A37: P/B 2025A ngầm định | B37: =B33/'Balance Sheet'!F73 -> 0.76720279
A38: Giá trị cuối kỳ nếu không chuẩn hóa = FCFF 2030 × (1 + g)/(WACC − g) | B38: =G10*(1+Assumption!B14)/(Assumption!B16-Assumption!B14) -> 97162820
A39: ROIC 2030E = NOPAT / (TSCĐ ròng + VLĐ) | B39: =G5/SUM('Pro Forma'!G24,'Pro Forma'!G36) -> 0.12311588
A40: Tỷ lệ tái đầu tư trong giá trị cuối kỳ = g / RONIC | B40: =Assumption!B14/Assumption!B17 -> 0.40612144

Sheet VCM
A1: The VC Method | C1: =DCF!G4 -> 2030
A2: Tỷ lệ chiết khấu có điều chỉnh
A3: Số kỳ | B3: =DCF!G3 -> 4.25 | D3: Nhu cầu vốn | E3: =DCF!B19 -> 40464671
A4: Tỷ lệ thất bại của VC | B4: 0.4 | C4: Giả định: z = 35–45%; lấy 40% (trung điểm). | D4: Giá trị thoái vốn kỳ vọng | E4: =B35 -> 2.0060787e+08
A5: Tỷ lệ chiết khấu (WACC) | B5: ='Discount rate'!E4 -> 0.14130984 | D5: Post-money value | E5: =E4/(1+B7)^B3 -> 68633172
D6: Tỷ lệ sở hữu của NĐT mới | E6: =E3/E5 -> 0.58957892
A7: Tỷ lệ chiết khấu có điều chỉnh p = (1 + r)/(1 − z)^(1/n) − 1 | B7: =(1+B5)/(1-B4)^(1/B3)-1 -> 0.28707326 | D7: Pre-money value | E7: =E5-E3 -> 28168501
D8: Tỷ lệ sở hữu của Founder và NĐT cũ | E8: =1-E6 -> 0.41042108
A11: Pitch: Kêu gọi | B11: =E3 -> 40464671 | C11: nghìn đồng tương ứng | D11: =E6 -> 0.58957892 | E11: cổ phần.
A15: Tỷ lệ thất bại theo giai đoạn đầu tư VC (đề bài) | B15: Thấp | C15: Cao | D15: Trung điểm
A16: Ươm mầm | B16: 0.65 | C16: 0.8 | D16: =AVERAGE(B16:C16) -> 0.725
A17: Thử nghiệm | B17: 0.5 | C17: 0.65 | D17: =AVERAGE(B17:C17) -> 0.575
A18: Đầu tăng trưởng | B18: 0.35 | C18: 0.45 | D18: =AVERAGE(B18:C18) -> 0.4
A19: Cuối tăng trưởng | B19: 0.2 | C19: 0.3 | D19: =AVERAGE(B19:C19) -> 0.25
A21: Giai đoạn của AgriPack | B21: Đầu tăng trưởng | C21: Lý do: doanh thu 47,5 tỷ, tăng 54–59%/năm, LNST và FCF vừa dương năm 2025, D/E 6,5%. Nguồn: kết luận Mục 2.
A23: GIÁ TRỊ THOÁI VỐN CUỐI 2030
A24: LNST 2030E | B24: ='Income Statement'!I78 -> 13374146
A25: P/E thoát vốn | B25: 9.4 | C25: Lý do: P/E ngành Containers & Packaging (ICB cấp 4) năm 2026: 9,43x; trung vị mẫu 14 DN: xem Multiples!G22. Nguồn: FiinX (giá đóng cửa 28/9/2026).
A26: Giá trị vốn CSH theo P/E | B26: =B24*B25 -> 1.2571697e+08
A27: EBITDA 2030E | B27: ='Income Statement'!I80 -> 36975566
A28: EV/EBITDA thoát vốn | B28: 8 | C28: EV/EBITDA ngành Containers & Packaging 2026: 7,99x (2025: 7,5x). Nguồn: FiinX (giá đóng cửa 28/9/2026).
A29: EV theo EV/EBITDA | B29: =B27*B28 -> 2.9580453e+08
A30: (+) Tiền mặt 2030E | B30: ='Balance Sheet'!K6 -> 12623217
A31: (−) Nợ vay 2030E | B31: =SUM('Balance Sheet'!K45,'Balance Sheet'!K58) -> 32928987
A32: Giá trị vốn CSH theo EV/EBITDA | B32: =B29+B30-B31 -> 2.7549876e+08
A33: Đối chiếu: giá trị vốn CSH theo DCF tại 2030 (TV + tiền − nợ) | B33: =DCF!G12+B30-B31 -> 91158461
A34: EV/EBITDA ngầm định của P/E thoát vốn | B34: =(B26-B30+B31)/B27 -> 3.9491685
A35: Giá trị thoái vốn sử dụng (bình quân P/E và EV/EBITDA) | B35: =AVERAGE(B26,B32) -> 2.0060787e+08
A37: IRR kỳ vọng của NĐT nếu thành công | B37: =(E4*E6/E3)^(1/B3)-1 -> 0.28707326
A38: IRR kỳ vọng có tính xác suất thất bại (= WACC) | B38: =((1-B4)*E4*E6/E3)^(1/B3)-1 -> 0.14130984

Sheet Multiples
A1: ĐỊNH GIÁ BẰNG BỘI SỐ SO SÁNH (MULTIPLES / COMPARABLES) – AgriPack
A2: Đơn vị: tỷ đồng; bội số: lần. Mẫu so sánh: 16 DN bao bì niêm yết (FiinX, giá đóng cửa 28/9/2026; BCTC quý đến Q2/2026, TTM).
A4: Mã | B4: Sàn | C4: Phân khúc | D4: DT TTM (tỷ) | E4: Biên EBITDA (%) | F4: EV/EBITDA (x) | G4: P/E (x) | H4: Đưa vào mẫu | I4: EV/EBITDA (mẫu) | J4: P/E (mẫu) | K4: Nguồn
A5: DHC | B5: HOSE | C5: Giấy, bao bì carton | D5: 3938 | E5: 18.9 | F5: 6.35 | G5: 7.48 | H5: 1 | I5: =IF(H5=1,F5,"") -> 6.35 | J5: =IF(H5=1,G5,"") -> 7.48 | K5: FiinX: BCTC 4 quý gần nhất đến Q2/2026; giá đóng cửa 28/9/2026
A6: TDP | B6: HOSE | C6: Bao bì nhựa | D6: 5488 | E6: 8.3 | F6: 8.98 | G6: 20.51 | H6: 1 | I6: =IF(H6=1,F6,"") -> 8.98 | J6: =IF(H6=1,G6,"") -> 20.51 | K6: FiinX: BCTC 4 quý gần nhất đến Q2/2026; giá đóng cửa 28/9/2026
A7: AAA | B7: HOSE | C7: Nhựa, nhựa sinh học | D7: 9243 | E7: 14.2 | F7: 3.85 | G7: 5.16 | H7: 1 | I7: =IF(H7=1,F7,"") -> 3.85 | J7: =IF(H7=1,G7,"") -> 5.16 | K7: FiinX: BCTC 4 quý gần nhất đến Q2/2026; giá đóng cửa 28/9/2026
A8: APH | B8: HOSE | C8: Bao bì nhựa (holding) | D8: 9252 | E8: 14 | F8: 5.05 | G8: 6.98 | H8: 1 | I8: =IF(H8=1,F8,"") -> 5.05 | J8: =IF(H8=1,G8,"") -> 6.98 | K8: FiinX: BCTC 4 quý gần nhất đến Q2/2026; giá đóng cửa 28/9/2026
A9: HHP | B9: HOSE | C9: Giấy bao bì | D9: 3112 | E9: 9.3 | F9: 13.71 | G9: 32.9 | H9: 1 | I9: =IF(H9=1,F9,"") -> 13.71 | J9: =IF(H9=1,G9,"") -> 32.9 | K9: FiinX: BCTC 4 quý gần nhất đến Q2/2026; giá đóng cửa 28/9/2026
A10: INN | B10: HNX | C10: Bao bì giấy, in | D10: 1921 | E10: 14.9 | F10: 2.66 | G10: 7.29 | H10: 1 | I10: =IF(H10=1,F10,"") -> 2.66 | J10: =IF(H10=1,G10,"") -> 7.29 | K10: FiinX: BCTC 4 quý gần nhất đến Q2/2026; giá đóng cửa 28/9/2026
A11: ILS | B11: UPCoM | C11: Bao bì khác | D11: 319 | E11: 16.4 | F11: 13.33 | G11: 16.64 | H11: 1 | I11: =IF(H11=1,F11,"") -> 13.33 | J11: =IF(H11=1,G11,"") -> 16.64 | K11: FiinX: BCTC 4 quý gần nhất đến Q2/2026; giá đóng cửa 28/9/2026
A12: TPP | B12: HNX | C12: Bao bì nhựa | D12: 3179 | E12: 15.9 | F12: 3.28 | G12: 2.54 | H12: 1 | I12: =IF(H12=1,F12,"") -> 3.28 | J12: =IF(H12=1,G12,"") -> 2.54 | K12: FiinX: BCTC 4 quý gần nhất đến Q2/2026; giá đóng cửa 28/9/2026
A13: MCP | B13: HOSE | C13: Bao bì kim loại, in | D13: 431 | E13: 2.9 | F13: 36.45 | G13: 84.23 | H13: 0 | I13: =IF(H13=1,F13,"") | J13: =IF(H13=1,G13,"") | K13: FiinX (28/9/2026); loại khỏi mẫu – xem ghi chú dòng 2
A14: PBT | B14: UPCoM | C14: Thương mại vật tư bao bì | D14: 2042 | E14: 1.9 | F14: 0.04 | G14: 9.97 | H14: 0 | I14: =IF(H14=1,F14,"") | J14: =IF(H14=1,G14,"") | K14: FiinX (28/9/2026); loại khỏi mẫu – xem ghi chú dòng 2
A15: TPC | B15: HOSE | C15: Màng, túi nhựa | D15: 490 | E15: 7 | F15: 4.21 | G15: 20.41 | H15: 1 | I15: =IF(H15=1,F15,"") -> 4.21 | J15: =IF(H15=1,G15,"") -> 20.41 | K15: FiinX: BCTC 4 quý gần nhất đến Q2/2026; giá đóng cửa 28/9/2026
A16: VBC | B16: HNX | C16: Bao bì nhựa | D16: 913 | F16: 4.17 | G16: 4.85 | H16: 1 | I16: =IF(H16=1,F16,"") -> 4.17 | J16: =IF(H16=1,G16,"") -> 4.85 | K16: FiinX: BCTC 4 quý gần nhất đến Q2/2026; giá đóng cửa 28/9/2026
A17: BBS | B17: HNX | C17: Bao bì giấy, bao xi măng | D17: 484 | E17: 6.5 | F17: 5.5 | G17: 9.19 | H17: 1 | I17: =IF(H17=1,F17,"") -> 5.5 | J17: =IF(H17=1,G17,"") -> 9.19 | K17: FiinX: BCTC 4 quý gần nhất đến Q2/2026; giá đóng cửa 28/9/2026
A18: STP | B18: HNX | C18: Bao bì giấy | D18: 212 | F18: 2.96 | G18: 6.65 | H18: 1 | I18: =IF(H18=1,F18,"") -> 2.96 | J18: =IF(H18=1,G18,"") -> 6.65 | K18: FiinX: BCTC 4 quý gần nhất đến Q2/2026; giá đóng cửa 28/9/2026
A19: PBP | B19: HNX | C19: Bao bì PP | D19: 372 | E19: 5.3 | F19: 2.06 | G19: 6.46 | H19: 1 | I19: =IF(H19=1,F19,"") -> 2.06 | J19: =IF(H19=1,G19,"") -> 6.46 | K19: FiinX: BCTC 4 quý gần nhất đến Q2/2026; giá đóng cửa 28/9/2026
A20: PMP | B20: HNX | C20: Bao bì PP | D20: 746 | E20: 4 | F20: 5.4 | G20: 5.53 | H20: 1 | I20: =IF(H20=1,F20,"") -> 5.4 | J20: =IF(H20=1,G20,"") -> 5.53 | K20: FiinX: BCTC 4 quý gần nhất đến Q2/2026; giá đóng cửa 28/9/2026
A22: Trung vị các DN trong mẫu | F22: =MEDIAN(I5:I20) -> 4.63 | G22: =MEDIAN(J5:J20) -> 7.135 | H22: =SUM(H5:H20) -> 14
A23: Bình quân ngành Containers & Packaging 2026 (FiinX, ICB cấp 4) | F23: 7.99 | G23: 9.43 | H23: Nguồn: FiinX – bình quân ngành Containers & Packaging (ICB cấp 4), cột 2026.
A24: Bội số dùng: trung vị (cận dưới, ít bị kéo bởi DN lỗ/lãi thấp) và bình quân ngành (cận trên)
A26: CHỈ TIÊU CỦA AGRIPACK (2025A – bộ máy hiện tại, trước khi gọi vốn)
A27: EBITDA 2025A | B27: ='Income Statement'!D80/1000000 -> 7.6946292
A28: Lợi nhuận trước thuế 2025A | B28: ='Income Statement'!D74/1000000 -> 4.4204952
A29: Thuế suất chuẩn hóa | B29: =Assumption!B13 -> 0.2
A30: LNST chuẩn hóa 2025A | B30: =B28*(1-B29) -> 3.5363962
A31: Tiền mặt 31/12/2025 | B31: ='Balance Sheet'!F6/1000000 -> 2.9334818
A32: Nợ vay 31/12/2025 | B32: =SUM('Balance Sheet'!F45,'Balance Sheet'!F58)/1000000 -> 1.6026
A33: Chiết khấu thiếu thanh khoản & quy mô (DLOM) | B33: 0.3 | C33: Lý do: DN tư nhân, cổ phần không giao dịch, doanh thu 47,5 tỷ (trung vị mẫu ~1.400 tỷ), phụ thuộc đội ngũ sáng lập → 30% (khoảng 20–35% theo nghiên cứu chiết khấu DN tư nhân). Nguồn: Damodaran (2026); Koeplin, Sarin & Shapiro (2000).
A35: ĐỊNH GIÁ VỐN CHỦ SỞ HỮU (PRE-MONEY)
A36: Cách tính | B36: Bội số (x) | C36: Chỉ tiêu áp dụng (tỷ) | D36: Giá trị vốn CSH trước chiết khấu | E36: Sau chiết khấu DLOM
A37: EV/EBITDA 2025A × trung vị mẫu | B37: =F22 -> 4.63 | C37: =B27 -> 7.6946292 | D37: =B37*C37+B31-B32 -> 36.957015 | E37: =D37*(1-$B$33) -> 25.869911
A38: EV/EBITDA 2025A × bình quân ngành | B38: =F23 -> 7.99 | C38: =B27 -> 7.6946292 | D38: =B38*C38+B31-B32 -> 62.810969 | E38: =D38*(1-$B$33) -> 43.967678
A39: P/E 2025A (LNST chuẩn hóa) × trung vị mẫu | B39: =G22 -> 7.135 | C39: =B30 -> 3.5363962 | D39: =B39*C39 -> 25.232187 | E39: =D39*(1-$B$33) -> 17.662531
A40: P/E 2025A (LNST chuẩn hóa) × bình quân ngành | B40: =G23 -> 9.43 | C40: =B30 -> 3.5363962 | D40: =B40*C40 -> 33.348216 | E40: =D40*(1-$B$33) -> 23.343751
A41: Pre-money theo Multiples (bình quân 4 cách) | E41: =AVERAGE(E37:E40) -> 27.710968
A42: Cận dưới / cận trên | D42: =MIN(E37:E40) -> 17.662531 | E42: =MAX(E37:E40) -> 43.967678
A44: KẾT QUẢ: GIÁ TRỊ DOANH NGHIỆP, PRE-MONEY, POST-MONEY VÀ TỶ LỆ CỔ PHẦN
A45: Giá trị doanh nghiệp (EV) | B45: =B49-B31+B32 -> 26.380086 | C45: EV = pre-money − tiền mặt (B31) + nợ vay (B32) tại 31/12/2025, cùng cầu nối giữa EV và vốn CSH như DCF!B22.
A46: Nhu cầu vốn | B46: =DCF!B19/1000000 -> 40.464671 | C46: Vốn cổ phần cần huy động năm 2026 (Pro Forma!B63), dùng chung cho DCF và VC Method.
A47: Tỷ lệ sở hữu của NĐT mới | B47: =B46/B48 -> 0.59353564
A48: Post-money value | B48: =SUM(B49,B46) -> 68.175639
A49: Pre-money value | B49: =E41 -> 27.710968 | C49: Lấy từ E41: bình quân 4 cách tính, sau chiết khấu thiếu thanh khoản 30%.
A50: Tỷ lệ sở hữu của Founder và NĐT cũ | B50: =1-B47 -> 0.40646436
A52: Pitch: Kêu gọi | B52: =B46 -> 40.464671 | C52: tỷ đồng tương ứng | D52: =B47 -> 0.59353564 | E52: cổ phần.

Sheet Summary
A1: TỔNG HỢP ĐỊNH GIÁ & ĐỀ XUẤT GỌI VỐN – AgriPack
A2: Đơn vị: tỷ đồng (trừ tỷ lệ). Thời điểm định giá t0 = 01/10/2026 (theo khung mô hình: BCTC đến 31/12/2025, năm hiện tại 2026).
A4: Phương pháp | B4: Pre-money | C4: Vốn CP cần huy động | D4: Post-money | E4: Tỷ lệ NĐT mới | F4: Trọng số | G4: Lý do trọng số / nguồn
A5: DCF (FCFF, WACC, giá trị cuối kỳ chuẩn hóa) | B5: =DCF!B22/1000000 -> 22.994761 | C5: =DCF!B19/1000000 -> 40.464671 | D5: =SUM(B5:C5) -> 63.459433 | E5: =IF(B5<=0,"n.m.",C5/D5) -> 0.63764628 | F5: 0.4 | G5: Lý do: DCF 40% – phản ánh dự phóng dòng tiền và công suất; chưa trừ rủi ro thất bại. Nguồn: lựa chọn của nhóm.
A6: VC Method (thoái vốn 2030, tỷ lệ thất bại 40%) | B6: =VCM!E7/1000000 -> 28.168501 | C6: =VCM!E3/1000000 -> 40.464671 | D6: =SUM(B6:C6) -> 68.633172 | E6: =IF(B6<=0,"n.m.",C6/D6) -> 0.58957892 | F6: 0.4 | G6: Lý do: VCM 40% – góc nhìn NĐT, có tỷ lệ thất bại 40% của giai đoạn đầu tăng trưởng (đề bài). Nguồn: lựa chọn của nhóm.
A7: Multiples/Comparables (EV/EBITDA, P/E 2025A; chiết khấu thanh khoản 30%) | B7: =Multiples!B49 -> 27.710968 | C7: =Multiples!B46 -> 40.464671 | D7: =SUM(B7:C7) -> 68.175639 | E7: =IF(B7<=0,"n.m.",C7/D7) -> 0.59353564 | F7: 0.2 | G7: Lý do: Multiples 20% – mẫu so sánh là DN niêm yết lớn, trưởng thành; chỉ phản ánh bộ máy 2025A nên chỉ dùng làm neo thị trường. Nguồn: lựa chọn của nhóm.
A8: Pre-money khuyến nghị (bình quân gia quyền DCF, VCM, Multiples) | B8: =(B5*F5+B6*F6+B7*F7)/SUM(F5:F7) -> 26.007498 | C8: =C5 -> 40.464671 | D8: =SUM(B8:C8) -> 66.47217 | E8: =IF(B8<=0,"n.m.",C8/D8) -> 0.60874606 | F8: =SUM(F5:F7) -> 1
A10: ĐỐI CHIẾU (không tham gia trọng số)
A11: DCF điều chỉnh xác suất sống sót = (1 − z) × DCF + z × giá trị thanh lý | B11: =(1-VCM!B4)*B5+VCM!B4*B12 -> 19.791298
A12: Giá trị thanh lý = tỷ lệ thu hồi × VCSH sổ sách 31/12/2025 | B12: =C12*'Balance Sheet'!F73/1000000 -> 14.986104 | C12: 0.5 | D12: Lý do: thu hồi 50% giá trị sổ sách khi thanh lý (máy ép chuyên dụng khó bán lại; nhà xưởng thuê). Nguồn: giả định của nhóm.
A17: KHOẢNG GIÁ TRỊ PRE-MONEY (football field)
A18: Phương pháp | B18: Thấp | C18: Cơ sở | D18: Cao | E18: Cách xác định khoảng
A19: DCF | B19: =MIN(Sensitivity!C7:E9) -> 13.469452 | C19: =B5 -> 22.994761 | D19: =MAX(Sensitivity!C7:E9) -> 33.049562 | E19: WACC ±1 điểm %, g ±1 điểm %
A20: VC Method | B20: =MIN(Sensitivity!C16:E18) -> 13.012008 | C20: =B6 -> 28.168501 | D20: =MAX(Sensitivity!C16:E18) -> 45.040822 | E20: z 35–45%, giá trị thoái vốn ±15%
A21: Multiples (EV/EBITDA, P/E 2025A) | B21: =Multiples!D42 -> 17.662531 | C21: =B7 -> 27.710968 | D21: =Multiples!E42 -> 43.967678 | E21: Trung vị mẫu – bình quân ngành, sau chiết khấu 30%
A22: Khuyến nghị (bình quân gia quyền) | B22: =(B19*F5+B20*F6+B21*F7)/F8 -> 14.12509 | C22: =B8 -> 26.007498 | D22: =(D19*F5+D20*F6+D21*F7)/F8 -> 40.029689 | E22: Bình quân gia quyền cận dưới/cận trên
A24: NHU CẦU VỐN – ĐẦU VÀO CỦA VC METHOD
A25: Vốn cổ phần cần huy động (tỷ đồng, Pro Forma!B63) | B25: =C8 -> 40.464671
A26: Tỷ lệ cổ phần tương ứng (theo pre-money khuyến nghị) | B26: =E8 -> 0.60874606
A27: Vay trung hạn/thuê tài chính cho nhà máy mới (tỷ đồng) | B27: =SUM(Drivers!F125:J125)/1000000 -> 39.157984
A28: Tổng vốn huy động bên ngoài 2026–2028 (tỷ đồng) | B28: =SUM(B25,B27) -> 79.622655
A31: TỔNG HỢP KỊCH BẢN
A32: Cột B tính trực tiếp theo kịch bản đang chọn ở Drivers!C3. Cột C–F là kết quả khi chạy lại toàn bộ mô hình với từng phương án
A33: Chỉ tiêu | B33: ="Đang chạy: "&Drivers!D3 -> Đang chạy: Base | C33: Bear (chạy lại mô hình) | D33: Bull (chạy lại mô hình) | E33: Chỉ vốn CP, không vay (chạy lại mô hình) | F33: Vay 75% CAPEX 2028 (chạy lại mô hình)
A34: Doanh thu thuần 2030E (tỷ) | B34: ='Income Statement'!I11/1000000 -> 178.89221 | C34: 121.16388 | D34: 227.44118 | E34: 178.89221 | F34: 178.89221
A35: CAGR doanh thu 2025–2030 | B35: =('Income Statement'!I11/'Income Statement'!D11)^(1/5)-1 -> 0.30345044 | C35: 0.20573224 | D35: 0.36757155 | E35: 0.30345044 | F35: 0.30345044
A36: Biên EBITDA 2030E | B36: ='Income Statement'!I80/'Income Statement'!I11 -> 0.20669187 | C36: 0.13983213 | D36: 0.24069873 | E36: 0.20669187 | F36: 0.20669187
A37: LNST 2030E (tỷ) | B37: ='Income Statement'!I78/1000000 -> 13.374146 | C37: -0.18814467 | D37: 25.741674 | E37: 16.193521 | F37: 12.669302
A38: Tổng FCFF 2026–2030 (tỷ) | B38: =SUM(DCF!C10:G10)/1000000 -> -53.937143 | C38: -57.632559 | D38: -49.391798 | E38: -53.937143 | F38: -53.937143
A39: Nhu cầu vốn cổ phần (tỷ) | B39: ='Pro Forma'!B61/1000000 -> 40.464671 | C39: 47.309474 | D39: 34.324259 | E39: 73.627751 | F39: 33.917456
A40: Vay trung hạn giải ngân (tỷ) | B40: =SUM(Drivers!F125:J125)/1000000 -> 39.157984 | C40: 31.401679 | D40: 44.855841 | E40: 0 | F40: 48.94748
A41: WACC | B41: ='Discount rate'!E4 -> 0.14130984 | C41: 0.14079554 | D41: 0.1416608 | E41: 0.13666812 | F41: 0.14234762
A42: DCF pre-money (tỷ) | B42: =B5 -> 22.994761 | C42: -60.287761 | D42: 99.820622 | E42: 27.256385 | F42: 22.107565
A43: VCM pre-money (tỷ) | B43: =B6 -> 28.168501 | C43: -27.186905 | D43: 77.906333 | E43: 7.8979078 | F43: 31.886146
A44: Pre-money bình quân (tỷ) | B44: =B8 -> 26.007498 | C44: -29.447673 | D44: 76.632976 | E44: 19.603911 | F44: 27.139678
A45: Tỷ lệ NĐT mới (theo pre-money bình quân) | B45: =E8 -> 0.60874606 | C45: n.m. | D45: 0.30934674 | E45: 0.78972904 | F45: 0.55550358
A46: Tỷ lệ founder & cổ đông hiện hữu sau vòng gọi vốn | B46: =IF(B8<=0,"n.m.",1-E8) -> 0.39125394 | C46: n.m. | D46: 0.69065326 | E46: 0.21027096 | F46: 0.44449642
A49: ĐỘ NHẠY THEO NHÂN TỐ VĨ MÔ – NGÀNH (kịch bản Base, đổi từng giả định, chạy lại toàn bộ mô hình)
A50: Mỗi dòng: một nhân tố ở Mục 3 được đưa về mức bất lợi và thuận lợi, các giả định khác giữ Base, rồi chạy lại toàn bộ mô hình; kết quả lưu dưới dạng số. Δ = chênh lệch pre-money so với Base, tỷ đồng.
A51: Nhân tố → giả định thay đổi (bất lợi / thuận lợi) | B51: Pre-money bất lợi | C51: Pre-money thuận lợi | D51: Δ bất lợi | E51: Δ thuận lợi | F51: DCF bất lợi | G51: DCF thuận lợi | H51: VCM bất lợi | I51: VCM thuận lợi | J51: DT 2030E bất lợi | K51: DT 2030E thuận lợi | L51: LNST 2030E bất lợi | M51: LNST 2030E thuận lợi | N51: Lý do biên độ / nguồn (ghi ngay cạnh giả định)
A52: Kịch bản cơ sở – Base | B52: 26.007498 | C52: 26.007498 | D52: 0 | E52: 0 | F52: 22.994761 | G52: 22.994761 | H52: 28.168501 | I52: 28.168501 | J52: 178.89221 | K52: 178.89221 | L52: 13.374146 | M52: 13.374146
A53: Cầu: tăng trưởng sản lượng ×0,8 / ×1,2 (GDP, tiêu dùng, TMĐT – Mục 3.1.1, 3.2.2) | B53: -1.9655464 | C53: 59.923392 | D53: -27.973045 | E53: 33.915894 | F53: -20.312298 | G53: 75.817145 | H53: 1.5429483 | I53: 60.135851 | J53: 142.91594 | K53: 221.94407 | L53: 5.8798042 | M53: 22.500917 | N53: Lý do biên độ: ±20% tốc độ tăng sản lượng mọi phân khúc – GDP 6T/2026 +8,18%, tiêu dùng +8,15%, TMĐT +18–25%/năm nhưng SAM chỉ +4,73%/năm; tăng trưởng của AgriPack phụ thuộc giành thị phần và tiến độ nhà máy (kịch bản Bear dùng ×0,7).
A54: Giá bán: +1% / +3% mỗi năm, Base +2% (CPI, sức mạnh khách hàng B2B – Mục 3.1.2, 3.2.3) | B54: 19.374139 | C54: 32.925863 | D54: -6.6333591 | E54: 6.9183651 | F54: 12.714415 | G54: 33.730614 | H54: 21.86545 | I54: 34.728561 | J54: 170.288 | K54: 187.84075 | L54: 11.584044 | M54: 15.243037 | N54: Lý do biên độ: ±1 điểm %/năm giá bán F&B, khuôn và đệm – CPI 8T/2026 +4,45% cho phép tăng giá gần lạm phát, nhưng khách hàng B2B có sức mạnh đàm phán rất cao và bao bì nhựa rẻ hơn nhiều lần (Mục 3.2.3).
A55: Chi phí biến đổi/DT: +1 / −1 điểm % (lạm phát chi phí thu gom, năng lượng – Mục 3.1.2) | B55: 16.991755 | C55: 35.004193 | D55: -9.0157435 | E55: 8.996695 | F55: 10.531126 | G55: 35.416697 | H55: 18.092778 | I55: 38.238302 | J55: 178.89221 | K55: 178.89221 | L55: 11.943008 | M55: 14.805284 | N55: Lý do biên độ: ±1 điểm % doanh thu – nhóm nhà ở, điện, nước, chất đốt, VLXD +6,71% (8T/2026); bã mía bị cạnh tranh bởi lò hơi nhà máy đường và nhà sản xuất bao bì sợi
A56: Chi phí nhân sự/DT: +1 / −1 điểm % (lương tối thiểu vùng +7,2% – NĐ 293/2025) | B56: 14.866605 | C56: 37.122173 | D56: -11.140894 | E56: 11.114674 | F56: 7.4676384 | G56: 38.464459 | H56: 15.843389 | I56: 40.485489 | J56: 178.89221 | K56: 178.89221 | L56: 11.54229 | M56: 15.206002 | N56: Lý do biên độ: ±1 điểm % doanh thu – lương tối thiểu vùng tăng 7,2% từ 01/01/2026 (NĐ 293/2025/NĐ-CP); tiền lương là khoản chi phí lớn thứ hai sau chi phí biến đổi.
A57: Lãi suất: Rf và Kd +1 / −1 điểm % (điều hành lãi suất, tín dụng – Mục 3.1.3) | B57: 21.62607 | C57: 31.198177 | D57: -4.3814287 | E57: 5.1906788 | F57: 15.728353 | G57: 32.150618 | H57: 24.481337 | I57: 31.989341 | J57: 178.89221 | K57: 178.89221 | L57: 13.079388 | M57: 13.668904 | N57: Lý do biên độ: ±1 điểm % cho cả lợi suất phi rủi ro (bình quân TPCP 10 năm 3,92%) và lãi vay (10%, khung cho vay 8,1–10,5%/năm); nhỏ hơn độ lệch chuẩn ~1,6 điểm % của lợi suất TPCP 10 năm 2016–2025 (Discount rate A28:C40) vì Rf là bình quân dài hạn.
A58: Rủi ro quốc gia CRP: +1 / −1 điểm % (xếp hạng Moody's Ba2, triển vọng tích cực – Mục 3.1) | B58: 21.755934 | C58: 31.259573 | D58: -4.251564 | E58: 5.2520748 | F58: 14.97826 | G58: 33.383648 | H58: 25.556092 | I58: 30.909801 | J58: 178.89221 | K58: 178.89221 | L58: 13.374146 | M58: 13.374146 | N58: Lý do biên độ: ±1 điểm % CRP 3,9% – Moody's nâng triển vọng Việt Nam lên tích cực (5/2026): nâng hạng làm CRP giảm; ngược lại nếu cú sốc bên ngoài làm chênh lệch lợi suất nới rộng.
A59: Ưu đãi thuế NQ 198/2025/QH15 nếu đủ điều kiện (miễn 2026–27, giảm 50% 2028–29 – Mục 3.1.6.2) | B59: 26.007498 | C59: 29.486015 | D59: 0 | E59: 3.4785162 | F59: 22.994761 | G59: 26.617747 | H59: 28.168501 | I59: 33.241805 | J59: 178.89221 | K59: 178.89221 | L59: 13.374146 | M59: 13.374146 | N59: Lý do: chỉ có chiều thuận lợi vì mô hình Base chưa đưa ưu đãi vào (chưa chứng minh đủ điều kiện). Chỉ tính ưu đãi đến 2029 để ưu đãi tạm thời không đi vào giá trị cuối kỳ (LNST 2030 chuẩn hóa ở thuế suất 20%).

Sheet Sensitivity
A1: PHÂN TÍCH ĐỘ NHẠY (mỗi ô tính lại toàn bộ DCF/VCM)
A2: Đơn vị: tỷ đồng
A4: Bảng 1. DCF – giá trị vốn CSH pre-money: WACC (dòng) × g (cột)
A5: WACC \ g | B5: =Assumption!$B$14+(-0.02) -> 0.03 | C5: =Assumption!$B$14+(-0.01) -> 0.04 | D5: =Assumption!$B$14+(0) -> 0.05 | E5: =Assumption!$B$14+(0.01) -> 0.06 | F5: =Assumption!$B$14+(0.02) -> 0.07
A6: =Assumption!$B$16+(-0.02) -> 0.12130984 | B6: =(SUMPRODUCT(DCF!$C$10:$G$10*DCF!$C$11:$G$11/(1+$A6)^DCF!$C$3:$G$3)+(DCF!$G$5*(1+B$5)*(1-B$5/Assumption!$B$17)/($A6-B$5))/(1+$A6)^DCF!$G$3+DCF!$B$31-DCF!$B$32)/1000000 -> 43.663278 | C6: =(SUMPRODUCT(DCF!$C$10:$G$10*DCF!$C$11:$G$11/(1+$A6)^DCF!$C$3:$G$3)+(DCF!$G$5*(1+C$5)*(1-C$5/Assumption!$B$17)/($A6-C$5))/(1+$A6)^DCF!$G$3+DCF!$B$31-DCF!$B$32)/1000000 -> 44.70049 | D6: =(SUMPRODUCT(DCF!$C$10:$G$10*DCF!$C$11:$G$11/(1+$A6)^DCF!$C$3:$G$3)+(DCF!$G$5*(1+D$5)*(1-D$5/Assumption!$B$17)/($A6-D$5))/(1+$A6)^DCF!$G$3+DCF!$B$31-DCF!$B$32)/1000000 -> 45.800045 | E6: =(SUMPRODUCT(DCF!$C$10:$G$10*DCF!$C$11:$G$11/(1+$A6)^DCF!$C$3:$G$3)+(DCF!$G$5*(1+E$5)*(1-E$5/Assumption!$B$17)/($A6-E$5))/(1+$A6)^DCF!$G$3+DCF!$B$31-DCF!$B$32)/1000000 -> 46.99245 | F6: =(SUMPRODUCT(DCF!$C$10:$G$10*DCF!$C$11:$G$11/(1+$A6)^DCF!$C$3:$G$3)+(DCF!$G$5*(1+F$5)*(1-F$5/Assumption!$B$17)/($A6-F$5))/(1+$A6)^DCF!$G$3+DCF!$B$31-DCF!$B$32)/1000000 -> 48.331991
A7: =Assumption!$B$16+(-0.01) -> 0.13130984 | B7: =(SUMPRODUCT(DCF!$C$10:$G$10*DCF!$C$11:$G$11/(1+$A7)^DCF!$C$3:$G$3)+(DCF!$G$5*(1+B$5)*(1-B$5/Assumption!$B$17)/($A7-B$5))/(1+$A7)^DCF!$G$3+DCF!$B$31-DCF!$B$32)/1000000 -> 33.051201 | C7: =(SUMPRODUCT(DCF!$C$10:$G$10*DCF!$C$11:$G$11/(1+$A7)^DCF!$C$3:$G$3)+(DCF!$G$5*(1+C$5)*(1-C$5/Assumption!$B$17)/($A7-C$5))/(1+$A7)^DCF!$G$3+DCF!$B$31-DCF!$B$32)/1000000 -> 33.049562 | D7: =(SUMPRODUCT(DCF!$C$10:$G$10*DCF!$C$11:$G$11/(1+$A7)^DCF!$C$3:$G$3)+(DCF!$G$5*(1+D$5)*(1-D$5/Assumption!$B$17)/($A7-D$5))/(1+$A7)^DCF!$G$3+DCF!$B$31-DCF!$B$32)/1000000 -> 32.854494 | E7: =(SUMPRODUCT(DCF!$C$10:$G$10*DCF!$C$11:$G$11/(1+$A7)^DCF!$C$3:$G$3)+(DCF!$G$5*(1+E$5)*(1-E$5/Assumption!$B$17)/($A7-E$5))/(1+$A7)^DCF!$G$3+DCF!$B$31-DCF!$B$32)/1000000 -> 32.38462 | F7: =(SUMPRODUCT(DCF!$C$10:$G$10*DCF!$C$11:$G$11/(1+$A7)^DCF!$C$3:$G$3)+(DCF!$G$5*(1+F$5)*(1-F$5/Assumption!$B$17)/($A7-F$5))/(1+$A7)^DCF!$G$3+DCF!$B$31-DCF!$B$32)/1000000 -> 31.505473
A8: =Assumption!$B$16+(0) -> 0.14130984 | B8: =(SUMPRODUCT(DCF!$C$10:$G$10*DCF!$C$11:$G$11/(1+$A8)^DCF!$C$3:$G$3)+(DCF!$G$5*(1+B$5)*(1-B$5/Assumption!$B$17)/($A8-B$5))/(1+$A8)^DCF!$G$3+DCF!$B$31-DCF!$B$32)/1000000 -> 24.571731 | C8: =(SUMPRODUCT(DCF!$C$10:$G$10*DCF!$C$11:$G$11/(1+$A8)^DCF!$C$3:$G$3)+(DCF!$G$5*(1+C$5)*(1-C$5/Assumption!$B$17)/($A8-C$5))/(1+$A8)^DCF!$G$3+DCF!$B$31-DCF!$B$32)/1000000 -> 23.935692 | D8: =(SUMPRODUCT(DCF!$C$10:$G$10*DCF!$C$11:$G$11/(1+$A8)^DCF!$C$3:$G$3)+(DCF!$G$5*(1+D$5)*(1-D$5/Assumption!$B$17)/($A8-D$5))/(1+$A8)^DCF!$G$3+DCF!$B$31-DCF!$B$32)/1000000 -> 22.994761 | E8: =(SUMPRODUCT(DCF!$C$10:$G$10*DCF!$C$11:$G$11/(1+$A8)^DCF!$C$3:$G$3)+(DCF!$G$5*(1+E$5)*(1-E$5/Assumption!$B$17)/($A8-E$5))/(1+$A8)^DCF!$G$3+DCF!$B$31-DCF!$B$32)/1000000 -> 21.636448 | F8: =(SUMPRODUCT(DCF!$C$10:$G$10*DCF!$C$11:$G$11/(1+$A8)^DCF!$C$3:$G$3)+(DCF!$G$5*(1+F$5)*(1-F$5/Assumption!$B$17)/($A8-F$5))/(1+$A8)^DCF!$G$3+DCF!$B$31-DCF!$B$32)/1000000 -> 19.685157
A9: =Assumption!$B$16+(0.01) -> 0.15130984 | B9: =(SUMPRODUCT(DCF!$C$10:$G$10*DCF!$C$11:$G$11/(1+$A9)^DCF!$C$3:$G$3)+(DCF!$G$5*(1+B$5)*(1-B$5/Assumption!$B$17)/($A9-B$5))/(1+$A9)^DCF!$G$3+DCF!$B$31-DCF!$B$32)/1000000 -> 17.688024 | C9: =(SUMPRODUCT(DCF!$C$10:$G$10*DCF!$C$11:$G$11/(1+$A9)^DCF!$C$3:$G$3)+(DCF!$G$5*(1+C$5)*(1-C$5/Assumption!$B$17)/($A9-C$5))/(1+$A9)^DCF!$G$3+DCF!$B$31-DCF!$B$32)/1000000 -> 16.665378 | D9: =(SUMPRODUCT(DCF!$C$10:$G$10*DCF!$C$11:$G$11/(1+$A9)^DCF!$C$3:$G$3)+(DCF!$G$5*(1+D$5)*(1-D$5/Assumption!$B$17)/($A9-D$5))/(1+$A9)^DCF!$G$3+DCF!$B$31-DCF!$B$32)/1000000 -> 15.297046 | E9: =(SUMPRODUCT(DCF!$C$10:$G$10*DCF!$C$11:$G$11/(1+$A9)^DCF!$C$3:$G$3)+(DCF!$G$5*(1+E$5)*(1-E$5/Assumption!$B$17)/($A9-E$5))/(1+$A9)^DCF!$G$3+DCF!$B$31-DCF!$B$32)/1000000 -> 13.469452 | F9: =(SUMPRODUCT(DCF!$C$10:$G$10*DCF!$C$11:$G$11/(1+$A9)^DCF!$C$3:$G$3)+(DCF!$G$5*(1+F$5)*(1-F$5/Assumption!$B$17)/($A9-F$5))/(1+$A9)^DCF!$G$3+DCF!$B$31-DCF!$B$32)/1000000 -> 11.013147
A10: =Assumption!$B$16+(0.02) -> 0.16130984 | B10: =(SUMPRODUCT(DCF!$C$10:$G$10*DCF!$C$11:$G$11/(1+$A10)^DCF!$C$3:$G$3)+(DCF!$G$5*(1+B$5)*(1-B$5/Assumption!$B$17)/($A10-B$5))/(1+$A10)^DCF!$G$3+DCF!$B$31-DCF!$B$32)/1000000 -> 12.027236 | C10: =(SUMPRODUCT(DCF!$C$10:$G$10*DCF!$C$11:$G$11/(1+$A10)^DCF!$C$3:$G$3)+(DCF!$G$5*(1+C$5)*(1-C$5/Assumption!$B$17)/($A10-C$5))/(1+$A10)^DCF!$G$3+DCF!$B$31-DCF!$B$32)/1000000 -> 10.77426 | D10: =(SUMPRODUCT(DCF!$C$10:$G$10*DCF!$C$11:$G$11/(1+$A10)^DCF!$C$3:$G$3)+(DCF!$G$5*(1+D$5)*(1-D$5/Assumption!$B$17)/($A10-D$5))/(1+$A10)^DCF!$G$3+DCF!$B$31-DCF!$B$32)/1000000 -> 9.1699924 | E10: =(SUMPRODUCT(DCF!$C$10:$G$10*DCF!$C$11:$G$11/(1+$A10)^DCF!$C$3:$G$3)+(DCF!$G$5*(1+E$5)*(1-E$5/Assumption!$B$17)/($A10-E$5))/(1+$A10)^DCF!$G$3+DCF!$B$31-DCF!$B$32)/1000000 -> 7.1104072 | F10: =(SUMPRODUCT(DCF!$C$10:$G$10*DCF!$C$11:$G$11/(1+$A10)^DCF!$C$3:$G$3)+(DCF!$G$5*(1+F$5)*(1-F$5/Assumption!$B$17)/($A10-F$5))/(1+$A10)^DCF!$G$3+DCF!$B$31-DCF!$B$32)/1000000 -> 4.4459094
A11: Ô trung tâm = DCF!B22 | B11: =ROUND(D8-DCF!B22/1000000,6) -> 0
A13: Bảng 2. VC method – pre-money: tỷ lệ thất bại z (dòng) × thay đổi giá trị thoái vốn (cột)
A14: z \ Exit value | B14: -0.3 | C14: -0.15 | D14: 0 | E14: 0.15 | F14: 0.3
A15: 0.3 | B15: =(VCM!$E$4*(1+B$14)*(1-$A15)/(1+VCM!$B$5)^VCM!$B$3-VCM!$E$3)/1000000 -> 15.585752 | C15: =(VCM!$E$4*(1+C$14)*(1-$A15)/(1+VCM!$B$5)^VCM!$B$3-VCM!$E$3)/1000000 -> 27.596558 | D15: =(VCM!$E$4*(1+D$14)*(1-$A15)/(1+VCM!$B$5)^VCM!$B$3-VCM!$E$3)/1000000 -> 39.607363 | E15: =(VCM!$E$4*(1+E$14)*(1-$A15)/(1+VCM!$B$5)^VCM!$B$3-VCM!$E$3)/1000000 -> 51.618168 | F15: =(VCM!$E$4*(1+F$14)*(1-$A15)/(1+VCM!$B$5)^VCM!$B$3-VCM!$E$3)/1000000 -> 63.628973
A16: 0.35 | B16: =(VCM!$E$4*(1+B$14)*(1-$A16)/(1+VCM!$B$5)^VCM!$B$3-VCM!$E$3)/1000000 -> 11.582151 | C16: =(VCM!$E$4*(1+C$14)*(1-$A16)/(1+VCM!$B$5)^VCM!$B$3-VCM!$E$3)/1000000 -> 22.735041 | D16: =(VCM!$E$4*(1+D$14)*(1-$A16)/(1+VCM!$B$5)^VCM!$B$3-VCM!$E$3)/1000000 -> 33.887932 | E16: =(VCM!$E$4*(1+E$14)*(1-$A16)/(1+VCM!$B$5)^VCM!$B$3-VCM!$E$3)/1000000 -> 45.040822 | F16: =(VCM!$E$4*(1+F$14)*(1-$A16)/(1+VCM!$B$5)^VCM!$B$3-VCM!$E$3)/1000000 -> 56.193713
A17: 0.4 | B17: =(VCM!$E$4*(1+B$14)*(1-$A17)/(1+VCM!$B$5)^VCM!$B$3-VCM!$E$3)/1000000 -> 7.578549 | C17: =(VCM!$E$4*(1+C$14)*(1-$A17)/(1+VCM!$B$5)^VCM!$B$3-VCM!$E$3)/1000000 -> 17.873525 | D17: =(VCM!$E$4*(1+D$14)*(1-$A17)/(1+VCM!$B$5)^VCM!$B$3-VCM!$E$3)/1000000 -> 28.168501 | E17: =(VCM!$E$4*(1+E$14)*(1-$A17)/(1+VCM!$B$5)^VCM!$B$3-VCM!$E$3)/1000000 -> 38.463476 | F17: =(VCM!$E$4*(1+F$14)*(1-$A17)/(1+VCM!$B$5)^VCM!$B$3-VCM!$E$3)/1000000 -> 48.758452
A18: 0.45 | B18: =(VCM!$E$4*(1+B$14)*(1-$A18)/(1+VCM!$B$5)^VCM!$B$3-VCM!$E$3)/1000000 -> 3.5749473 | C18: =(VCM!$E$4*(1+C$14)*(1-$A18)/(1+VCM!$B$5)^VCM!$B$3-VCM!$E$3)/1000000 -> 13.012008 | D18: =(VCM!$E$4*(1+D$14)*(1-$A18)/(1+VCM!$B$5)^VCM!$B$3-VCM!$E$3)/1000000 -> 22.44907 | E18: =(VCM!$E$4*(1+E$14)*(1-$A18)/(1+VCM!$B$5)^VCM!$B$3-VCM!$E$3)/1000000 -> 31.886131 | F18: =(VCM!$E$4*(1+F$14)*(1-$A18)/(1+VCM!$B$5)^VCM!$B$3-VCM!$E$3)/1000000 -> 41.323192
A19: 0.5 | B19: =(VCM!$E$4*(1+B$14)*(1-$A19)/(1+VCM!$B$5)^VCM!$B$3-VCM!$E$3)/1000000 -> -0.42865436 | C19: =(VCM!$E$4*(1+C$14)*(1-$A19)/(1+VCM!$B$5)^VCM!$B$3-VCM!$E$3)/1000000 -> 8.1504921 | D19: =(VCM!$E$4*(1+D$14)*(1-$A19)/(1+VCM!$B$5)^VCM!$B$3-VCM!$E$3)/1000000 -> 16.729639 | E19: =(VCM!$E$4*(1+E$14)*(1-$A19)/(1+VCM!$B$5)^VCM!$B$3-VCM!$E$3)/1000000 -> 25.308785 | F19: =(VCM!$E$4*(1+F$14)*(1-$A19)/(1+VCM!$B$5)^VCM!$B$3-VCM!$E$3)/1000000 -> 33.887932
A20: Ô trung tâm = VCM!E11 | B20: =ROUND(D17-VCM!E7/1000000,6) -> 0
A22: Bảng 3. DCF – pre-money: WACC (dòng) × RONIC (cột)
A23: WACC \ RONIC | B23: =Assumption!$B$17+(-0.04) -> 0.083115883 | C23: =Assumption!$B$17+(-0.02) -> 0.10311588 | D23: =Assumption!$B$17+(0) -> 0.12311588 | E23: =Assumption!$B$17+(0.02) -> 0.14311588 | F23: =Assumption!$B$17+(0.04) -> 0.16311588
A24: =Assumption!$B$16+(-0.02) -> 0.12130984 | B24: =(SUMPRODUCT(DCF!$C$10:$G$10*DCF!$C$11:$G$11/(1+$A24)^DCF!$C$3:$G$3)+(DCF!$G$5*(1+Assumption!$B$14)*(1-Assumption!$B$14/B$23)/($A24-Assumption!$B$14))/(1+$A24)^DCF!$G$3+DCF!$B$31-DCF!$B$32)/1000000 -> 16.926245 | C24: =(SUMPRODUCT(DCF!$C$10:$G$10*DCF!$C$11:$G$11/(1+$A24)^DCF!$C$3:$G$3)+(DCF!$G$5*(1+Assumption!$B$14)*(1-Assumption!$B$14/C$23)/($A24-Assumption!$B$14))/(1+$A24)^DCF!$G$3+DCF!$B$31-DCF!$B$32)/1000000 -> 34.163276 | D24: =(SUMPRODUCT(DCF!$C$10:$G$10*DCF!$C$11:$G$11/(1+$A24)^DCF!$C$3:$G$3)+(DCF!$G$5*(1+Assumption!$B$14)*(1-Assumption!$B$14/D$23)/($A24-Assumption!$B$14))/(1+$A24)^DCF!$G$3+DCF!$B$31-DCF!$B$32)/1000000 -> 45.800045 | E24: =(SUMPRODUCT(DCF!$C$10:$G$10*DCF!$C$11:$G$11/(1+$A24)^DCF!$C$3:$G$3)+(DCF!$G$5*(1+Assumption!$B$14)*(1-Assumption!$B$14/E$23)/($A24-Assumption!$B$14))/(1+$A24)^DCF!$G$3+DCF!$B$31-DCF!$B$32)/1000000 -> 54.184409 | F24: =(SUMPRODUCT(DCF!$C$10:$G$10*DCF!$C$11:$G$11/(1+$A24)^DCF!$C$3:$G$3)+(DCF!$G$5*(1+Assumption!$B$14)*(1-Assumption!$B$14/F$23)/($A24-Assumption!$B$14))/(1+$A24)^DCF!$G$3+DCF!$B$31-DCF!$B$32)/1000000 -> 60.512723
A25: =Assumption!$B$16+(-0.01) -> 0.13130984 | B25: =(SUMPRODUCT(DCF!$C$10:$G$10*DCF!$C$11:$G$11/(1+$A25)^DCF!$C$3:$G$3)+(DCF!$G$5*(1+Assumption!$B$14)*(1-Assumption!$B$14/B$23)/($A25-Assumption!$B$14))/(1+$A25)^DCF!$G$3+DCF!$B$31-DCF!$B$32)/1000000 -> 8.4695031 | C25: =(SUMPRODUCT(DCF!$C$10:$G$10*DCF!$C$11:$G$11/(1+$A25)^DCF!$C$3:$G$3)+(DCF!$G$5*(1+Assumption!$B$14)*(1-Assumption!$B$14/C$23)/($A25-Assumption!$B$14))/(1+$A25)^DCF!$G$3+DCF!$B$31-DCF!$B$32)/1000000 -> 23.026813 | D25: =(SUMPRODUCT(DCF!$C$10:$G$10*DCF!$C$11:$G$11/(1+$A25)^DCF!$C$3:$G$3)+(DCF!$G$5*(1+Assumption!$B$14)*(1-Assumption!$B$14/D$23)/($A25-Assumption!$B$14))/(1+$A25)^DCF!$G$3+DCF!$B$31-DCF!$B$32)/1000000 -> 32.854494 | E25: =(SUMPRODUCT(DCF!$C$10:$G$10*DCF!$C$11:$G$11/(1+$A25)^DCF!$C$3:$G$3)+(DCF!$G$5*(1+Assumption!$B$14)*(1-Assumption!$B$14/E$23)/($A25-Assumption!$B$14))/(1+$A25)^DCF!$G$3+DCF!$B$31-DCF!$B$32)/1000000 -> 39.935399 | F25: =(SUMPRODUCT(DCF!$C$10:$G$10*DCF!$C$11:$G$11/(1+$A25)^DCF!$C$3:$G$3)+(DCF!$G$5*(1+Assumption!$B$14)*(1-Assumption!$B$14/F$23)/($A25-Assumption!$B$14))/(1+$A25)^DCF!$G$3+DCF!$B$31-DCF!$B$32)/1000000 -> 45.279893
A26: =Assumption!$B$16+(0) -> 0.14130984 | B26: =(SUMPRODUCT(DCF!$C$10:$G$10*DCF!$C$11:$G$11/(1+$A26)^DCF!$C$3:$G$3)+(DCF!$G$5*(1+Assumption!$B$14)*(1-Assumption!$B$14/B$23)/($A26-Assumption!$B$14))/(1+$A26)^DCF!$G$3+DCF!$B$31-DCF!$B$32)/1000000 -> 2.0775094 | C26: =(SUMPRODUCT(DCF!$C$10:$G$10*DCF!$C$11:$G$11/(1+$A26)^DCF!$C$3:$G$3)+(DCF!$G$5*(1+Assumption!$B$14)*(1-Assumption!$B$14/C$23)/($A26-Assumption!$B$14))/(1+$A26)^DCF!$G$3+DCF!$B$31-DCF!$B$32)/1000000 -> 14.564654 | D26: =(SUMPRODUCT(DCF!$C$10:$G$10*DCF!$C$11:$G$11/(1+$A26)^DCF!$C$3:$G$3)+(DCF!$G$5*(1+Assumption!$B$14)*(1-Assumption!$B$14/D$23)/($A26-Assumption!$B$14))/(1+$A26)^DCF!$G$3+DCF!$B$31-DCF!$B$32)/1000000 -> 22.994761 | E26: =(SUMPRODUCT(DCF!$C$10:$G$10*DCF!$C$11:$G$11/(1+$A26)^DCF!$C$3:$G$3)+(DCF!$G$5*(1+Assumption!$B$14)*(1-Assumption!$B$14/E$23)/($A26-Assumption!$B$14))/(1+$A26)^DCF!$G$3+DCF!$B$31-DCF!$B$32)/1000000 -> 29.068706 | F26: =(SUMPRODUCT(DCF!$C$10:$G$10*DCF!$C$11:$G$11/(1+$A26)^DCF!$C$3:$G$3)+(DCF!$G$5*(1+Assumption!$B$14)*(1-Assumption!$B$14/F$23)/($A26-Assumption!$B$14))/(1+$A26)^DCF!$G$3+DCF!$B$31-DCF!$B$32)/1000000 -> 33.653171
A27: =Assumption!$B$16+(0.01) -> 0.15130984 | B27: =(SUMPRODUCT(DCF!$C$10:$G$10*DCF!$C$11:$G$11/(1+$A27)^DCF!$C$3:$G$3)+(DCF!$G$5*(1+Assumption!$B$14)*(1-Assumption!$B$14/B$23)/($A27-Assumption!$B$14))/(1+$A27)^DCF!$G$3+DCF!$B$31-DCF!$B$32)/1000000 -> -2.8693504 | C27: =(SUMPRODUCT(DCF!$C$10:$G$10*DCF!$C$11:$G$11/(1+$A27)^DCF!$C$3:$G$3)+(DCF!$G$5*(1+Assumption!$B$14)*(1-Assumption!$B$14/C$23)/($A27-Assumption!$B$14))/(1+$A27)^DCF!$G$3+DCF!$B$31-DCF!$B$32)/1000000 -> 7.9755938 | D27: =(SUMPRODUCT(DCF!$C$10:$G$10*DCF!$C$11:$G$11/(1+$A27)^DCF!$C$3:$G$3)+(DCF!$G$5*(1+Assumption!$B$14)*(1-Assumption!$B$14/D$23)/($A27-Assumption!$B$14))/(1+$A27)^DCF!$G$3+DCF!$B$31-DCF!$B$32)/1000000 -> 15.297046 | E27: =(SUMPRODUCT(DCF!$C$10:$G$10*DCF!$C$11:$G$11/(1+$A27)^DCF!$C$3:$G$3)+(DCF!$G$5*(1+Assumption!$B$14)*(1-Assumption!$B$14/E$23)/($A27-Assumption!$B$14))/(1+$A27)^DCF!$G$3+DCF!$B$31-DCF!$B$32)/1000000 -> 20.572199 | F27: =(SUMPRODUCT(DCF!$C$10:$G$10*DCF!$C$11:$G$11/(1+$A27)^DCF!$C$3:$G$3)+(DCF!$G$5*(1+Assumption!$B$14)*(1-Assumption!$B$14/F$23)/($A27-Assumption!$B$14))/(1+$A27)^DCF!$G$3+DCF!$B$31-DCF!$B$32)/1000000 -> 24.553755
A28: =Assumption!$B$16+(0.02) -> 0.16130984 | B28: =(SUMPRODUCT(DCF!$C$10:$G$10*DCF!$C$11:$G$11/(1+$A28)^DCF!$C$3:$G$3)+(DCF!$G$5*(1+Assumption!$B$14)*(1-Assumption!$B$14/B$23)/($A28-Assumption!$B$14))/(1+$A28)^DCF!$G$3+DCF!$B$31-DCF!$B$32)/1000000 -> -6.7676595 | C28: =(SUMPRODUCT(DCF!$C$10:$G$10*DCF!$C$11:$G$11/(1+$A28)^DCF!$C$3:$G$3)+(DCF!$G$5*(1+Assumption!$B$14)*(1-Assumption!$B$14/C$23)/($A28-Assumption!$B$14))/(1+$A28)^DCF!$G$3+DCF!$B$31-DCF!$B$32)/1000000 -> 2.7467724 | D28: =(SUMPRODUCT(DCF!$C$10:$G$10*DCF!$C$11:$G$11/(1+$A28)^DCF!$C$3:$G$3)+(DCF!$G$5*(1+Assumption!$B$14)*(1-Assumption!$B$14/D$23)/($A28-Assumption!$B$14))/(1+$A28)^DCF!$G$3+DCF!$B$31-DCF!$B$32)/1000000 -> 9.1699924 | E28: =(SUMPRODUCT(DCF!$C$10:$G$10*DCF!$C$11:$G$11/(1+$A28)^DCF!$C$3:$G$3)+(DCF!$G$5*(1+Assumption!$B$14)*(1-Assumption!$B$14/E$23)/($A28-Assumption!$B$14))/(1+$A28)^DCF!$G$3+DCF!$B$31-DCF!$B$32)/1000000 -> 13.797962 | F28: =(SUMPRODUCT(DCF!$C$10:$G$10*DCF!$C$11:$G$11/(1+$A28)^DCF!$C$3:$G$3)+(DCF!$G$5*(1+Assumption!$B$14)*(1-Assumption!$B$14/F$23)/($A28-Assumption!$B$14))/(1+$A28)^DCF!$G$3+DCF!$B$31-DCF!$B$32)/1000000 -> 17.291041

Sheet Checks
A1: KIỂM TRA TÍNH TOÀN VẸN MÔ HÌNH
A3: Kiểm tra | B3: 2026E | C3: 2027E | D3: 2028E | E3: 2029E | F3: 2030E | G3: Trạng thái
A4: BCĐKT cân (Tài sản − Nguồn vốn) | B4: =ROUND('Balance Sheet'!G32-'Balance Sheet'!G75,0) -> 0 | C4: =ROUND('Balance Sheet'!H32-'Balance Sheet'!H75,0) -> 0 | D4: =ROUND('Balance Sheet'!I32-'Balance Sheet'!I75,0) -> 0 | E4: =ROUND('Balance Sheet'!J32-'Balance Sheet'!J75,0) -> 0 | F4: =ROUND('Balance Sheet'!K32-'Balance Sheet'!K75,0) -> 0 | G4: =IF(AND(MAX(B4:F4)=0,MIN(B4:F4)=0),"OK","LỖI") -> OK
A5: Tiền cuối kỳ LCTT − Tiền BCĐKT | B5: =ROUND('Cash Flow Statement'!F34-'Balance Sheet'!G6,0) -> 0 | C5: =ROUND('Cash Flow Statement'!G34-'Balance Sheet'!H6,0) -> 0 | D5: =ROUND('Cash Flow Statement'!H34-'Balance Sheet'!I6,0) -> 0 | E5: =ROUND('Cash Flow Statement'!I34-'Balance Sheet'!J6,0) -> 0 | F5: =ROUND('Cash Flow Statement'!J34-'Balance Sheet'!K6,0) -> 0 | G5: =IF(AND(MAX(B5:F5)=0,MIN(B5:F5)=0),"OK","LỖI") -> OK
A6: LNST BCKQKD − LNST trên LCTT | B6: =ROUND('Income Statement'!E78-'Cash Flow Statement'!F4,0) -> 0 | C6: =ROUND('Income Statement'!F78-'Cash Flow Statement'!G4,0) -> 0 | D6: =ROUND('Income Statement'!G78-'Cash Flow Statement'!H4,0) -> 0 | E6: =ROUND('Income Statement'!H78-'Cash Flow Statement'!I4,0) -> 0 | F6: =ROUND('Income Statement'!I78-'Cash Flow Statement'!J4,0) -> 0 | G6: =IF(AND(MAX(B6:F6)=0,MIN(B6:F6)=0),"OK","LỖI") -> OK
A7: Doanh thu Pro Forma − BCKQKD | B7: =ROUND('Pro Forma'!C4-'Income Statement'!E11,0) -> 0 | C7: =ROUND('Pro Forma'!D4-'Income Statement'!F11,0) -> 0 | D7: =ROUND('Pro Forma'!E4-'Income Statement'!G11,0) -> 0 | E7: =ROUND('Pro Forma'!F4-'Income Statement'!H11,0) -> 0 | F7: =ROUND('Pro Forma'!G4-'Income Statement'!I11,0) -> 0 | G7: =IF(AND(MAX(B7:F7)=0,MIN(B7:F7)=0),"OK","LỖI") -> OK
A8: LNST Pro Forma − BCKQKD | B8: =ROUND('Pro Forma'!C14-'Income Statement'!E78,0) -> 0 | C8: =ROUND('Pro Forma'!D14-'Income Statement'!F78,0) -> 0 | D8: =ROUND('Pro Forma'!E14-'Income Statement'!G78,0) -> 0 | E8: =ROUND('Pro Forma'!F14-'Income Statement'!H78,0) -> 0 | F8: =ROUND('Pro Forma'!G14-'Income Statement'!I78,0) -> 0 | G8: =IF(AND(MAX(B8:F8)=0,MIN(B8:F8)=0),"OK","LỖI") -> OK
A9: VLĐ Pro Forma − Drivers | B9: =ROUND('Pro Forma'!C36-Drivers!F115,0) -> 0 | C9: =ROUND('Pro Forma'!D36-Drivers!G115,0) -> 0 | D9: =ROUND('Pro Forma'!E36-Drivers!H115,0) -> 0 | E9: =ROUND('Pro Forma'!F36-Drivers!I115,0) -> 0 | F9: =ROUND('Pro Forma'!G36-Drivers!J115,0) -> 0 | G9: =IF(AND(MAX(B9:F9)=0,MIN(B9:F9)=0),"OK","LỖI") -> OK
A10: Khấu hao Pro Forma − BCKQKD | B10: =ROUND('Pro Forma'!C9-'Income Statement'!E69,0) -> 0 | C10: =ROUND('Pro Forma'!D9-'Income Statement'!F69,0) -> 0 | D10: =ROUND('Pro Forma'!E9-'Income Statement'!G69,0) -> 0 | E10: =ROUND('Pro Forma'!F9-'Income Statement'!H69,0) -> 0 | F10: =ROUND('Pro Forma'!G9-'Income Statement'!I69,0) -> 0 | G10: =IF(AND(MAX(B10:F10)=0,MIN(B10:F10)=0),"OK","LỖI") -> OK
A11: CAPEX Drivers + dòng tiền đầu tư | B11: =ROUND(SUM(Drivers!F96,'Cash Flow Statement'!F20),0) -> 0 | C11: =ROUND(SUM(Drivers!G96,'Cash Flow Statement'!G20),0) -> 0 | D11: =ROUND(SUM(Drivers!H96,'Cash Flow Statement'!H20),0) -> 0 | E11: =ROUND(SUM(Drivers!I96,'Cash Flow Statement'!I20),0) -> 0 | F11: =ROUND(SUM(Drivers!J96,'Cash Flow Statement'!J20),0) -> 0 | G11: =IF(AND(MAX(B11:F11)=0,MIN(B11:F11)=0),"OK","LỖI") -> OK
A12: Tiền mặt sau gọi vốn − tiền tối thiểu (≥ 0) | B12: =ROUND(MIN(0,'Balance Sheet'!G6-Drivers!F121),0) -> 0 | C12: =ROUND(MIN(0,'Balance Sheet'!H6-Drivers!G121),0) -> 0 | D12: =ROUND(MIN(0,'Balance Sheet'!I6-Drivers!H121),0) -> 0 | E12: =ROUND(MIN(0,'Balance Sheet'!J6-Drivers!I121),0) -> 0 | F12: =ROUND(MIN(0,'Balance Sheet'!K6-Drivers!J121),0) -> 0 | G12: =IF(AND(MAX(B12:F12)=0,MIN(B12:F12)=0),"OK","LỖI") -> OK
A13: CAPEX/DT năm đầu tư lớn = 65% | B13: =SUMPRODUCT((Drivers!F7:J7=Drivers!C156)*Drivers!F94:J94) -> 0.65 | G13: =IF(ROUND(B13,4)=Drivers!C158,"OK","LỖI") -> OK
A14: Ô trung tâm bảng độ nhạy = kết quả DCF/VCM | B14: =Sensitivity!B11 -> 0 | C14: =Sensitivity!B20 -> 0 | G14: =IF(AND(B14=0,C14=0),"OK","LỖI") -> OK
A15: g < WACC | G15: =IF(Assumption!B14<Assumption!B16,"OK","LỖI") -> OK
A16: Vay trung hạn chỉ phát sinh ở năm đầu tư lớn | B16: =IF(Drivers!F$7=Drivers!$C$156,0,Drivers!F124) -> 0 | C16: =IF(Drivers!G$7=Drivers!$C$156,0,Drivers!G124) -> 0 | D16: =IF(Drivers!H$7=Drivers!$C$156,0,Drivers!H124) -> 0 | E16: =IF(Drivers!I$7=Drivers!$C$156,0,Drivers!I124) -> 0 | F16: =IF(Drivers!J$7=Drivers!$C$156,0,Drivers!J124) -> 0 | G16: =IF(AND(MAX(B16:F16)=0,MIN(B16:F16)=0),"OK","LỖI") -> OK
A17: TỔNG HỢP | G17: =IF(AND(COUNTIF(G4:G16,"LỖI")=0,SUMPRODUCT(ISERROR(G4:G16)*1)=0),"TẤT CẢ OK","CÓ LỖI") -> TẤT CẢ OK
