Workbook

Sheet Hướng dẫn
B4: Three Statement Model
I6: Năm hiện tại | J6: 2026
C8: LƯU Ý
B9: Model Legend
C11: Ô nhập liệu | D11: ABC | E11: Chỉ nhập dữ liệu vào những ô màu vàng này
C13: Tất cả các ô khác đã được nhập sẵn hàm hoặc là ô chứa dữ liệu cho trước. KHÔNG thay đổi những ô này!
B16: CẤU TRÚC FILE SAU KHI HOÀN THIỆN (Lộc)
B17: Drivers | D17: Mô hình động lực: sản lượng × giá theo 4 phân khúc, chi phí theo dòng, BCKQKD theo chức năng (70/30 tiền lương, 90/10 khấu hao), CAPEX/khấu hao, vốn lưu động, vay, thuế, kịch bản (ô chọn C3, C4). Cột K: nguồn/lý do của từng giả định.
B18: Assumption | D18: Tỷ lệ tổng hợp 2026E–2030E (liên kết từ Drivers) + g, RONIC (nguồn ở cột E).
B19: Pro Forma | D19: KQKD 5 năm, CAPEX, VLĐ, lưu chuyển tiền trước khi huy động vốn, nhu cầu vốn (B61:B63).
B20: IS / BS / CF | D20: Báo cáo tài chính đầy đủ 2023A–2030E; BCKQKD theo chức năng (VAS), EBITDA ghi nhớ ở IS hàng 82; BCĐKT cân (hàng 80).
B21: Discount rate | D21: WACC: Rf = bình quân lợi suất TPCP 10 năm 2016–2025 (bảng A28:D40), ERP Việt Nam, beta ngành → total beta, Kd, cơ cấu vốn mục tiêu; nguồn ở cột C.
B22: DCF / VCM / Multiples | D22: Định giá theo 3 phương pháp: DCF (FCFF), VC Method (thoái vốn 2030, z 40%), bội số EV/EBITDA và P/E của 14 DN bao bì niêm yết (DLOM 30%).
B23: Summary / Sensitivity | D23: Tổng hợp định giá (trọng số 40/40/20), football field, kịch bản, độ nhạy theo nhân tố vĩ mô – ngành (Summary hàng 48–58); bảng độ nhạy tính lại toàn bộ mô hình.
B24: Checks / Chart_Data / Ghi chu | D24: Kiểm tra toàn vẹn; dữ liệu cho từng Fig. của báo cáo; các chỉnh sửa template.

Sheet Investment
A1: Các khoản đầu tư dự kiến 5 năm
B3: Đơn giá (nghìn đồng) | C3: Số lượng | D3: Thành tiền | E3: Tháng | F3: Năm | G3: Thời gian sử dụng | H3: Giá trị còn lại
D4: =SUM(D5:D7) -> 24090000 | F4: ='Cash Flow Statement'!E4+1 -> 2026
A5: Nhà máy sản xuất | B5: 30550000 | C5: 0 | D5: =B5*C5 -> 0 | E5: 10 | G5: 8
A6: Thiết bị sản xuất | B6: 3600000 | C6: 5 | D6: =B6*C6 -> 18000000 | E6: 11 | G6: 5
A7: Xe tải chở hàng | B7: 1218000 | C7: 5 | D7: =B7*C7 -> 6090000 | E7: 11 | G7: 5
D8: =SUM(D9:D10) -> 77100000 | F8: =F4+1 -> 2027
A9: Nhà máy sản xuất | B9: 30550000 | C9: 2 | D9: =B9*C9 -> 61100000 | E9: 10 | G9: 7
A10: Kho hàng | B10: 4000000 | C10: 4 | D10: =B10*C10 -> 16000000 | E10: 5 | G10: 7
D11: =SUM(D12) -> 22640000 | F11: =F8+1 -> 2028 | I11: Đầu tư mạnh tăng trưởng mở rộng KD
A12: Thiết bị sản xuất | B12: 5660000 | C12: 4 | D12: =B12*C12 -> 22640000 | E12: 9 | G12: 5 | I12: CAPEX/Revenue = 60%
D13: =SUM(D14) -> 35220000 | F13: =F11+1 -> 2029
A14: Thiết bị sản xuất | B14: 5870000 | C14: 6 | D14: =B14*C14 -> 35220000 | E14: 4 | G14: 8
D15: =SUM(D16:D17) -> 32460000 | F15: =F13+1 -> 2030
A16: Nâng cấp văn phòng | B16: 8115000 | C16: 4 | D16: =B16*C16 -> 32460000 | E16: 1 | G16: 6

Sheet Income Statement
A1: Income Statement
D3: Đơn vị: Nghìn đồng
B4: ='Hướng dẫn'!J6-3 -> 2023 | C4: =B4+1 -> 2024 | D4: =C4+1 -> 2025 | E4: =D4+1 -> 2026 | F4: =E4+1 -> 2027 | G4: =F4+1 -> 2028 | H4: =G4+1 -> 2029 | I4: =H4+1 -> 2030 | J4: Ngoài kỳ dự phóng 5 năm – không sử dụng
A5: Doanh thu bán hàng
A6: Doanh thu 1 | B6: 15055000 | C6: 24088000 | D6: 38059040 | E6: =Drivers!F14 -> 51242691 | F6: =Drivers!G14 -> 63766405 | G6: =Drivers!H14 -> 87806340 | H6: =Drivers!I14 -> 1.1195308e+08 | I6: =Drivers!J14 -> 1.3360481e+08
A7: Doanh thu 2 | B7: 3020000 | C7: 4228000 | D7: 5898060 | E7: =Drivers!F21 -> 7339545.9 | F7: =Drivers!G21 -> 8833877.4 | G7: =Drivers!H21 -> 11533510 | H7: =Drivers!I21 -> 14117017 | I7: =Drivers!J21 -> 16559261
A8: Doanh thu 3 | B8: 1520000 | C8: 2280000 | D8: 2736000 | E8: =Drivers!F28 -> 3610152 | F8: =Drivers!G28 -> 4763595.6 | G8: =Drivers!H28 -> 6769069.3 | H8: =Drivers!I28 -> 9069199 | I8: =Drivers!J28 -> 11506546
A9: Doanh thu 4 | B9: 0 | C9: 566000 | D9: 1188600 | E9: =Drivers!F35 -> 1930286.4 | F9: =Drivers!G35 -> 2938861 | G9: =Drivers!H35 -> 5071004.7 | H9: =Drivers!I35 -> 7463251.2 | I9: =Drivers!J35 -> 9847760
A11: (-) Khoản giảm trừ | B11: -156760 | C11: -233715 | D11: -335171.9 | E11: =-SUM(E6:E9)*Drivers!F38 -> -448858.73 | F11: =-SUM(F6:F9)*Drivers!G38 -> -562119.17 | G11: =-SUM(G6:G9)*Drivers!H38 -> -778259.47 | H11: =-SUM(H6:H9)*Drivers!I38 -> -998217.85 | I11: =-SUM(I6:I9)*Drivers!J38 -> -1200628.6
A13: Doanh thu thuần | B13: 19438240 | C13: 30928285 | D13: 47546528 | E13: =SUM(E6:E12) -> 63673817 | F13: =SUM(F6:F12) -> 79740620 | G13: =SUM(G6:G12) -> 1.1040166e+08 | H13: =SUM(H6:H12) -> 1.4160433e+08 | I13: =SUM(I6:I12) -> 1.7031775e+08
A15: Giá vốn hàng bán
A16: Chi phí biến đổi | B16: 4956751.2 | C16: 7732071.2 | D16: 11648899 | E16: =Drivers!F55 -> 15918454 | F16: =Drivers!G55 -> 20333858 | G16: =Drivers!H55 -> 29808450 | H16: =Drivers!I55 -> 37525148 | I16: =Drivers!J55 -> 45985792
A17: Chi phí cố định | B17: 1055000 | C17: 1160500 | D17: 1276550 | E17: =Drivers!F56 -> 1404205 | F17: =Drivers!G56 -> 1544625.5 | G17: =Drivers!H56 -> 2599088 | H17: =Drivers!I56 -> 2858996.9 | I17: =Drivers!J56 -> 3144896.5
A18: Tiền lương bộ phận sản xuất (70% quỹ lương) | B18: =Drivers!$C$167*B55 -> 4894400 | C18: =Drivers!$C$167*C55 -> 5383840 | D18: =Drivers!$C$167*D55 -> 7537376 | E18: =Drivers!$C$167*E55 -> 10028626 | F18: =Drivers!$C$167*F55 -> 12838240 | G18: =Drivers!$C$167*G55 -> 18161074 | H18: =Drivers!$C$167*H55 -> 22798298 | I18: =Drivers!$C$167*I55 -> 26825045
A19: Khấu hao TSCĐ sản xuất (90% khấu hao) | B19: =Drivers!$C$168*B71 -> 1288980 | C19: =Drivers!$C$168*C71 -> 2137752 | D19: =Drivers!$C$168*D71 -> 2818756.8 | E19: =Drivers!$C$168*E71 -> 3367885 | F19: =Drivers!$C$168*F71 -> 4743239.4 | G19: =Drivers!$C$168*G71 -> 10341031 | H19: =Drivers!$C$168*H71 -> 11771837 | I19: =Drivers!$C$168*I71 -> 13301163
A20: Tổng Giá vốn hàng bán | B20: =SUM(B16:B19) -> 12195131 | C20: =SUM(C16:C19) -> 16414163 | D20: =SUM(D16:D19) -> 23281582 | E20: =SUM(E16:E19) -> 30719170 | F20: =SUM(F16:F19) -> 39459963 | G20: =SUM(G16:G19) -> 60909642 | H20: =SUM(H16:H19) -> 74954279 | I20: =SUM(I16:I19) -> 89256897
A21: Lợi nhuận gộp | B21: =B13-B20 -> 7243108.8 | C21: =C13-C20 -> 14514122 | D21: =D13-D20 -> 24264946 | E21: =E13-E20 -> 32954647 | F21: =F13-F20 -> 40280657 | G21: =G13-G20 -> 49492023 | H21: =H13-H20 -> 66650054 | I21: =I13-I20 -> 81060851
A22: Biên lợi nhuận gộp | B22: =B21/B13 -> 0.37262164 | C22: =C21/C13 -> 0.46928311 | D22: =D21/D13 -> 0.51034107 | E22: =E21/E13 -> 0.51755412 | F22: =F21/F13 -> 0.50514602 | G22: =G21/G13 -> 0.44829054 | H22: =H21/H13 -> 0.47067807 | I22: =I21/I13 -> 0.47593895
A23: Chi phí
A24: Chi phí Bán hàng và quản lý doanh nghiệp
A25: Tiền lương bộ phận bán hàng & quản lý (30% quỹ lương) | B25: =(1-Drivers!$C$167)*B55 -> 2097600 | C25: =(1-Drivers!$C$167)*C55 -> 2307360 | D25: =(1-Drivers!$C$167)*D55 -> 3230304 | E25: =(1-Drivers!$C$167)*E55 -> 4297982.6 | F25: =(1-Drivers!$C$167)*F55 -> 5502102.8 | G25: =(1-Drivers!$C$167)*G55 -> 7783317.4 | H25: =(1-Drivers!$C$167)*H55 -> 9770698.9 | I25: =(1-Drivers!$C$167)*I55 -> 11496448
A26: Thuê mặt bằng | B26: 3977000 | C26: 5368950 | D26: 7570219.5 | E26: =Drivers!F66 -> 8478645.8 | F26: =Drivers!G66 -> 9750442.7 | G26: =Drivers!H66 -> 12675576 | H26: =Drivers!I66 -> 14196645 | I26: =Drivers!J66 -> 15900242
A27: Khấu hao TSCĐ bộ phận bán hàng & quản lý (10% khấu hao) | B27: =(1-Drivers!$C$168)*B71 -> 143220 | C27: =(1-Drivers!$C$168)*C71 -> 237528 | D27: =(1-Drivers!$C$168)*D71 -> 313195.2 | E27: =(1-Drivers!$C$168)*E71 -> 374209.44 | F27: =(1-Drivers!$C$168)*F71 -> 527026.6 | G27: =(1-Drivers!$C$168)*G71 -> 1149003.4 | H27: =(1-Drivers!$C$168)*H71 -> 1307981.8 | I27: =(1-Drivers!$C$168)*I71 -> 1477907
A28: Sửa chữa, bảo dưỡng | B28: 950000 | C28: 1615000 | D28: 2083350 | E28: =Drivers!F68 -> 2801647.9 | F28: =Drivers!G68 -> 3508587.3 | G28: =Drivers!H68 -> 4857673.3 | H28: =Drivers!I68 -> 6230590.6 | I28: =Drivers!J68 -> 7493980.9
A29: Furniture & Fixtures | B29: 0 | C29: 0 | D29: 0 | E29: 0 | F29: 0 | G29: 0 | H29: 0 | I29: 0
A30: Chi phí dịch vụ chung (điện, nước...) | B30: 1200000 | C30: 1800000 | D30: 2250000 | E30: =Drivers!F70 -> 3183690.8 | F30: =Drivers!G70 -> 3987031 | G30: =Drivers!H70 -> 5520083.2 | H30: =Drivers!I70 -> 7080216.6 | I30: =Drivers!J70 -> 8515887.4
A31: Internet & Communications | B31: 0 | C31: 0 | D31: 0 | E31: 0 | F31: 0 | G31: 0 | H31: 0 | I31: 0
A32: Infrastructure Services | B32: 0 | C32: 0 | D32: 0 | E32: 0 | F32: 0 | G32: 0 | H32: 0 | I32: 0
A33: Software | B33: 0 | C33: 0 | D33: 0 | E33: 0 | F33: 0 | G33: 0 | H33: 0 | I33: 0
A34: Bank Service Charges | B34: 0 | C34: 0 | D34: 0 | E34: 0 | F34: 0 | G34: 0 | H34: 0 | I34: 0
A35: Business Licenses and Permits | B35: 0 | C35: 0 | D35: 0 | E35: 0 | F35: 0 | G35: 0 | H35: 0 | I35: 0
A36: Conferences, Dues, and Subscriptions | B36: 0 | C36: 0 | D36: 0 | E36: 0 | F36: 0 | G36: 0 | H36: 0 | I36: 0
A37: Văn phòng phẩm | B37: 0 | C37: 0 | D37: 0 | E37: 0 | F37: 0 | G37: 0 | H37: 0 | I37: 0
A38: Gifts | B38: 0 | C38: 0 | D38: 0 | E38: 0 | F38: 0 | G38: 0 | H38: 0 | I38: 0
A39: Printing , Postage and Delivery | B39: 0 | C39: 0 | D39: 0 | E39: 0 | F39: 0 | G39: 0 | H39: 0 | I39: 0
A40: Miscellaneous | B40: 0 | C40: 0 | D40: 0 | E40: 0 | F40: 0 | G40: 0 | H40: 0 | I40: 0
A41: Recruiting Expense | B41: 0 | C41: 0 | D41: 0 | E41: 0 | F41: 0 | G41: 0 | H41: 0 | I41: 0
A42: Hỗ trợ tiền ăn cho CNV | B42: 2150000 | C42: 2580000 | D42: 3096000 | E42: =Drivers!F64 -> 4011450.5 | F42: =Drivers!G64 -> 5135295.9 | G42: =Drivers!H64 -> 7264429.6 | H42: =Drivers!I64 -> 9119319 | I42: =Drivers!J64 -> 10730018
A43: Equipment Rental | B43: 0 | C43: 0 | D43: 0 | E43: 0 | F43: 0 | G43: 0 | H43: 0 | I43: 0
A44: Other Tech Expense | B44: 0 | C44: 0 | D44: 0 | E44: 0 | F44: 0 | G44: 0 | H44: 0 | I44: 0
A45: Professional Services (dùng cho: Kiểm nghiệm, chứng nhận & R&D vật liệu) | B45: 0 | C45: 0 | D45: 0 | E45: =Drivers!F74 -> 382042.9 | F45: =Drivers!G74 -> 478443.72 | G45: =Drivers!H74 -> 662409.99 | H45: =Drivers!I74 -> 849626 | I45: =Drivers!J74 -> 1021906.5
A46: Accounting Fees | B46: 0 | C46: 0 | D46: 0 | E46: 0 | F46: 0 | G46: 0 | H46: 0 | I46: 0
A47: Legal Fees | B47: 0 | C47: 0 | D47: 0 | E47: 0 | F47: 0 | G47: 0 | H47: 0 | I47: 0
A48: Consultant Fees | B48: 0 | C48: 0 | D48: 0 | E48: 0 | F48: 0 | G48: 0 | H48: 0 | I48: 0
A49: Other Professional Services | B49: 0 | C49: 0 | D49: 0 | E49: 0 | F49: 0 | G49: 0 | H49: 0 | I49: 0
A50: Marketing | B50: 920000 | C50: 966000 | D50: 1159200 | E50: =Drivers!F72 -> 1782866.9 | F50: =Drivers!G72 -> 2392218.6 | G50: =Drivers!H72 -> 3312049.9 | H50: =Drivers!I72 -> 4248130 | I50: =Drivers!J72 -> 4768896.9
A51: Public Relations | B51: 0 | C51: 0 | D51: 0 | E51: 0 | F51: 0 | G51: 0 | H51: 0 | I51: 0
A52: Tổng Chi phí bán hàng và quản lý doanh nghiệp | B52: =SUBTOTAL(9,B25:B51) -> 11437820 | C52: =SUBTOTAL(9,C25:C51) -> 14874838 | D52: =SUBTOTAL(9,D25:D51) -> 19702269 | E52: =SUBTOTAL(9,E25:E51) -> 25312537 | F52: =SUBTOTAL(9,F25:F51) -> 31281149 | G52: =SUBTOTAL(9,G25:G51) -> 43224542 | H52: =SUBTOTAL(9,H25:H51) -> 52803208 | I52: =SUBTOTAL(9,I25:I51) -> 61405287
A54: Tiền lương
A55: Tổng quỹ tiền lương (trước phân bổ) | B55: 6992000 | C55: 7691200 | D55: 10767680 | E55: =Drivers!F62 -> 14326609 | F55: =Drivers!G62 -> 18340343 | G55: =Drivers!H62 -> 25944391 | H55: =Drivers!I62 -> 32568996 | I55: =Drivers!J62 -> 38321493
A56: (−) Phân bổ vào giá vốn hàng bán (70%) | B56: =-B18 -> -4894400 | C56: =-C18 -> -5383840 | D56: =-D18 -> -7537376 | E56: =-E18 -> -10028626 | F56: =-F18 -> -12838240 | G56: =-G18 -> -18161074 | H56: =-H18 -> -22798298 | I56: =-I18 -> -26825045
A57: (−) Phân bổ vào chi phí bán hàng & QLDN (30%) | B57: =-B25 -> -2097600 | C57: =-C25 -> -2307360 | D57: =-D25 -> -3230304 | E57: =-E25 -> -4297982.6 | F57: =-F25 -> -5502102.8 | G57: =-G25 -> -7783317.4 | H57: =-H25 -> -9770698.9 | I57: =-I25 -> -11496448
A58: Payroll Processing Fees | B58: 0 | C58: 0 | D58: 0 | E58: 0 | F58: 0 | G58: 0 | H58: 0 | I58: 0
A59: Bonuses | B59: 0 | C59: 0 | D59: 0 | E59: 0 | F59: 0 | G59: 0 | H59: 0 | I59: 0
A60: Commissions | B60: 0 | C60: 0 | D60: 0 | E60: 0 | F60: 0 | G60: 0 | H60: 0 | I60: 0
A61: Tiền lương chưa phân bổ (= 0) | B61: =SUBTOTAL(9,B55:B60) -> 0 | C61: =SUBTOTAL(9,C55:C60) -> 0 | D61: =SUBTOTAL(9,D55:D60) -> 0 | E61: =SUBTOTAL(9,E55:E60) -> 0 | F61: =SUBTOTAL(9,F55:F60) -> 0 | G61: =SUBTOTAL(9,G55:G60) -> 0 | H61: =SUBTOTAL(9,H55:H60) -> 0 | I61: =SUBTOTAL(9,I55:I60) -> 0
A63: Tổng chi phí bán hàng & QLDN (theo chức năng) | B63: =SUBTOTAL(9,B25:B62) -> 11437820 | C63: =SUBTOTAL(9,C25:C62) -> 14874838 | D63: =SUBTOTAL(9,D25:D62) -> 19702269 | E63: =SUBTOTAL(9,E25:E62) -> 25312537 | F63: =SUBTOTAL(9,F25:F62) -> 31281149 | G63: =SUBTOTAL(9,G25:G62) -> 43224542 | H63: =SUBTOTAL(9,H25:H62) -> 52803208 | I63: =SUBTOTAL(9,I25:I62) -> 61405287
A65: Lợi nhuận thuần từ HĐKD trước lãi vay (EBIT) | B65: =B21-B63 -> -4194711.2 | C65: =C21-C63 -> -360716.25 | D65: =D21-D63 -> 4562677.2 | E65: =E21-E63 -> 7642109.6 | F65: =F21-F63 -> 8999508.6 | G65: =G21-G63 -> 6267480.2 | H65: =H21-H63 -> 13846846 | I65: =I21-I63 -> 19655564
A66: Thu/chi khác
A67: Interest Income | B67: 0 | C67: 0 | D67: 0 | E67: 0 | F67: 0 | G67: 0 | H67: 0 | I67: 0
A68: Other Income | B68: 0 | C68: 0 | D68: 0 | E68: 0 | F68: 0 | G68: 0 | H68: 0 | I68: 0
A69: Chi phí tài chính | B69: 114300 | C69: 142560 | D69: 142182 | E69: =Drivers!F129 -> 160260 | F69: =Drivers!G129 -> 1715202.1 | G69: =Drivers!H129 -> 3270144.2 | H69: =Drivers!I129 -> 2959155.8 | I69: =Drivers!J129 -> 2337178.9
A70: Bad Debt Expense | B70: 0 | C70: 0 | D70: 0 | E70: 0 | F70: 0 | G70: 0 | H70: 0 | I70: 0
A71: Khấu hao (ghi nhớ – đã phân bổ 90% vào GVHB, 10% vào CPBH & QLDN) | B71: 1432200 | C71: 2375280 | D71: 3131952 | E71: =Drivers!F98 -> 3742094.4 | F71: =Drivers!G98 -> 5270266 | G71: =Drivers!H98 -> 11490034 | H71: =Drivers!I98 -> 13079818 | I71: =Drivers!J98 -> 14779070
A72: Amortization | B72: 0 | C72: 0 | D72: 0 | E72: 0 | F72: 0 | G72: 0 | H72: 0 | I72: 0
A74: Tổng chi phí tài chính (khấu hao đã nằm trong GVHB và CPBH & QLDN) | B74: =SUM(B67:B70)+SUM(B72:B73) -> 114300 | C74: =SUM(C67:C70)+SUM(C72:C73) -> 142560 | D74: =SUM(D67:D70)+SUM(D72:D73) -> 142182 | E74: =SUM(E67:E70)+SUM(E72:E73) -> 160260 | F74: =SUM(F67:F70)+SUM(F72:F73) -> 1715202.1 | G74: =SUM(G67:G70)+SUM(G72:G73) -> 3270144.2 | H74: =SUM(H67:H70)+SUM(H72:H73) -> 2959155.8 | I74: =SUM(I67:I70)+SUM(I72:I73) -> 2337178.9
A76: Lợi nhuận trước thuế | B76: =B65-B74 -> -4309011.2 | C76: =C65-C74 -> -503276.25 | D76: =D65-D74 -> 4420495.2 | E76: =E65-E74 -> 7481849.6 | F76: =F65-F74 -> 7284306.5 | G76: =G65-G74 -> 2997336 | H76: =H65-H74 -> 10887690 | I76: =I65-I74 -> 17318385
A77: Thuế
A78: Thuế thu nhập doanh nghiệp | B78: 0 | C78: 0 | D78: 0 | E78: =Drivers!F137 -> 902709.76 | F78: =Drivers!G137 -> 1456861.3 | G78: =Drivers!H137 -> 599467.2 | H78: =Drivers!I137 -> 2177538 | I78: =Drivers!J137 -> 3463677
A80: Lợi nhuận sau thuế | B80: =B76-B78 -> -4309011.2 | C80: =C76-C78 -> -503276.25 | D80: =D76-D78 -> 4420495.2 | E80: =E76-E78 -> 6579139.9 | F80: =F76-F78 -> 5827445.2 | G80: =G76-G78 -> 2397868.8 | H80: =H76-H78 -> 8710152.1 | I80: =I76-I78 -> 13854708
A82: EBITDA = EBIT + khấu hao | B82: =B65+B71 -> -2762511.2 | C82: =C65+C71 -> 2014563.8 | D82: =D65+D71 -> 7694629.2 | E82: =E65+E71 -> 11384204 | F82: =F65+F71 -> 14269775 | G82: =G65+G71 -> 17757515 | H82: =H65+H71 -> 26926664 | I82: =I65+I71 -> 34434634
A83: Biên EBITDA | B83: =B82/B13 -> -0.14211735 | C83: =C82/C13 -> 0.065136614 | D83: =D82/D13 -> 0.16183367 | E83: =E82/E13 -> 0.17878941 | F83: =F82/F13 -> 0.17895239 | G83: =G82/G13 -> 0.16084463 | H83: =H82/H13 -> 0.19015424 | I83: =I82/I13 -> 0.20217878

Sheet Balance Sheet
B1: Balance Sheet
G2: Đơn vị: Nghìn đồng
D3: ='Hướng dẫn'!J6-3 -> 2023 | F3: =D3+1 -> 2024 | G3: =F3+1 -> 2025 | H3: =G3+1 -> 2026 | I3: =H3+1 -> 2027 | J3: =I3+1 -> 2028 | K3: =J3+1 -> 2029 | L3: =K3+1 -> 2030 | M3: Ngoài kỳ dự phóng – không sử dụng
A4: Tài sản ngắn hạn | D4: 01/01/2023 (đầu kỳ) | E4: 31/12/2023
B5: Tiền và các khoản tương đương tiền
C6: Tiền mặt | D6: 910000 | E6: 43988.8 | F6: 1735532.6 | G6: 2933481.8 | H6: ='Cash Flow Statement'!F36 -> 35546329 | I6: ='Cash Flow Statement'!G36 -> 22631264 | J6: ='Cash Flow Statement'!H36 -> 16331816 | K6: ='Cash Flow Statement'!I36 -> 11367772 | L6: ='Cash Flow Statement'!J36 -> 11935048
C7: Tổng tiền mặt | D7: 910000 | E7: 43988.8 | F7: 1735532.6 | G7: 2933481.8 | H7: =SUBTOTAL(9,H6) -> 35546329 | I7: =SUBTOTAL(9,I6) -> 22631264 | J7: =SUBTOTAL(9,J6) -> 16331816 | K7: =SUBTOTAL(9,K6) -> 11367772 | L7: =SUBTOTAL(9,L6) -> 11935048
B8: Hàng tồn kho
C9: Hàng tồn kho | D9: 1785000 | E9: 2499000 | F9: 2998800 | G9: 3748500 | H9: =Drivers!F105 -> 4745934 | I9: =Drivers!G105 -> 5994105.1 | J9: =Drivers!H105 -> 9322716.3 | K9: =Drivers!I105 -> 11064149 | L9: =Drivers!J105 -> 12787439
C10: Tổng hàng tồn kho | D10: 1785000 | E10: 2499000 | F10: 2998800 | G10: 3748500 | H10: =SUBTOTAL(9, H9) -> 4745934 | I10: =SUBTOTAL(9, I9) -> 5994105.1 | J10: =SUBTOTAL(9, J9) -> 9322716.3 | K10: =SUBTOTAL(9, K9) -> 11064149 | L10: =SUBTOTAL(9, L9) -> 12787439
B11: Khoản phải thu
C12: Phải thu khách hàng | D12: 1050000 | E12: 1260000 | F12: 1537200 | G12: 1767780 | H12: =Drivers!F107 -> 3140078.6 | I12: =Drivers!G107 -> 4806284 | J12: =Drivers!H107 -> 7864228.2 | K12: =Drivers!I107 -> 11638712 | L12: =Drivers!J107 -> 13998719
C13: Tổng khoản phải thu | D13: 1050000 | E13: 1260000 | F13: 1537200 | G13: 1767780 | H13: =SUBTOTAL(9, H12) -> 3140078.6 | I13: =SUBTOTAL(9, I12) -> 4806284 | J13: =SUBTOTAL(9, J12) -> 7864228.2 | K13: =SUBTOTAL(9, K12) -> 11638712 | L13: =SUBTOTAL(9, L12) -> 13998719
B14: Tài sản ngắn hạn khác
C15: Other Receivable | D15: 0 | E15: 0 | F15: 0 | G15: 0 | H15: 0 | I15: 0 | J15: 0 | K15: 0 | L15: 0
C16: Chi phí trả trước | D16: 890000 | E16: 1068000 | F16: 1495200 | G16: 1794240 | H16: =Drivers!F109*$G$16/$G$20 -> 2204363.7 | I16: =Drivers!G109*$G$16/$G$20 -> 2760590.4 | J16: =Drivers!H109*$G$16/$G$20 -> 3822064.3 | K16: =Drivers!I109*$G$16/$G$20 -> 4902289 | L16: =Drivers!J109*$G$16/$G$20 -> 5896336.7
C17: Prepaid Insurance | D17: - | E17: - | F17: - | G17: - | H17: 0 | I17: 0 | J17: 0 | K17: 0 | L17: 0
C18: Unbilled Revenue | D18: - | E18: - | F18: - | G18: - | H18: 0 | I18: 0 | J18: 0 | K18: 0 | L18: 0
C19: Tài sản ngắn hạn khác | D19: 150000 | E19: 165000 | F19: 214500 | G19: 278850 | H19: =Drivers!F109*$G$19/$G$20 -> 342588.96 | I19: =Drivers!G109*$G$19/$G$20 -> 429034.38 | J19: =Drivers!H109*$G$19/$G$20 -> 594002.27 | K19: =Drivers!I109*$G$19/$G$20 -> 761884.3 | L19: =Drivers!J109*$G$19/$G$20 -> 916373.22
C20: Tổng tài sản ngắn hạn khác | D20: 1040000 | E20: 1233000 | F20: 1709700 | G20: 2073090 | H20: =SUBTOTAL(9,H15:H19) -> 2546952.7 | I20: =SUBTOTAL(9,I15:I19) -> 3189624.8 | J20: =SUBTOTAL(9,J15:J19) -> 4416066.6 | K20: =SUBTOTAL(9,K15:K19) -> 5664173.3 | L20: =SUBTOTAL(9,L15:L19) -> 6812709.9
B22: Tổng tài sản ngắn hạn | D22: 4785000 | E22: 5035988.8 | F22: 7981232.5 | G22: 10522852 | H22: =SUBTOTAL(9,H5:H21) -> 45979295 | I22: =SUBTOTAL(9,I5:I21) -> 36621278 | J22: =SUBTOTAL(9,J5:J21) -> 37934827 | K22: =SUBTOTAL(9,K5:K21) -> 39734807 | L22: =SUBTOTAL(9,L5:L21) -> 45533916
D23: 0 | E23: 0 | F23: 0 | G23: 0
A24: Tài sản dài hạn
B25: Khấu khao
C26: Khấu hao lũy kế | D26: 2850000 | E26: 4282200 | F26: 6657480 | G26: 9789432 | H26: =G26+'Income Statement'!E71 -> 13531526 | I26: =H26+'Income Statement'!F71 -> 18801792 | J26: =I26+'Income Statement'!G71 -> 30291827 | K26: =J26+'Income Statement'!H71 -> 43371645 | L26: =K26+'Income Statement'!I71 -> 58150715
C27: Accumulated Amortization | D27: 0 | E27: 0 | F27: 0 | G27: 0 | H27: =G27+'Income Statement'!E72 -> 0 | I27: =H27+'Income Statement'!F72 -> 0 | J27: =I27+'Income Statement'!G72 -> 0 | K27: =J27+'Income Statement'!H72 -> 0 | L27: =K27+'Income Statement'!I72 -> 0
B28: Tài sản dài hạn
C29: Tài sản cố định vô hình | D29: 985000 | E29: 985000 | F29: 1020000 | G29: 1020000 | H29: =G29 -> 1020000 | I29: =H29 -> 1020000 | J29: =I29 -> 1020000 | K29: =J29 -> 1020000 | L29: =K29 -> 1020000
C30: Thiết bị, nhà xưởng | D30: 10220000 | E30: 13797000 | F30: 19315800 | G30: 21633696 | H30: =G30+Drivers!F95 -> 34368459 | I30: =H30+Drivers!G95 -> 86199862 | J30: =I30+Drivers!H95 -> 99448062 | K30: =J30+Drivers!I95 -> 1.136085e+08 | L30: =K30+Drivers!J95 -> 1.3064027e+08
C31: Văn phòng | D31: 3580000 | E31: 5012000 | F31: 5763800 | G31: 8530424 | H31: =G31 -> 8530424 | I31: =H31 -> 8530424 | J31: =I31 -> 8530424 | K31: =J31 -> 8530424 | L31: =K31 -> 8530424
B32: Tổng tài sản dài hạn | D32: 11935000 | E32: 15511800 | F32: 19442120 | G32: 21394688 | H32: =SUM(H29:H31)-H26-H27 -> 30387357 | I32: =SUM(I29:I31)-I26-I27 -> 76948494 | J32: =SUM(J29:J31)-J26-J27 -> 78706659 | K32: =SUM(K29:K31)-K26-K27 -> 79787274 | L32: =SUM(L29:L31)-L26-L27 -> 82039979
A34: Tổng tài sản | D34: 16720000 | E34: 20547789 | F34: 27423353 | G34: 31917540 | H34: =H22+H32 -> 76366652 | I34: =I22+I32 -> 1.1356977e+08 | J34: =J22+J32 -> 1.1664149e+08 | K34: =K22+K32 -> 1.1952208e+08 | L34: =L22+L32 -> 1.2757389e+08
D35: 0 | E35: 0 | F35: 0 | G35: 0
A37: Nợ phải trả và Vốn chủ sở hữu
A38: Nợ ngắn hạn
B39: Khoản phải trả
C40: Phải trả người bán | D40: 120000 | E40: 156000 | F40: 202800 | G40: 263640 | H40: =Drivers!F111 -> 474593.4 | I40: =Drivers!G111 -> 719292.61 | J40: =Drivers!H111 -> 1331816.6 | K40: =Drivers!I111 -> 1659622.4 | L40: =Drivers!J111 -> 2019069.4
C41: Tổng khoản khải trả | D41: 120000 | E41: 156000 | F41: 202800 | G41: 263640 | H41: =SUBTOTAL(9, H40) -> 474593.4 | I41: =SUBTOTAL(9, I40) -> 719292.61 | J41: =SUBTOTAL(9, J40) -> 1331816.6 | K41: =SUBTOTAL(9, K40) -> 1659622.4 | L41: =SUBTOTAL(9, L40) -> 2019069.4
B42: Credit Cards
C43: Credit Card 1 | D43: 0 | E43: 0 | F43: 0 | G43: 0 | H43: 0 | I43: 0 | J43: 0 | K43: 0 | L43: 0
C44: Credit Card 2 | D44: 0 | E44: 0 | F44: 0 | G44: 0 | H44: 0 | I44: 0 | J44: 0 | K44: 0 | L44: 0
C45: Total Credit Cards Payable | D45: 0 | E45: 0 | F45: 0 | G45: 0 | H45: =SUBTOTAL(9,H43:H44) -> 0 | I45: =SUBTOTAL(9,I43:I44) -> 0 | J45: =SUBTOTAL(9,J43:J44) -> 0 | K45: =SUBTOTAL(9,K43:K44) -> 0 | L45: =SUBTOTAL(9,L43:L44) -> 0
B46: Nợ vay ngắn hạn
C47: Khoản vay 1 | D47: 100000 | E47: 90000 | F47: 108000 | G47: 102600 | H47: =Drivers!F121 -> 102600 | I47: =Drivers!G121 -> 102600 | J47: =Drivers!H121 -> 102600 | K47: =Drivers!I121 -> 102600 | L47: =Drivers!J121 -> 102600
C48: Tổng nợ vay ngắn hạn | D48: 100000 | E48: 90000 | F48: 108000 | G48: 102600 | H48: =SUBTOTAL(9,H47:H47) -> 102600 | I48: =SUBTOTAL(9,I47:I47) -> 102600 | J48: =SUBTOTAL(9,J47:J47) -> 102600 | K48: =SUBTOTAL(9,K47:K47) -> 102600 | L48: =SUBTOTAL(9,L47:L47) -> 102600
B49: Deferred Income/Advances from Customers
C50: Deferred Income - current | D50: 0 | E50: 0 | F50: 0 | G50: 0 | H50: 0 | I50: 0 | J50: 0 | K50: 0 | L50: 0
C51: Total Deferred Income | D51: 0 | E51: 0 | F51: 0 | G51: 0 | H51: =SUBTOTAL(9, H50) -> 0 | I51: =SUBTOTAL(9, I50) -> 0 | J51: =SUBTOTAL(9, J50) -> 0 | K51: =SUBTOTAL(9, K50) -> 0 | L51: =SUBTOTAL(9, L50) -> 0
B52: Nợ phải trả ngắn hạn khác
C53: Accrued Expenses | D53: 0 | E53: 0 | F53: 0 | G53: 0 | H53: 0 | I53: 0 | J53: 0 | K53: 0 | L53: 0
C54: Accrued Income Taxes | D54: 0 | E54: 0 | F54: 0 | G54: 0 | H54: 0 | I54: 0 | J54: 0 | K54: 0 | L54: 0
C55: Nợ phải trả ngắn hạn khác | D55: 36000 | E55: 46800 | F55: 60840 | G55: 79092 | H55: =Drivers!F113 -> 127347.63 | I55: =Drivers!G113 -> 159481.24 | J55: =Drivers!H113 -> 220803.33 | K55: =Drivers!I113 -> 283208.67 | L55: =Drivers!J113 -> 340635.5
C56: Tổng nợ phải trả ngắn hạn khác | D56: 36000 | E56: 46800 | F56: 60840 | G56: 79092 | H56: =SUBTOTAL(9,H53:H55) -> 127347.63 | I56: =SUBTOTAL(9,I53:I55) -> 159481.24 | J56: =SUBTOTAL(9,J53:J55) -> 220803.33 | K56: =SUBTOTAL(9,K53:K55) -> 283208.67 | L56: =SUBTOTAL(9,L53:L55) -> 340635.5
B58: Tổng nợ ngắn hạn | D58: 256000 | E58: 292800 | F58: 371640 | G58: 445332 | H58: =SUBTOTAL(9,H40:H56) -> 704541.04 | I58: =SUBTOTAL(9,I40:I56) -> 981373.85 | J58: =SUBTOTAL(9,J40:J56) -> 1655219.9 | K58: =SUBTOTAL(9,K40:K56) -> 2045431.1 | L58: =SUBTOTAL(9,L40:L56) -> 2462304.9
D59: 0 | E59: 0 | F59: 0 | G59: 0
A60: Nợ dài hạn
C61: Nợ vay dài hạn | D61: 1200000 | E61: 1200000 | F61: 1500000 | G61: 1500000 | H61: =Drivers!F127 -> 1500000 | I61: =Drivers!G127 -> 32598842 | J61: =Drivers!H127 -> 32598842 | K61: =Drivers!I127 -> 26379073 | L61: =Drivers!J127 -> 20159305
C62: Deferred Income Taxes | D62: 0 | E62: 0 | F62: 0 | G62: 0 | H62: 0 | I62: 0 | J62: 0 | K62: 0 | L62: 0
C63: Nợ dài hạn khác | D63: 0 | E63: 0 | F63: 0 | G63: 0 | H63: 0 | I63: 0 | J63: 0 | K63: 0 | L63: 0
B64: Tổng nợ dài hạn | D64: 1200000 | E64: 1200000 | F64: 1500000 | G64: 1500000 | H64: =SUBTOTAL(9,H61:H63) -> 1500000 | I64: =SUBTOTAL(9,I61:I63) -> 32598842 | J64: =SUBTOTAL(9,J61:J63) -> 32598842 | K64: =SUBTOTAL(9,K61:K63) -> 26379073 | L64: =SUBTOTAL(9,L61:L63) -> 20159305
A66: Tổng nợ phải trả | D66: 1456000 | E66: 1492800 | F66: 1871640 | G66: 1945332 | H66: =H58+H64 -> 2204541 | I66: =I58+I64 -> 33580216 | J66: =J58+J64 -> 34254062 | K66: =K58+K64 -> 28424505 | L66: =L58+L64 -> 22621610
D67: 0 | E67: 0 | F67: 0 | G67: 0
A68: Vốn chủ sở hữu
C69: Paid-in Capital | D69: 0 | E69: 0 | F69: 0 | G69: 0 | H69: 0 | I69: 0 | J69: 0 | K69: 0 | L69: 0
C70: Vốn cổ phần | D70: 17044000 | E70: 17044000 | F70: 25144000 | G70: 32144000 | H70: =G70+G72 -> 32144000 | I70: =H70+H72 -> 69754763 | J70: =I70+I72 -> 69754763 | K70: =J70+J72 -> 69754763 | L70: =K70+K72 -> 69754763
C71: Preferred Stock | D71: 0 | E71: 0 | F71: 0 | G71: 0 | H71: 0 | I71: 0 | J71: 0 | K71: 0 | L71: 0
C72: Vốn cổ phần tăng thêm | D72: 0 | E72: 8100000 | F72: 7000000 | G72: 0 | H72: =Drivers!F131 -> 37610763 | I72: =Drivers!G131 -> 0 | J72: =Drivers!H131 -> 0 | K72: =Drivers!I131 -> 0 | L72: =Drivers!J131 -> 0
C73: Capital Raising Round B | D73: 0 | E73: 0 | F73: 0 | G73: 0 | H73: 0 | I73: 0 | J73: 0 | K73: 0 | L73: 0
C74: Capital Raising Round C | D74: 0 | E74: 0 | F74: 0 | G74: 0 | H74: 0 | I74: 0 | J74: 0 | K74: 0 | L74: 0
C75: Lợi nhuận giữ lại | D75: -1780000 | E75: -6089011.2 | F75: -6592287.5 | G75: -2171792.2 | H75: ='Income Statement'!E80+G75 -> 4407347.6 | I75: ='Income Statement'!F80+H75 -> 10234793 | J75: ='Income Statement'!G80+I75 -> 12632662 | K75: ='Income Statement'!H80+J75 -> 21342814 | L75: ='Income Statement'!I80+K75 -> 35197522
A76: Tổng vốn chủ sở hữu | D76: 15264000 | E76: 19054989 | F76: 25551713 | G76: 29972208 | H76: =SUM(H69:H75) -> 74162111 | I76: =SUM(I69:I75) -> 79989556 | J76: =SUM(J69:J75) -> 82387425 | K76: =SUM(K69:K75) -> 91097577 | L76: =SUM(L69:L75) -> 1.0495228e+08
A78: Tổng Nợ phải trả và Vốn chủ sở hữu | D78: 16720000 | E78: 20547789 | F78: 27423353 | G78: 31917540 | H78: =H66+H76 -> 76366652 | I78: =I66+I76 -> 1.1356977e+08 | J78: =J66+J76 -> 1.1664149e+08 | K78: =K66+K76 -> 1.1952208e+08 | L78: =L66+L76 -> 1.2757389e+08
E80: =ROUND(E34-E78,0) -> 0 | F80: =ROUND(F34-F78,0) -> 0 | G80: =ROUND(G34-G78,0) -> 0 | H80: =ROUND(H34-H78,0) -> 0 | I80: =ROUND(I34-I78,0) -> 0 | J80: =ROUND(J34-J78,0) -> 0 | K80: =ROUND(K34-K78,0) -> 0 | L80: =ROUND(L34-L78,0) -> 0

Sheet Cash Flow Statement
A1: Statement of Cash Flows
E3: Đơn vị: Nghìn đồng
C4: ='Income Statement'!B4 -> 2023 | D4: =C4+1 -> 2024 | E4: =D4+1 -> 2025 | F4: =E4+1 -> 2026 | G4: =F4+1 -> 2027 | H4: =G4+1 -> 2028 | I4: =H4+1 -> 2029 | J4: =I4+1 -> 2030 | K4: Ngoài kỳ dự phóng – không sử dụng
A5: Hoạt động kinh doanh
B6: Lợi nhuận sau thuế | C6: -4309011.2 | D6: -503276.25 | E6: 4420495.2 | F6: ='Income Statement'!E80 -> 6579139.9 | G6: ='Income Statement'!F80 -> 5827445.2 | H6: ='Income Statement'!G80 -> 2397868.8 | I6: ='Income Statement'!H80 -> 8710152.1 | J6: ='Income Statement'!I80 -> 13854708
B8: Khấu hao | C8: 1432200 | D8: 2375280 | E8: 3131952 | F8: ='Income Statement'!E71 -> 3742094.4 | G8: ='Income Statement'!F71 -> 5270266 | H8: ='Income Statement'!G71 -> 11490034 | I8: ='Income Statement'!H71 -> 13079818 | J8: ='Income Statement'!I71 -> 14779070
A10: Biến động Tài sản ngắn hạn
B11: Khoản phải thu | C11: -210000 | D11: -277200 | E11: -230580 | F11: ='Balance Sheet'!G12-'Balance Sheet'!H12 -> -1372298.6 | G11: ='Balance Sheet'!H12-'Balance Sheet'!I12 -> -1666205.3 | H11: ='Balance Sheet'!I12-'Balance Sheet'!J12 -> -3057944.2 | I11: ='Balance Sheet'!J12-'Balance Sheet'!K12 -> -3774484.1 | J11: ='Balance Sheet'!K12-'Balance Sheet'!L12 -> -2360006.7
B12: Hàng tồn kho | C12: -714000 | D12: -499800 | E12: -749700 | F12: ='Balance Sheet'!G10-'Balance Sheet'!H10 -> -997434.04 | G12: ='Balance Sheet'!H10-'Balance Sheet'!I10 -> -1248171.1 | H12: ='Balance Sheet'!I10-'Balance Sheet'!J10 -> -3328611.2 | I12: ='Balance Sheet'!J10-'Balance Sheet'!K10 -> -1741433 | J12: ='Balance Sheet'!K10-'Balance Sheet'!L10 -> -1723290.2
B13: Tài sản ngắn hạn khác | C13: -193000 | D13: -476700 | E13: -363390 | F13: ='Balance Sheet'!G20-'Balance Sheet'!H20 -> -473862.68 | G13: ='Balance Sheet'!H20-'Balance Sheet'!I20 -> -642672.12 | H13: ='Balance Sheet'!I20-'Balance Sheet'!J20 -> -1226441.8 | I13: ='Balance Sheet'!J20-'Balance Sheet'!K20 -> -1248106.7 | J13: ='Balance Sheet'!K20-'Balance Sheet'!L20 -> -1148536.6
A14: Biến động Nợ ngắn hạn
B15: Khoản phải trả | C15: 36000 | D15: 46800 | E15: 60840 | F15: ='Balance Sheet'!H41-'Balance Sheet'!G41 -> 210953.4 | G15: ='Balance Sheet'!I41-'Balance Sheet'!H41 -> 244699.21 | H15: ='Balance Sheet'!J41-'Balance Sheet'!I41 -> 612524 | I15: ='Balance Sheet'!K41-'Balance Sheet'!J41 -> 327805.78 | J15: ='Balance Sheet'!L41-'Balance Sheet'!K41 -> 359446.99
B16: ='Balance Sheet'!B46 -> Nợ vay ngắn hạn | C16: -10000 | D16: 18000 | E16: -5400 | F16: ='Balance Sheet'!H48-'Balance Sheet'!G48 -> 0 | G16: ='Balance Sheet'!I48-'Balance Sheet'!H48 -> 0 | H16: ='Balance Sheet'!J48-'Balance Sheet'!I48 -> 0 | I16: ='Balance Sheet'!K48-'Balance Sheet'!J48 -> 0 | J16: ='Balance Sheet'!L48-'Balance Sheet'!K48 -> 0
B17: Nợ ngắn hạn khác | C17: 10800 | D17: 14040 | E17: 18252 | F17: =('Balance Sheet'!H56-'Balance Sheet'!G56)+('Balance Sheet'!H51-'Balance Sheet'!G51) -> 48255.634 | G17: =('Balance Sheet'!I56-'Balance Sheet'!H56)+('Balance Sheet'!I51-'Balance Sheet'!H51) -> 32133.606 | H17: =('Balance Sheet'!J56-'Balance Sheet'!I56)+('Balance Sheet'!J51-'Balance Sheet'!I51) -> 61322.09 | I17: =('Balance Sheet'!K56-'Balance Sheet'!J56)+('Balance Sheet'!K51-'Balance Sheet'!J51) -> 62405.335 | J17: =('Balance Sheet'!L56-'Balance Sheet'!K56)+('Balance Sheet'!L51-'Balance Sheet'!K51) -> 57426.831
A19: Lưu chuyển tiền thuần từ hoạt động kinh doanh | C19: -3957011.2 | D19: 697143.75 | E19: 6282469.2 | F19: =SUM(F6:F18) -> 7736847.9 | G19: =SUM(G6:G18) -> 7817495.5 | H19: =SUM(H6:H18) -> 6948752.1 | I19: =SUM(I6:I18) -> 15416158 | J19: =SUM(J6:J18) -> 23818819
A21: Đầu tư
B22: Biến động Tài sản cố định | C22: -5009000 | D22: -6305600 | E22: -5084520 | F22: =SUM('Balance Sheet'!G29:G31)-SUM('Balance Sheet'!H29:H31) -> -12734763 | G22: =SUM('Balance Sheet'!H29:H31)-SUM('Balance Sheet'!I29:I31) -> -51831403 | H22: =SUM('Balance Sheet'!I29:I31)-SUM('Balance Sheet'!J29:J31) -> -13248200 | I22: =SUM('Balance Sheet'!J29:J31)-SUM('Balance Sheet'!K29:K31) -> -14160433 | J22: =SUM('Balance Sheet'!K29:K31)-SUM('Balance Sheet'!L29:L31) -> -17031775
A24: Lưu chuyển tiền thuần từ hoạt động đầu tư | C24: -5009000 | D24: -6305600 | E24: -5084520 | F24: =SUM(F22:F23) -> -12734763 | G24: =SUM(G22:G23) -> -51831403 | H24: =SUM(H22:H23) -> -13248200 | I24: =SUM(I22:I23) -> -14160433 | J24: =SUM(J22:J23) -> -17031775
A26: Tài chính
B27: Nhận vốn góp cổ phần | C27: 8100000 | D27: 7000000 | E27: 0 | F27: ='Balance Sheet'!H72 -> 37610763 | G27: ='Balance Sheet'!I72 -> 0 | H27: ='Balance Sheet'!J72 -> 0 | I27: ='Balance Sheet'!K72 -> 0 | J27: ='Balance Sheet'!L72 -> 0
B28: Vay (trả) nợ dài hạn | C28: 0 | D28: 300000 | E28: 0 | F28: =('Balance Sheet'!H61-'Balance Sheet'!G61) -> 0 | G28: =('Balance Sheet'!I61-'Balance Sheet'!H61) -> 31098842 | H28: =('Balance Sheet'!J61-'Balance Sheet'!I61) -> 0 | I28: =('Balance Sheet'!K61-'Balance Sheet'!J61) -> -6219768.4 | J28: =('Balance Sheet'!L61-'Balance Sheet'!K61) -> -6219768.4
A30: Lưu chuyển tiền thuần từ hoạt động tài chính | C30: 8100000 | D30: 7300000 | E30: 0 | F30: =SUM(F27:F29) -> 37610763 | G30: =SUM(G27:G29) -> 31098842 | H30: =SUM(H27:H29) -> 0 | I30: =SUM(I27:I29) -> -6219768.4 | J30: =SUM(J27:J29) -> -6219768.4
A32: Số dư tiền mặt đầu kỳ | C32: 910000 | D32: 43988.8 | E32: 1735532.6 | F32: =E36 -> 2933481.8 | G32: =F36 -> 35546329 | H32: =G36 -> 22631264 | I32: =H36 -> 16331816 | J32: =I36 -> 11367772
A34: Biến động tiền mặt trong kỳ | C34: -866011.2 | D34: 1691543.8 | E34: 1197949.2 | F34: =F19+F24+F30 -> 32612848 | G34: =G19+G24+G30 -> -12915066 | H34: =H19+H24+H30 -> -6299447.7 | I34: =I19+I24+I30 -> -4964043.9 | J34: =J19+J24+J30 -> 567275.57
A36: Số dư tiền mặt cuối kỳ | C36: 43988.8 | D36: 1735532.6 | E36: 2933481.8 | F36: =F34+F32 -> 35546329 | G36: =G34+G32 -> 22631264 | H36: =H34+H32 -> 16331816 | I36: =I34+I32 -> 11367772 | J36: =J34+J32 -> 11935048

Sheet Discount rate
A1: Discount rate calculation
A3: Beta | B3: =B23 -> 1.4787208 | C3: Beta tổng của AgriPack (B23 = beta có đòn bẩy / ρ); chỉ dùng trong chi phí vốn chủ sở hữu ở E3. | D3: Chi phí vốn CSH | E3: =B4+B3*(B5-B4) -> 0.159427 | F3: CAPM: Ke = Rf + β × (Rm − Rf)
A4: Risk-free rate | B4: =B13 -> 0.039207 | D4: Chi phí vốn nợ (sau thuế) | E4: =B15*(1-Assumption!D15) -> 0.08 | F4: Kd × (1 − thuế suất)
A5: Market return | B5: =B24 -> 0.120507 | C5: Rm = Rf + ERP Việt Nam (B24). Thị trường có beta bằng 1 nên lợi suất thị trường không nhân beta. | D5: WACC | E5: =(B7*E3+B8*E4)/B9 -> 0.13637833 | F5: WACC = E/(D + E) × Ke + D/(D + E) × Kd × (1 − t)
A7: Vốn CSH | B7: ='Balance Sheet'!I76 -> 79989556
A8: Nợ vay dài hạn | B8: ='Balance Sheet'!I61+'Balance Sheet'!I48 -> 32701442
A9: Total | B9: =B7+B8 -> 1.12691e+08
A12: CƠ SỞ TÍNH CHI PHÍ VỐN | C12: Nguồn / lý do (ghi ngay cạnh ô giả định)
A13: Lợi suất phi rủi ro Rf = bình quân lợi suất TPCP 10 năm, 2016–2025 | B13: =B40 -> 0.039207 | C13: Lý do: bình quân lợi suất TPCP kỳ hạn 10 năm của 10 năm 2016–2025 (bảng A28:D40) để không đưa đỉnh/đáy chu kỳ lãi suất vào chi phí vốn dài hạn
A14: ERP thị trường phát triển | B14: 0.0423 | C14: Nguồn: Damodaran (01/2026) – ERP thị trường trưởng thành (Aaa) 4,23%; bản 07/2026: 4,20%.
A15: Lãi suất vay trước thuế (Kd) | B15: 0.1 | C15: Lý do: lãi suất cho vay VND 8,1–10,5%/năm (6/2026); DN nhỏ vay ở nửa trên khung → 10%. Nguồn: NHNN (2026), Mục 3.1.3.
A16: Phần bù rủi ro quốc gia Việt Nam (CRP) | B16: 0.039 | C16: ƯỚC TÍNH: Moody's Ba2 (triển vọng tích cực từ 5/2026); chênh lệch vỡ nợ Ba2 ~2,9% × hệ số biến động cổ phiếu/trái phiếu ~1,35 (phương pháp Damodaran). Nguồn: Moody's (2026); Damodaran (2026).
A17: ERP Việt Nam = ERP phát triển + CRP | B17: =B14+B16 -> 0.0813
A18: Beta không đòn bẩy ngành bao bì (βu) | B18: 0.78 | C18: Nguồn: Damodaran (01/2026) – beta không đòn bẩy ngành Packaging & Container 0,78 (hiệu chỉnh tiền mặt 0,81). Beta 2 năm của DN bao bì niêm yết VN thấp (~0,6) do thanh khoản mỏng nên không dùng.
A19: D/E mục tiêu (BCĐKT dự phóng 2027, sau huy động) | B19: =B8/B7 -> 0.40882139 | C19: Công thức: D/E theo BCĐKT dự phóng cuối 2027 (sau huy động vốn cổ phần và khoản vay trung hạn).
A20: Thuế suất | B20: =Assumption!D15 -> 0.2 | C20: Nguồn: Luật Thuế TNDN 67/2025/QH15 (20%).
A21: Beta có đòn bẩy = βu × [1 + (1 − t) × D/E] | B21: =B18*(1+(1-B20)*B19) -> 1.0351046
A22: Hệ số tương quan ρ (NĐT VC đa dạng hóa một phần) | B22: 0.7 | C22: Công thức: beta tổng = beta có đòn bẩy / ρ (B23 = B21/B22), trong đó ρ là hệ số tương quan giữa danh mục của nhà đầu tư VC và thị trường. ρ = 0,7 vì quỹ VC nắm 20–30 khoản đầu tư nên chỉ đa dạng hóa một phần. Nguồn: Damodaran (2009), Valuing Young, Start-up and Growth Companies.
A23: Beta điều chỉnh cho startup (total beta = β / ρ) | B23: =B21/B22 -> 1.4787208
A24: Lợi suất thị trường kỳ vọng = Rf + ERP Việt Nam | B24: =B13+B17 -> 0.120507
A26: Ghi chú: Trọng số theo cơ cấu vốn mục tiêu (BCĐKT dự phóng cuối 2027, sau Series A và khoản vay trung hạn). CAPM với total beta phản ánh rủi ro phi hệ thống mà NĐT VC không đa dạng hóa hết; rủi ro thất bại được xử lý riêng ở VCM để tránh tính trùng.
A28: LỢI SUẤT TPCP KỲ HẠN 10 NĂM – BÌNH QUÂN 10 NĂM (cơ sở của Rf)
A29: Năm | B29: Lợi suất 10 năm | C29: Thời điểm quan sát | D29: Nguồn
A30: 2016 | B30: 0.0695 | C30: Q1/2016 – lãi suất phát hành kỳ hạn 10 năm | D30: Oxford Business Group (2017). The Report: Vietnam 2017 – Attractive yields (bonds)
A31: 2017 | B31: 0.0542 | C31: 10/2017 – lãi suất trúng thầu kỳ hạn 10 năm | D31: Vietnam News (2017), tin đấu thầu TPCP tháng 10/2017; tháng 11/2017: 5,41–5,91%
A32: 2018 | B32: 0.04997 | C32: 03/12/2018 – lợi suất spot kỳ hạn 10 năm | D32: CEIC Data (dữ liệu HNX), Vietnam Government Bond Yield: Spot
A33: 2019 | B33: 0.0342 | C33: 12/2019 – thị trường thứ cấp (mức thấp kỷ lục) | D33: Vietnam News (2020). Gov't bond yields hit record low
A34: 2020 | B34: 0.0224 | C34: 12/2020 – thị trường thứ cấp (−34 bps so với 11/2020) | D34: VBMA (2021). Bond Market Report 12/2020; MBS Fixed Income 01/2021
A35: 2021 | B35: 0.0209 | C35: 12/2021 – thị trường thứ cấp | D35: VBMA (2022). Bond Market Monthly Highlights 12/2021
A36: 2022 | B36: 0.048 | C36: 31/12/2022 – thị trường thứ cấp | D36: ADB AsianBondsOnline (2023); VBMA Monthly Bond Market Report 12/2022
A37: 2023 | B37: 0.0228 | C37: 29/11/2023 – lãi suất trúng thầu kỳ hạn 10 năm | D37: VBMA (2023). Kết quả đấu thầu TPCP ngày 29/11/2023
A38: 2024 | B38: 0.0297 | C38: Cuối năm 2024 – lợi suất kỳ hạn 10 năm | D38: Thị trường Tài chính Tiền tệ (2025). Thị trường TPCP: kỳ hạn 10 năm tiếp tục chi phối nhu cầu
A39: 2025 | B39: 0.0404 | C39: Cuối năm 2025 – lợi suất kỳ hạn 10 năm | D39: VNDirect (2025). La bàn thị trường; Thị trường Tài chính Tiền tệ (2026)
A40: Bình quân 2016–2025 = Rf dùng trong CAPM | B40: =AVERAGE(B30:B39) -> 0.039207
A41: Tham khảo: lợi suất hiện hành đầu 06/2026 ~4,47%; 03/04/2026 4,35% (TradingEconomics). Dùng bình quân 10 năm để không đưa đỉnh/đáy chu kỳ lãi suất vào chi phí vốn dài hạn; 2016–2017 dùng quan sát phát hành/đấu thầu gần nhất có nguồn.

Sheet Assumption
A1: Assumption
D2: 0 | E2: 1 | F2: 2 | G2: 3 | H2: 4 | I2: 5
D3: ='Income Statement'!D4 -> 2025 | E3: =D3+1 -> 2026 | F3: =E3+1 -> 2027 | G3: =F3+1 -> 2028 | H3: =G3+1 -> 2029 | I3: =H3+1 -> 2030
A4: % Tăng trưởng doanh thu | D4: ='Income Statement'!D13/'Income Statement'!C13-1 -> 0.53731538 | E4: =Drivers!F40 -> 0.33918962 | F4: =Drivers!G40 -> 0.25232982 | G4: =Drivers!H40 -> 0.38450974 | H4: =Drivers!I40 -> 0.2826286 | I4: =Drivers!J40 -> 0.20277215
A5: GVHB/Doanh thu | D5: ='Income Statement'!D20/'Income Statement'!D13 -> 0.48965893 | E5: =Drivers!F83 -> 0.48244588 | F5: =Drivers!G83 -> 0.49485398 | G5: =Drivers!H83 -> 0.55170946 | H5: =Drivers!I83 -> 0.52932193 | I5: =Drivers!J83 -> 0.52406105
A6: Tổng CP hoạt động/Doanh thu | D6: ='Income Statement'!D63/'Income Statement'!D13 -> 0.4143787 | E6: =Drivers!F89 -> 0.39753447 | F6: =Drivers!G89 -> 0.39228625 | G6: =Drivers!H89 -> 0.39152075 | H6: =Drivers!I89 -> 0.3728926 | I6: =Drivers!J89 -> 0.36053369
A7: CP Tài chính/Doanh thu | D7: ='Income Statement'!D69/'Income Statement'!D13 -> 0.0029903761 | E7: =Drivers!F130 -> 0.0025168901 | F7: =Drivers!G130 -> 0.021509766 | G7: =Drivers!H130 -> 0.029620425 | H7: =Drivers!I130 -> 0.020897353 | I7: =Drivers!J130 -> 0.013722463
A8: TSNH (ngoài tiền)/Doanh thu | D8: =('Balance Sheet'!G22-'Balance Sheet'!G7)/'Income Statement'!D13 -> 0.15961986 | E8: =(Drivers!F105+Drivers!F107+Drivers!F109)/Drivers!F39 -> 0.16385016 | F8: =(Drivers!G105+Drivers!G107+Drivers!G109)/Drivers!G39 -> 0.17544401 | G8: =(Drivers!H105+Drivers!H107+Drivers!H109)/Drivers!H39 -> 0.1956765 | H8: =(Drivers!I105+Drivers!I107+Drivers!I109)/Drivers!I39 -> 0.20032604 | I8: =(Drivers!J105+Drivers!J107+Drivers!J109)/Drivers!J39 -> 0.19727168
A9: Nợ ngắn hạn (ngoài vay)/Doanh thu | D9: =('Balance Sheet'!G58-'Balance Sheet'!G48)/'Income Statement'!D13 -> 0.0072083497 | E9: =(Drivers!F111+Drivers!F113)/Drivers!F39 -> 0.0094535096 | F9: =(Drivers!G111+Drivers!G113)/Drivers!G39 -> 0.011020404 | G9: =(Drivers!H111+Drivers!H113)/Drivers!H39 -> 0.014063374 | H9: =(Drivers!I111+Drivers!I113)/Drivers!I39 -> 0.013720139 | I9: =(Drivers!J111+Drivers!J113)/Drivers!J39 -> 0.013854721
A10: Hàng tồn kho/TSNH ngoài tiền | D10: ='Balance Sheet'!G10/('Balance Sheet'!G22-'Balance Sheet'!G7) -> 0.49391451 | E10: =Drivers!F105/(Drivers!F105+Drivers!F107+Drivers!F109) -> 0.4548979 | F10: =Drivers!G105/(Drivers!G105+Drivers!G107+Drivers!G109) -> 0.42845598 | G10: =Drivers!H105/(Drivers!H105+Drivers!H107+Drivers!H109) -> 0.43154708 | H10: =Drivers!I105/(Drivers!I105+Drivers!I107+Drivers!I109) -> 0.39003545 | I10: =Drivers!J105/(Drivers!J105+Drivers!J107+Drivers!J109) -> 0.38059137
A11: Khoản phải thu/TSNH ngoài tiền | D11: ='Balance Sheet'!G13/('Balance Sheet'!G22-'Balance Sheet'!G7) -> 0.23292842 | E11: =Drivers!F107/(Drivers!F105+Drivers!F107+Drivers!F109) -> 0.30097662 | F11: =Drivers!G107/(Drivers!G105+Drivers!G107+Drivers!G109) -> 0.34355105 | G11: =Drivers!H107/(Drivers!H105+Drivers!H107+Drivers!H109) -> 0.36403389 | H11: =Drivers!I107/(Drivers!I105+Drivers!I107+Drivers!I109) -> 0.41029005 | I11: =Drivers!J107/(Drivers!J105+Drivers!J107+Drivers!J109) -> 0.41664257
A12: Khoản phải trả/Nợ NH ngoài vay | D12: ='Balance Sheet'!G41/('Balance Sheet'!G58-'Balance Sheet'!G48) -> 0.76923077 | E12: =Drivers!F111/(Drivers!F111+Drivers!F113) -> 0.78843836 | F12: =Drivers!G111/(Drivers!G111+Drivers!G113) -> 0.81851845 | G12: =Drivers!H111/(Drivers!H111+Drivers!H113) -> 0.85778662 | H12: =Drivers!I111/(Drivers!I111+Drivers!I113) -> 0.85422888 | I12: =Drivers!J111/(Drivers!J111+Drivers!J113) -> 0.85564487
A13: CAPEX/Doanh thu | D13: ='Pro Forma'!B25/'Income Statement'!D13 -> 0.10693778 | E13: =Drivers!F93 -> 0.2 | F13: =Drivers!G93 -> 0.65 | G13: =Drivers!H93 -> 0.12 | H13: =Drivers!I93 -> 0.1 | I13: =Drivers!J93 -> 0.1
A15: Thuế suất thuế TNDN | D15: 0.2 | E15: Nguồn: Luật Thuế TNDN 67/2025/QH15 – thuế suất phổ thông 20% (dùng cho NOPAT dài hạn và P/E chuẩn hóa).
A16: Tỷ lệ tăng trưởng vĩnh viễn | D16: 0.05 | E16: Lý do: tăng trưởng dài hạn danh nghĩa VND 5%: lạm phát mục tiêu ~4–4,5% cộng tăng trưởng thực thấp; thấp hơn GDP danh nghĩa VN (~10–12%) và thấp hơn Rf + tăng trưởng thực. Nguồn: NHNN, Quốc hội (mục tiêu CPI 2026 ~4,5%); Damodaran (2026).
A17: Tỷ lệ khấu hao | D17: 0.12 | E17: Nguồn: file Excel mẫu (12% nguyên giá đầu kỳ), khớp BCTC 2024–2025.
A18: Tỷ lệ chiết khấu WACC | D18: ='Discount rate'!E5 -> 0.13637833 | E18: Công thức: = WACC tính ở sheet Discount rate (E5).
A19: Lợi nhuận trên vốn đầu tư mới sau 2030 (RONIC) = ROIC 2030E | D19: =DCF!B39 -> 0.13881153 | E19: Công thức: RONIC = ROIC 2030E của chính mô hình (DCF!B39 = NOPAT 2030/(tài sản dài hạn ròng + VLĐ)). Lý do: file mẫu tính giá trị cuối kỳ = FCFF 2031/(WACC − g); FCFF 2031 được chuẩn hóa = NOPAT 2031 × (1 − g/RONIC) để phần tái đầu tư chỉ vừa đủ cho tăng trưởng 5%/năm, vì FCFF 2030 còn chứa CAPEX của giai đoạn tăng ~20%. Lấy RONIC bằng ROIC 2030 nghĩa là vốn mới sinh lời như năm cuối dự phóng, không giả định thêm lợi thế; ROIC 2030 xấp xỉ WACC nên tăng trưởng sau 2030 gần như không tạo thêm giá trị (thận trọng). Nguồn: tính toán từ mô hình; Damodaran (2026).
A21: Ghi chú: các tỷ lệ 2026E–2030E là kết quả của mô hình động lực ở sheet Drivers (sản lượng × giá, chi phí theo dòng, số ngày VLĐ, lịch CAPEX/vay/thuế) để tránh giả định % doanh thu thiếu cơ sở.

Sheet Drivers
A1: GIẢ ĐỊNH CHI TIẾT & MÔ HÌNH ĐỘNG LỰC (DRIVERS) – AgriPack
A2: Đơn vị: nghìn đồng (trừ khi ghi khác). Ô vàng chữ xanh dương = giả định/số liệu nhập; chữ đen = công thức; chữ xanh lá = liên kết sheet khác. Lịch sử 2023A–2025A liên kết từ BCTC do đề bài cung cấp.
A3: Kịch bản đang chạy (1 = Bear, 2 = Base, 3 = Bull) | C3: 2 | D3: =CHOOSE(C3,"Bear","Base","Bull") -> Base | K3: Ô chọn kịch bản: mọi hàng giả định kịch bản (mục F) được chọn bằng INDEX theo ô này.
A4: Năm thực hiện khoản đầu tư lớn (CAPEX/Doanh thu = 65%) | C4: 2027 | K4: Đề bài ghi 2027; template khóa 65% ở cột 2028 → base case theo đề bài, 2028 là độ nhạy (xem Summary).
A6: Chỉ tiêu | B6: Đơn vị / cơ sở | C6: 2023A | D6: 2024A | E6: 2025A | F6: 2026E | G6: 2027E | H6: 2028E | I6: 2029E | J6: 2030E | K6: Nguồn / lý do (ghi ngay cạnh ô giả định)
A7: năm (dùng cho công thức) | C7: 2023 | D7: 2024 | E7: 2025 | F7: 2026 | G7: 2027 | H7: 2028 | I7: 2029 | J7: 2030
A8: A. DOANH THU THEO PHÂN KHÚC (Sản lượng × Giá bán)
A9: A1. Bao bì F&B/FMCG (hộp, khay ép khuôn từ bã mía + vỏ trứng)
A10: Giá bán bình quân (ASP) | B10: nghìn đ/sản phẩm | E10: 2.5 | F10: =E10*(1+F11) -> 2.55 | G10: =F10*(1+G11) -> 2.601 | H10: =G10*(1+H11) -> 2.65302 | I10: =H10*(1+I11) -> 2.7060804 | J10: =I10*(1+J11) -> 2.760202 | K10: Lý do: giá 2025 lấy cận dưới khung giá hộp/khay 2.500–4.000đ/cái của nhóm vì doanh thu gồm cả khay nhỏ và đơn hàng sỉ; cao hơn hộp bã mía 500 ml bán lẻ 1.900–2.700đ nhờ ép khuôn theo mẫu. Nguồn: bảng chiến lược giá (Mục 1.2.2; ecoeshop.com), bảng giá hộp 500 ml (Mục 1.1.1; QueenPack.com, baobixanh.com).
A11: Tăng giá bán bình quân | B11: %/năm | F11: =INDEX($C$143:$E$143,$C$3) -> 0.02 | G11: =INDEX($C$143:$E$143,$C$3) -> 0.02 | H11: =INDEX($C$143:$E$143,$C$3) -> 0.02 | I11: =INDEX($C$143:$E$143,$C$3) -> 0.02 | J11: =INDEX($C$143:$E$143,$C$3) -> 0.02 | K11: Lý do: Base +2%/năm, thấp hơn CPI 8T/2026 (+4,45%) vì khách hàng B2B có sức mạnh đàm phán rất cao và bao bì nhựa rẻ hơn nhiều lần (Mục 3.1.2, 3.2.3); Bear +1%, Bull +2,5%. Nguồn: Cục Thống kê (2026); phân tích ngành của nhóm.
A12: Sản lượng quy đổi | B12: sản phẩm | C12: =C14/$E$10 -> 6022000 | D12: =D14/$E$10 -> 9635200 | E12: =E14/$E$10 -> 15223616 | F12: =E12*(1+F13) -> 20095173 | G12: =F12*(1+G13) -> 24516111 | H12: =G12*(1+H13) -> 33096750 | I12: =H12*(1+I13) -> 41370938 | J12: =I12*(1+J13) -> 48403997 | K12: Lịch sử = doanh thu / ASP 2025 (quy đổi, giả định giá không đổi 2023–25 – do BCTC không công bố sản lượng).
A13: Tăng trưởng sản lượng | B13: % | D13: =D12/C12-1 -> 0.6 | E13: =E12/D12-1 -> 0.58 | F13: =IF($C$4=2027,F149,F150)*INDEX($C$142:$E$142,$C$3) -> 0.32 | G13: =IF($C$4=2027,G149,G150)*INDEX($C$142:$E$142,$C$3) -> 0.22 | H13: =IF($C$4=2027,H149,H150)*INDEX($C$142:$E$142,$C$3) -> 0.35 | I13: =IF($C$4=2027,I149,I150)*INDEX($C$142:$E$142,$C$3) -> 0.25 | J13: =IF($C$4=2027,J149,J150)*INDEX($C$142:$E$142,$C$3) -> 0.17 | K13: Lý do: sản lượng bị giới hạn bởi công suất: 2026 +32% nhờ máy ép bổ sung (CAPEX 20% DT); 2027 +22% do nhà máy mới đang xây; 2028 +35% khi 2 nhà máy mới chạy; giảm dần về +17% năm 2030. Lịch sử +60% (2024), +58% (2025). Đối chiếu: thị phần SAM tăng từ 4,3% lên ~11% năm 2030. Nguồn: BCTC 2023–2025 (đề bài); IMARC Group (2025); giả định của nhóm.
A14: Doanh thu F&B/FMCG | B14: nghìn đồng | C14: ='Income Statement'!B6 -> 15055000 | D14: ='Income Statement'!C6 -> 24088000 | E14: ='Income Statement'!D6 -> 38059040 | F14: =F12*F10 -> 51242691 | G14: =G12*G10 -> 63766405 | H14: =H12*H10 -> 87806340 | I14: =I12*I10 -> 1.1195308e+08 | J14: =J12*J10 -> 1.3360481e+08
A16: A2. Thiết kế & sản xuất khuôn theo mẫu
A17: Giá bình quân/bộ khuôn | B17: nghìn đ/bộ | E17: 20000 | F17: =E17*(1+F18) -> 20400 | G17: =F17*(1+G18) -> 20808 | H17: =G17*(1+H18) -> 21224.16 | I17: =H17*(1+I18) -> 21648.643 | J17: =I17*(1+J18) -> 22081.616 | K17: Lý do: ~20 triệu đồng/bộ khuôn, bằng giá tham chiếu khuôn ép bã mía/tre. Nguồn: bảng chiến lược giá (Mục 1.2.2; HTAECO.com).
A18: Tăng giá | B18: %/năm | F18: =F11 -> 0.02 | G18: =G11 -> 0.02 | H18: =H11 -> 0.02 | I18: =I11 -> 0.02 | J18: =J11 -> 0.02
A19: Số bộ khuôn bàn giao | B19: bộ | C19: =C21/$E$17 -> 151 | D19: =D21/$E$17 -> 211.4 | E19: =E21/$E$17 -> 294.903 | F19: =E19*(1+F20) -> 359.78166 | G19: =F19*(1+G20) -> 424.54236 | H19: =G19*(1+H20) -> 543.41422 | I19: =H19*(1+I20) -> 652.09706 | J19: =I19*(1+J20) -> 749.91162
A20: Tăng trưởng số bộ khuôn | B20: % | D20: =D19/C19-1 -> 0.4 | E20: =E19/D19-1 -> 0.395 | F20: =F151*INDEX($C$142:$E$142,$C$3) -> 0.22 | G20: =G151*INDEX($C$142:$E$142,$C$3) -> 0.18 | H20: =H151*INDEX($C$142:$E$142,$C$3) -> 0.28 | I20: =I151*INDEX($C$142:$E$142,$C$3) -> 0.2 | J20: =J151*INDEX($C$142:$E$142,$C$3) -> 0.15 | K20: Lý do: số bộ khuôn gắn với số SKU/khách hàng mới; tăng nhanh năm 2028 khi mở thị trường miền Bắc, sau đó chậm dần. Lịch sử +40% (2024), +39,5% (2025). Nguồn: BCTC 2023–2025; giả định của nhóm.
A21: Doanh thu thiết kế & khuôn | B21: nghìn đồng | C21: ='Income Statement'!B7 -> 3020000 | D21: ='Income Statement'!C7 -> 4228000 | E21: ='Income Statement'!D7 -> 5898060 | F21: =F19*F17 -> 7339545.9 | G21: =G19*G17 -> 8833877.4 | H21: =H19*H17 -> 11533510 | I21: =I19*I17 -> 14117017 | J21: =J19*J17 -> 16559261
A23: A3. Đệm bảo vệ nội thất / thương mại điện tử
A24: Giá bình quân | B24: nghìn đ/m² | E24: 22.5 | F24: =E24*(1+F25) -> 22.8375 | G24: =F24*(1+G25) -> 23.180062 | H24: =G24*(1+H25) -> 23.527763 | I24: =H24*(1+I25) -> 23.88068 | J24: =I24*(1+J25) -> 24.23889 | K24: Lý do: trung điểm khung 15.000–30.000đ/m² của vật liệu đệm định hình (PE foam) mà sản phẩm thay thế. Nguồn: báo giá PE foam định hình trên thị trường (2026); Mục 3.2.6.
A25: Tăng giá | B25: %/năm | F25: =INDEX($C$144:$E$144,$C$3) -> 0.015 | G25: =INDEX($C$144:$E$144,$C$3) -> 0.015 | H25: =INDEX($C$144:$E$144,$C$3) -> 0.015 | I25: =INDEX($C$144:$E$144,$C$3) -> 0.015 | J25: =INDEX($C$144:$E$144,$C$3) -> 0.015 | K25: Lý do: đệm bảo vệ cạnh tranh trực tiếp với EPE/PE foam giá rẻ (áp lực thay thế cao, Mục 3.2.6) nên chỉ tăng 1,5%/năm (Base); Bear 0,5%, Bull 2%. Nguồn: phân tích ngành của nhóm.
A26: Diện tích quy đổi | B26: m² | C26: =C28/$E$24 -> 67555.556 | D26: =D28/$E$24 -> 101333.33 | E26: =E28/$E$24 -> 121600 | F26: =E26*(1+F27) -> 158080 | G26: =F26*(1+G27) -> 205504 | H26: =G26*(1+H27) -> 287705.6 | I26: =H26*(1+I27) -> 379771.39 | J26: =I26*(1+J27) -> 474714.24
A27: Tăng trưởng diện tích | B27: % | D27: =D26/C26-1 -> 0.5 | E27: =E26/D26-1 -> 0.2 | F27: =F152*INDEX($C$142:$E$142,$C$3) -> 0.3 | G27: =G152*INDEX($C$142:$E$142,$C$3) -> 0.3 | H27: =H152*INDEX($C$142:$E$142,$C$3) -> 0.4 | I27: =I152*INDEX($C$142:$E$142,$C$3) -> 0.32 | J27: =J152*INDEX($C$142:$E$142,$C$3) -> 0.25 | K27: Lý do: bám theo tăng trưởng TMĐT 18–25%/năm và khách hàng nội thất xuất khẩu; năm 2028 +40% nhờ công suất mới. Nguồn: Mục 3.2.2 (VECOM; Bộ Công Thương); BCTC 2023–2025.
A28: Doanh thu nội thất/TMĐT | B28: nghìn đồng | C28: ='Income Statement'!B8 -> 1520000 | D28: ='Income Statement'!C8 -> 2280000 | E28: ='Income Statement'!D8 -> 2736000 | F28: =F26*F24 -> 3610152 | G28: =G26*G24 -> 4763595.6 | H28: =H26*H24 -> 6769069.3 | I28: =I26*I24 -> 9069199 | J28: =J26*J24 -> 11506546
A30: A4. Đệm bảo vệ thiết bị, linh kiện điện tử
A31: Giá bình quân | B31: nghìn đ/m² | E31: 40 | F31: =E31*(1+F32) -> 40.6 | G31: =F31*(1+G32) -> 41.209 | H31: =G31*(1+H32) -> 41.827135 | I31: =H31*(1+I32) -> 42.454542 | J31: =I31*(1+J32) -> 43.09136 | K31: Lý do: trung điểm khung 25.000–55.000đ/m² của khay EPE/EPE chống tĩnh điện mà sản phẩm thay thế. Nguồn: báo giá khay EPE trên thị trường (2026); Mục 3.2.6.
A32: Tăng giá | B32: %/năm | F32: =F25 -> 0.015 | G32: =G25 -> 0.015 | H32: =H25 -> 0.015 | I32: =I25 -> 0.015 | J32: =J25 -> 0.015
A33: Diện tích quy đổi | B33: m² | C33: =C35/$E$31 -> 0 | D33: =D35/$E$31 -> 14150 | E33: =E35/$E$31 -> 29715 | F33: =E33*(1+F34) -> 47544 | G33: =F33*(1+G34) -> 71316 | H33: =G33*(1+H34) -> 121237.2 | I33: =H33*(1+I34) -> 175793.94 | J33: =I33*(1+J34) -> 228532.12
A34: Tăng trưởng diện tích | B34: % | E34: =E33/D33-1 -> 1.1 | F34: =F153*INDEX($C$142:$E$142,$C$3) -> 0.6 | G34: =G153*INDEX($C$142:$E$142,$C$3) -> 0.5 | H34: =H153*INDEX($C$142:$E$142,$C$3) -> 0.7 | I34: =I153*INDEX($C$142:$E$142,$C$3) -> 0.45 | J34: =J153*INDEX($C$142:$E$142,$C$3) -> 0.3 | K34: Lý do: nền nhỏ (1,2 tỷ đồng năm 2025); thay thế khay EPS/EPE cho khách hàng FDI điện tử khi chuỗi cung ứng xuất khẩu yêu cầu xanh hóa. Nguồn: Mục 3.2.2 (xuất khẩu 475 tỷ USD năm 2025, FDI chiếm 80%); BCTC 2024–2025.
A35: Doanh thu điện tử | B35: nghìn đồng | C35: ='Income Statement'!B9 -> 0 | D35: ='Income Statement'!C9 -> 566000 | E35: ='Income Statement'!D9 -> 1188600 | F35: =F33*F31 -> 1930286.4 | G35: =G33*G31 -> 2938861 | H35: =H33*H31 -> 5071004.7 | I35: =I33*I31 -> 7463251.2 | J35: =J33*J31 -> 9847760
A37: Tổng doanh thu gộp | B37: nghìn đồng | C37: =C14+C21+C28+C35 -> 19595000 | D37: =D14+D21+D28+D35 -> 31162000 | E37: =E14+E21+E28+E35 -> 47881700 | F37: =F14+F21+F28+F35 -> 64122676 | G37: =G14+G21+G28+G35 -> 80302739 | H37: =H14+H21+H28+H35 -> 1.1117992e+08 | I37: =I14+I21+I28+I35 -> 1.4260255e+08 | J37: =J14+J21+J28+J35 -> 1.7151838e+08
A38: Khoản giảm trừ / doanh thu gộp | B38: % | C38: =-'Income Statement'!B11/C37 -> 0.008 | D38: =-'Income Statement'!C11/D37 -> 0.0075 | E38: =-'Income Statement'!D11/E37 -> 0.007 | F38: 0.007 | G38: 0.007 | H38: 0.007 | I38: 0.007 | J38: 0.007 | K38: Lý do: giữ mức 2025 (0,70% doanh thu gộp), xu hướng giảm từ 0,80% (2023). Nguồn: BCTC 2023–2025 (đề bài).
A39: Doanh thu thuần | B39: nghìn đồng | C39: ='Income Statement'!B13 -> 19438240 | D39: ='Income Statement'!C13 -> 30928285 | E39: ='Income Statement'!D13 -> 47546528 | F39: =F37*(1-F38) -> 63673817 | G39: =G37*(1-G38) -> 79740620 | H39: =H37*(1-H38) -> 1.1040166e+08 | I39: =I37*(1-I38) -> 1.4160433e+08 | J39: =J37*(1-J38) -> 1.7031775e+08
A40: Tăng trưởng doanh thu thuần | B40: % | D40: =D39/C39-1 -> 0.59110521 | E40: =E39/D39-1 -> 0.53731538 | F40: =F39/E39-1 -> 0.33918962 | G40: =G39/F39-1 -> 0.25232982 | H40: =H39/G39-1 -> 0.38450974 | I40: =I39/H39-1 -> 0.2826286 | J40: =J39/I39-1 -> 0.20277215
A41: Tỷ trọng F&B/FMCG trong doanh thu gộp | B41: % | C41: =C14/C37 -> 0.76830824 | D41: =D14/D37 -> 0.77299275 | E41: =E14/E37 -> 0.79485565 | F41: =F14/F37 -> 0.79913527 | G41: =G14/G37 -> 0.79407509 | H41: =H14/H37 -> 0.78976794 | I41: =I14/I37 -> 0.7850707 | J41: =J14/J37 -> 0.77895333
A43: A5. Kiểm tra công suất (vòng quay tài sản) & thị phần ngầm định
A44: Nguyên giá TSCĐ bình quân | B44: nghìn đồng | C44: =(SUM('Balance Sheet'!D29:D31)+C96)/2 -> 17289500 | D44: =(C96+D96)/2 -> 22946800 | E44: =(D96+E96)/2 -> 28641860 | F44: =(E96+F96)/2 -> 37551502 | G44: =(F96+G96)/2 -> 69834585 | H44: =(G96+H96)/2 -> 1.0237439e+08 | I44: =(H96+I96)/2 -> 1.160787e+08 | J44: =(I96+J96)/2 -> 1.3167481e+08
A45: Vòng quay nguyên giá TSCĐ (DT thuần / NG bình quân) | B45: lần | C45: =C39/C44 -> 1.1242801 | D45: =D39/D44 -> 1.3478256 | E45: =E39/E44 -> 1.6600363 | F45: =F39/F44 -> 1.6956397 | G45: =G39/G44 -> 1.14185 | H45: =H39/H44 -> 1.078411 | I45: =I39/I44 -> 1.2198993 | J45: =J39/J44 -> 1.2934725 | K45: Vòng quay 2025 = 1,66x. Nếu vòng quay dự phóng < 2025 → còn công suất trống (không cần CAPEX lớn tiếp theo); nếu >> 2025 → dự báo vượt công suất.
A46: Tỷ giá USD/VND bình quân | B46: VND/USD | E46: 26000 | F46: 26300 | G46: =F46*(1+0.02) -> 26826 | H46: =G46*(1+0.02) -> 27362.52 | I46: =H46*(1+0.02) -> 27909.77 | J46: =I46*(1+0.02) -> 28467.966 | K46: Lý do: dùng để quy đổi doanh thu sang USD khi so với TAM/SAM của IMARC. 2025: 26.000; 2026: 26.300; sau đó VND mất giá 2%/năm. Nguồn: Vietcombank (tỷ giá bán ra); MBS Research dự báo 26.800–27.000 cuối 2026 (Mục 3.1.4).
A47: Doanh thu F&B/FMCG quy USD | B47: triệu USD | E47: =E14*1000/E46/1000000 -> 1.4638092 | F47: =F14*1000/F46/1000000 -> 1.9483913 | G47: =G14*1000/G46/1000000 -> 2.3770374 | H47: =H14*1000/H46/1000000 -> 3.2090005 | I47: =I14*1000/I46/1000000 -> 4.0112506 | J47: =J14*1000/J46/1000000 -> 4.6931632
A48: SAM: bao bì dùng một lần phân hủy sinh học ngành F&B VN | B48: triệu USD | E48: 33.93 | F48: =E48*(1+0.0473) -> 35.534889 | G48: =F48*(1+0.0473) -> 37.215689 | H48: =G48*(1+0.0473) -> 38.975991 | I48: =H48*(1+0.0473) -> 40.819556 | J48: =I48*(1+0.0473) -> 42.750321 | K48: Lý do: SAM = bao bì dùng một lần phân hủy sinh học cho ngành dịch vụ ăn uống VN, 33,93 triệu USD (2025), CAGR 4,73%. Nguồn: IMARC Group (2025), Mục 1.2.1.
A49: Thị phần ngầm định trong SAM | B49: % | E49: =E47/E48 -> 0.043142035 | F49: =F47/F48 -> 0.054830376 | G49: =G47/G48 -> 0.063871917 | H49: =H47/H48 -> 0.082332748 | I49: =I47/I48 -> 0.098267865 | J49: =J47/J48 -> 0.10978077 | K49: Cờ đỏ nếu > 15%: SAM của IMARC hẹp (chỉ đồ dùng một lần ngành dịch vụ ăn uống); cần luận điểm mở rộng thị trường (lộ trình dừng nhựa dùng một lần sau 2030, bao bì FMCG, xuất khẩu).
A50: TAM: thị trường bao bì xanh VN | B50: triệu USD | E50: 1129.79 | F50: =E50*(1+0.0415) -> 1176.6763 | G50: =F50*(1+0.0415) -> 1225.5084 | H50: =G50*(1+0.0415) -> 1276.3669 | I50: =H50*(1+0.0415) -> 1329.3362 | J50: =I50*(1+0.0415) -> 1384.5036 | K50: Lý do: TAM = thị trường bao bì xanh VN 1.129,79 triệu USD (2025), CAGR 4,15% (2026–2034). Nguồn: IMARC Group (2025), Mục 1.2.1.
A51: Thị phần ngầm định trong TAM (toàn bộ doanh thu) | B51: % | E51: =(E39*1000/E46/1000000)/E50 -> 0.0016186306 | F51: =(F39*1000/F46/1000000)/F50 -> 0.0020575393 | G51: =(G39*1000/G46/1000000)/G50 -> 0.0024255343 | H51: =(H39*1000/H46/1000000)/H50 -> 0.0031611418 | I51: =(I39*1000/I46/1000000)/I50 -> 0.0038166774 | J51: =(J39*1000/J46/1000000)/J50 -> 0.0043212498
A53: B. GIÁ VỐN & CHI PHÍ HOẠT ĐỘNG
A54: Chi phí biến đổi (NVL, nhân công trực tiếp) / DT thuần | B54: % | C54: ='Income Statement'!B16/C39 -> 0.255 | D54: ='Income Statement'!C16/D39 -> 0.25 | E54: ='Income Statement'!D16/E39 -> 0.245 | F54: =F154+INDEX($C$145:$E$145,$C$3) -> 0.25 | G54: =G154+INDEX($C$145:$E$145,$C$3) -> 0.255 | H54: =H154+INDEX($C$145:$E$145,$C$3) -> 0.27 | I54: =I154+INDEX($C$145:$E$145,$C$3) -> 0.265 | J54: =J154+INDEX($C$145:$E$145,$C$3) -> 0.27 | K54: Lý do: 25,5% → 25,0% → 24,5% (2023–25). Tăng lên 25,0–27,0% vì lạm phát tác động chủ yếu vào chi phí thu gom, vận chuyển, sấy và năng lượng (Mục 3.1.2), bã mía bị cạnh tranh bởi lò hơi nhà máy đường và các nhà sản xuất bao bì sợi trước mốc dừng nhựa dùng một lần 2030; năm đầu chạy nhà máy mới hao hụt cao. Nguồn: BCTC 2023–2025; Cục Thống kê (CPI 8T/2026 +4,45%, nhóm nhà ở-điện-nước +6,71%).
A55: Chi phí biến đổi | B55: nghìn đồng | C55: ='Income Statement'!B16 -> 4956751.2 | D55: ='Income Statement'!C16 -> 7732071.2 | E55: ='Income Statement'!D16 -> 11648899 | F55: =F39*F54 -> 15918454 | G55: =G39*G54 -> 20333858 | H55: =H39*H54 -> 29808450 | I55: =I39*I54 -> 37525148 | J55: =J39*J54 -> 45985792
A56: Chi phí cố định sản xuất | B56: nghìn đồng | C56: ='Income Statement'!B17 -> 1055000 | D56: ='Income Statement'!C17 -> 1160500 | E56: ='Income Statement'!D17 -> 1276550 | F56: =E56*(1+F57)+F58 -> 1404205 | G56: =F56*(1+G57)+G58 -> 1544625.5 | H56: =G56*(1+H57)+H58 -> 2599088 | I56: =H56*(1+I57)+I58 -> 2858996.9 | J56: =I56*(1+J57)+J58 -> 3144896.5
A57: Tăng chi phí cố định sản xuất (nền) | B57: % | D57: =D56/C56-1 -> 0.1 | E57: =E56/D56-1 -> 0.1 | F57: 0.1 | G57: 0.1 | H57: 0.1 | I57: 0.1 | J57: 0.1 | K57: Lý do: giữ mức tăng 10%/năm như 2024–2025. Nguồn: BCTC 2023–2025 (đề bài).
A58: Chi phí cố định tăng thêm của nhà máy mới | B58: nghìn đồng | F58: =IF(F$7=$C$4+1,$C$160,0) -> 0 | G58: =IF(G$7=$C$4+1,$C$160,0) -> 0 | H58: =IF(H$7=$C$4+1,$C$160,0) -> 900000 | I58: =IF(I$7=$C$4+1,$C$160,0) -> 0 | J58: =IF(J$7=$C$4+1,$C$160,0) -> 0 | K58: Lý do: bước nhảy chi phí cố định (phòng QC, bảo trì, quản đốc) 0,9 tỷ đồng/năm khi 2 nhà máy mới vận hành. Nguồn: giả định của nhóm.
A59: Giá vốn theo BCTC gốc (NVL, nhân công theo sản lượng, chi phí cố định SX) | B59: nghìn đồng | C59: =C55+C56 -> 6011751.2 | D59: =D55+D56 -> 8892571.2 | E59: =E55+E56 -> 12925449 | F59: =F55+F56 -> 17322659 | G59: =G55+G56 -> 21878484 | H59: =H55+H56 -> 32407538 | I59: =I55+I56 -> 40384145 | J59: =J55+J56 -> 49130689 | K59: Theo tính chất, chưa gồm tiền lương và khấu hao. Là cơ sở tính số ngày tồn kho/phải trả (DIO, DPO) như BCTC 2023–2025.
A61: Chi phí nhân sự / DT thuần | B61: % | C61: ='Income Statement'!B55/C39 -> 0.35970335 | D61: ='Income Statement'!C55/D39 -> 0.24867852 | E61: ='Income Statement'!D55/E39 -> 0.22646617 | F61: =F155+INDEX($C$146:$E$146,$C$3) -> 0.225 | G61: =G155+INDEX($C$146:$E$146,$C$3) -> 0.23 | H61: =H155+INDEX($C$146:$E$146,$C$3) -> 0.235 | I61: =I155+INDEX($C$146:$E$146,$C$3) -> 0.23 | J61: =J155+INDEX($C$146:$E$146,$C$3) -> 0.225 | K61: Lý do: 36,0% → 24,9% → 22,6% (2023–25). Giảm chậm lại (22,5–23,5%) vì lương tối thiểu vùng tăng 7,2% từ 01/01/2026 và nhà máy mới phải tuyển trước khi đạt công suất. Nguồn: BCTC 2023–2025; Nghị định 293/2025/NĐ-CP.
A62: Chi phí nhân sự (tiền lương) | B62: nghìn đồng | C62: ='Income Statement'!B55 -> 6992000 | D62: ='Income Statement'!C55 -> 7691200 | E62: ='Income Statement'!D55 -> 10767680 | F62: =F39*F61 -> 14326609 | G62: =G39*G61 -> 18340343 | H62: =H39*H61 -> 25944391 | I62: =I39*I61 -> 32568996 | J62: =J39*J61 -> 38321493
A63: Hỗ trợ tiền ăn / tiền lương | B63: % | C63: ='Income Statement'!B42/'Income Statement'!B55 -> 0.30749428 | D63: ='Income Statement'!C42/'Income Statement'!C55 -> 0.3354483 | E63: ='Income Statement'!D42/'Income Statement'!D55 -> 0.28752712 | F63: 0.28 | G63: 0.28 | H63: 0.28 | I63: 0.28 | J63: 0.28 | K63: Lý do: giữ ~mức 2025 (28,8% quỹ lương). Nguồn: BCTC 2023–2025.
A64: Hỗ trợ tiền ăn CNV | B64: nghìn đồng | C64: ='Income Statement'!B42 -> 2150000 | D64: ='Income Statement'!C42 -> 2580000 | E64: ='Income Statement'!D42 -> 3096000 | F64: =F62*F63 -> 4011450.5 | G64: =G62*G63 -> 5135295.9 | H64: =H62*H63 -> 7264429.6 | I64: =I62*I63 -> 9119319 | J64: =J62*J63 -> 10730018
A65: Tăng chi phí thuê mặt bằng | B65: % | D65: =D66/C66-1 -> 0.35 | E65: =E66/D66-1 -> 0.41 | F65: =IF(F$7=$C$4+1,$C$163,IF(F$7=$C$4,$C$162,IF(F$7=2026,$C$164,$C$161))) -> 0.12 | G65: =IF(G$7=$C$4+1,$C$163,IF(G$7=$C$4,$C$162,IF(G$7=2026,$C$164,$C$161))) -> 0.15 | H65: =IF(H$7=$C$4+1,$C$163,IF(H$7=$C$4,$C$162,IF(H$7=2026,$C$164,$C$161))) -> 0.3 | I65: =IF(I$7=$C$4+1,$C$163,IF(I$7=$C$4,$C$162,IF(I$7=2026,$C$164,$C$161))) -> 0.12 | J65: =IF(J$7=$C$4+1,$C$163,IF(J$7=$C$4,$C$162,IF(J$7=2026,$C$164,$C$161))) -> 0.12 | K65: Lý do: tiền thuê tăng 35%, 41% (2024–25) khi thuê thêm kho, xưởng. Sau đó tăng chậm (12%/năm) vì nhà máy mới là tài sản tự đầu tư; năm sau đầu tư lớn +30% do thuê kho vệ tinh gần khách hàng. Nguồn: BCTC 2023–2025; giả định của nhóm.
A66: Thuê mặt bằng | B66: nghìn đồng | C66: ='Income Statement'!B26 -> 3977000 | D66: ='Income Statement'!C26 -> 5368950 | E66: ='Income Statement'!D26 -> 7570219.5 | F66: =E66*(1+F65) -> 8478645.8 | G66: =F66*(1+G65) -> 9750442.7 | H66: =G66*(1+H65) -> 12675576 | I66: =H66*(1+I65) -> 14196645 | J66: =I66*(1+J65) -> 15900242
A67: Sửa chữa, bảo dưỡng / DT | B67: % | C67: ='Income Statement'!B28/C39 -> 0.048872737 | D67: ='Income Statement'!C28/D39 -> 0.052217574 | E67: ='Income Statement'!D28/E39 -> 0.043817079 | F67: 0.044 | G67: 0.044 | H67: 0.044 | I67: 0.044 | J67: 0.044 | K67: Lý do: giữ ~mức 2025 (4,4% DT; 2023–24: 4,9%, 5,2%). Nguồn: BCTC 2023–2025.
A68: Sửa chữa, bảo dưỡng | B68: nghìn đồng | C68: ='Income Statement'!B28 -> 950000 | D68: ='Income Statement'!C28 -> 1615000 | E68: ='Income Statement'!D28 -> 2083350 | F68: =F39*F67 -> 2801647.9 | G68: =G39*G67 -> 3508587.3 | H68: =H39*H67 -> 4857673.3 | I68: =I39*I67 -> 6230590.6 | J68: =J39*J67 -> 7493980.9
A69: Điện, nước, dịch vụ chung / DT | B69: % | C69: ='Income Statement'!B30/C39 -> 0.061733984 | D69: ='Income Statement'!C30/D39 -> 0.058199153 | E69: ='Income Statement'!D30/E39 -> 0.047322067 | F69: 0.05 | G69: 0.05 | H69: 0.05 | I69: 0.05 | J69: 0.05 | K69: Lý do: 6,2% → 5,8% → 4,7% (2023–25). Nâng lên 5,0% vì sấy, ép nhiệt tốn điện và giá bán lẻ điện bình quân tăng 4,8% ngày 11/10/2024 và 4,8% ngày 10/5/2025 (2.204,07 đ/kWh). Nguồn: BCTC 2023–2025; Quyết định 1279/QĐ-BCT (2025); Mục 3.1.2.
A70: Điện, nước, dịch vụ chung | B70: nghìn đồng | C70: ='Income Statement'!B30 -> 1200000 | D70: ='Income Statement'!C30 -> 1800000 | E70: ='Income Statement'!D30 -> 2250000 | F70: =F39*F69 -> 3183690.8 | G70: =G39*G69 -> 3987031 | H70: =H39*H69 -> 5520083.2 | I70: =I39*I69 -> 7080216.6 | J70: =J39*J69 -> 8515887.4
A71: Marketing / DT | B71: % | C71: ='Income Statement'!B50/C39 -> 0.047329388 | D71: ='Income Statement'!C50/D39 -> 0.031233546 | E71: ='Income Statement'!D50/E39 -> 0.024380329 | F71: 0.028 | G71: 0.03 | H71: 0.03 | I71: 0.03 | J71: 0.028 | K71: Lý do: 4,7% → 3,1% → 2,4% (2023–25). Tăng lại 2,8–3,0% khi mở rộng ra miền Bắc và khách hàng FDI (hội chợ, mẫu thử). Nguồn: BCTC 2023–2025; Mục 1.2.1.
A72: Marketing | B72: nghìn đồng | C72: ='Income Statement'!B50 -> 920000 | D72: ='Income Statement'!C50 -> 966000 | E72: ='Income Statement'!D50 -> 1159200 | F72: =F39*F71 -> 1782866.9 | G72: =G39*G71 -> 2392218.6 | H72: =H39*H71 -> 3312049.9 | I72: =I39*I71 -> 4248130 | J72: =J39*J71 -> 4768896.9
A73: Kiểm nghiệm, chứng nhận & R&D vật liệu / DT | B73: % | C73: 0 | D73: 0 | E73: 0 | F73: 0.006 | G73: 0.006 | H73: 0.006 | I73: 0.006 | J73: 0.006 | K73: Lý do: dòng chi phí mới 0,6% DT cho kiểm nghiệm bao bì tiếp xúc trực tiếp với thực phẩm, chứng nhận phân hủy (BPI, OK compost) và R&D lớp chống thấm không PFAS. Nguồn: Thông tư 27/2026/TT-BYT (hiệu lực 01/7/2026); Mục 3.1.6.1, 3.2.5.
A74: Kiểm nghiệm, chứng nhận & R&D | B74: nghìn đồng | C74: 0 | D74: 0 | E74: 0 | F74: =F39*F73 -> 382042.9 | G74: =G39*G73 -> 478443.72 | H74: =H39*H73 -> 662409.99 | I74: =I39*I73 -> 849626 | J74: =J39*J73 -> 1021906.5
A75: Chi phí hoạt động theo tính chất (tiền lương + chi phí khác, không gồm khấu hao) | B75: nghìn đồng | C75: =C62+C64+C66+C68+C70+C72+C74 -> 16189000 | D75: =D62+D64+D66+D68+D70+D72+D74 -> 20021150 | E75: =E62+E64+E66+E68+E70+E72+E74 -> 26926450 | F75: =F62+F64+F66+F68+F70+F72+F74 -> 34966954 | G75: =G62+G64+G66+G68+G70+G72+G74 -> 43592362 | H75: =H62+H64+H66+H68+H70+H72+H74 -> 60236613 | I75: =I62+I64+I66+I68+I70+I72+I74 -> 74293523 | J75: =J62+J64+J66+J68+J70+J72+J74 -> 86752425
A76: EBITDA | B76: nghìn đồng | C76: =C39-C59-C75 -> -2762511.2 | D76: =D39-D59-D75 -> 2014563.8 | E76: =E39-E59-E75 -> 7694629.2 | F76: =F39-F59-F75 -> 11384204 | G76: =G39-G59-G75 -> 14269775 | H76: =H39-H59-H75 -> 17757515 | I76: =I39-I59-I75 -> 26926664 | J76: =J39-J59-J75 -> 34434634
A77: Biên EBITDA | B77: % | C77: =C76/C39 -> -0.14211735 | D77: =D76/D39 -> 0.065136614 | E77: =E76/E39 -> 0.16183367 | F77: =F76/F39 -> 0.17878941 | G77: =G76/G39 -> 0.17895239 | H77: =H76/H39 -> 0.16084463 | I77: =I76/I39 -> 0.19015424 | J77: =J76/J39 -> 0.20217878
A79: B2. BCKQKD theo chức năng (VAS): tiền lương 70% vào giá vốn – 30% vào CPBH & QLDN; khấu hao 90% vào giá vốn – 10% vào CPBH & QLDN
A80: Tiền lương bộ phận sản xuất (phân bổ vào giá vốn) | B80: nghìn đồng | C80: =C62*$C$167 -> 4894400 | D80: =D62*$C$167 -> 5383840 | E80: =E62*$C$167 -> 7537376 | F80: =F62*$C$167 -> 10028626 | G80: =G62*$C$167 -> 12838240 | H80: =H62*$C$167 -> 18161074 | I80: =I62*$C$167 -> 22798298 | J80: =J62*$C$167 -> 26825045
A81: Khấu hao TSCĐ sản xuất (phân bổ vào giá vốn) | B81: nghìn đồng | C81: =C98*$C$168 -> 1288980 | D81: =D98*$C$168 -> 2137752 | E81: =E98*$C$168 -> 2818756.8 | F81: =F98*$C$168 -> 3367885 | G81: =G98*$C$168 -> 4743239.4 | H81: =H98*$C$168 -> 10341031 | I81: =I98*$C$168 -> 11771837 | J81: =J98*$C$168 -> 13301163
A82: Tổng giá vốn hàng bán (theo chức năng) | B82: nghìn đồng | C82: =C59+C80+C81 -> 12195131 | D82: =D59+D80+D81 -> 16414163 | E82: =E59+E80+E81 -> 23281582 | F82: =F59+F80+F81 -> 30719170 | G82: =G59+G80+G81 -> 39459963 | H82: =H59+H80+H81 -> 60909642 | I82: =I59+I80+I81 -> 74954279 | J82: =J59+J80+J81 -> 89256897
A83: GVHB / DT thuần | B83: % | C83: =C82/C39 -> 0.62737836 | D83: =D82/D39 -> 0.53071689 | E83: =E82/E39 -> 0.48965893 | F83: =F82/F39 -> 0.48244588 | G83: =G82/G39 -> 0.49485398 | H83: =H82/H39 -> 0.55170946 | I83: =I82/I39 -> 0.52932193 | J83: =J82/J39 -> 0.52406105
A84: Biên lợi nhuận gộp (sau phân bổ tiền lương và khấu hao) | B84: % | C84: =1-C83 -> 0.37262164 | D84: =1-D83 -> 0.46928311 | E84: =1-E83 -> 0.51034107 | F84: =1-F83 -> 0.51755412 | G84: =1-G83 -> 0.50514602 | H84: =1-H83 -> 0.44829054 | I84: =1-I83 -> 0.47067807 | J84: =1-J83 -> 0.47593895 | K84: BCTC gốc hạch toán toàn bộ tiền lương và khấu hao ngoài giá vốn nên biên gộp 69–73%. Mô hình phân bổ 70% tiền lương (công nhân, quản đốc, QC) và 90% khấu hao (máy ép, sấy, nhà xưởng) vào giá vốn theo đặc thù nhà máy sản xuất.
A85: Biên gộp theo BCTC gốc (tham khảo, chưa phân bổ) | B85: % | C85: =1-C59/C39 -> 0.69072554 | D85: =1-D59/D39 -> 0.71247771 | E85: =1-E59/E39 -> 0.72815156 | F85: =1-F59/F39 -> 0.7279469 | G85: =1-G59/G39 -> 0.72562938 | H85: =1-H59/H39 -> 0.70645789 | I85: =1-I59/I39 -> 0.71480996 | J85: =1-J59/J39 -> 0.71153512
A86: Tiền lương bộ phận bán hàng & quản lý | B86: nghìn đồng | C86: =C62*(1-$C$167) -> 2097600 | D86: =D62*(1-$C$167) -> 2307360 | E86: =E62*(1-$C$167) -> 3230304 | F86: =F62*(1-$C$167) -> 4297982.6 | G86: =G62*(1-$C$167) -> 5502102.8 | H86: =H62*(1-$C$167) -> 7783317.4 | I86: =I62*(1-$C$167) -> 9770698.9 | J86: =J62*(1-$C$167) -> 11496448
A87: Khấu hao TSCĐ bộ phận bán hàng & quản lý | B87: nghìn đồng | C87: =C98*(1-$C$168) -> 143220 | D87: =D98*(1-$C$168) -> 237528 | E87: =E98*(1-$C$168) -> 313195.2 | F87: =F98*(1-$C$168) -> 374209.44 | G87: =G98*(1-$C$168) -> 527026.6 | H87: =H98*(1-$C$168) -> 1149003.4 | I87: =I98*(1-$C$168) -> 1307981.8 | J87: =J98*(1-$C$168) -> 1477907
A88: Tổng chi phí bán hàng & QLDN (theo chức năng) | B88: nghìn đồng | C88: =C86+C64+C66+C68+C70+C72+C74+C87 -> 11437820 | D88: =D86+D64+D66+D68+D70+D72+D74+D87 -> 14874838 | E88: =E86+E64+E66+E68+E70+E72+E74+E87 -> 19702269 | F88: =F86+F64+F66+F68+F70+F72+F74+F87 -> 25312537 | G88: =G86+G64+G66+G68+G70+G72+G74+G87 -> 31281149 | H88: =H86+H64+H66+H68+H70+H72+H74+H87 -> 43224542 | I88: =I86+I64+I66+I68+I70+I72+I74+I87 -> 52803208 | J88: =J86+J64+J66+J68+J70+J72+J74+J87 -> 61405287
A89: CPBH & QLDN / DT thuần | B89: % | C89: =C88/C39 -> 0.5884185 | D89: =D88/D39 -> 0.4809461 | E89: =E88/E39 -> 0.4143787 | F89: =F88/F39 -> 0.39753447 | G89: =G88/G39 -> 0.39228625 | H89: =H88/H39 -> 0.39152075 | I89: =I88/I39 -> 0.3728926 | J89: =J88/J39 -> 0.36053369
A90: EBIT = DT thuần − GVHB − CPBH & QLDN (= EBITDA − khấu hao) | B90: nghìn đồng | C90: =C39-C82-C88 -> -4194711.2 | D90: =D39-D82-D88 -> -360716.25 | E90: =E39-E82-E88 -> 4562677.2 | F90: =F39-F82-F88 -> 7642109.6 | G90: =G39-G82-G88 -> 8999508.6 | H90: =H39-H82-H88 -> 6267480.2 | I90: =I39-I82-I88 -> 13846846 | J90: =J39-J82-J88 -> 19655564
A92: C. CAPEX, TÀI SẢN CỐ ĐỊNH & KHẤU HAO
A93: CAPEX / DT thuần (tỷ lệ tái đầu tư) | B93: % | C93: =C95/C39 -> 0.25768794 | D93: =D95/D39 -> 0.2038781 | E93: =E95/E39 -> 0.10693778 | F93: =IF(F$7=$C$4,$C$158,IF(F$7=$C$4+1,$C$159,F94)) -> 0.2 | G93: =IF(G$7=$C$4,$C$158,IF(G$7=$C$4+1,$C$159,G94)) -> 0.65 | H93: =IF(H$7=$C$4,$C$158,IF(H$7=$C$4+1,$C$159,H94)) -> 0.12 | I93: =IF(I$7=$C$4,$C$158,IF(I$7=$C$4+1,$C$159,I94)) -> 0.1 | J93: =IF(J$7=$C$4,$C$158,IF(J$7=$C$4+1,$C$159,J94)) -> 0.1 | K93: Lý do: tỷ lệ tái đầu tư = CAPEX/DT từng năm: 2026 20%, 2027 65% (đầu tư lớn theo đề bài), 2028 12% (hoàn thiện, chạy thử), 2029–30 10%. Ngành: trung vị CAPEX/DT của 16 DN bao bì niêm yết 2023–25 là 3,1%, tứ phân vị trên 8,3%, DN đang mở rộng 13–30% (Fig. A10); AgriPack cao hơn vì còn tăng trưởng 17–35%/năm và khấu hao chiếm 9–10% DT. Nguồn: đề bài (Mục III.2); FiinX (2026); BCTC 2023–2025.
A94: Tỷ lệ CAPEX năm thường | B94: % | F94: 0.2 | G94: 0.2 | H94: 0.1 | I94: 0.1 | J94: 0.1 | K94: Lý do: 2026: 20% (mức mặc định của file mẫu, tương đương 2024 là 20,4%) cho máy ép, xe tải, kho; sau mở rộng 10% ≈ khấu hao/DT (duy trì + nâng cấp). Nguồn: file Excel mẫu; BCTC 2023–2025; FiinX (Fig. A10).
A95: CAPEX | B95: nghìn đồng | C95: =SUM('Balance Sheet'!E29:E31)-SUM('Balance Sheet'!D29:D31) -> 5009000 | D95: =SUM('Balance Sheet'!F29:F31)-SUM('Balance Sheet'!E29:E31) -> 6305600 | E95: =SUM('Balance Sheet'!G29:G31)-SUM('Balance Sheet'!F29:F31) -> 5084520 | F95: =F39*F93 -> 12734763 | G95: =G39*G93 -> 51831403 | H95: =H39*H93 -> 13248200 | I95: =I39*I93 -> 14160433 | J95: =J39*J93 -> 17031775
A96: Nguyên giá TSCĐ cuối kỳ | B96: nghìn đồng | C96: =SUM('Balance Sheet'!E29:E31) -> 19794000 | D96: =SUM('Balance Sheet'!F29:F31) -> 26099600 | E96: =SUM('Balance Sheet'!G29:G31) -> 31184120 | F96: =E96+F95 -> 43918883 | G96: =F96+G95 -> 95750286 | H96: =G96+H95 -> 1.0899849e+08 | I96: =H96+I95 -> 1.2315892e+08 | J96: =I96+J95 -> 1.4019069e+08
A97: Tỷ lệ khấu hao (% nguyên giá đầu kỳ) | B97: % | D97: =D98/C96 -> 0.12 | E97: =E98/D96 -> 0.12 | F97: =Assumption!$D$17 -> 0.12 | G97: =Assumption!$D$17 -> 0.12 | H97: =Assumption!$D$17 -> 0.12 | I97: =Assumption!$D$17 -> 0.12 | J97: =Assumption!$D$17 -> 0.12 | K97: Lý do: 12% nguyên giá đầu kỳ, khớp số liệu 2024–2025. Nguồn: file Excel mẫu (Assumption!D17); BCTC 2024–2025.
A98: Khấu hao | B98: nghìn đồng | C98: ='Income Statement'!B71 -> 1432200 | D98: ='Income Statement'!C71 -> 2375280 | E98: ='Income Statement'!D71 -> 3131952 | F98: =E96*F97 -> 3742094.4 | G98: =F96*G97 -> 5270266 | H98: =G96*H97 -> 11490034 | I98: =H96*I97 -> 13079818 | J98: =I96*J97 -> 14779070
A99: Khấu hao lũy kế | B99: nghìn đồng | C99: ='Balance Sheet'!E26 -> 4282200 | D99: ='Balance Sheet'!F26 -> 6657480 | E99: ='Balance Sheet'!G26 -> 9789432 | F99: =E99+F98 -> 13531526 | G99: =F99+G98 -> 18801792 | H99: =G99+H98 -> 30291827 | I99: =H99+I98 -> 43371645 | J99: =I99+J98 -> 58150715
A100: Giá trị còn lại TSCĐ | B100: nghìn đồng | C100: =C96-C99 -> 15511800 | D100: =D96-D99 -> 19442120 | E100: =E96-E99 -> 21394688 | F100: =F96-F99 -> 30387357 | G100: =G96-G99 -> 76948494 | H100: =H96-H99 -> 78706659 | I100: =I96-I99 -> 79787274 | J100: =J96-J99 -> 82039979
A101: Khấu hao / DT | B101: % | C101: =C98/C39 -> 0.07367951 | D101: =D98/D39 -> 0.076799603 | E101: =E98/E39 -> 0.065871308 | F101: =F98/F39 -> 0.058769751 | G101: =G98/G39 -> 0.066092614 | H101: =H98/H39 -> 0.10407483 | I101: =I98/I39 -> 0.092368772 | J101: =J98/J39 -> 0.086773519
A103: D. VỐN LƯU ĐỘNG
A104: Số ngày tồn kho (DIO, theo giá vốn chưa gồm lương, khấu hao) | B104: ngày | C104: ='Balance Sheet'!E10/C59*365 -> 151.72534 | D104: ='Balance Sheet'!F10/D59*365 -> 123.08723 | E104: ='Balance Sheet'!G10/E59*365 -> 105.85338 | F104: 100 | G104: 100 | H104: 105 | I104: 100 | J104: 95 | K104: Lý do: 152 → 123 → 106 ngày (2023–25), cao do tích trữ bã mía theo vụ ép (khoảng tháng 11–4). Giữ ~100 ngày; 2028 tăng lên 105 ngày để tích trữ cho 2 nhà máy mới. Nguồn: BCTC 2023–2025; lịch vụ ép mía.
A105: Hàng tồn kho | B105: nghìn đồng | C105: ='Balance Sheet'!E10 -> 2499000 | D105: ='Balance Sheet'!F10 -> 2998800 | E105: ='Balance Sheet'!G10 -> 3748500 | F105: =F59*F104/365 -> 4745934 | G105: =G59*G104/365 -> 5994105.1 | H105: =H59*H104/365 -> 9322716.3 | I105: =I59*I104/365 -> 11064149 | J105: =J59*J104/365 -> 12787439
A106: Số ngày phải thu (DSO, theo DT) | B106: ngày | C106: ='Balance Sheet'!E13/C39*365 -> 23.659549 | D106: ='Balance Sheet'!F13/D39*365 -> 18.141258 | E106: ='Balance Sheet'!G13/E39*365 -> 13.570701 | F106: 18 | G106: 22 | H106: 26 | I106: 30 | J106: 30 | K106: Lý do: 24 → 18 → 14 ngày (2023–25), rất ngắn cho B2B vì nhiều khách F&B nhỏ trả ngay. Khi phục vụ chuỗi F&B, FMCG, FDI điện tử (điều khoản 30–45 ngày), DSO tăng dần lên 30 ngày. Nguồn: BCTC 2023–2025; Mục 3.2.7 (khách hàng B2B có sức mạnh cao).
A107: Phải thu khách hàng | B107: nghìn đồng | C107: ='Balance Sheet'!E13 -> 1260000 | D107: ='Balance Sheet'!F13 -> 1537200 | E107: ='Balance Sheet'!G13 -> 1767780 | F107: =F39*F106/365 -> 3140078.6 | G107: =G39*G106/365 -> 4806284 | H107: =H39*H106/365 -> 7864228.2 | I107: =I39*I106/365 -> 11638712 | J107: =J39*J106/365 -> 13998719
A108: TSNH khác (chi phí trả trước...) / DT | B108: % | C108: ='Balance Sheet'!E20/C39 -> 0.063431669 | D108: ='Balance Sheet'!F20/D39 -> 0.055279496 | E108: ='Balance Sheet'!G20/E39 -> 0.043601291 | F108: 0.04 | G108: 0.04 | H108: 0.04 | I108: 0.04 | J108: 0.04 | K108: Lý do: 6,3% → 5,5% → 4,4% (2023–25); giữ 4,0%. Nguồn: BCTC 2023–2025.
A109: TSNH khác | B109: nghìn đồng | C109: ='Balance Sheet'!E20 -> 1233000 | D109: ='Balance Sheet'!F20 -> 1709700 | E109: ='Balance Sheet'!G20 -> 2073090 | F109: =F39*F108 -> 2546952.7 | G109: =G39*G108 -> 3189624.8 | H109: =H39*H108 -> 4416066.6 | I109: =I39*I108 -> 5664173.3 | J109: =J39*J108 -> 6812709.9
A110: Số ngày phải trả (DPO, theo giá vốn chưa gồm lương, khấu hao) | B110: ngày | C110: ='Balance Sheet'!E41/C59*365 -> 9.4714498 | D110: ='Balance Sheet'!F41/D59*365 -> 8.3240266 | E110: ='Balance Sheet'!G41/E59*365 -> 7.444894 | F110: 10 | G110: 12 | H110: 15 | I110: 15 | J110: 15 | K110: Lý do: 9 → 8 → 7 ngày (2023–25). Quy mô lớn hơn giúp đàm phán kỳ hạn 15 ngày với nhà máy đường và đơn vị thu gom. Nguồn: BCTC 2023–2025.
A111: Phải trả người bán | B111: nghìn đồng | C111: ='Balance Sheet'!E41 -> 156000 | D111: ='Balance Sheet'!F41 -> 202800 | E111: ='Balance Sheet'!G41 -> 263640 | F111: =F59*F110/365 -> 474593.4 | G111: =G59*G110/365 -> 719292.61 | H111: =H59*H110/365 -> 1331816.6 | I111: =I59*I110/365 -> 1659622.4 | J111: =J59*J110/365 -> 2019069.4
...

Sheet Pro Forma
A1: Báo cáo kết quả hoạt động kinh doanh (dự kiến) 5 năm
B2: 0 | C2: 1 | D2: 2 | E2: 3 | F2: 4 | G2: 5
B3: ='Income Statement'!D4 -> 2025 | C3: =B3+1 -> 2026 | D3: =C3+1 -> 2027 | E3: =D3+1 -> 2028 | F3: =E3+1 -> 2029 | G3: =F3+1 -> 2030
A4: Doanh thu | B4: ='Income Statement'!D13 -> 47546528 | C4: =B4*(1+Assumption!E4) -> 63673817 | D4: =C4*(1+Assumption!F4) -> 79740620 | E4: =D4*(1+Assumption!G4) -> 1.1040166e+08 | F4: =E4*(1+Assumption!H4) -> 1.4160433e+08 | G4: =F4*(1+Assumption!I4) -> 1.7031775e+08
A5: Giá vốn hàng bán (gồm 70% tiền lương, 90% khấu hao) | B5: ='Income Statement'!D20 -> 23281582 | C5: =C4*Assumption!E5 -> 30719170 | D5: =D4*Assumption!F5 -> 39459963 | E5: =E4*Assumption!G5 -> 60909642 | F5: =F4*Assumption!H5 -> 74954279 | G5: =G4*Assumption!I5 -> 89256897
A6: Lợi nhuận gộp | B6: =B4-B5 -> 24264946 | C6: =C4-C5 -> 32954647 | D6: =D4-D5 -> 40280657 | E6: =E4-E5 -> 49492023 | F6: =F4-F5 -> 66650054 | G6: =G4-G5 -> 81060851
A7: Chi phí bán hàng & QLDN (gồm 30% tiền lương, 10% khấu hao) | B7: ='Income Statement'!D63 -> 19702269 | C7: =C4*Assumption!E6 -> 25312537 | D7: =D4*Assumption!F6 -> 31281149 | E7: =E4*Assumption!G6 -> 43224542 | F7: =F4*Assumption!H6 -> 52803208 | G7: =G4*Assumption!I6 -> 61405287
A8: Chi phí thuê cửa hàng | B8: 0 | C8: 0 | D8: 0 | E8: 0 | F8: 0 | G8: 0
A9: Khấu hao (ghi nhớ – đã phân bổ vào GVHB và CPBH & QLDN) | B9: ='Income Statement'!D71 -> 3131952 | C9: =Assumption!$D$17*B22 -> 3742094.4 | D9: =Assumption!$D$17*C22 -> 5270266 | E9: =Assumption!$D$17*D22 -> 11490034 | F9: =Assumption!$D$17*E22 -> 13079818 | G9: =Assumption!$D$17*F22 -> 14779070
A10: Lợi nhuận trước thuế và lãi vay (EBIT) | B10: =B6-B7-B8 -> 4562677.2 | C10: =C6-C7-C8 -> 7642109.6 | D10: =D6-D7-D8 -> 8999508.6 | E10: =E6-E7-E8 -> 6267480.2 | F10: =F6-F7-F8 -> 13846846 | G10: =G6-G7-G8 -> 19655564
A11: Chi phí tài chính | B11: ='Income Statement'!D69 -> 142182 | C11: =C4*Assumption!E7 -> 160260 | D11: =D4*Assumption!F7 -> 1715202.1 | E11: =E4*Assumption!G7 -> 3270144.2 | F11: =F4*Assumption!H7 -> 2959155.8 | G11: =G4*Assumption!I7 -> 2337178.9
A12: Lợi nhuận trước thuế | B12: =B10-B11 -> 4420495.2 | C12: =C10-C11 -> 7481849.6 | D12: =D10-D11 -> 7284306.5 | E12: =E10-E11 -> 2997336 | F12: =F10-F11 -> 10887690 | G12: =G10-G11 -> 17318385
A13: Thuế TNDN | B13: 0 | C13: =Drivers!F137 -> 902709.76 | D13: =Drivers!G137 -> 1456861.3 | E13: =Drivers!H137 -> 599467.2 | F13: =Drivers!I137 -> 2177538 | G13: =Drivers!J137 -> 3463677
A14: Lợi nhuận sau thuế | B14: =B12-B13 -> 4420495.2 | C14: =C12-C13 -> 6579139.9 | D14: =D12-D13 -> 5827445.2 | E14: =E12-E13 -> 2397868.8 | F14: =F12-F13 -> 8710152.1 | G14: =G12-G13 -> 13854708
A17: Tính toán chi tiết:
A19: Chi phí đầu tư tài sản cố định (CAPEX)
B21: =B3 -> 2025 | C21: =B21+1 -> 2026 | D21: =C21+1 -> 2027 | E21: =D21+1 -> 2028 | F21: =E21+1 -> 2029 | G21: =F21+1 -> 2030
A22: Tài sản dài hạn | B22: =SUM('Balance Sheet'!G29:G31) -> 31184120 | C22: =B22+C25 -> 43918883 | D22: =C22+D25 -> 95750286 | E22: =D22+E25 -> 1.0899849e+08 | F22: =E22+F25 -> 1.2315892e+08 | G22: =F22+G25 -> 1.4019069e+08
A23: Khấu hao lũy kế | B23: ='Balance Sheet'!G26 -> 9789432 | C23: =B23+C9 -> 13531526 | D23: =C23+D9 -> 18801792 | E23: =D23+E9 -> 30291827 | F23: =E23+F9 -> 43371645 | G23: =F23+G9 -> 58150715
A24: Tổng tài sản dài hạn (ròng) | B24: =B22-B23 -> 21394688 | C24: =C22-C23 -> 30387357 | D24: =D22-D23 -> 76948494 | E24: =E22-E23 -> 78706659 | F24: =F22-F23 -> 79787274 | G24: =G22-G23 -> 82039979
A25: CAPEX | B25: =B22-SUM('Balance Sheet'!F29:F31) -> 5084520 | C25: =C4*Assumption!E13 -> 12734763 | D25: =D4*Assumption!F13 -> 51831403 | E25: =E4*Assumption!G13 -> 13248200 | F25: =F4*Assumption!H13 -> 14160433 | G25: =G4*Assumption!I13 -> 17031775
A28: Điều chỉnh Vốn lưu động ròng
B30: =B21 -> 2025 | C30: =B30+1 -> 2026 | D30: =C30+1 -> 2027 | E30: =D30+1 -> 2028 | F30: =E30+1 -> 2029 | G30: =F30+1 -> 2030
A31: Tài sản ngắn hạn (ngoài tiền) | B31: ='Balance Sheet'!G22-'Balance Sheet'!G7 -> 7589370 | C31: =C4*Assumption!E8 -> 10432965 | D31: =D4*Assumption!F8 -> 13990014 | E31: =E4*Assumption!G8 -> 21603011 | F31: =F4*Assumption!H8 -> 28367035 | G31: =G4*Assumption!I8 -> 33598868
A32: Hàng tồn kho | B32: ='Balance Sheet'!G10 -> 3748500 | C32: =C31*Assumption!E10 -> 4745934 | D32: =D31*Assumption!F10 -> 5994105.1 | E32: =E31*Assumption!G10 -> 9322716.3 | F32: =F31*Assumption!H10 -> 11064149 | G32: =G31*Assumption!I10 -> 12787439
A33: Khoản phải thu ngắn hạn | B33: ='Balance Sheet'!G13 -> 1767780 | C33: =C31*Assumption!E11 -> 3140078.6 | D33: =D31*Assumption!F11 -> 4806284 | E33: =E31*Assumption!G11 -> 7864228.2 | F33: =F31*Assumption!H11 -> 11638712 | G33: =G31*Assumption!I11 -> 13998719
A34: Nợ ngắn hạn (ngoài vay) | B34: ='Balance Sheet'!G58-'Balance Sheet'!G48 -> 342732 | C34: =C4*Assumption!E9 -> 601941.04 | D34: =D4*Assumption!F9 -> 878773.85 | E34: =E4*Assumption!G9 -> 1552619.9 | F34: =F4*Assumption!H9 -> 1942831.1 | G34: =G4*Assumption!I9 -> 2359704.9
A35: Khoản phải trả ngắn hạn | B35: ='Balance Sheet'!G41 -> 263640 | C35: =C34*Assumption!E12 -> 474593.4 | D35: =D34*Assumption!F12 -> 719292.61 | E35: =E34*Assumption!G12 -> 1331816.6 | F35: =F34*Assumption!H12 -> 1659622.4 | G35: =G34*Assumption!I12 -> 2019069.4
A36: Vốn lưu động hoạt động ròng (TSNH ngoài tiền − Nợ NH ngoài vay) | B36: =B31-B34 -> 7246638 | C36: =C31-C34 -> 9831024.3 | D36: =D31-D34 -> 13111240 | E36: =E31-E34 -> 20050391 | F36: =F31-F34 -> 26424204 | G36: =G31-G34 -> 31239164
A37: Biến động VLĐ ròng | C37: =C36-B36 -> 2584386.3 | D37: =D36-C36 -> 3280215.7 | E37: =E36-D36 -> 6939151.1 | F37: =F36-E36 -> 6373812.7 | G37: =G36-F36 -> 4814959.7
A40: Xác định nhu cầu vốn
A41: Cash Flow Statment Pro-forma
B42: 0 | C42: 1 | D42: 2 | E42: 3 | F42: 4 | G42: 5
B43: =B30 -> 2025 | C43: =B43+1 -> 2026 | D43: =C43+1 -> 2027 | E43: =D43+1 -> 2028 | F43: =E43+1 -> 2029 | G43: =F43+1 -> 2030
A44: ='Cash Flow Statement'!A5 -> Hoạt động kinh doanh
A45: ='Cash Flow Statement'!B6 -> Lợi nhuận sau thuế | B45: =B14 -> 4420495.2 | C45: =C14 -> 6579139.9 | D45: =D14 -> 5827445.2 | E45: =E14 -> 2397868.8 | F45: =F14 -> 8710152.1 | G45: =G14 -> 13854708
A46: ='Cash Flow Statement'!B8 -> Khấu hao | B46: =B9 -> 3131952 | C46: =C9 -> 3742094.4 | D46: =D9 -> 5270266 | E46: =E9 -> 11490034 | F46: =F9 -> 13079818 | G46: =G9 -> 14779070
A47: Biến động TSNH | B47: =SUM('Cash Flow Statement'!E11:E13) -> -1343670 | C47: =B31-C31 -> -2843595.4 | D47: =C31-D31 -> -3557048.5 | E47: =D31-E31 -> -7612997.2 | F47: =E31-F31 -> -6764023.8 | G47: =F31-G31 -> -5231833.5
A48: Biến động Nợ NH | B48: =SUM('Cash Flow Statement'!E15:E17) -> 73692 | C48: =C34-B34 -> 259209.04 | D48: =D34-C34 -> 276832.81 | E48: =E34-D34 -> 673846.09 | F48: =F34-E34 -> 390211.12 | G48: =G34-F34 -> 416873.82
A49: Lưu chuyển tiền thuần từ HĐKD | B49: =SUM(B45:B48) -> 6282469.2 | C49: =SUM(C45:C48) -> 7736847.9 | D49: =SUM(D45:D48) -> 7817495.5 | E49: =SUM(E45:E48) -> 6948752.1 | F49: =SUM(F45:F48) -> 15416158 | G49: =SUM(G45:G48) -> 23818819
A50: Hoạt động đầu tư
A51: Lưu chuyển tiền thuần từ HĐ đầu tư | B51: ='Cash Flow Statement'!E22 -> -5084520 | C51: =-C25 -> -12734763 | D51: =-D25 -> -51831403 | E51: =-E25 -> -13248200 | F51: =-F25 -> -14160433 | G51: =-G25 -> -17031775
A52: Hoạt động tài chính
A53: Lưu chuyển tiền thuần từ HĐ tài chính (vay/trả nợ theo kế hoạch, chưa gồm vốn cổ phần) | B53: ='Cash Flow Statement'!E30 -> 0 | C53: =(Drivers!F121-Drivers!E121)+(Drivers!F127-Drivers!E127) -> 0 | D53: =(Drivers!G121-Drivers!F121)+(Drivers!G127-Drivers!F127) -> 31098842 | E53: =(Drivers!H121-Drivers!G121)+(Drivers!H127-Drivers!G127) -> 0 | F53: =(Drivers!I121-Drivers!H121)+(Drivers!I127-Drivers!H127) -> -6219768.4 | G53: =(Drivers!J121-Drivers!I121)+(Drivers!J127-Drivers!I127) -> -6219768.4
A55: Số dư tiền mặt đầu kỳ | B55: ='Cash Flow Statement'!E32 -> 1735532.6 | C55: =B59 -> 2933481.8 | D55: =C59 -> -2064433.7 | E55: =D59 -> -14979499 | F55: =E59 -> -21278947 | G55: =F59 -> -26242991
A57: Biến động tiền mặt trong kỳ | B57: ='Cash Flow Statement'!E34 -> 1197949.2 | C57: =C49+C51+C53 -> -4997915.4 | D57: =D49+D51+D53 -> -12915066 | E57: =E49+E51+E53 -> -6299447.7 | F57: =F49+F51+F53 -> -4964043.9 | G57: =G49+G51+G53 -> 567275.57
A59: Số dư tiền mặt cuối kỳ | B59: ='Cash Flow Statement'!E36 -> 2933481.8 | C59: =C55+C57 -> -2064433.7 | D59: =D55+D57 -> -14979499 | E59: =E55+E57 -> -21278947 | F59: =F55+F57 -> -26242991 | G59: =G55+G57 -> -25675715
A60: Thiếu hụt so với tiền mặt tối thiểu (trước khi gọi vốn cổ phần) | C60: =MAX(0,Drivers!F120-C59) -> 5248124.5 | D60: =MAX(0,Drivers!G120-D59) -> 18966530 | E60: =MAX(0,Drivers!H120-E59) -> 26799030 | F60: =MAX(0,Drivers!I120-F59) -> 33323208 | G60: =MAX(0,Drivers!J120-G59) -> 34191603
A61: Nhu cầu vốn | B61: =MAX(C60:G60) -> 34191603
A62: (+) Dự phòng | B62: =B61*0.1 -> 3419160.3
A63: Tổng vốn cần huy động | B63: =B61+B62 -> 37610763
A64: Ghi chú (Lộc): Nhu cầu vốn cổ phần = thiếu hụt tiền lớn nhất so với mức tiền tối thiểu (5% DT) sau khi đã tính khoản vay trung hạn tài trợ 50% CAPEX nhà máy mới; cộng 10% dự phòng theo template.

Sheet DCF
A1: Dòng tiền tự do (FCFF) của doanh nghiệp
C3: 1 | D3: =C3+1 -> 2 | E3: =D3+1 -> 3 | F3: =E3+1 -> 4 | G3: =F3+1 -> 5
B4: ='Income Statement'!D4 -> 2025 | C4: =B4+1 -> 2026 | D4: =C4+1 -> 2027 | E4: =D4+1 -> 2028 | F4: =E4+1 -> 2029 | G4: =F4+1 -> 2030 | H4: =G4+1 -> 2031
A5: Lợi nhuận sau thuế trước lãi vay EBIT*(1-t) | C5: ='Pro Forma'!C10-Drivers!F135*MAX(0,'Pro Forma'!C10-Drivers!F133) -> 6712155.7 | D5: ='Pro Forma'!D10-Drivers!G135*MAX(0,'Pro Forma'!D10-Drivers!G133) -> 7199606.9 | E5: ='Pro Forma'!E10-Drivers!H135*MAX(0,'Pro Forma'!E10-Drivers!H133) -> 5013984.2 | F5: ='Pro Forma'!F10-Drivers!I135*MAX(0,'Pro Forma'!F10-Drivers!I133) -> 11077477 | G5: ='Pro Forma'!G10-Drivers!J135*MAX(0,'Pro Forma'!G10-Drivers!J133) -> 15724451
A6: + Khấu hao | C6: ='Pro Forma'!C9 -> 3742094.4 | D6: ='Pro Forma'!D9 -> 5270266 | E6: ='Pro Forma'!E9 -> 11490034 | F6: ='Pro Forma'!F9 -> 13079818 | G6: ='Pro Forma'!G9 -> 14779070
A7: - Điều chỉnh VLĐ | C7: ='Pro Forma'!C37 -> 2584386.3 | D7: ='Pro Forma'!D37 -> 3280215.7 | E7: ='Pro Forma'!E37 -> 6939151.1 | F7: ='Pro Forma'!F37 -> 6373812.7 | G7: ='Pro Forma'!G37 -> 4814959.7
A8: - CAPEX | C8: ='Pro Forma'!C25 -> 12734763 | D8: ='Pro Forma'!D25 -> 51831403 | E8: ='Pro Forma'!E25 -> 13248200 | F8: ='Pro Forma'!F25 -> 14160433 | G8: ='Pro Forma'!G25 -> 17031775
H9: FCFF 2031 chuẩn hóa
A10: Dòng tiền tự do (FCFF) | C10: =C5+C6-C7-C8 -> -4864899.6 | D10: =D5+D6-D7-D8 -> -42641746 | E10: =E5+E6-E7-E8 -> -3683332.4 | F10: =F5+F6-F7-F8 -> 3623049.1 | G10: =G5+G6-G7-G8 -> 8656787.1 | H10: =G5*(1+Assumption!D16)*(1-Assumption!D16/Assumption!D19) -> 10563519 | I10: FCFF 2031 = NOPAT 2031 × (1 − g/RONIC): phần tái đầu tư chỉ vừa đủ cho tăng trưởng g; RONIC = ROIC 2030E (Assumption!D19).
A12: Giá trị cuối kỳ tại t=5 = FCFF 2031 / (WACC − g) | G12: =H10/(Assumption!D18-Assumption!D16) -> 1.2229362e+08
A14: Giá trị hiện tại của các dòng tiền (FCFF; năm 2030 gồm giá trị cuối kỳ) | C14: =C10/(1+Assumption!$D$18)^C3 -> -4281056.3 | D14: =D10/(1+Assumption!$D$18)^D3 -> -33020914 | E14: =E10/(1+Assumption!$D$18)^E3 -> -2509990.5 | F14: =F10/(1+Assumption!$D$18)^F3 -> 2172613.4 | G14: =(G10+G12)/(1+Assumption!$D$18)^G3 -> 69102241
A16: Giá trị doanh nghiệp | C16: =SUM(C14:G14) -> 31462893
A19: Nhu cầu vốn | B19: ='Pro Forma'!B63 -> 37610763
A20: Tỷ lệ nắm giữ | B20: =B19/B21 -> 0.53420936
A21: Post-money value | B21: =B22+B19 -> 70404538
A22: Pre-money value | B22: =C16+'Balance Sheet'!G7-'Balance Sheet'!G48-'Balance Sheet'!G61 -> 32793775 | D22: Pitch: Kêu gọi | E22: =B19 -> 37610763 | F22: nghìn đồng tương ứng | G22: =B20 -> 0.53420936 | H22: cổ phần.
A26: CẦU NỐI EV → VỐN CSH & KIỂM TRA
A27: PV dòng tiền tự do 2026–2030 | B27: =SUM(C14:F14)+G10/(1+Assumption!D18)^G3 -> -33071180
A28: PV giá trị cuối kỳ | B28: =G12/(1+Assumption!D18)^G3 -> 64534073
A29: Giá trị doanh nghiệp (EV) | B29: =C16 -> 31462893
A30: Tỷ trọng giá trị cuối kỳ / EV | B30: =B28/B29 -> 2.0511169
A31: (+) Tiền mặt 31/12/2025 | B31: ='Balance Sheet'!G7 -> 2933481.8
A32: (−) Nợ vay 31/12/2025 | B32: ='Balance Sheet'!G48+'Balance Sheet'!G61 -> 1602600
A33: Giá trị vốn CSH trước gọi vốn (pre-money) | B33: =B29+B31-B32 -> 32793775
A34: EV/EBITDA 2025A ngầm định | B34: =B29/Drivers!E76 -> 4.0889421
A35: EV/EBITDA 2026E ngầm định | B35: =B29/Drivers!F76 -> 2.7637324
A36: P/E 2026E ngầm định (pre-money) | B36: =B33/'Income Statement'!E80 -> 4.984508
A37: P/B 2025A ngầm định | B37: =B33/'Balance Sheet'!G76 -> 1.0941395
A38: Giá trị cuối kỳ nếu không chuẩn hóa = FCFF 2030 × (1 + g)/(WACC − g) | B38: =G10*(1+Assumption!D16)/(Assumption!D18-Assumption!D16) -> 1.052304e+08
A39: ROIC 2030E = NOPAT / (TSCĐ ròng + VLĐ) | B39: =G5/('Pro Forma'!G24+'Pro Forma'!G36) -> 0.13881153
A40: Tỷ lệ tái đầu tư trong giá trị cuối kỳ = g / RONIC | B40: =Assumption!D16/Assumption!D19 -> 0.36020062
A41: Kiểm tra: pre-money = B22 | B41: =B33-B22 -> 0

Sheet VCM
A1: The VC Method | C1: =DCF!G4 -> 2030
A3: Tỷ lệ chiết khấu có điều chỉnh
A5: Số kỳ | B5: =DCF!G3 -> 5 | D5: Nhu cầu vốn | E5: =DCF!B19 -> 37610763
A6: Tỷ lệ thất bại của VC | B6: 0.4 | C6: Giả định: theo hướng dẫn của BTL, DN giai đoạn đầu tăng trưởng có z = 35–45%; lấy 40% (trung điểm). | D6: Giá trị thoái vốn kỳ vọng | E6: =B39 -> 1.9869224e+08
A7: Tỷ lệ chiết khấu (WACC) | B7: ='Discount rate'!E5 -> 0.13637833
D8: Post-money value | E8: =E6/(1+B9)^B5 -> 62909673
A9: Tỷ lệ chiết khấu có điều chỉnh p = (1 + r)/(1 − z)^(1/n) − 1 | B9: =(1+B7)/(1-B6)^(1/B5)-1 -> 0.25861439 | C9: Công thức giáo trình: (1 + p)^n = (1 + r)^n/(1 − z), với r = WACC (B7), z = B6, n = 5 năm. | D9: Tỷ lệ sở hữu của NĐT mới | E9: =E5/E8 -> 0.59785342
D11: Pre-money value | E11: =E8-E5 -> 25298910
D12: Tỷ lệ sở hữu của Founder và NĐT cũ | E12: =1-E9 -> 0.40214658
A15: Pitch: Kêu gọi | B15: =E5 -> 37610763 | C15: nghìn đồng tương ứng | D15: =E9 -> 0.59785342 | E15: cổ phần.
A19: Tỷ lệ thất bại theo giai đoạn đầu tư VC (đề bài) | B19: Thấp | C19: Cao | D19: Trung điểm
A20: Ươm mầm | B20: 0.65 | C20: 0.8 | D20: =AVERAGE(B20:C20) -> 0.725 | E20: Nguồn: đề bài (BTL, Mục III.1 – tỷ lệ thất bại tại mỗi giai đoạn đầu tư của VC); bảng dùng cho Mục 8 (giai đoạn chưa có doanh thu).
A21: Thử nghiệm | B21: 0.5 | C21: 0.65 | D21: =AVERAGE(B21:C21) -> 0.575
A22: Đầu tăng trưởng | B22: 0.35 | C22: 0.45 | D22: =AVERAGE(B22:C22) -> 0.4
A23: Cuối tăng trưởng | B23: 0.2 | C23: 0.3 | D23: =AVERAGE(B23:C23) -> 0.25
A25: Giai đoạn của AgriPack (kết luận mục 2) | B25: Đầu tăng trưởng | C25: Lý do: doanh thu 47,5 tỷ, tăng 54–59%/năm, LNST và FCF vừa dương năm 2025, D/E 6,5%. Nguồn: kết luận Mục 2.
A27: GIÁ TRỊ THOÁI VỐN CUỐI 2030
A28: LNST 2030E | B28: ='Income Statement'!I80 -> 13854708
A29: P/E thoát vốn | B29: 9.4 | C29: Lý do: P/E ngành Containers & Packaging (ICB cấp 4) năm 2026: 9,43x; trung vị mẫu 14 DN: xem Multiples!G22. Nguồn: FiinX (giá đóng cửa 28/9/2026).
A30: Giá trị vốn CSH theo P/E | B30: =B28*B29 -> 1.3023426e+08
A31: EBITDA 2030E | B31: ='Income Statement'!I82 -> 34434634
A32: EV/EBITDA thoát vốn | B32: 8 | C32: Lý do: EV/EBITDA ngành Containers & Packaging 2026: 7,99x (2025: 7,5x). Nguồn: FiinX (giá đóng cửa 28/9/2026).
A33: EV theo EV/EBITDA | B33: =B31*B32 -> 2.7547708e+08
A34: (+) Tiền mặt 2030E | B34: ='Balance Sheet'!L7 -> 11935048
A35: (−) Nợ vay 2030E | B35: ='Balance Sheet'!L48+'Balance Sheet'!L61 -> 20261905
A36: Giá trị vốn CSH theo EV/EBITDA | B36: =B33+B34-B35 -> 2.6715022e+08
A37: Đối chiếu: giá trị vốn CSH theo DCF tại 2030 (TV + tiền − nợ) | B37: =DCF!G12+B34-B35 -> 1.1396676e+08
A38: EV/EBITDA ngầm định của P/E thoát vốn | B38: =(B30-B34+B35)/B31 -> 4.023888
A39: Giá trị thoái vốn sử dụng (bình quân P/E và EV/EBITDA) | B39: =AVERAGE(B30,B36) -> 1.9869224e+08
A41: IRR kỳ vọng của NĐT nếu thành công | B41: =(E6*E9/E5)^(1/B5)-1 -> 0.25861439
A42: IRR kỳ vọng có tính xác suất thất bại (= WACC) | B42: =((1-B6)*E6*E9/E5)^(1/B5)-1 -> 0.13637833

Sheet Multiples
A1: ĐỊNH GIÁ BẰNG BỘI SỐ SO SÁNH (MULTIPLES / COMPARABLES) – AgriPack
A2: Đơn vị: tỷ đồng; bội số: lần. Mẫu so sánh: 16 DN bao bì niêm yết (FiinX, giá đóng cửa 28/9/2026; BCTC quý đến Q2/2026, TTM). Cột H = 1: đưa vào mẫu; loại MCP (EV/EBITDA 36x, P/E 84x do lợi nhuận quá thấp) và PBT (DN thương mại, EV/EBITDA ≈ 0).
A4: Mã | B4: Sàn | C4: Phân khúc | D4: DT TTM (tỷ) | E4: Biên EBITDA (%) | F4: EV/EBITDA (x) | G4: P/E (x) | H4: Đưa vào mẫu | I4: EV/EBITDA (mẫu) | J4: P/E (mẫu) | K4: Nguồn
A5: DHC | B5: HOSE | C5: Giấy, bao bì carton | D5: 3938 | E5: 18.9 | F5: 6.35 | G5: 7.48 | H5: 1 | I5: =IF(H5=1,F5,"") -> 6.35 | J5: =IF(H5=1,G5,"") -> 7.48 | K5: FiinX: BCTC 4 quý gần nhất đến Q2/2026; giá đóng cửa 28/9/2026
A6: TDP | B6: HOSE | C6: Bao bì nhựa | D6: 5488 | E6: 8.3 | F6: 8.98 | G6: 20.51 | H6: 1 | I6: =IF(H6=1,F6,"") -> 8.98 | J6: =IF(H6=1,G6,"") -> 20.51 | K6: FiinX: BCTC 4 quý gần nhất đến Q2/2026; giá đóng cửa 28/9/2026
A7: AAA | B7: HOSE | C7: Nhựa, nhựa sinh học | D7: 9243 | E7: 14.2 | F7: 3.85 | G7: 5.16 | H7: 1 | I7: =IF(H7=1,F7,"") -> 3.85 | J7: =IF(H7=1,G7,"") -> 5.16 | K7: FiinX: BCTC 4 quý gần nhất đến Q2/2026; giá đóng cửa 28/9/2026
A8: APH | B8: HOSE | C8: Bao bì nhựa (holding) | D8: 9252 | E8: 14 | F8: 5.05 | G8: 6.98 | H8: 1 | I8: =IF(H8=1,F8,"") -> 5.05 | J8: =IF(H8=1,G8,"") -> 6.98 | K8: FiinX: BCTC 4 quý gần nhất đến Q2/2026; giá đóng cửa 28/9/2026
A9: HHP | B9: HOSE | C9: Giấy bao bì | D9: 3112 | E9: 9.3 | F9: 13.71 | G9: 32.9 | H9: 1 | I9: =IF(H9=1,F9,"") -> 13.71 | J9: =IF(H9=1,G9,"") -> 32.9 | K9: FiinX: BCTC 4 quý gần nhất đến Q2/2026; giá đóng cửa 28/9/2026
A10: INN | B10: HNX | C10: Bao bì giấy, in | D10: 1921 | E10: 14.9 | F10: 2.66 | G10: 7.29 | H10: 1 | I10: =IF(H10=1,F10,"") -> 2.66 | J10: =IF(H10=1,G10,"") -> 7.29 | K10: FiinX: BCTC 4 quý gần nhất đến Q2/2026; giá đóng cửa 28/9/2026
A11: ILS | B11: UPCoM | C11: Bao bì khác | D11: 319 | E11: 16.4 | F11: 13.33 | G11: 16.64 | H11: 1 | I11: =IF(H11=1,F11,"") -> 13.33 | J11: =IF(H11=1,G11,"") -> 16.64 | K11: FiinX: BCTC 4 quý gần nhất đến Q2/2026; giá đóng cửa 28/9/2026
A12: TPP | B12: HNX | C12: Bao bì nhựa | D12: 3179 | E12: 15.9 | F12: 3.28 | G12: 2.54 | H12: 1 | I12: =IF(H12=1,F12,"") -> 3.28 | J12: =IF(H12=1,G12,"") -> 2.54 | K12: FiinX: BCTC 4 quý gần nhất đến Q2/2026; giá đóng cửa 28/9/2026
A13: MCP | B13: HOSE | C13: Bao bì kim loại, in | D13: 431 | E13: 2.9 | F13: 36.45 | G13: 84.23 | H13: 0 | I13: =IF(H13=1,F13,"") | J13: =IF(H13=1,G13,"") | K13: FiinX (28/9/2026); loại khỏi mẫu – xem ghi chú dòng 2
A14: PBT | B14: UPCoM | C14: Thương mại vật tư bao bì | D14: 2042 | E14: 1.9 | F14: 0.04 | G14: 9.97 | H14: 0 | I14: =IF(H14=1,F14,"") | J14: =IF(H14=1,G14,"") | K14: FiinX (28/9/2026); loại khỏi mẫu – xem ghi chú dòng 2
A15: TPC | B15: HOSE | C15: Màng, túi nhựa | D15: 490 | E15: 7 | F15: 4.21 | G15: 20.41 | H15: 1 | I15: =IF(H15=1,F15,"") -> 4.21 | J15: =IF(H15=1,G15,"") -> 20.41 | K15: FiinX: BCTC 4 quý gần nhất đến Q2/2026; giá đóng cửa 28/9/2026
A16: VBC | B16: HNX | C16: Bao bì nhựa | D16: 913 | F16: 4.17 | G16: 4.85 | H16: 1 | I16: =IF(H16=1,F16,"") -> 4.17 | J16: =IF(H16=1,G16,"") -> 4.85 | K16: FiinX: BCTC 4 quý gần nhất đến Q2/2026; giá đóng cửa 28/9/2026
A17: BBS | B17: HNX | C17: Bao bì giấy, bao xi măng | D17: 484 | E17: 6.5 | F17: 5.5 | G17: 9.19 | H17: 1 | I17: =IF(H17=1,F17,"") -> 5.5 | J17: =IF(H17=1,G17,"") -> 9.19 | K17: FiinX: BCTC 4 quý gần nhất đến Q2/2026; giá đóng cửa 28/9/2026
A18: STP | B18: HNX | C18: Bao bì giấy | D18: 212 | F18: 2.96 | G18: 6.65 | H18: 1 | I18: =IF(H18=1,F18,"") -> 2.96 | J18: =IF(H18=1,G18,"") -> 6.65 | K18: FiinX: BCTC 4 quý gần nhất đến Q2/2026; giá đóng cửa 28/9/2026
A19: PBP | B19: HNX | C19: Bao bì PP | D19: 372 | E19: 5.3 | F19: 2.06 | G19: 6.46 | H19: 1 | I19: =IF(H19=1,F19,"") -> 2.06 | J19: =IF(H19=1,G19,"") -> 6.46 | K19: FiinX: BCTC 4 quý gần nhất đến Q2/2026; giá đóng cửa 28/9/2026
A20: PMP | B20: HNX | C20: Bao bì PP | D20: 746 | E20: 4 | F20: 5.4 | G20: 5.53 | H20: 1 | I20: =IF(H20=1,F20,"") -> 5.4 | J20: =IF(H20=1,G20,"") -> 5.53 | K20: FiinX: BCTC 4 quý gần nhất đến Q2/2026; giá đóng cửa 28/9/2026
A22: Trung vị các DN trong mẫu | F22: =MEDIAN(I5:I20) -> 4.63 | G22: =MEDIAN(J5:J20) -> 7.135 | H22: =SUM(H5:H20) -> 14
A23: Bình quân ngành Containers & Packaging 2026 (FiinX, ICB cấp 4) | F23: 7.99 | G23: 9.43 | H23: Nguồn: FiinX – bình quân ngành Containers & Packaging (ICB cấp 4), cột 2026.
A24: Bội số dùng: trung vị (cận dưới, ít bị kéo bởi DN lỗ/lãi thấp) và bình quân ngành (cận trên)
A26: CHỈ TIÊU CỦA AGRIPACK (2025A – bộ máy hiện tại, trước khi gọi vốn)
A27: EBITDA 2025A | B27: ='Income Statement'!D82/1000000 -> 7.6946292
A28: Lợi nhuận trước thuế 2025A | B28: ='Income Statement'!D76/1000000 -> 4.4204952
A29: Thuế suất chuẩn hóa | B29: =Assumption!D15 -> 0.2 | C29: Lý do: LNST 2025 không phải nộp thuế nhờ chuyển lỗ; chuẩn hóa theo thuế suất phổ thông 20% để so sánh với P/E của DN đã nộp thuế. Nguồn: Luật Thuế TNDN 67/2025/QH15.
A30: LNST chuẩn hóa 2025A | B30: =B28*(1-B29) -> 3.5363962
A31: Tiền mặt 31/12/2025 | B31: ='Balance Sheet'!G7/1000000 -> 2.9334818
A32: Nợ vay 31/12/2025 | B32: =('Balance Sheet'!G48+'Balance Sheet'!G61)/1000000 -> 1.6026
A33: Chiết khấu thiếu thanh khoản & quy mô (DLOM) | B33: 0.3 | C33: Lý do: DN tư nhân, cổ phần không giao dịch, doanh thu 47,5 tỷ (trung vị mẫu ~1.400 tỷ), phụ thuộc đội ngũ sáng lập → 30% (khoảng 20–35% theo nghiên cứu chiết khấu DN tư nhân). Nguồn: Damodaran (2026); Koeplin, Sarin & Shapiro (2000).
A35: ĐỊNH GIÁ VỐN CHỦ SỞ HỮU (PRE-MONEY)
A36: Cách tính | B36: Bội số (x) | C36: Chỉ tiêu áp dụng (tỷ) | D36: Giá trị vốn CSH trước chiết khấu | E36: Sau chiết khấu DLOM
A37: EV/EBITDA 2025A × trung vị mẫu | B37: =F22 -> 4.63 | C37: =B27 -> 7.6946292 | D37: =B37*C37+B31-B32 -> 36.957015 | E37: =D37*(1-$B$33) -> 25.869911
A38: EV/EBITDA 2025A × bình quân ngành | B38: =F23 -> 7.99 | C38: =B27 -> 7.6946292 | D38: =B38*C38+B31-B32 -> 62.810969 | E38: =D38*(1-$B$33) -> 43.967678
A39: P/E 2025A (LNST chuẩn hóa) × trung vị mẫu | B39: =G22 -> 7.135 | C39: =B30 -> 3.5363962 | D39: =B39*C39 -> 25.232187 | E39: =D39*(1-$B$33) -> 17.662531
A40: P/E 2025A (LNST chuẩn hóa) × bình quân ngành | B40: =G23 -> 9.43 | C40: =B30 -> 3.5363962 | D40: =B40*C40 -> 33.348216 | E40: =D40*(1-$B$33) -> 23.343751
A41: Pre-money theo Multiples (bình quân 4 cách) | E41: =AVERAGE(E37:E40) -> 27.710968
A42: Cận dưới / cận trên | D42: =MIN(E37:E40) -> 17.662531 | E42: =MAX(E37:E40) -> 43.967678
A44: KẾT QUẢ: GIÁ TRỊ DOANH NGHIỆP, PRE-MONEY, POST-MONEY VÀ TỶ LỆ CỔ PHẦN
A45: Giá trị doanh nghiệp (EV) | B45: =B49-B31+B32 -> 26.380086 | C45: EV = pre-money − tiền mặt (B31) + nợ vay (B32) tại 31/12/2025, cùng cầu nối giữa EV và vốn CSH như DCF!B22.
A46: Nhu cầu vốn | B46: =DCF!B19/1000000 -> 37.610763 | C46: Vốn cổ phần cần huy động năm 2026 (Pro Forma!B63), dùng chung cho DCF và VC Method.
A47: Tỷ lệ sở hữu của NĐT mới | B47: =B46/B48 -> 0.5757772
A48: Post-money value | B48: =B49+B46 -> 65.321731
A49: Pre-money value | B49: =E41 -> 27.710968 | C49: Lấy từ E41: bình quân 4 cách tính, sau chiết khấu thiếu thanh khoản 30%.
A50: Tỷ lệ sở hữu của Founder và NĐT cũ | B50: =1-B47 -> 0.4242228
A52: Pitch: Kêu gọi | B52: =B46 -> 37.610763 | C52: tỷ đồng tương ứng | D52: =B47 -> 0.5757772 | E52: cổ phần.
A54: ĐỐI CHIẾU: bội số trên chỉ tiêu 2026E (không dùng)
A55: EV/EBITDA 2026E × trung vị mẫu, chưa chiết khấu | D55: =F22*Drivers!F76/1000000+B31-B32 -> 54.039746
A56: Lý do không dùng: EBITDA 2026E cần máy ép bổ sung và vốn lưu động được tài trợ bởi chính khoản vốn mới – áp bội số lên chỉ tiêu tương lai sẽ trả cho nhà đầu tư phần giá trị mà tiền của họ tạo ra.

Sheet Summary
A1: TỔNG HỢP ĐỊNH GIÁ & ĐỀ XUẤT GỌI VỐN – AgriPack
A2: Đơn vị: tỷ đồng (trừ tỷ lệ). Thời điểm định giá t0 = 01/01/2026 (theo khung mô hình: BCTC đến 31/12/2025, năm hiện tại 2026).
A4: Phương pháp | B4: Pre-money | C4: Vốn CP cần huy động | D4: Post-money | E4: Tỷ lệ NĐT mới | F4: Trọng số | G4: Lý do trọng số / nguồn
A5: DCF (FCFF, WACC, giá trị cuối kỳ chuẩn hóa) | B5: =DCF!B22/1000000 -> 32.793775 | C5: =DCF!B19/1000000 -> 37.610763 | D5: =B5+C5 -> 70.404538 | E5: =IF(B5<=0,"n.m.",C5/D5) -> 0.53420936 | F5: 0.4 | G5: Lý do: DCF 40% – phản ánh dự phóng dòng tiền và công suất; chưa trừ rủi ro thất bại. Nguồn: lựa chọn của nhóm.
A6: VC Method (thoái vốn 2030, tỷ lệ thất bại 40%) | B6: =VCM!E11/1000000 -> 25.29891 | C6: =VCM!E5/1000000 -> 37.610763 | D6: =B6+C6 -> 62.909673 | E6: =IF(B6<=0,"n.m.",C6/D6) -> 0.59785342 | F6: 0.4 | G6: Lý do: VCM 40% – góc nhìn NĐT, có tỷ lệ thất bại 40% của giai đoạn đầu tăng trưởng (đề bài). Nguồn: lựa chọn của nhóm.
A7: Multiples/Comparables (EV/EBITDA, P/E 2025A; chiết khấu thanh khoản 30%) | B7: =Multiples!B49 -> 27.710968 | C7: =Multiples!B46 -> 37.610763 | D7: =B7+C7 -> 65.321731 | E7: =IF(B7<=0,"n.m.",C7/D7) -> 0.5757772 | F7: 0.2 | G7: Lý do: Multiples 20% – mẫu so sánh là DN niêm yết lớn, trưởng thành; chỉ phản ánh bộ máy 2025A nên chỉ dùng làm neo thị trường. Nguồn: lựa chọn của nhóm.
A8: Pre-money khuyến nghị (bình quân gia quyền DCF, VCM, Multiples) | B8: =(B5*F5+B6*F6+B7*F7)/(F5+F6+F7) -> 28.779268 | C8: =C5 -> 37.610763 | D8: =B8+C8 -> 66.390031 | E8: =IF(B8<=0,"n.m.",C8/D8) -> 0.56651221 | F8: =F5+F6+F7 -> 1
A9: ĐỐI CHIẾU (không tham gia trọng số)
A10: DCF điều chỉnh xác suất sống sót = (1 − z) × DCF + z × giá trị thanh lý | B10: =(1-VCM!B6)*B5+VCM!B6*B11 -> 25.670707
A11: Giá trị thanh lý = tỷ lệ thu hồi × VCSH sổ sách 31/12/2025 | B11: =C11*'Balance Sheet'!G76/1000000 -> 14.986104 | C11: 0.5 | D11: Lý do: thu hồi 50% giá trị sổ sách khi thanh lý (máy ép chuyên dụng khó bán lại; nhà xưởng thuê). Nguồn: giả định của nhóm.
A12: Multiples trên chỉ tiêu 2026E (tham khảo – xem Multiples!D55; không dùng vì chỉ tiêu 2026E cần chính vốn mới) | B12: =Multiples!D55*(1-Multiples!B33) -> 37.827823
A16: KHOẢNG GIÁ TRỊ PRE-MONEY (football field)
A17: Phương pháp | B17: Thấp | C17: Cơ sở | D17: Cao | E17: Cách xác định khoảng
A18: DCF | B18: =MIN(Sensitivity!C7:E9) -> 23.936193 | C18: =B5 -> 32.793775 | D18: =MAX(Sensitivity!C7:E9) -> 46.481654 | E18: WACC ±1 điểm %, g ±1 điểm %
A19: VC Method | B19: =MIN(Sensitivity!C16:E18) -> 11.406357 | C19: =B6 -> 25.29891 | D19: =MAX(Sensitivity!C16:E18) -> 40.764205 | E19: z 35–45%, giá trị thoái vốn ±15%
A20: Multiples (EV/EBITDA, P/E 2025A) | B20: =Multiples!D42 -> 17.662531 | C20: =B7 -> 27.710968 | D20: =Multiples!E42 -> 43.967678 | E20: Trung vị mẫu – bình quân ngành, sau chiết khấu 30%
A21: Khuyến nghị (bình quân gia quyền) | B21: =(B18*F5+B19*F6+B20*F7)/F8 -> 17.669526 | C21: =B8 -> 28.779268 | D21: =(D18*F5+D19*F6+D20*F7)/F8 -> 43.691879 | E21: Bình quân gia quyền cận dưới/cận trên
A23: NHU CẦU VỐN – ĐẦU VÀO CỦA VC METHOD (kế hoạch huy động vốn chi tiết thuộc Mục 6, không nằm trong phạm vi file này)
A24: Vốn cổ phần cần huy động (tỷ đồng, Pro Forma!B63) | B24: =C8 -> 37.610763
A25: Tỷ lệ cổ phần tương ứng (theo pre-money khuyến nghị) | B25: =E8 -> 0.56651221
A26: Vay trung hạn/thuê tài chính cho nhà máy mới (tỷ đồng) | B26: =SUM(Drivers!F124:J124)/1000000 -> 31.098842
A27: Tổng vốn huy động bên ngoài 2026–2027 (tỷ đồng) | B27: =B24+B26 -> 68.709605
A30: TỔNG HỢP KỊCH BẢN
A31: Cột B = kịch bản đang chạy (công thức sống). Cột C–F = kết quả chụp lại khi đổi ô chọn ở Drivers (giá trị tĩnh, cập nhật lại nếu đổi giả định).
A32: Chỉ tiêu | B32: ="Đang chạy: "&Drivers!D3 -> Đang chạy: Base | C32: Bear (chụp) | D32: Bull (chụp) | E32: Đầu tư lớn 2028 (chụp) | F32: Chỉ vốn CP, không vay (chụp) | G32: Vay 75% CAPEX 2027 (chụp)
A33: Doanh thu thuần 2030E (tỷ) | B33: ='Income Statement'!I13/1000000 -> 170.31775 | C33: 116.89912 | D33: 214.75589 | E33: 174.74193 | F33: 170.31775 | G33: 170.31775
A34: CAGR doanh thu 2025–2030 | B34: =('Income Statement'!I13/'Income Statement'!D13)^(1/5)-1 -> 0.29070865 | C34: 0.19712221 | D34: 0.35196439 | E34: 0.29734554 | F34: 0.29070865 | G34: 0.29070865
A35: Biên EBITDA 2030E | B35: ='Income Statement'!I82/'Income Statement'!I13 -> 0.20217878 | C35: 0.13468057 | D35: 0.23671727 | E35: 0.20557646 | F35: 0.20217878 | G35: 0.20217878
A36: LNST 2030E (tỷ) | B36: ='Income Statement'!I80/1000000 -> 13.854708 | C36: 0.74152445 | D36: 25.755175 | E36: 12.078367 | F36: 15.596243 | G36: 13.419324
A37: Tổng FCFF 2026–2030 (tỷ) | B37: =SUM(DCF!C10:G10)/1000000 -> -38.910142 | C37: -48.928458 | D37: -29.302826 | E37: -58.616408 | F37: -38.910142 | G37: -38.910142
A38: Nhu cầu vốn cổ phần (tỷ) | B38: ='Pro Forma'!B63/1000000 -> 37.610763 | C38: 48.24625 | D38: 32.986934 | E38: 45.15121 | F38: 59.582612 | G38: 34.600395
A39: Vay trung hạn giải ngân (tỷ) | B39: =SUM(Drivers!F124:J124)/1000000 -> 31.098842 | C39: 26.723224 | D39: 34.135019 | E39: 39.505454 | F39: 0 | G39: 38.873552
A40: WACC | B40: ='Discount rate'!E5 -> 0.13637833 | C40: 0.13547094 | D40: 0.13682777 | E40: 0.13019784 | F40: 0.13014514 | G40: 0.13763308
A41: DCF pre-money (tỷ) | B41: =B5 -> 32.793775 | C41: -50.007136 | D41: 107.84768 | E41: 17.308997 | F41: 39.497249 | G41: 31.570856
A42: VCM pre-money (tỷ) | B42: =B6 -> 25.29891 | C42: -28.296198 | D42: 68.872518 | E42: 16.759421 | F42: 12.575354 | G42: 26.541271
A43: Pre-money bình quân (tỷ) | B43: =B8 -> 28.779268 | C43: -25.77914 | D43: 76.230273 | E43: 19.169561 | F43: 26.371235 | G43: 28.787044
A44: Tỷ lệ NĐT mới (theo pre-money bình quân) | B44: =E8 -> 0.56651221 | C44: n.m. | D44: 0.30203056 | E44: 0.70196936 | F44: 0.69319308 | G44: 0.5458557
A45: Tỷ lệ founder & cổ đông hiện hữu sau vòng gọi vốn | B45: =IF(ISNUMBER(E8),1-E8,"n.m.") -> 0.43348779 | C45: n.m. | D45: 0.69796944 | E45: 0.29803064 | F45: 0.30680692 | G45: 0.4541443
A48: ĐỘ NHẠY THEO NHÂN TỐ VĨ MÔ – NGÀNH (kịch bản Base, đổi từng giả định, chạy lại toàn bộ mô hình)
A49: Mỗi dòng: một nhân tố ở Mục 3 được đưa về mức bất lợi và thuận lợi, các giả định khác giữ Base; kết quả chụp lại sau khi tính lại toàn bộ mô hình (giá trị tĩnh – chạy lại run_tornado.py nếu đổi giả định). Δ = chênh lệch pre-money so với Base (chụp), tỷ đồng.
A50: Nhân tố → giả định thay đổi (bất lợi / thuận lợi) | B50: Pre-money bất lợi | C50: Pre-money thuận lợi | D50: Δ bất lợi | E50: Δ thuận lợi | F50: DCF bất lợi | G50: DCF thuận lợi | H50: VCM bất lợi | I50: VCM thuận lợi | J50: DT 2030E bất lợi | K50: DT 2030E thuận lợi | L50: LNST 2030E bất lợi | M50: LNST 2030E thuận lợi | N50: Lý do biên độ / nguồn (ghi ngay cạnh giả định)
A51: Kịch bản cơ sở – Base (chụp) | B51: 28.779268 | C51: 28.779268 | D51: =B51-B$51 -> 0 | E51: =C51-C$51 -> 0 | F51: 32.793775 | G51: 32.793775 | H51: 25.29891 | I51: 25.29891 | J51: 170.31775 | K51: 170.31775 | L51: 13.854708 | M51: 13.854708
A52: Cầu: tăng trưởng sản lượng ×0,8 / ×1,2 (GDP, tiêu dùng, TMĐT – Mục 3.1.1, 3.2.2) | B52: 1.2034817 | C52: 61.072509 | D52: =B52-B$51 -> -27.575786 | E52: =C52-C$51 -> 32.293241 | F52: -10.312495 | G52: 84.64753 | H52: -0.53428432 | I52: 54.178258 | J52: 137.25939 | K52: 209.56544 | L52: 6.5651549 | M52: 22.624423 | N52: Lý do biên độ: ±20% tốc độ tăng sản lượng mọi phân khúc – GDP 6T/2026 +8,18%, tiêu dùng +8,15%, TMĐT +18–25%/năm nhưng SAM chỉ +4,73%/năm; tăng trưởng của AgriPack phụ thuộc giành thị phần và tiến độ nhà máy (kịch bản Bear dùng ×0,7).
A53: Giá bán: +1% / +3% mỗi năm, Base +2% (CPI, sức mạnh khách hàng B2B – Mục 3.1.2, 3.2.3) | B53: 21.948998 | C53: 35.889583 | D53: =B53-B$51 -> -6.8302698 | E53: =C53-C$51 -> 7.110315 | F53: 22.029117 | G53: 44.008879 | H53: 18.987894 | I53: 31.859593 | J53: 162.12602 | K53: 178.8373 | L53: 12.029687 | M53: 15.758482 | N53: Lý do biên độ: ±1 điểm %/năm giá bán F&B, khuôn và đệm – CPI 8T/2026 +4,45% cho phép tăng giá gần lạm phát, nhưng khách hàng B2B có sức mạnh đàm phán rất cao và bao bì nhựa rẻ hơn nhiều lần (Mục 3.2.3).
A54: Chi phí biến đổi/DT: +1 / −1 điểm % (lạm phát chi phí thu gom, năng lượng – Mục 3.1.2) | B54: 20.23906 | C54: 37.099232 | D54: =B54-B$51 -> -8.5402076 | E54: =C54-C$51 -> 8.3199643 | F54: 20.898351 | G54: 44.639628 | H54: 15.843815 | I54: 34.252968 | J54: 170.31775 | K54: 170.31775 | L54: 12.492166 | M54: 15.21725 | N54: Lý do biên độ: ±1 điểm % doanh thu – nhóm nhà ở, điện, nước, chất đốt, VLXD +6,71% (8T/2026); bã mía bị cạnh tranh bởi lò hơi nhà máy đường và nhà sản xuất bao bì sợi (Mục 3.1.2, 3.2.3).
A55: Chi phí nhân sự/DT: +1 / −1 điểm % (lương tối thiểu vùng +7,2% – NĐ 293/2025) | B55: 18.239839 | C55: 38.969594 | D55: =B55-B$51 -> -10.539429 | E55: =C55-C$51 -> 10.190326 | F55: 18.039136 | G55: 47.488397 | H55: 13.704978 | I55: 36.080105 | J55: 170.31775 | K55: 170.31775 | L55: 12.110654 | M55: 15.598762 | N55: Lý do biên độ: ±1 điểm % doanh thu – lương tối thiểu vùng tăng 7,2% từ 01/01/2026 (NĐ 293/2025/NĐ-CP); tiền lương là khoản chi phí lớn thứ hai sau chi phí biến đổi.
A56: Lãi suất: Rf và Kd +1 / −1 điểm % (điều hành lãi suất, tín dụng – Mục 3.1.3) | B56: 23.98281 | C56: 34.532569 | D56: =B56-B$51 -> -4.796458 | E56: =C56-C$51 -> 5.7533011 | F56: 24.509413 | G56: 43.322256 | H56: 21.592128 | I56: 29.153682 | J56: 170.31775 | K56: 170.31775 | L56: 13.667734 | M56: 14.041682 | N56: Lý do biên độ: ±1 điểm % cho cả lợi suất phi rủi ro (bình quân TPCP 10 năm 3,92%) và lãi vay (10%, khung cho vay 8,1–10,5%/năm); nhỏ hơn độ lệch chuẩn ~1,6 điểm % của lợi suất TPCP 10 năm 2016–2025 (Discount rate A28:C40) vì Rf là bình quân dài hạn.
A57: Rủi ro quốc gia CRP: +1 / −1 điểm % (xếp hạng Moody's Ba2, triển vọng tích cực – Mục 3.1) | B57: 23.987829 | C57: 34.768271 | D57: =B57-B$51 -> -4.7914386 | E57: =C57-C$51 -> 5.9890032 | F57: 23.641702 | G57: 44.778686 | H57: 22.472387 | I57: 28.286508 | J57: 170.31775 | K57: 170.31775 | L57: 13.854708 | M57: 13.854708 | N57: Lý do biên độ: ±1 điểm % CRP 3,9% – Moody's nâng triển vọng Việt Nam lên tích cực (5/2026): nâng hạng làm CRP giảm; ngược lại nếu cú sốc bên ngoài làm chênh lệch lợi suất nới rộng.
A58: Ưu đãi thuế NQ 198/2025/QH15 nếu đủ điều kiện (miễn 2026–27, giảm 50% 2028–29 – Mục 3.1.6.2) | B58: 28.779268 | C58: 31.73928 | D58: =B58-B$51 -> 0 | E58: =C58-C$51 -> 2.9600122 | F58: 32.793775 | G58: 36.159176 | H58: 25.29891 | I58: 29.333539 | J58: 170.31775 | K58: 170.31775 | L58: 13.854708 | M58: 13.854708 | N58: Lý do: chỉ có chiều thuận lợi vì mô hình Base chưa đưa ưu đãi vào (chưa chứng minh đủ điều kiện). Chỉ tính ưu đãi đến 2029 để ưu đãi tạm thời không đi vào giá trị cuối kỳ (LNST 2030 chuẩn hóa ở thuế suất 20%).

Sheet Sensitivity
A1: PHÂN TÍCH ĐỘ NHẠY (mỗi ô tính lại toàn bộ DCF/VCM)
A2: Đơn vị: tỷ đồng
A4: Bảng 1. DCF – giá trị vốn CSH pre-money: WACC (dòng) × g (cột)
A5: WACC \ g | B5: =Assumption!$D$16+(-0.02) -> 0.03 | C5: =Assumption!$D$16+(-0.01) -> 0.04 | D5: =Assumption!$D$16+(0) -> 0.05 | E5: =Assumption!$D$16+(0.01) -> 0.06 | F5: =Assumption!$D$16+(0.02) -> 0.07
A6: =Assumption!$D$18+(-0.02) -> 0.11637833 | B6: =(SUMPRODUCT(DCF!$C$10:$G$10,1/(1+$A6)^DCF!$C$3:$G$3)+(DCF!$G$5*(1+B$5)*(1-B$5/Assumption!$D$19)/($A6-B$5))/(1+$A6)^DCF!$G$3+'Balance Sheet'!$G$7-'Balance Sheet'!$G$48-'Balance Sheet'!$G$61)/1000000 -> 52.197803 | C6: =(SUMPRODUCT(DCF!$C$10:$G$10,1/(1+$A6)^DCF!$C$3:$G$3)+(DCF!$G$5*(1+C$5)*(1-C$5/Assumption!$D$19)/($A6-C$5))/(1+$A6)^DCF!$G$3+'Balance Sheet'!$G$7-'Balance Sheet'!$G$48-'Balance Sheet'!$G$61)/1000000 -> 55.330896 | D6: =(SUMPRODUCT(DCF!$C$10:$G$10,1/(1+$A6)^DCF!$C$3:$G$3)+(DCF!$G$5*(1+D$5)*(1-D$5/Assumption!$D$19)/($A6-D$5))/(1+$A6)^DCF!$G$3+'Balance Sheet'!$G$7-'Balance Sheet'!$G$48-'Balance Sheet'!$G$61)/1000000 -> 59.211167 | E6: =(SUMPRODUCT(DCF!$C$10:$G$10,1/(1+$A6)^DCF!$C$3:$G$3)+(DCF!$G$5*(1+E$5)*(1-E$5/Assumption!$D$19)/($A6-E$5))/(1+$A6)^DCF!$G$3+'Balance Sheet'!$G$7-'Balance Sheet'!$G$48-'Balance Sheet'!$G$61)/1000000 -> 64.236205 | F6: =(SUMPRODUCT(DCF!$C$10:$G$10,1/(1+$A6)^DCF!$C$3:$G$3)+(DCF!$G$5*(1+F$5)*(1-F$5/Assumption!$D$19)/($A6-F$5))/(1+$A6)^DCF!$G$3+'Balance Sheet'!$G$7-'Balance Sheet'!$G$48-'Balance Sheet'!$G$61)/1000000 -> 71.146505
A7: =Assumption!$D$18+(-0.01) -> 0.12637833 | B7: =(SUMPRODUCT(DCF!$C$10:$G$10,1/(1+$A7)^DCF!$C$3:$G$3)+(DCF!$G$5*(1+B$5)*(1-B$5/Assumption!$D$19)/($A7-B$5))/(1+$A7)^DCF!$G$3+'Balance Sheet'!$G$7-'Balance Sheet'!$G$48-'Balance Sheet'!$G$61)/1000000 -> 40.504216 | C7: =(SUMPRODUCT(DCF!$C$10:$G$10,1/(1+$A7)^DCF!$C$3:$G$3)+(DCF!$G$5*(1+C$5)*(1-C$5/Assumption!$D$19)/($A7-C$5))/(1+$A7)^DCF!$G$3+'Balance Sheet'!$G$7-'Balance Sheet'!$G$48-'Balance Sheet'!$G$61)/1000000 -> 42.180019 | D7: =(SUMPRODUCT(DCF!$C$10:$G$10,1/(1+$A7)^DCF!$C$3:$G$3)+(DCF!$G$5*(1+D$5)*(1-D$5/Assumption!$D$19)/($A7-D$5))/(1+$A7)^DCF!$G$3+'Balance Sheet'!$G$7-'Balance Sheet'!$G$48-'Balance Sheet'!$G$61)/1000000 -> 44.131037 | E7: =(SUMPRODUCT(DCF!$C$10:$G$10,1/(1+$A7)^DCF!$C$3:$G$3)+(DCF!$G$5*(1+E$5)*(1-E$5/Assumption!$D$19)/($A7-E$5))/(1+$A7)^DCF!$G$3+'Balance Sheet'!$G$7-'Balance Sheet'!$G$48-'Balance Sheet'!$G$61)/1000000 -> 46.481654 | F7: =(SUMPRODUCT(DCF!$C$10:$G$10,1/(1+$A7)^DCF!$C$3:$G$3)+(DCF!$G$5*(1+F$5)*(1-F$5/Assumption!$D$19)/($A7-F$5))/(1+$A7)^DCF!$G$3+'Balance Sheet'!$G$7-'Balance Sheet'!$G$48-'Balance Sheet'!$G$61)/1000000 -> 49.444504
A8: =Assumption!$D$18+(0) -> 0.13637833 | B8: =(SUMPRODUCT(DCF!$C$10:$G$10,1/(1+$A8)^DCF!$C$3:$G$3)+(DCF!$G$5*(1+B$5)*(1-B$5/Assumption!$D$19)/($A8-B$5))/(1+$A8)^DCF!$G$3+'Balance Sheet'!$G$7-'Balance Sheet'!$G$48-'Balance Sheet'!$G$61)/1000000 -> 31.238476 | C8: =(SUMPRODUCT(DCF!$C$10:$G$10,1/(1+$A8)^DCF!$C$3:$G$3)+(DCF!$G$5*(1+C$5)*(1-C$5/Assumption!$D$19)/($A8-C$5))/(1+$A8)^DCF!$G$3+'Balance Sheet'!$G$7-'Balance Sheet'!$G$48-'Balance Sheet'!$G$61)/1000000 -> 31.997462 | D8: =(SUMPRODUCT(DCF!$C$10:$G$10,1/(1+$A8)^DCF!$C$3:$G$3)+(DCF!$G$5*(1+D$5)*(1-D$5/Assumption!$D$19)/($A8-D$5))/(1+$A8)^DCF!$G$3+'Balance Sheet'!$G$7-'Balance Sheet'!$G$48-'Balance Sheet'!$G$61)/1000000 -> 32.793775 | E8: =(SUMPRODUCT(DCF!$C$10:$G$10,1/(1+$A8)^DCF!$C$3:$G$3)+(DCF!$G$5*(1+E$5)*(1-E$5/Assumption!$D$19)/($A8-E$5))/(1+$A8)^DCF!$G$3+'Balance Sheet'!$G$7-'Balance Sheet'!$G$48-'Balance Sheet'!$G$61)/1000000 -> 33.642077 | F8: =(SUMPRODUCT(DCF!$C$10:$G$10,1/(1+$A8)^DCF!$C$3:$G$3)+(DCF!$G$5*(1+F$5)*(1-F$5/Assumption!$D$19)/($A8-F$5))/(1+$A8)^DCF!$G$3+'Balance Sheet'!$G$7-'Balance Sheet'!$G$48-'Balance Sheet'!$G$61)/1000000 -> 34.565865
A9: =Assumption!$D$18+(0.01) -> 0.14637833 | B9: =(SUMPRODUCT(DCF!$C$10:$G$10,1/(1+$A9)^DCF!$C$3:$G$3)+(DCF!$G$5*(1+B$5)*(1-B$5/Assumption!$D$19)/($A9-B$5))/(1+$A9)^DCF!$G$3+'Balance Sheet'!$G$7-'Balance Sheet'!$G$48-'Balance Sheet'!$G$61)/1000000 -> 23.764932 | C9: =(SUMPRODUCT(DCF!$C$10:$G$10,1/(1+$A9)^DCF!$C$3:$G$3)+(DCF!$G$5*(1+C$5)*(1-C$5/Assumption!$D$19)/($A9-C$5))/(1+$A9)^DCF!$G$3+'Balance Sheet'!$G$7-'Balance Sheet'!$G$48-'Balance Sheet'!$G$61)/1000000 -> 23.936193 | D9: =(SUMPRODUCT(DCF!$C$10:$G$10,1/(1+$A9)^DCF!$C$3:$G$3)+(DCF!$G$5*(1+D$5)*(1-D$5/Assumption!$D$19)/($A9-D$5))/(1+$A9)^DCF!$G$3+'Balance Sheet'!$G$7-'Balance Sheet'!$G$48-'Balance Sheet'!$G$61)/1000000 -> 24.024262 | E9: =(SUMPRODUCT(DCF!$C$10:$G$10,1/(1+$A9)^DCF!$C$3:$G$3)+(DCF!$G$5*(1+E$5)*(1-E$5/Assumption!$D$19)/($A9-E$5))/(1+$A9)^DCF!$G$3+'Balance Sheet'!$G$7-'Balance Sheet'!$G$48-'Balance Sheet'!$G$61)/1000000 -> 24.000248 | F9: =(SUMPRODUCT(DCF!$C$10:$G$10,1/(1+$A9)^DCF!$C$3:$G$3)+(DCF!$G$5*(1+F$5)*(1-F$5/Assumption!$D$19)/($A9-F$5))/(1+$A9)^DCF!$G$3+'Balance Sheet'!$G$7-'Balance Sheet'!$G$48-'Balance Sheet'!$G$61)/1000000 -> 23.820125
A10: =Assumption!$D$18+(0.02) -> 0.15637833 | B10: =(SUMPRODUCT(DCF!$C$10:$G$10,1/(1+$A10)^DCF!$C$3:$G$3)+(DCF!$G$5*(1+B$5)*(1-B$5/Assumption!$D$19)/($A10-B$5))/(1+$A10)^DCF!$G$3+'Balance Sheet'!$G$7-'Balance Sheet'!$G$48-'Balance Sheet'!$G$61)/1000000 -> 17.649626 | C10: =(SUMPRODUCT(DCF!$C$10:$G$10,1/(1+$A10)^DCF!$C$3:$G$3)+(DCF!$G$5*(1+C$5)*(1-C$5/Assumption!$D$19)/($A10-C$5))/(1+$A10)^DCF!$G$3+'Balance Sheet'!$G$7-'Balance Sheet'!$G$48-'Balance Sheet'!$G$61)/1000000 -> 17.440806 | D10: =(SUMPRODUCT(DCF!$C$10:$G$10,1/(1+$A10)^DCF!$C$3:$G$3)+(DCF!$G$5*(1+D$5)*(1-D$5/Assumption!$D$19)/($A10-D$5))/(1+$A10)^DCF!$G$3+'Balance Sheet'!$G$7-'Balance Sheet'!$G$48-'Balance Sheet'!$G$61)/1000000 -> 17.089729 | E10: =(SUMPRODUCT(DCF!$C$10:$G$10,1/(1+$A10)^DCF!$C$3:$G$3)+(DCF!$G$5*(1+E$5)*(1-E$5/Assumption!$D$19)/($A10-E$5))/(1+$A10)^DCF!$G$3+'Balance Sheet'!$G$7-'Balance Sheet'!$G$48-'Balance Sheet'!$G$61)/1000000 -> 16.552114 | F10: =(SUMPRODUCT(DCF!$C$10:$G$10,1/(1+$A10)^DCF!$C$3:$G$3)+(DCF!$G$5*(1+F$5)*(1-F$5/Assumption!$D$19)/($A10-F$5))/(1+$A10)^DCF!$G$3+'Balance Sheet'!$G$7-'Balance Sheet'!$G$48-'Balance Sheet'!$G$61)/1000000 -> 15.763173
A11: Kiểm tra ô trung tâm = DCF!B22 | B11: =ROUND(D8-DCF!B22/1000000,6) -> 0
A13: Bảng 2. VC method – pre-money: tỷ lệ thất bại z (dòng) × thay đổi giá trị thoái vốn (cột)
A14: z \ Exit value | B14: -0.3 | C14: -0.15 | D14: 0 | E14: 0.15 | F14: 0.3
A15: 0.3 | B15: =(VCM!$E$6*(1+B$14)*(1-$A15)/(1+VCM!$B$7)^VCM!$B$5-VCM!$E$5)/1000000 -> 13.76547 | C15: =(VCM!$E$6*(1+C$14)*(1-$A15)/(1+VCM!$B$7)^VCM!$B$5-VCM!$E$5)/1000000 -> 24.774663 | D15: =(VCM!$E$6*(1+D$14)*(1-$A15)/(1+VCM!$B$7)^VCM!$B$5-VCM!$E$5)/1000000 -> 35.783856 | E15: =(VCM!$E$6*(1+E$14)*(1-$A15)/(1+VCM!$B$7)^VCM!$B$5-VCM!$E$5)/1000000 -> 46.793048 | F15: =(VCM!$E$6*(1+F$14)*(1-$A15)/(1+VCM!$B$7)^VCM!$B$5-VCM!$E$5)/1000000 -> 57.802241
A16: 0.35 | B16: =(VCM!$E$6*(1+B$14)*(1-$A16)/(1+VCM!$B$7)^VCM!$B$5-VCM!$E$5)/1000000 -> 10.095739 | C16: =(VCM!$E$6*(1+C$14)*(1-$A16)/(1+VCM!$B$7)^VCM!$B$5-VCM!$E$5)/1000000 -> 20.318561 | D16: =(VCM!$E$6*(1+D$14)*(1-$A16)/(1+VCM!$B$7)^VCM!$B$5-VCM!$E$5)/1000000 -> 30.541383 | E16: =(VCM!$E$6*(1+E$14)*(1-$A16)/(1+VCM!$B$7)^VCM!$B$5-VCM!$E$5)/1000000 -> 40.764205 | F16: =(VCM!$E$6*(1+F$14)*(1-$A16)/(1+VCM!$B$7)^VCM!$B$5-VCM!$E$5)/1000000 -> 50.987027
A17: 0.4 | B17: =(VCM!$E$6*(1+B$14)*(1-$A17)/(1+VCM!$B$7)^VCM!$B$5-VCM!$E$5)/1000000 -> 6.4260082 | C17: =(VCM!$E$6*(1+C$14)*(1-$A17)/(1+VCM!$B$7)^VCM!$B$5-VCM!$E$5)/1000000 -> 15.862459 | D17: =(VCM!$E$6*(1+D$14)*(1-$A17)/(1+VCM!$B$7)^VCM!$B$5-VCM!$E$5)/1000000 -> 25.29891 | E17: =(VCM!$E$6*(1+E$14)*(1-$A17)/(1+VCM!$B$7)^VCM!$B$5-VCM!$E$5)/1000000 -> 34.735361 | F17: =(VCM!$E$6*(1+F$14)*(1-$A17)/(1+VCM!$B$7)^VCM!$B$5-VCM!$E$5)/1000000 -> 44.171812
A18: 0.45 | B18: =(VCM!$E$6*(1+B$14)*(1-$A18)/(1+VCM!$B$7)^VCM!$B$5-VCM!$E$5)/1000000 -> 2.7562772 | C18: =(VCM!$E$6*(1+C$14)*(1-$A18)/(1+VCM!$B$7)^VCM!$B$5-VCM!$E$5)/1000000 -> 11.406357 | D18: =(VCM!$E$6*(1+D$14)*(1-$A18)/(1+VCM!$B$7)^VCM!$B$5-VCM!$E$5)/1000000 -> 20.056437 | E18: =(VCM!$E$6*(1+E$14)*(1-$A18)/(1+VCM!$B$7)^VCM!$B$5-VCM!$E$5)/1000000 -> 28.706517 | F18: =(VCM!$E$6*(1+F$14)*(1-$A18)/(1+VCM!$B$7)^VCM!$B$5-VCM!$E$5)/1000000 -> 37.356598
A19: 0.5 | B19: =(VCM!$E$6*(1+B$14)*(1-$A19)/(1+VCM!$B$7)^VCM!$B$5-VCM!$E$5)/1000000 -> -0.91345371 | C19: =(VCM!$E$6*(1+C$14)*(1-$A19)/(1+VCM!$B$7)^VCM!$B$5-VCM!$E$5)/1000000 -> 6.9502554 | D19: =(VCM!$E$6*(1+D$14)*(1-$A19)/(1+VCM!$B$7)^VCM!$B$5-VCM!$E$5)/1000000 -> 14.813965 | E19: =(VCM!$E$6*(1+E$14)*(1-$A19)/(1+VCM!$B$7)^VCM!$B$5-VCM!$E$5)/1000000 -> 22.677674 | F19: =(VCM!$E$6*(1+F$14)*(1-$A19)/(1+VCM!$B$7)^VCM!$B$5-VCM!$E$5)/1000000 -> 30.541383
A20: Kiểm tra ô trung tâm = VCM!E11 | B20: =ROUND(D17-VCM!E11/1000000,6) -> 0
A22: Bảng 3. DCF – pre-money: WACC (dòng) × RONIC (cột)
A23: WACC \ RONIC | B23: =Assumption!$D$19+(-0.04) -> 0.098811532 | C23: =Assumption!$D$19+(-0.02) -> 0.11881153 | D23: =Assumption!$D$19+(0) -> 0.13881153 | E23: =Assumption!$D$19+(0.02) -> 0.15881153 | F23: =Assumption!$D$19+(0.04) -> 0.17881153
A24: =Assumption!$D$18+(-0.02) -> 0.11637833 | B24: =(SUMPRODUCT(DCF!$C$10:$G$10,1/(1+$A24)^DCF!$C$3:$G$3)+(DCF!$G$5*(1+Assumption!$D$16)*(1-Assumption!$D$16/B$23)/($A24-Assumption!$D$16))/(1+$A24)^DCF!$G$3+'Balance Sheet'!$G$7-'Balance Sheet'!$G$48-'Balance Sheet'!$G$61)/1000000 -> 38.295184 | C24: =(SUMPRODUCT(DCF!$C$10:$G$10,1/(1+$A24)^DCF!$C$3:$G$3)+(DCF!$G$5*(1+Assumption!$D$16)*(1-Assumption!$D$16/C$23)/($A24-Assumption!$D$16))/(1+$A24)^DCF!$G$3+'Balance Sheet'!$G$7-'Balance Sheet'!$G$48-'Balance Sheet'!$G$61)/1000000 -> 50.513609 | D24: =(SUMPRODUCT(DCF!$C$10:$G$10,1/(1+$A24)^DCF!$C$3:$G$3)+(DCF!$G$5*(1+Assumption!$D$16)*(1-Assumption!$D$16/D$23)/($A24-Assumption!$D$16))/(1+$A24)^DCF!$G$3+'Balance Sheet'!$G$7-'Balance Sheet'!$G$48-'Balance Sheet'!$G$61)/1000000 -> 59.211167 | E24: =(SUMPRODUCT(DCF!$C$10:$G$10,1/(1+$A24)^DCF!$C$3:$G$3)+(DCF!$G$5*(1+Assumption!$D$16)*(1-Assumption!$D$16/E$23)/($A24-Assumption!$D$16))/(1+$A24)^DCF!$G$3+'Balance Sheet'!$G$7-'Balance Sheet'!$G$48-'Balance Sheet'!$G$61)/1000000 -> 65.718064 | F24: =(SUMPRODUCT(DCF!$C$10:$G$10,1/(1+$A24)^DCF!$C$3:$G$3)+(DCF!$G$5*(1+Assumption!$D$16)*(1-Assumption!$D$16/F$23)/($A24-Assumption!$D$16))/(1+$A24)^DCF!$G$3+'Balance Sheet'!$G$7-'Balance Sheet'!$G$48-'Balance Sheet'!$G$61)/1000000 -> 70.769373
A25: =Assumption!$D$18+(-0.01) -> 0.12637833 | B25: =(SUMPRODUCT(DCF!$C$10:$G$10,1/(1+$A25)^DCF!$C$3:$G$3)+(DCF!$G$5*(1+Assumption!$D$16)*(1-Assumption!$D$16/B$23)/($A25-Assumption!$D$16))/(1+$A25)^DCF!$G$3+'Balance Sheet'!$G$7-'Balance Sheet'!$G$48-'Balance Sheet'!$G$61)/1000000 -> 26.746225 | C25: =(SUMPRODUCT(DCF!$C$10:$G$10,1/(1+$A25)^DCF!$C$3:$G$3)+(DCF!$G$5*(1+Assumption!$D$16)*(1-Assumption!$D$16/C$23)/($A25-Assumption!$D$16))/(1+$A25)^DCF!$G$3+'Balance Sheet'!$G$7-'Balance Sheet'!$G$48-'Balance Sheet'!$G$61)/1000000 -> 36.901857 | D25: =(SUMPRODUCT(DCF!$C$10:$G$10,1/(1+$A25)^DCF!$C$3:$G$3)+(DCF!$G$5*(1+Assumption!$D$16)*(1-Assumption!$D$16/D$23)/($A25-Assumption!$D$16))/(1+$A25)^DCF!$G$3+'Balance Sheet'!$G$7-'Balance Sheet'!$G$48-'Balance Sheet'!$G$61)/1000000 -> 44.131037 | E25: =(SUMPRODUCT(DCF!$C$10:$G$10,1/(1+$A25)^DCF!$C$3:$G$3)+(DCF!$G$5*(1+Assumption!$D$16)*(1-Assumption!$D$16/E$23)/($A25-Assumption!$D$16))/(1+$A25)^DCF!$G$3+'Balance Sheet'!$G$7-'Balance Sheet'!$G$48-'Balance Sheet'!$G$61)/1000000 -> 49.539397 | F25: =(SUMPRODUCT(DCF!$C$10:$G$10,1/(1+$A25)^DCF!$C$3:$G$3)+(DCF!$G$5*(1+Assumption!$D$16)*(1-Assumption!$D$16/F$23)/($A25-Assumption!$D$16))/(1+$A25)^DCF!$G$3+'Balance Sheet'!$G$7-'Balance Sheet'!$G$48-'Balance Sheet'!$G$61)/1000000 -> 53.737912
A26: =Assumption!$D$18+(0) -> 0.13637833 | B26: =(SUMPRODUCT(DCF!$C$10:$G$10,1/(1+$A26)^DCF!$C$3:$G$3)+(DCF!$G$5*(1+Assumption!$D$16)*(1-Assumption!$D$16/B$23)/($A26-Assumption!$D$16))/(1+$A26)^DCF!$G$3+'Balance Sheet'!$G$7-'Balance Sheet'!$G$48-'Balance Sheet'!$G$61)/1000000 -> 18.086166 | C26: =(SUMPRODUCT(DCF!$C$10:$G$10,1/(1+$A26)^DCF!$C$3:$G$3)+(DCF!$G$5*(1+Assumption!$D$16)*(1-Assumption!$D$16/C$23)/($A26-Assumption!$D$16))/(1+$A26)^DCF!$G$3+'Balance Sheet'!$G$7-'Balance Sheet'!$G$48-'Balance Sheet'!$G$61)/1000000 -> 26.677865 | D26: =(SUMPRODUCT(DCF!$C$10:$G$10,1/(1+$A26)^DCF!$C$3:$G$3)+(DCF!$G$5*(1+Assumption!$D$16)*(1-Assumption!$D$16/D$23)/($A26-Assumption!$D$16))/(1+$A26)^DCF!$G$3+'Balance Sheet'!$G$7-'Balance Sheet'!$G$48-'Balance Sheet'!$G$61)/1000000 -> 32.793775 | E26: =(SUMPRODUCT(DCF!$C$10:$G$10,1/(1+$A26)^DCF!$C$3:$G$3)+(DCF!$G$5*(1+Assumption!$D$16)*(1-Assumption!$D$16/E$23)/($A26-Assumption!$D$16))/(1+$A26)^DCF!$G$3+'Balance Sheet'!$G$7-'Balance Sheet'!$G$48-'Balance Sheet'!$G$61)/1000000 -> 37.369266 | F26: =(SUMPRODUCT(DCF!$C$10:$G$10,1/(1+$A26)^DCF!$C$3:$G$3)+(DCF!$G$5*(1+Assumption!$D$16)*(1-Assumption!$D$16/F$23)/($A26-Assumption!$D$16))/(1+$A26)^DCF!$G$3+'Balance Sheet'!$G$7-'Balance Sheet'!$G$48-'Balance Sheet'!$G$61)/1000000 -> 40.921223
A27: =Assumption!$D$18+(0.01) -> 0.14637833 | B27: =(SUMPRODUCT(DCF!$C$10:$G$10,1/(1+$A27)^DCF!$C$3:$G$3)+(DCF!$G$5*(1+Assumption!$D$16)*(1-Assumption!$D$16/B$23)/($A27-Assumption!$D$16))/(1+$A27)^DCF!$G$3+'Balance Sheet'!$G$7-'Balance Sheet'!$G$48-'Balance Sheet'!$G$61)/1000000 -> 11.407661 | C27: =(SUMPRODUCT(DCF!$C$10:$G$10,1/(1+$A27)^DCF!$C$3:$G$3)+(DCF!$G$5*(1+Assumption!$D$16)*(1-Assumption!$D$16/C$23)/($A27-Assumption!$D$16))/(1+$A27)^DCF!$G$3+'Balance Sheet'!$G$7-'Balance Sheet'!$G$48-'Balance Sheet'!$G$61)/1000000 -> 18.777862 | D27: =(SUMPRODUCT(DCF!$C$10:$G$10,1/(1+$A27)^DCF!$C$3:$G$3)+(DCF!$G$5*(1+Assumption!$D$16)*(1-Assumption!$D$16/D$23)/($A27-Assumption!$D$16))/(1+$A27)^DCF!$G$3+'Balance Sheet'!$G$7-'Balance Sheet'!$G$48-'Balance Sheet'!$G$61)/1000000 -> 24.024262 | E27: =(SUMPRODUCT(DCF!$C$10:$G$10,1/(1+$A27)^DCF!$C$3:$G$3)+(DCF!$G$5*(1+Assumption!$D$16)*(1-Assumption!$D$16/E$23)/($A27-Assumption!$D$16))/(1+$A27)^DCF!$G$3+'Balance Sheet'!$G$7-'Balance Sheet'!$G$48-'Balance Sheet'!$G$61)/1000000 -> 27.949247 | F27: =(SUMPRODUCT(DCF!$C$10:$G$10,1/(1+$A27)^DCF!$C$3:$G$3)+(DCF!$G$5*(1+Assumption!$D$16)*(1-Assumption!$D$16/F$23)/($A27-Assumption!$D$16))/(1+$A27)^DCF!$G$3+'Balance Sheet'!$G$7-'Balance Sheet'!$G$48-'Balance Sheet'!$G$61)/1000000 -> 30.996216
A28: =Assumption!$D$18+(0.02) -> 0.15637833 | B28: =(SUMPRODUCT(DCF!$C$10:$G$10,1/(1+$A28)^DCF!$C$3:$G$3)+(DCF!$G$5*(1+Assumption!$D$16)*(1-Assumption!$D$16/B$23)/($A28-Assumption!$D$16))/(1+$A28)^DCF!$G$3+'Balance Sheet'!$G$7-'Balance Sheet'!$G$48-'Balance Sheet'!$G$61)/1000000 -> 6.1449067 | C28: =(SUMPRODUCT(DCF!$C$10:$G$10,1/(1+$A28)^DCF!$C$3:$G$3)+(DCF!$G$5*(1+Assumption!$D$16)*(1-Assumption!$D$16/C$23)/($A28-Assumption!$D$16))/(1+$A28)^DCF!$G$3+'Balance Sheet'!$G$7-'Balance Sheet'!$G$48-'Balance Sheet'!$G$61)/1000000 -> 12.53851 | D28: =(SUMPRODUCT(DCF!$C$10:$G$10,1/(1+$A28)^DCF!$C$3:$G$3)+(DCF!$G$5*(1+Assumption!$D$16)*(1-Assumption!$D$16/D$23)/($A28-Assumption!$D$16))/(1+$A28)^DCF!$G$3+'Balance Sheet'!$G$7-'Balance Sheet'!$G$48-'Balance Sheet'!$G$61)/1000000 -> 17.089729 | E28: =(SUMPRODUCT(DCF!$C$10:$G$10,1/(1+$A28)^DCF!$C$3:$G$3)+(DCF!$G$5*(1+Assumption!$D$16)*(1-Assumption!$D$16/E$23)/($A28-Assumption!$D$16))/(1+$A28)^DCF!$G$3+'Balance Sheet'!$G$7-'Balance Sheet'!$G$48-'Balance Sheet'!$G$61)/1000000 -> 20.494629 | F28: =(SUMPRODUCT(DCF!$C$10:$G$10,1/(1+$A28)^DCF!$C$3:$G$3)+(DCF!$G$5*(1+Assumption!$D$16)*(1-Assumption!$D$16/F$23)/($A28-Assumption!$D$16))/(1+$A28)^DCF!$G$3+'Balance Sheet'!$G$7-'Balance Sheet'!$G$48-'Balance Sheet'!$G$61)/1000000 -> 23.137855

Sheet Checks
A1: KIỂM TRA TÍNH TOÀN VẸN MÔ HÌNH
A3: Kiểm tra | B3: 2026E | C3: 2027E | D3: 2028E | E3: 2029E | F3: 2030E | G3: Trạng thái
A4: BCĐKT cân (Tài sản − Nguồn vốn) | B4: =ROUND('Balance Sheet'!H34-'Balance Sheet'!H78,0) -> 0 | C4: =ROUND('Balance Sheet'!I34-'Balance Sheet'!I78,0) -> 0 | D4: =ROUND('Balance Sheet'!J34-'Balance Sheet'!J78,0) -> 0 | E4: =ROUND('Balance Sheet'!K34-'Balance Sheet'!K78,0) -> 0 | F4: =ROUND('Balance Sheet'!L34-'Balance Sheet'!L78,0) -> 0 | G4: =IF(SUMPRODUCT(ABS(B4:F4))=0,"OK","LỖI") -> OK
A5: Tiền cuối kỳ LCTT − Tiền BCĐKT | B5: =ROUND('Cash Flow Statement'!F36-'Balance Sheet'!H7,0) -> 0 | C5: =ROUND('Cash Flow Statement'!G36-'Balance Sheet'!I7,0) -> 0 | D5: =ROUND('Cash Flow Statement'!H36-'Balance Sheet'!J7,0) -> 0 | E5: =ROUND('Cash Flow Statement'!I36-'Balance Sheet'!K7,0) -> 0 | F5: =ROUND('Cash Flow Statement'!J36-'Balance Sheet'!L7,0) -> 0 | G5: =IF(SUMPRODUCT(ABS(B5:F5))=0,"OK","LỖI") -> OK
A6: LNST BCKQKD − LNST trên LCTT | B6: =ROUND('Income Statement'!E80-'Cash Flow Statement'!F6,0) -> 0 | C6: =ROUND('Income Statement'!F80-'Cash Flow Statement'!G6,0) -> 0 | D6: =ROUND('Income Statement'!G80-'Cash Flow Statement'!H6,0) -> 0 | E6: =ROUND('Income Statement'!H80-'Cash Flow Statement'!I6,0) -> 0 | F6: =ROUND('Income Statement'!I80-'Cash Flow Statement'!J6,0) -> 0 | G6: =IF(SUMPRODUCT(ABS(B6:F6))=0,"OK","LỖI") -> OK
A7: Doanh thu Pro Forma − BCKQKD | B7: =ROUND('Pro Forma'!C4-'Income Statement'!E13,0) -> 0 | C7: =ROUND('Pro Forma'!D4-'Income Statement'!F13,0) -> 0 | D7: =ROUND('Pro Forma'!E4-'Income Statement'!G13,0) -> 0 | E7: =ROUND('Pro Forma'!F4-'Income Statement'!H13,0) -> 0 | F7: =ROUND('Pro Forma'!G4-'Income Statement'!I13,0) -> 0 | G7: =IF(SUMPRODUCT(ABS(B7:F7))=0,"OK","LỖI") -> OK
A8: LNST Pro Forma − BCKQKD | B8: =ROUND('Pro Forma'!C14-'Income Statement'!E80,0) -> 0 | C8: =ROUND('Pro Forma'!D14-'Income Statement'!F80,0) -> 0 | D8: =ROUND('Pro Forma'!E14-'Income Statement'!G80,0) -> 0 | E8: =ROUND('Pro Forma'!F14-'Income Statement'!H80,0) -> 0 | F8: =ROUND('Pro Forma'!G14-'Income Statement'!I80,0) -> 0 | G8: =IF(SUMPRODUCT(ABS(B8:F8))=0,"OK","LỖI") -> OK
A9: VLĐ Pro Forma − Drivers | B9: =ROUND('Pro Forma'!C36-Drivers!F114,0) -> 0 | C9: =ROUND('Pro Forma'!D36-Drivers!G114,0) -> 0 | D9: =ROUND('Pro Forma'!E36-Drivers!H114,0) -> 0 | E9: =ROUND('Pro Forma'!F36-Drivers!I114,0) -> 0 | F9: =ROUND('Pro Forma'!G36-Drivers!J114,0) -> 0 | G9: =IF(SUMPRODUCT(ABS(B9:F9))=0,"OK","LỖI") -> OK
A10: Khấu hao Pro Forma − BCKQKD | B10: =ROUND('Pro Forma'!C9-'Income Statement'!E71,0) -> 0 | C10: =ROUND('Pro Forma'!D9-'Income Statement'!F71,0) -> 0 | D10: =ROUND('Pro Forma'!E9-'Income Statement'!G71,0) -> 0 | E10: =ROUND('Pro Forma'!F9-'Income Statement'!H71,0) -> 0 | F10: =ROUND('Pro Forma'!G9-'Income Statement'!I71,0) -> 0 | G10: =IF(SUMPRODUCT(ABS(B10:F10))=0,"OK","LỖI") -> OK
A11: CAPEX Drivers + dòng tiền đầu tư | B11: =ROUND(Drivers!F95+'Cash Flow Statement'!F22,0) -> 0 | C11: =ROUND(Drivers!G95+'Cash Flow Statement'!G22,0) -> 0 | D11: =ROUND(Drivers!H95+'Cash Flow Statement'!H22,0) -> 0 | E11: =ROUND(Drivers!I95+'Cash Flow Statement'!I22,0) -> 0 | F11: =ROUND(Drivers!J95+'Cash Flow Statement'!J22,0) -> 0 | G11: =IF(SUMPRODUCT(ABS(B11:F11))=0,"OK","LỖI") -> OK
A12: Tiền mặt sau gọi vốn − tiền tối thiểu (≥ 0) | B12: =ROUND(MIN(0,'Balance Sheet'!H7-Drivers!F120),0) -> 0 | C12: =ROUND(MIN(0,'Balance Sheet'!I7-Drivers!G120),0) -> 0 | D12: =ROUND(MIN(0,'Balance Sheet'!J7-Drivers!H120),0) -> 0 | E12: =ROUND(MIN(0,'Balance Sheet'!K7-Drivers!I120),0) -> 0 | F12: =ROUND(MIN(0,'Balance Sheet'!L7-Drivers!J120),0) -> 0 | G12: =IF(SUMPRODUCT(ABS(B12:F12))=0,"OK","LỖI") -> OK
A13: CAPEX/DT năm đầu tư lớn = 65% | B13: =INDEX(Drivers!F93:J93,Drivers!C4-2025) -> 0.65 | G13: =IF(ROUND(B13,4)=Drivers!C158,"OK","LỖI") -> OK
A14: Ô trung tâm bảng độ nhạy = kết quả DCF/VCM | B14: =Sensitivity!B11 -> 0 | C14: =Sensitivity!B20 -> 0 | G14: =IF(AND(B14=0,C14=0),"OK","LỖI") -> OK
A15: g < WACC | G15: =IF(Assumption!D16<Assumption!D18,"OK","LỖI") -> OK
A17: TỔNG HỢP | G17: =IF(COUNTIF(G4:G15,"LỖI")=0,"TẤT CẢ OK","CÓ LỖI") -> TẤT CẢ OK

Sheet Sheet1

Sheet Chart_Data
A1: CHART_DATA – dữ liệu của toàn bộ Fig. trong báo cáo HTML (đánh số theo báo cáo)
A2: Mỗi block bắt đầu bằng mã Fig_xx (trùng số Fig. trong báo cáo). Số liệu mô hình = công thức liên kết (chữ xanh lá/đen); số liệu bên ngoài = ô nhập (chữ xanh dương, nền vàng) kèm nguồn ngay dưới block. Đơn vị: tỷ đồng trừ khi ghi khác.
A4: Fig. | B4: Tiêu đề | C4: Vùng dữ liệu | D4: Sheet nguồn | E4: Mục báo cáo
A5: Fig_01 | B5: Doanh thu thuần và biên EBITDA 2023A–2030E | C5: A81:I86 | D5: Drivers | E5: Tóm tắt
A6: Fig_02 | B6: Khoảng giá trị pre-money theo phương pháp | C6: A88:D95 | D6: Summary | E6: Tóm tắt
A7: Fig_03 | B7: Tóm tắt tài chính 2023A–2030E | C7: A97:I110 | D7: Drivers, IS, CF, DCF, BS | E7: Tóm tắt
A8: Fig_04 | B8: Thị trường nhựa Việt Nam 2026–2031 | C8: A112:C118 | D8: External | E8: Mục 1
A9: Fig_05 | B9: Lộ trình hạn chế nhựa dùng một lần và kế hoạch AgriPack | C9: — | D9: Bảng/hình văn bản: nguồn ghi dưới hình trong báo cáo | E9: Mục 1
A10: Fig_06 | B10: Giá tham khảo hộp đựng thực phẩm 500 ml | C10: A120:D127 | D10: External | E10: Mục 1
A11: Fig_07 | B11: Thị trường mục tiêu TAM – SAM – SOM | C11: A129:D135 | D11: Drivers | E11: Mục 1
A12: Fig_08 | B12: Chiến lược giá bán của AgriPack | C12: A137:F145 | D12: External + Drivers | E12: Mục 1
A13: Fig_09 | B13: Cơ cấu doanh thu 2023–2025 | C13: A147:D154 | D13: Income Statement | E13: Mục 1
A14: Fig_10 | B14: Cơ cấu chi phí 2023–2025 | C14: A156:D161 | D14: Drivers | E14: Mục 1
A15: Fig_11 | B15: Chuỗi giá trị 7 hoạt động | C15: — | D15: Bảng/hình văn bản: nguồn ghi dưới hình trong báo cáo | E15: Mục 1
... A78: Fig_A15 | B78: Độ nhạy theo nhân tố vĩ mô – ngành | C78: A834:L844 | D78: Summary | E78: Phụ lục
A81: Fig_01 | Doanh thu thuần và biên EBITDA 2023A–2030E
A82: Chỉ tiêu | B82: 2023A | C82: 2024A | D82: 2025A | E82: 2026E | F82: 2027E | G82: 2028E | H82: 2029E | I82: 2030E
A83: Doanh thu thuần (tỷ đồng) | B83: =Drivers!C39/1000000 -> 19.43824 | C83: =Drivers!D39/1000000 -> 30.928285 | D83: =Drivers!E39/1000000 -> 47.546528 | E83: =Drivers!F39/1000000 -> 63.673817 | F83: =Drivers!G39/1000000 -> 79.74062 | G83: =Drivers!H39/1000000 -> 110.40166 | H83: =Drivers!I39/1000000 -> 141.60433 | I83: =Drivers!J39/1000000 -> 170.31775
A84: Tăng trưởng doanh thu | C84: =Drivers!D40 -> 0.59110521 | D84: =Drivers!E40 -> 0.53731538 | E84: =Drivers!F40 -> 0.33918962 | F84: =Drivers!G40 -> 0.25232982 | G84: =Drivers!H40 -> 0.38450974 | H84: =Drivers!I40 -> 0.2826286 | I84: =Drivers!J40 -> 0.20277215
A85: Biên EBITDA | B85: =Drivers!C77 -> -0.14211735 | C85: =Drivers!D77 -> 0.065136614 | D85: =Drivers!E77 -> 0.16183367 | E85: =Drivers!F77 -> 0.17878941 | F85: =Drivers!G77 -> 0.17895239 | G85: =Drivers!H77 -> 0.16084463 | H85: =Drivers!I77 -> 0.19015424 | I85: =Drivers!J77 -> 0.20217878
A86: Nguồn: BCTC 2023–2025 do đề bài cung cấp; dự phóng của nhóm (sheet Drivers)
A88: Fig_02 | Khoảng giá trị pre-money theo phương pháp
A89: Phương pháp | B89: Thấp | C89: Cơ sở | D89: Cao
A90: DCF (WACC ±1 điểm %, g ±1 điểm %) | B90: =Summary!B18 -> 23.936193 | C90: =Summary!C18 -> 32.793775 | D90: =Summary!D18 -> 46.481654
A91: VC Method (z 35–45%, giá trị thoái vốn ±15%) | B91: =Summary!B19 -> 11.406357 | C91: =Summary!C19 -> 25.29891 | D91: =Summary!D19 -> 40.764205
A92: Multiples (EV/EBITDA, P/E 2025A; DLOM 30%) | B92: =Summary!B20 -> 17.662531 | C92: =Summary!C20 -> 27.710968 | D92: =Summary!D20 -> 43.967678
A93: Khuyến nghị (bình quân gia quyền 40/40/20) | B93: =Summary!B21 -> 17.669526 | C93: =Summary!C21 -> 28.779268 | D93: =Summary!D21 -> 43.691879
A94: Vốn cổ phần cần huy động (đầu vào VC Method) | C94: =Summary!B24 -> 37.610763
A95: Nguồn: Mô hình (Summary, Sensitivity, Multiples)
A97: Fig_03 | Tóm tắt tài chính 2023A–2030E
A98: Chỉ tiêu | B98: 2023A | C98: 2024A | D98: 2025A | E98: 2026E | F98: 2027E | G98: 2028E | H98: 2029E | I98: 2030E
A99: Doanh thu thuần | B99: =Drivers!C39/1000000 -> 19.43824 | C99: =Drivers!D39/1000000 -> 30.928285 | D99: =Drivers!E39/1000000 -> 47.546528 | E99: =Drivers!F39/1000000 -> 63.673817 | F99: =Drivers!G39/1000000 -> 79.74062 | G99: =Drivers!H39/1000000 -> 110.40166 | H99: =Drivers!I39/1000000 -> 141.60433 | I99: =Drivers!J39/1000000 -> 170.31775
A100: Tăng trưởng | C100: =Drivers!D40 -> 0.59110521 | D100: =Drivers!E40 -> 0.53731538 | E100: =Drivers!F40 -> 0.33918962 | F100: =Drivers!G40 -> 0.25232982 | G100: =Drivers!H40 -> 0.38450974 | H100: =Drivers!I40 -> 0.2826286 | I100: =Drivers!J40 -> 0.20277215
A101: Biên lợi nhuận gộp (VAS) | B101: =Drivers!C84 -> 0.37262164 | C101: =Drivers!D84 -> 0.46928311 | D101: =Drivers!E84 -> 0.51034107 | E101: =Drivers!F84 -> 0.51755412 | F101: =Drivers!G84 -> 0.50514602 | G101: =Drivers!H84 -> 0.44829054 | H101: =Drivers!I84 -> 0.47067807 | I101: =Drivers!J84 -> 0.47593895
A102: EBITDA | B102: =Drivers!C76/1000000 -> -2.7625112 | C102: =Drivers!D76/1000000 -> 2.0145638 | D102: =Drivers!E76/1000000 -> 7.6946292 | E102: =Drivers!F76/1000000 -> 11.384204 | F102: =Drivers!G76/1000000 -> 14.269775 | G102: =Drivers!H76/1000000 -> 17.757515 | H102: =Drivers!I76/1000000 -> 26.926664 | I102: =Drivers!J76/1000000 -> 34.434634
A103: Biên EBITDA | B103: =Drivers!C77 -> -0.14211735 | C103: =Drivers!D77 -> 0.065136614 | D103: =Drivers!E77 -> 0.16183367 | E103: =Drivers!F77 -> 0.17878941 | F103: =Drivers!G77 -> 0.17895239 | G103: =Drivers!H77 -> 0.16084463 | H103: =Drivers!I77 -> 0.19015424 | I103: =Drivers!J77 -> 0.20217878
A104: LNST | B104: ='Income Statement'!B80/1000000 -> -4.3090112 | C104: ='Income Statement'!C80/1000000 -> -0.50327625 | D104: ='Income Statement'!D80/1000000 -> 4.4204952 | E104: ='Income Statement'!E80/1000000 -> 6.5791399 | F104: ='Income Statement'!F80/1000000 -> 5.8274452 | G104: ='Income Statement'!G80/1000000 -> 2.3978688 | H104: ='Income Statement'!H80/1000000 -> 8.7101521 | I104: ='Income Statement'!I80/1000000 -> 13.854708
A105: FCF (2023–25A: CFO − CAPEX) / FCFF (2026–30E) | B105: =('Cash Flow Statement'!C19+'Cash Flow Statement'!C22)/1000000 -> -8.9660112 | C105: =('Cash Flow Statement'!D19+'Cash Flow Statement'!D22)/1000000 -> -5.6084562 | D105: =('Cash Flow Statement'!E19+'Cash Flow Statement'!E22)/1000000 -> 1.1979492 | E105: =DCF!C10/1000000 -> -4.8648996 | F105: =DCF!D10/1000000 -> -42.641746 | G105: =DCF!E10/1000000 -> -3.6833324 | H105: =DCF!F10/1000000 -> 3.6230491 | I105: =DCF!G10/1000000 -> 8.6567871
A106: CAPEX / doanh thu (tỷ lệ tái đầu tư) | B106: =Drivers!C93 -> 0.25768794 | C106: =Drivers!D93 -> 0.2038781 | D106: =Drivers!E93 -> 0.10693778 | E106: =Drivers!F93 -> 0.2 | F106: =Drivers!G93 -> 0.65 | G106: =Drivers!H93 -> 0.12 | H106: =Drivers!I93 -> 0.1 | I106: =Drivers!J93 -> 0.1
A107: ROIC = NOPAT / (TSCĐ ròng + VLĐ) | D107: =('Income Statement'!D65*(1-Assumption!$D$15))/(Drivers!E100+Drivers!E114) -> 0.12744318 | E107: =DCF!C5/(Drivers!F100+Drivers!F114) -> 0.16689274 | F107: =DCF!D5/(Drivers!G100+Drivers!G114) -> 0.079942573 | G107: =DCF!E5/(Drivers!H100+Drivers!H114) -> 0.050770898 | H107: =DCF!F5/(Drivers!I100+Drivers!I114) -> 0.10429642 | I107: =DCF!G5/(Drivers!J100+Drivers!J114) -> 0.13881153
A108: Vốn chủ sở hữu cuối kỳ | B108: ='Balance Sheet'!E76/1000000 -> 19.054989 | C108: ='Balance Sheet'!F76/1000000 -> 25.551713 | D108: ='Balance Sheet'!G76/1000000 -> 29.972208 | E108: ='Balance Sheet'!H76/1000000 -> 74.162111 | F108: ='Balance Sheet'!I76/1000000 -> 79.989556 | G108: ='Balance Sheet'!J76/1000000 -> 82.387425 | H108: ='Balance Sheet'!K76/1000000 -> 91.097577 | I108: ='Balance Sheet'!L76/1000000 -> 104.95228
A109: Nợ vay cuối kỳ (ngắn + dài hạn) | B109: =('Balance Sheet'!E48+'Balance Sheet'!E61)/1000000 -> 1.29 | C109: =('Balance Sheet'!F48+'Balance Sheet'!F61)/1000000 -> 1.608 | D109: =('Balance Sheet'!G48+'Balance Sheet'!G61)/1000000 -> 1.6026 | E109: =('Balance Sheet'!H48+'Balance Sheet'!H61)/1000000 -> 1.6026 | F109: =('Balance Sheet'!I48+'Balance Sheet'!I61)/1000000 -> 32.701442 | G109: =('Balance Sheet'!J48+'Balance Sheet'!J61)/1000000 -> 32.701442 | H109: =('Balance Sheet'!K48+'Balance Sheet'!K61)/1000000 -> 26.481673 | I109: =('Balance Sheet'!L48+'Balance Sheet'!L61)/1000000 -> 20.261905
A110: Nguồn: BCTC 2023–2025 (đề bài); dự phóng của nhóm; BCKQKD theo chức năng (70% tiền lương, 90% khấu hao vào giá vốn)
A112: Fig_04 | Thị trường nhựa Việt Nam 2026–2031
A113: Chỉ tiêu | B113: 2026 | C113: 2031
A114: Thị trường nhựa Việt Nam (triệu tấn) | B114: 12.83 | C114: 19.16
A115: Nhựa bao bì năm 2026 = 50,35% thị trường (triệu tấn) | B115: =12.83*0.5035 -> 6.459905
A116: Tốc độ tăng bình quân 2026–2031 | B116: =(19.16/12.83)^(1/5)-1 -> 0.08351211
A117: Tỷ trọng rác thải nhựa toàn cầu đến từ bao bì (UNEP) | B117: 0.46
A118: Nguồn: Số liệu trong bài của nhóm (Mục 1.1.1); tỷ lệ 46%: UNEP (2021)
A120: Fig_06 | Giá tham khảo hộp đựng thực phẩm 500 ml
A121: Loại hộp (có nắp) | B121: Giá thấp (đ/chiếc) | C121: Giá cao (đ/chiếc) | D121: Dung tích
A122: Xốp EPS | B122: 400 | C122: 600 | D122: 500 ml
A123: PP | B123: 988 | C123: 988 | D123: 500 ml
A124: Kraft (nắp PP) | B124: 1350 | C124: 1550 | D124: 500 ml
A125: Bã mía | B125: 1900 | C125: 2700 | D125: 500 ml
A126: AgriPack – hộp/khay F&B (bảng giá Mục 1.2.2) | B126: 2500 | C126: 4000 | D126: 500–800 ml
A127: Nguồn: QueenPack.com; baobixanh.com (bảng của nhóm, Mục 1.1.1); giá AgriPack: bảng chiến lược giá (Mục 1.2.2)
A129: Fig_07 | Thị trường mục tiêu TAM – SAM – SOM
A130: Chỉ tiêu (triệu USD) | B130: 2025A | C130: 2030E | D130: CAGR
A131: TAM – thị trường bao bì xanh Việt Nam (IMARC) | B131: =Drivers!E50 -> 1129.79 | C131: =Drivers!J50 -> 1384.5036 | D131: =(C131/B131)^(1/5)-1 -> 0.0415
A132: SAM – bao bì dùng một lần phân hủy sinh học ngành F&B (IMARC) | B132: =Drivers!E48 -> 33.93 | C132: =Drivers!J48 -> 42.750321 | D132: =(C132/B132)^(1/5)-1 -> 0.0473
A133: SOM – doanh thu F&B/FMCG của AgriPack | B133: =Drivers!E47 -> 1.4638092 | C133: =Drivers!J47 -> 4.6931632 | D133: =(C133/B133)^(1/5)-1 -> 0.26239782
A134: SOM / SAM | B134: =Drivers!E49 -> 0.043142035 | C134: =Drivers!J49 -> 0.10978077
A135: Nguồn: IMARC Group (2025); doanh thu F&B quy đổi USD theo tỷ giá bình quân (Drivers)
A137: Fig_08 | Chiến lược giá bán của AgriPack
A138: Phân khúc | B138: Tham chiếu – thấp | C138: Tham chiếu – cao | D138: AgriPack – thấp | E138: AgriPack – cao | F138: Đơn vị
A139: Hộp/khay F&B, FMCG – hộp bã mía Thái Lan (600 ml) | B139: 2100 | C139: 2400 | D139: 2500 | E139: 4000 | F139: đ/cái
A140: Hộp/khay F&B, FMCG – hộp bã mía Trung Quốc (600–750 ml) | B140: 1900 | C140: 4000 | D140: 2500 | E140: 4000 | F140: đ/cái
A141: Đệm bảo vệ thiết bị, linh kiện điện tử | B141: 2600 | C141: 18200 | D141: 2500 | E141: 18500 | F141: đ/cái
A142: Đệm bảo vệ nội thất/e-commerce | B142: 520 | C142: 11700 | D142: 600 | E142: 11500 | F142: đ/cái
A143: Thiết kế – chế tạo khuôn – ép mẫu thử | B143: 20 | C143: 20 | D143: 20 | E143: 20 | F143: triệu đ/bộ khuôn
A144: ASP hộp/khay F&B 2025 dùng trong mô hình | D144: =Drivers!E10*1000 -> 2500 | F144: đ/cái
A145: Nguồn: Bảng chiến lược giá của nhóm (Mục 1.2.2: ecoeshop.com, HTAECO.com); ASP mô hình: Drivers
A147: Fig_09 | Cơ cấu doanh thu 2023–2025
A148: Nhóm sản phẩm (nghìn đồng) | B148: 2023 | C148: 2024 | D148: 2025
A149: Thực phẩm/FMCG | B149: ='Income Statement'!B6 -> 15055000 | C149: ='Income Statement'!C6 -> 24088000 | D149: ='Income Statement'!D6 -> 38059040
A150: Thiết kế theo mẫu | B150: ='Income Statement'!B7 -> 3020000 | C150: ='Income Statement'!C7 -> 4228000 | D150: ='Income Statement'!D7 -> 5898060
A151: Nội thất/E-commerce | B151: ='Income Statement'!B8 -> 1520000 | C151: ='Income Statement'!C8 -> 2280000 | D151: ='Income Statement'!D8 -> 2736000
A152: Thiết bị điện tử | B152: ='Income Statement'!B9 -> 0 | C152: ='Income Statement'!C9 -> 566000 | D152: ='Income Statement'!D9 -> 1188600
A153: Tổng doanh thu bán hàng | B153: =Drivers!C37 -> 19595000 | C153: =Drivers!D37 -> 31162000 | D153: =Drivers!E37 -> 47881700
A154: Nguồn: BCTC 2023–2025 (đề bài); biểu đồ cơ cấu doanh thu của nhóm (Mục 1.3.1)
A156: Fig_10 | Cơ cấu chi phí 2023–2025
A157: Nhóm chi phí (nghìn đồng) | B157: 2023 | C157: 2024 | D157: 2025
A158: COGS (giá vốn theo BCTC gốc) | B158: =Drivers!C59 -> 6011751.2 | C158: =Drivers!D59 -> 8892571.2 | D158: =Drivers!E59 -> 12925449
A159: SG&A (CPBH & QLDN, không gồm lương) | B159: =Drivers!C75-Drivers!C62 -> 9197000 | C159: =Drivers!D75-Drivers!D62 -> 12329950 | D159: =Drivers!E75-Drivers!E62 -> 16158770
A160: Payroll (tiền lương) | B160: =Drivers!C62 -> 6992000 | C160: =Drivers!D62 -> 7691200 | D160: =Drivers!E62 -> 10767680
A161: Nguồn: BCTC 2023–2025 (đề bài); cách phân loại của nhóm (Mục 1.3.1) – chưa phân bổ tiền lương, khấu hao vào giá vốn
A163: Fig_12 | Quy mô doanh thu 2023–2025
A164: Chỉ tiêu | B164: 2023 | C164: 2024 | D164: 2025
A165: Doanh thu thuần (nghìn đồng) | B165: ='Income Statement'!B13 -> 19438240 | C165: ='Income Statement'!C13 -> 30928285 | D165: ='Income Statement'!D13 -> 47546528
A166: Tăng trưởng doanh thu (%) | C166: ='Income Statement'!C13/'Income Statement'!B13-1 -> 0.59110521 | D166: ='Income Statement'!D13/'Income Statement'!C13-1 -> 0.53731538
A167: Nguồn: BCTC 2023–2025 (đề bài); tính toán của nhóm
A169: Fig_13 | Quy mô doanh thu 2025 so với doanh nghiệp dẫn đầu
A170: Doanh nghiệp | B170: Doanh thu 2025 (tỷ đồng) | C170: Gấp AgriPack (lần)
A171: An Phát Holdings | B171: 10746 | C171: =B171/(Drivers!E39/1000000) -> 226.01019
A172: Đông Hải Bến Tre (DHC) | B172: 3633 | C172: =B172/(Drivers!E39/1000000) -> 76.409365
A173: AgriPack | B173: =Drivers!E39/1000000 -> 47.546528 | C173: 1
A174: Nguồn: Bài của nhóm (Mục 2.1), BCTC 2025 của An Phát Holdings, Đông Hải Bến Tre; AgriPack: BCTC 2025 (đề bài)
A176: Fig_14 | Mức độ sinh lời 2023–2025
...

Sheet Ghi chu
A1: GHI CHÚ MÔ HÌNH (người lập: Lộc)
A3: Luồng dữ liệu | B3: BCTC 2023–2025 (đề bài) → Drivers (sản lượng × giá, chi phí theo dòng, CAPEX/khấu hao, VLĐ, vay, thuế) → Assumption (tỷ lệ tổng hợp) → Pro Forma (KQKD, CAPEX, VLĐ, lưu chuyển tiền trước gọi vốn, nhu cầu vốn) → IS/BS/CF 2026–2030 → Discount rate → DCF, VCM → Sensitivity, Summary → Chart_Data.
A4: Quy ước | B4: Ô vàng chữ xanh dương = số liệu/giả định nhập; chữ đen = công thức; chữ xanh lá = liên kết sheet khác. Đơn vị nghìn đồng (Summary, Chart_Data: tỷ đồng). Chiết khấu cuối năm, t0 = 01/01/2026.
A5: Kịch bản | B5: Drivers!C3: 1 Bear / 2 Base / 3 Bull. Drivers!C4: năm đầu tư lớn 2027 (đề bài) hoặc 2028 (template). Drivers!E123: tỷ lệ CAPEX năm đầu tư lớn tài trợ bằng vay.
A6: Cần cập nhật | B6: Rf = bình quân lợi suất TPCP 10 năm 2016–2025 (Discount rate!A28:D40); 2016–2017 dùng quan sát phát hành/đấu thầu gần nhất có nguồn. CRP Việt Nam (B16) là ước tính theo phương pháp Damodaran – kiểm tra lại bảng Damodaran 01/2026 trước khi nộp.
A7: Trình bày BCKQKD | B7: Theo chức năng (VAS): 70% tiền lương và 90% khấu hao vào giá vốn; 30% tiền lương và 10% khấu hao vào CPBH & QLDN (tham số ở Drivers, mục F). EBITDA là dòng ghi nhớ (IS hàng 82).
A8: Nguồn chính | B8: NSO/Cục Thống kê & NHNN qua FiinX (truy xuất 29/9/2026); Damodaran (01/2026, 07/2026); IMARC Group (2025); Mordor Intelligence; VECOM (2025); BCG–NIC–VPCA (2026); FiinX – DN bao bì niêm yết (giá 28/9/2026); Nghị định 08/2022/NĐ-CP Điều 64; Nghị định 110/2026/NĐ-CP; Luật Thuế TNDN 67/2025/QH15; NQ 198/2025/QH15; TB 846/TB-NATIF.
A9: Độ nhạy theo nhân tố | B9: Summary!A48:N58: mỗi nhân tố vĩ mô – ngành (cầu, giá bán, chi phí biến đổi, nhân sự, lãi suất, CRP, ưu đãi thuế) được đổi một mình trên kịch bản Base và toàn bộ mô hình được tính lại (run_tornado.py); giá trị lưu dạng chụp, lý do biên độ ghi ở cột N cạnh từng dòng. Báo cáo: Fig. 30, Fig. A15.
A10: CÁC CHỈNH SỬA ĐỐI VỚI FILE MẪU (lỗi logic của template)
A11: Sheet | B11: Ô | C11: Nội dung chỉnh sửa | D11: Lý do
A12: Assumption | B12: A8:A12 | C12: Làm rõ nhãn: TSNH/Nợ NH không gồm tiền và vay | D12: Tiền mặt là kết quả của dòng tiền và vay là quyết định tài trợ – đưa vào tỷ lệ theo doanh thu sẽ gây vòng lặp và sai VLĐ.
A13: Assumption | B13: G13 | C13: Ô khóa 65% (cột 2028) được thay bằng liên kết Drivers | D13: Đề bài quy định đầu tư lớn năm 2027. Ô chọn Drivers!C4 cho phép chạy lại phương án 65% vào 2028 như template.
A14: Pro Forma | B14: B31, B34, B36, C47:G48 | C14: Sửa công thức biến động TSNH/Nợ NH | D14: Template: C47 = (B31−B32)−(C31−C33) trộn hàng tồn kho với phải thu; C48 = B34−C34 ngược dấu; B31/B34 gồm cả tiền và vay. Nay: VLĐ hoạt động = TSNH ngoài tiền − Nợ NH ngoài vay; dòng tiền = −ΔVLĐ.
A15: Pro Forma | B15: C53:G53 | C15: Thay công thức "=-D54" (tham chiếu ô trống) | D15: Ghi nhận giải ngân/trả nợ vay theo kế hoạch để tính nhu cầu vốn cổ phần.
A16: Pro Forma | B16: A60:G60, B61 | C16: Thêm hàng thiếu hụt tiền và công thức nhu cầu vốn | D16: B61 là ô vàng để trống; nay = thiếu hụt tối đa so với tiền mặt tối thiểu.
A17: Discount rate | B17: B13, A28:D41 | C17: Rf = bình quân lợi suất TPCP 10 năm giai đoạn 2016–2025 | D17: Thay giá trị ước tính 4,2% bằng bình quân 10 quan sát có nguồn (VBMA, HNX/CEIC, ADB, Vietnam News, VNDirect).
A18: DCF | B18: G12, G14, H10 | C18: Giá trị cuối kỳ dùng FCFF chuẩn hóa và được chiết khấu vào EV | D18: Template: C16 = SUM(C14:G14) nhưng không có ô PV của TV → G14 gộp FCFF 2030 + TV. Giữ công thức TV = FCFF 2031/(WACC − g) của template; FCFF 2031 (H10) được chuẩn hóa = NOPAT 2031 × (1 − g/RONIC), RONIC = ROIC 2030E, vì FCFF 2030 còn chứa CAPEX/VLĐ của giai đoạn tăng ~20%/năm.
A19: VCM | B19: B6, B9, E6:E12 | C19: Điền công thức VC method theo giáo trình: p = (1 + r)/(1 − z)^(1/n) − 1 | D19: z = 40% nhập tay theo hướng dẫn của BTL cho DN giai đoạn đầu tăng trưởng (35–45%).
A20: Income Statement | B20: E6:I80; J:N | C20: Dựng lại dự phóng 2026–2030 từ Drivers; xóa cột 2031–2034 | D20: Template chứa số giữ chỗ (VD: GVHB 2027 = 163 triệu → biên gộp 97,7%; chi phí "Insurance" 1.000...) không phản ánh DN. Đề bài chỉ yêu cầu 5 năm.
A21: Income Statement | B21: D78 | C21: Thay '-' bằng 0 | D21: Ô text '-' làm lỗi phép tính thuế 2025.
A22: Income Statement | B22: hàng 18–27, 52–65, 71–84 (mọi năm) | C22: Trình bày BCKQKD theo chức năng (VAS) | D22: 70% tiền lương và 90% khấu hao phân bổ vào giá vốn; 30% tiền lương và 10% khấu hao vào CPBH & QLDN. EBIT, LNTT, LNST không đổi; EBITDA chuyển thành dòng ghi nhớ (hàng 82). Biên gộp theo BCTC gốc ở hàng 84.
... A29: Cash Flow Statement | B29: F27:J27 | C29: Dòng "Nhận vốn góp" tham chiếu thẻ tín dụng (hàng 45) | D29: Nay = vốn cổ phần tăng thêm trong năm (BCĐKT hàng 72).
